Workbook
Name Button_429: "LeaseCalc_Lease_Data_List"
Name CellAbove: INDIRECT(ADDRESS(ROW()-1,COLUMN()))
Name CIT: #N/A
Name IQ_CH: 110000
Name IQ_CQ: 5000
Name IQ_CY: 10000
Name IQ_DAILY: 500000
Name IQ_FH: 100000
Name IQ_FQ: 500
Name IQ_FY: 1000
Name IQ_LTM: 2000
Name IQ_MONTH: 15000
Name IQ_NTM: 6000
Name IQ_WEEK: 50000
Name IQ_YTD: 3000
Name TM1REBUILDOPTION: 1

Sheet Combined | IS
A1: Combined IS
A2: Source: <document_source>
A7: Combined IS
A8: LineKey | B8: $'000 | C8: TB Account No. | D8: Sign | E8: Source | F8: Comments | G8: ='Control | Setup'!A22 | H8: ='Control | Setup'!A23 | I8: ='Control | Setup'!A24 | J8: ='Control | Setup'!A25 | K8: ='Control | Setup'!A26 | L8: ='Control | Setup'!A27 | M8: ='Control | Setup'!A28 | N8: ='Control | Setup'!A29 | O8: ='Control | Setup'!A30 | P8: ='Control | Setup'!A31 | Q8: ='Control | Setup'!A32 | R8: ='Control | Setup'!A33 | S8: ='Control | Setup'!A34 | T8: ='Control | Setup'!A35 | U8: ='Control | Setup'!A36 | V8: ='Control | Setup'!A37 | W8: ='Control | Setup'!A38 | X8: ='Control | Setup'!A39 | Y8: ='Control | Setup'!A40 | Z8: ='Control | Setup'!A41 | AA8: ='Control | Setup'!A42 | AB8: ='Control | Setup'!A43 | AC8: ='Control | Setup'!A44 | AD8: ='Control | Setup'!A45 | AE8: ='Control | Setup'!A46 | AF8: ='Control | Setup'!A47 | AG8: ='Control | Setup'!A48 | AH8: ='Control | Setup'!A49 | AI8: ='Control | Setup'!A50 | AJ8: ='Control | Setup'!A51 | AK8: ='Control | Setup'!A52 | AL8: ='Control | Setup'!A53 | AM8: ='Control | Setup'!A54 | AN8: ='Control | Setup'!A55 | AO8: ='Control | Setup'!A56 | AP8: ='Control | Setup'!A57 | AQ8: FY-2 | AR8: FY-1 | AS8: TTM
A9: IS_REV | B9: Revenue | C9: 4000 | D9: + | E9: TB/Map | G9: =SUMIFS('Data | TB'!G:G,'Data | TB'!$B:$B,$C9) | H9: =SUMIFS('Data | TB'!H:H,'Data | TB'!$B:$B,$C9) | I9: =SUMIFS('Data | TB'!I:I,'Data | TB'!$B:$B,$C9) | J9: =SUMIFS('Data | TB'!J:J,'Data | TB'!$B:$B,$C9) | K9: =SUMIFS('Data | TB'!K:K,'Data | TB'!$B:$B,$C9) | AQ9: =IF(COUNT(G9:R9)=0,"",SUM(G9:R9)) | AR9: =IF(COUNT(S9:AD9)=0,"",SUM(S9:AD9)) | AS9: =IF(COUNT(AE9:AP9)=0,"",SUM(AE9:AP9))
A10: IS_COGS | B10: Cost of goods sold | C10: 5000 | D10: + | E10: TB/Map | G10: =SUMIFS('Data | TB'!G:G,'Data | TB'!$B:$B,$C10) | H10: =SUMIFS('Data | TB'!H:H,'Data | TB'!$B:$B,$C10) | I10: =SUMIFS('Data | TB'!I:I,'Data | TB'!$B:$B,$C10) | J10: =SUMIFS('Data | TB'!J:J,'Data | TB'!$B:$B,$C10) | K10: =SUMIFS('Data | TB'!K:K,'Data | TB'!$B:$B,$C10) | AQ10: =IF(COUNT(G10:R10)=0,"",SUM(G10:R10)) | AR10: =IF(COUNT(S10:AD10)=0,"",SUM(S10:AD10)) | AS10: =IF(COUNT(AE10:AP10)=0,"",SUM(AE10:AP10))
A11: IS_GP | B11: Gross profit | D11: + | E11: Formula | F11: Derived | G11: =IF(OR(G9="",G10=""),"",G9+G10) | H11: =IF(OR(H9="",H10=""),"",H9+H10) | I11: =IF(OR(I9="",I10=""),"",I9+I10) | J11: =IF(OR(J9="",J10=""),"",J9+J10) | K11: =IF(OR(K9="",K10=""),"",K9+K10) | L11: =IF(OR(L9="",L10=""),"",L9+L10) | M11: =IF(OR(M9="",M10=""),"",M9+M10) | N11: =IF(OR(N9="",N10=""),"",N9+N10) | ... AP11: =IF(OR(AP9="",AP10=""),"",AP9+AP10) | AQ11: =IF(COUNT(G11:R11)=0,"",SUM(G11:R11)) | AR11: =IF(COUNT(S11:AD11)=0,"",SUM(S11:AD11)) | AS11: =IF(COUNT(AE11:AP11)=0,"",SUM(AE11:AP11))
A12: IS_OPEX | B12: Operating expenses | C12: 6100 | D12: + | E12: TB/Map | G12: =SUMIFS('Data | TB'!G:G,'Data | TB'!$B:$B,$C12) | H12: =SUMIFS('Data | TB'!H:H,'Data | TB'!$B:$B,$C12) | I12: =SUMIFS('Data | TB'!I:I,'Data | TB'!$B:$B,$C12) | J12: =SUMIFS('Data | TB'!J:J,'Data | TB'!$B:$B,$C12) | K12: =SUMIFS('Data | TB'!K:K,'Data | TB'!$B:$B,$C12) | AQ12: =IF(COUNT(G12:R12)=0,"",SUM(G12:R12)) | AR12: =IF(COUNT(S12:AD12)=0,"",SUM(S12:AD12)) | AS12: =IF(COUNT(AE12:AP12)=0,"",SUM(AE12:AP12))
A13: IS_OPINC | B13: Operating income | D13: + | E13: Formula | F13: Derived | G13: =IF(OR(G11="",G12=""),"",G11+G12) | H13: =IF(OR(H11="",H12=""),"",H11+H12) | I13: =IF(OR(I11="",I12=""),"",I11+I12) | J13: =IF(OR(J11="",J12=""),"",J11+J12) | K13: =IF(OR(K11="",K12=""),"",K11+K12) | L13: =IF(OR(L11="",L12=""),"",L11+L12) | M13: =IF(OR(M11="",M12=""),"",M11+M12) | N13: =IF(OR(N11="",N12=""),"",N11+N12) | ... AP13: =IF(OR(AP11="",AP12=""),"",AP11+AP12) | AQ13: =IF(COUNT(G13:R13)=0,"",SUM(G13:R13)) | AR13: =IF(COUNT(S13:AD13)=0,"",SUM(S13:AD13)) | AS13: =IF(COUNT(AE13:AP13)=0,"",SUM(AE13:AP13))
A14: IS_INT | B14: Interest expense | C14: 7100 | D14: + | E14: TB/Map | G14: =SUMIFS('Data | TB'!G:G,'Data | TB'!$B:$B,$C14) | H14: =SUMIFS('Data | TB'!H:H,'Data | TB'!$B:$B,$C14) | I14: =SUMIFS('Data | TB'!I:I,'Data | TB'!$B:$B,$C14) | J14: =SUMIFS('Data | TB'!J:J,'Data | TB'!$B:$B,$C14) | K14: =SUMIFS('Data | TB'!K:K,'Data | TB'!$B:$B,$C14) | AQ14: =IF(COUNT(G14:R14)=0,"",SUM(G14:R14)) | AR14: =IF(COUNT(S14:AD14)=0,"",SUM(S14:AD14)) | AS14: =IF(COUNT(AE14:AP14)=0,"",SUM(AE14:AP14))
A15: IS_TAX | B15: Taxes | C15: 7200 | D15: + | E15: TB/Map | G15: =SUMIFS('Data | TB'!G:G,'Data | TB'!$B:$B,$C15) | H15: =SUMIFS('Data | TB'!H:H,'Data | TB'!$B:$B,$C15) | I15: =SUMIFS('Data | TB'!I:I,'Data | TB'!$B:$B,$C15) | J15: =SUMIFS('Data | TB'!J:J,'Data | TB'!$B:$B,$C15) | K15: =SUMIFS('Data | TB'!K:K,'Data | TB'!$B:$B,$C15) | AQ15: =IF(COUNT(G15:R15)=0,"",SUM(G15:R15)) | AR15: =IF(COUNT(S15:AD15)=0,"",SUM(S15:AD15)) | AS15: =IF(COUNT(AE15:AP15)=0,"",SUM(AE15:AP15))
A16: IS_NI | B16: Net income | D16: + | E16: Formula | F16: Main total | G16: =IF(OR(G13="",G14="",G15=""),"",G13+G14+G15) | H16: =IF(OR(H13="",H14="",H15=""),"",H13+H14+H15) | I16: =IF(OR(I13="",I14="",I15=""),"",I13+I14+I15) | J16: =IF(OR(J13="",J14="",J15=""),"",J13+J14+J15) | K16: =IF(OR(K13="",K14="",K15=""),"",K13+K14+K15) | L16: =IF(OR(L13="",L14="",L15=""),"",L13+L14+L15) | M16: =IF(OR(M13="",M14="",M15=""),"",M13+M14+M15) | N16: =IF(OR(N13="",N14="",N15=""),"",N13+N14+N15) | ... AP16: =IF(OR(AP13="",AP14="",AP15=""),"",AP13+AP14+AP15) | AQ16: =IF(COUNT(G16:R16)=0,"",SUM(G16:R16)) | AR16: =IF(COUNT(S16:AD16)=0,"",SUM(S16:AD16)) | AS16: =IF(COUNT(AE16:AP16)=0,"",SUM(AE16:AP16))
A17: IS_ADD_DA | B17: Add back: Depreciation & amortization | C17: 7300 | D17: + | E17: TB/Map | G17: =SUMIFS('Data | TB'!G:G,'Data | TB'!$B:$B,$C17) | H17: =SUMIFS('Data | TB'!H:H,'Data | TB'!$B:$B,$C17) | I17: =SUMIFS('Data | TB'!I:I,'Data | TB'!$B:$B,$C17) | J17: =SUMIFS('Data | TB'!J:J,'Data | TB'!$B:$B,$C17) | K17: =SUMIFS('Data | TB'!K:K,'Data | TB'!$B:$B,$C17) | AQ17: =IF(COUNT(G17:R17)=0,"",SUM(G17:R17)) | AR17: =IF(COUNT(S17:AD17)=0,"",SUM(S17:AD17)) | AS17: =IF(COUNT(AE17:AP17)=0,"",SUM(AE17:AP17))
A18: IS_ADD_INT | B18: Add back: Interest | C18: 7310 | D18: + | E18: TB/Map | G18: =SUMIFS('Data | TB'!G:G,'Data | TB'!$B:$B,$C18) | H18: =SUMIFS('Data | TB'!H:H,'Data | TB'!$B:$B,$C18) | I18: =SUMIFS('Data | TB'!I:I,'Data | TB'!$B:$B,$C18) | J18: =SUMIFS('Data | TB'!J:J,'Data | TB'!$B:$B,$C18) | K18: =SUMIFS('Data | TB'!K:K,'Data | TB'!$B:$B,$C18) | AQ18: =IF(COUNT(G18:R18)=0,"",SUM(G18:R18)) | AR18: =IF(COUNT(S18:AD18)=0,"",SUM(S18:AD18)) | AS18: =IF(COUNT(AE18:AP18)=0,"",SUM(AE18:AP18))
A19: IS_ADD_TAX | B19: Add back: Taxes | C19: 7320 | D19: + | E19: TB/Map | G19: =SUMIFS('Data | TB'!G:G,'Data | TB'!$B:$B,$C19) | H19: =SUMIFS('Data | TB'!H:H,'Data | TB'!$B:$B,$C19) | I19: =SUMIFS('Data | TB'!I:I,'Data | TB'!$B:$B,$C19) | J19: =SUMIFS('Data | TB'!J:J,'Data | TB'!$B:$B,$C19) | K19: =SUMIFS('Data | TB'!K:K,'Data | TB'!$B:$B,$C19) | AQ19: =IF(COUNT(G19:R19)=0,"",SUM(G19:R19)) | AR19: =IF(COUNT(S19:AD19)=0,"",SUM(S19:AD19)) | AS19: =IF(COUNT(AE19:AP19)=0,"",SUM(AE19:AP19))
A20: IS_EBITDA | B20: EBITDA | D20: + | E20: Formula | F20: Secondary total | G20: =IF(OR(G16="",G17="",G18="",G19=""),"",G16+G17+G18+G19) | H20: =IF(OR(H16="",H17="",H18="",H19=""),"",H16+H17+H18+H19) | I20: =IF(OR(I16="",I17="",I18="",I19=""),"",I16+I17+I18+I19) | J20: =IF(OR(J16="",J17="",J18="",J19=""),"",J16+J17+J18+J19) | K20: =IF(OR(K16="",K17="",K18="",K19=""),"",K16+K17+K18+K19) | L20: =IF(OR(L16="",L17="",L18="",L19=""),"",L16+L17+L18+L19) | M20: =IF(OR(M16="",M17="",M18="",M19=""),"",M16+M17+M18+M19) | N20: =IF(OR(N16="",N17="",N18="",N19=""),"",N16+N17+N18+N19) | ... AP20: =IF(OR(AP16="",AP17="",AP18="",AP19=""),"",AP16+AP17+AP18+AP19) | AQ20: =IF(COUNT(G20:R20)=0,"",SUM(G20:R20)) | AR20: =IF(COUNT(S20:AD20)=0,"",SUM(S20:AD20)) | AS20: =IF(COUNT(AE20:AP20)=0,"",SUM(AE20:AP20))
A27: IS_CHECKS
A28: Net income tie-out | G28: =IF(G16="","",G16-(G13+G14+G15)) | H28: =IF(H16="","",H16-(H13+H14+H15)) | I28: =IF(I16="","",I16-(I13+I14+I15)) | J28: =IF(J16="","",J16-(J13+J14+J15)) | K28: =IF(K16="","",K16-(K13+K14+K15)) | L28: =IF(L16="","",L16-(L13+L14+L15)) | M28: =IF(M16="","",M16-(M13+M14+M15)) | N28: =IF(N16="","",N16-(N13+N14+N15)) | ... AS28: =IF(AS16="","",AS16-(AS13+AS14+AS15))
A29: EBITDA tie-out | G29: =IF(G20="","",G20-(G16+G17+G18+G19)) | H29: =IF(H20="","",H20-(H16+H17+H18+H19)) | I29: =IF(I20="","",I20-(I16+I17+I18+I19)) | J29: =IF(J20="","",J20-(J16+J17+J18+J19)) | K29: =IF(K20="","",K20-(K16+K17+K18+K19)) | L29: =IF(L20="","",L20-(L16+L17+L18+L19)) | M29: =IF(M20="","",M20-(M16+M17+M18+M19)) | N29: =IF(N20="","",N20-(N16+N17+N18+N19)) | ... AS29: =IF(AS20="","",AS20-(AS16+AS17+AS18+AS19))
