Workbook
Name Button_429: "LeaseCalc_Lease_Data_List"
Name CellAbove: INDIRECT(ADDRESS(ROW()-1,COLUMN()))
Name CIT: #N/A
Name IQ_CH: 110000
Name IQ_CQ: 5000
Name IQ_CY: 10000
Name IQ_DAILY: 500000
Name IQ_FH: 100000
Name IQ_FQ: 500
Name IQ_FY: 1000
Name IQ_LTM: 2000
Name IQ_MONTH: 15000
Name IQ_NTM: 6000
Name IQ_WEEK: 50000
Name IQ_YTD: 3000
Name TM1REBUILDOPTION: 1

Sheet Combined | BS
A1: Combined BS
A2: Source: <document_source>
A7: Combined BS
A8: LineKey | B8: $'000 | C8: TB Account No. | D8: Sign | E8: Source | F8: Comments | G8: ='Control | Setup'!A22 | H8: ='Control | Setup'!A23 | I8: ='Control | Setup'!A24 | J8: ='Control | Setup'!A25 | K8: ='Control | Setup'!A26 | L8: ='Control | Setup'!A27 | M8: ='Control | Setup'!A28 | N8: ='Control | Setup'!A29 | O8: ='Control | Setup'!A30 | P8: ='Control | Setup'!A31 | Q8: ='Control | Setup'!A32 | R8: ='Control | Setup'!A33 | S8: ='Control | Setup'!A34 | T8: ='Control | Setup'!A35 | U8: ='Control | Setup'!A36 | V8: ='Control | Setup'!A37 | W8: ='Control | Setup'!A38 | X8: ='Control | Setup'!A39 | Y8: ='Control | Setup'!A40 | Z8: ='Control | Setup'!A41 | AA8: ='Control | Setup'!A42 | AB8: ='Control | Setup'!A43 | AC8: ='Control | Setup'!A44 | AD8: ='Control | Setup'!A45 | AE8: ='Control | Setup'!A46 | AF8: ='Control | Setup'!A47 | AG8: ='Control | Setup'!A48 | AH8: ='Control | Setup'!A49 | AI8: ='Control | Setup'!A50 | AJ8: ='Control | Setup'!A51 | AK8: ='Control | Setup'!A52 | AL8: ='Control | Setup'!A53 | AM8: ='Control | Setup'!A54 | AN8: ='Control | Setup'!A55 | AO8: ='Control | Setup'!A56 | AP8: ='Control | Setup'!A57 | AQ8: FY-2 | AR8: FY-1 | AS8: TTM
A9: BS_CASH | B9: Cash | C9: 1000 | D9: + | E9: TB/Map | G9: =SUMIFS('Data | TB'!G:G,'Data | TB'!$B:$B,$C9) | H9: =SUMIFS('Data | TB'!H:H,'Data | TB'!$B:$B,$C9) | I9: =SUMIFS('Data | TB'!I:I,'Data | TB'!$B:$B,$C9) | J9: =SUMIFS('Data | TB'!J:J,'Data | TB'!$B:$B,$C9) | K9: =SUMIFS('Data | TB'!K:K,'Data | TB'!$B:$B,$C9) | AQ9: =R9 | AR9: =AD9 | AS9: =AP9
A10: BS_AR | B10: Accounts receivable | C10: 1100 | D10: + | E10: TB/Map | G10: =SUMIFS('Data | TB'!G:G,'Data | TB'!$B:$B,$C10) | H10: =SUMIFS('Data | TB'!H:H,'Data | TB'!$B:$B,$C10) | I10: =SUMIFS('Data | TB'!I:I,'Data | TB'!$B:$B,$C10) | J10: =SUMIFS('Data | TB'!J:J,'Data | TB'!$B:$B,$C10) | K10: =SUMIFS('Data | TB'!K:K,'Data | TB'!$B:$B,$C10) | AQ10: =R10 | AR10: =AD10 | AS10: =AP10
A11: BS_INV | B11: Inventory | C11: 1200 | D11: + | E11: TB/Map | G11: =SUMIFS('Data | TB'!G:G,'Data | TB'!$B:$B,$C11) | H11: =SUMIFS('Data | TB'!H:H,'Data | TB'!$B:$B,$C11) | I11: =SUMIFS('Data | TB'!I:I,'Data | TB'!$B:$B,$C11) | J11: =SUMIFS('Data | TB'!J:J,'Data | TB'!$B:$B,$C11) | K11: =SUMIFS('Data | TB'!K:K,'Data | TB'!$B:$B,$C11) | AQ11: =R11 | AR11: =AD11 | AS11: =AP11
A12: BS_OCA | B12: Other current assets | C12: 1300 | D12: + | E12: TB/Map | G12: =SUMIFS('Data | TB'!G:G,'Data | TB'!$B:$B,$C12) | H12: =SUMIFS('Data | TB'!H:H,'Data | TB'!$B:$B,$C12) | I12: =SUMIFS('Data | TB'!I:I,'Data | TB'!$B:$B,$C12) | J12: =SUMIFS('Data | TB'!J:J,'Data | TB'!$B:$B,$C12) | K12: =SUMIFS('Data | TB'!K:K,'Data | TB'!$B:$B,$C12) | AQ12: =R12 | AR12: =AD12 | AS12: =AP12
A13: BS_TCA | B13: Total current assets | D13: + | E13: Formula | F13: Derived | G13: =IF(COUNT(G9:G12)=0,"",SUM(G9:G12)) | H13: =IF(COUNT(H9:H12)=0,"",SUM(H9:H12)) | I13: =IF(COUNT(I9:I12)=0,"",SUM(I9:I12)) | J13: =IF(COUNT(J9:J12)=0,"",SUM(J9:J12)) | K13: =IF(COUNT(K9:K12)=0,"",SUM(K9:K12)) | L13: =IF(COUNT(L9:L12)=0,"",SUM(L9:L12)) | M13: =IF(COUNT(M9:M12)=0,"",SUM(M9:M12)) | N13: =IF(COUNT(N9:N12)=0,"",SUM(N9:N12)) | ... AP13: =IF(COUNT(AP9:AP12)=0,"",SUM(AP9:AP12)) | AQ13: =R13 | AR13: =AD13 | AS13: =AP13
A14: BS_PPE | B14: PP&E | C14: 1500 | D14: + | E14: TB/Map | G14: =SUMIFS('Data | TB'!G:G,'Data | TB'!$B:$B,$C14) | H14: =SUMIFS('Data | TB'!H:H,'Data | TB'!$B:$B,$C14) | I14: =SUMIFS('Data | TB'!I:I,'Data | TB'!$B:$B,$C14) | J14: =SUMIFS('Data | TB'!J:J,'Data | TB'!$B:$B,$C14) | K14: =SUMIFS('Data | TB'!K:K,'Data | TB'!$B:$B,$C14) | AQ14: =R14 | AR14: =AD14 | AS14: =AP14
A15: BS_OTA | B15: Other assets | C15: 1600 | D15: + | E15: TB/Map | G15: =SUMIFS('Data | TB'!G:G,'Data | TB'!$B:$B,$C15) | H15: =SUMIFS('Data | TB'!H:H,'Data | TB'!$B:$B,$C15) | I15: =SUMIFS('Data | TB'!I:I,'Data | TB'!$B:$B,$C15) | J15: =SUMIFS('Data | TB'!J:J,'Data | TB'!$B:$B,$C15) | K15: =SUMIFS('Data | TB'!K:K,'Data | TB'!$B:$B,$C15) | AQ15: =R15 | AR15: =AD15 | AS15: =AP15
A16: BS_TA | B16: Total assets | D16: + | E16: Formula | F16: Main total | G16: =IF(COUNT(G13:G15)=0,"",SUM(G13:G15)) | H16: =IF(COUNT(H13:H15)=0,"",SUM(H13:H15)) | I16: =IF(COUNT(I13:I15)=0,"",SUM(I13:I15)) | J16: =IF(COUNT(J13:J15)=0,"",SUM(J13:J15)) | K16: =IF(COUNT(K13:K15)=0,"",SUM(K13:K15)) | L16: =IF(COUNT(L13:L15)=0,"",SUM(L13:L15)) | M16: =IF(COUNT(M13:M15)=0,"",SUM(M13:M15)) | N16: =IF(COUNT(N13:N15)=0,"",SUM(N13:N15)) | ... AP16: =IF(COUNT(AP13:AP15)=0,"",SUM(AP13:AP15)) | AQ16: =R16 | AR16: =AD16 | AS16: =AP16
A17: BS_AP | B17: Accounts payable | C17: 2000 | D17: + | E17: TB/Map | G17: =SUMIFS('Data | TB'!G:G,'Data | TB'!$B:$B,$C17) | H17: =SUMIFS('Data | TB'!H:H,'Data | TB'!$B:$B,$C17) | I17: =SUMIFS('Data | TB'!I:I,'Data | TB'!$B:$B,$C17) | J17: =SUMIFS('Data | TB'!J:J,'Data | TB'!$B:$B,$C17) | K17: =SUMIFS('Data | TB'!K:K,'Data | TB'!$B:$B,$C17) | AQ17: =R17 | AR17: =AD17 | AS17: =AP17
A18: BS_ACCR | B18: Accrued liabilities | C18: 2100 | D18: + | E18: TB/Map | G18: =SUMIFS('Data | TB'!G:G,'Data | TB'!$B:$B,$C18) | H18: =SUMIFS('Data | TB'!H:H,'Data | TB'!$B:$B,$C18) | I18: =SUMIFS('Data | TB'!I:I,'Data | TB'!$B:$B,$C18) | J18: =SUMIFS('Data | TB'!J:J,'Data | TB'!$B:$B,$C18) | K18: =SUMIFS('Data | TB'!K:K,'Data | TB'!$B:$B,$C18) | AQ18: =R18 | AR18: =AD18 | AS18: =AP18
A19: BS_DEBT | B19: Debt | C19: 2200 | D19: + | E19: TB/Map | G19: =SUMIFS('Data | TB'!G:G,'Data | TB'!$B:$B,$C19) | H19: =SUMIFS('Data | TB'!H:H,'Data | TB'!$B:$B,$C19) | I19: =SUMIFS('Data | TB'!I:I,'Data | TB'!$B:$B,$C19) | J19: =SUMIFS('Data | TB'!J:J,'Data | TB'!$B:$B,$C19) | K19: =SUMIFS('Data | TB'!K:K,'Data | TB'!$B:$B,$C19) | AQ19: =R19 | AR19: =AD19 | AS19: =AP19
A20: BS_OL | B20: Other liabilities | C20: 2300 | D20: + | E20: TB/Map | G20: =SUMIFS('Data | TB'!G:G,'Data | TB'!$B:$B,$C20) | H20: =SUMIFS('Data | TB'!H:H,'Data | TB'!$B:$B,$C20) | I20: =SUMIFS('Data | TB'!I:I,'Data | TB'!$B:$B,$C20) | J20: =SUMIFS('Data | TB'!J:J,'Data | TB'!$B:$B,$C20) | K20: =SUMIFS('Data | TB'!K:K,'Data | TB'!$B:$B,$C20) | AQ20: =R20 | AR20: =AD20 | AS20: =AP20
A21: BS_TL | B21: Total liabilities | D21: + | E21: Formula | F21: Derived | G21: =IF(COUNT(G17:G20)=0,"",SUM(G17:G20)) | H21: =IF(COUNT(H17:H20)=0,"",SUM(H17:H20)) | I21: =IF(COUNT(I17:I20)=0,"",SUM(I17:I20)) | J21: =IF(COUNT(J17:J20)=0,"",SUM(J17:J20)) | K21: =IF(COUNT(K17:K20)=0,"",SUM(K17:K20)) | L21: =IF(COUNT(L17:L20)=0,"",SUM(L17:L20)) | M21: =IF(COUNT(M17:M20)=0,"",SUM(M17:M20)) | N21: =IF(COUNT(N17:N20)=0,"",SUM(N17:N20)) | ... AP21: =IF(COUNT(AP17:AP20)=0,"",SUM(AP17:AP20)) | AQ21: =R21 | AR21: =AD21 | AS21: =AP21
A22: BS_EQ | B22: Equity | C22: 3000 | D22: + | E22: TB/Map | G22: =SUMIFS('Data | TB'!G:G,'Data | TB'!$B:$B,$C22) | H22: =SUMIFS('Data | TB'!H:H,'Data | TB'!$B:$B,$C22) | I22: =SUMIFS('Data | TB'!I:I,'Data | TB'!$B:$B,$C22) | J22: =SUMIFS('Data | TB'!J:J,'Data | TB'!$B:$B,$C22) | K22: =SUMIFS('Data | TB'!K:K,'Data | TB'!$B:$B,$C22) | AQ22: =R22 | AR22: =AD22 | AS22: =AP22
A23: BS_TLE | B23: Total liabilities + equity | D23: + | E23: Formula | F23: Derived | G23: =IF(COUNT(G21:G22)=0,"",SUM(G21:G22)) | H23: =IF(COUNT(H21:H22)=0,"",SUM(H21:H22)) | I23: =IF(COUNT(I21:I22)=0,"",SUM(I21:I22)) | J23: =IF(COUNT(J21:J22)=0,"",SUM(J21:J22)) | K23: =IF(COUNT(K21:K22)=0,"",SUM(K21:K22)) | L23: =IF(COUNT(L21:L22)=0,"",SUM(L21:L22)) | M23: =IF(COUNT(M21:M22)=0,"",SUM(M21:M22)) | N23: =IF(COUNT(N21:N22)=0,"",SUM(N21:N22)) | ... AP23: =IF(COUNT(AP21:AP22)=0,"",SUM(AP21:AP22)) | AQ23: =R23 | AR23: =AD23 | AS23: =AP23
A27: BS_CHECKS
A28: Balance check (Assets - Liabilities & Equity) | G28: =IF(OR(G16="",G23=""),"",G16-G23) | H28: =IF(OR(H16="",H23=""),"",H16-H23) | I28: =IF(OR(I16="",I23=""),"",I16-I23) | J28: =IF(OR(J16="",J23=""),"",J16-J23) | K28: =IF(OR(K16="",K23=""),"",K16-K23) | L28: =IF(OR(L16="",L23=""),"",L16-L23) | M28: =IF(OR(M16="",M23=""),"",M16-M23) | N28: =IF(OR(N16="",N23=""),"",N16-N23) | ... AS28: =IF(OR(AS16="",AS23=""),"",AS16-AS23)
