Workbook
Name Button_429: "LeaseCalc_Lease_Data_List"
Name CellAbove: INDIRECT(ADDRESS(ROW()-1,COLUMN()))
Name CIT: #N/A
Name IQ_CH: 110000
Name IQ_CQ: 5000
Name IQ_CY: 10000
Name IQ_DAILY: 500000
Name IQ_FH: 100000
Name IQ_FQ: 500
Name IQ_FY: 1000
Name IQ_LTM: 2000
Name IQ_MONTH: 15000
Name IQ_NTM: 6000
Name IQ_WEEK: 50000
Name IQ_YTD: 3000
Name TM1REBUILDOPTION: 1

Sheet Recons
A1: Recons
A2: Source: <document_source>
A4: Cross-tab reconciliation mini-grids for IS, BS, CF, and other tie-outs.
A7: Recons | IS
A8: LineKey | B8: $'000 | C8: TB Account No. | D8: Source value | E8: Databook value | F8: Variance | G8: Explanation | H8: Check (=0) | I8: Status
A9: R_IS_REV | B9: Revenue | D9: ='Combined | IS'!G9 | E9: ='QofE | Detail'!G9 | F9: =IF(OR(D9="",E9=""),"",E9-D9) | H9: =IF(F9="","",F9) | I9: =IF(H9="","",IF(ABS(H9)<=0.01,"PASS","FAIL"))
A10: R_IS_NI | B10: Net income | D10: ='Combined | IS'!G16 | E10: ='Combined | IS'!G16 | F10: =IF(OR(D10="",E10=""),"",E10-D10) | H10: =IF(F10="","",F10) | I10: =IF(H10="","",IF(ABS(H10)<=0.01,"PASS","FAIL"))
A11: R_IS_EBITDA | B11: EBITDA | D11: ='Combined | IS'!G20 | E11: ='QofE | Summary'!G16 | F11: =IF(OR(D11="",E11=""),"",E11-D11) | H11: =IF(F11="","",F11) | I11: =IF(H11="","",IF(ABS(H11)<=0.01,"PASS","FAIL"))
A12: R_IS_OPEX | B12: Operating expenses | D12: ='Combined | IS'!G12 | E12: ='Combined | IS'!G12 | F12: =IF(OR(D12="",E12=""),"",E12-D12) | H12: =IF(F12="","",F12) | I12: =IF(H12="","",IF(ABS(H12)<=0.01,"PASS","FAIL"))
A13: R_IS_OTHER | B13: Other IS line | D13: ='Combined | IS'!G13 | E13: ='Combined | IS'!G13 | F13: =IF(OR(D13="",E13=""),"",E13-D13) | H13: =IF(F13="","",F13) | I13: =IF(H13="","",IF(ABS(H13)<=0.01,"PASS","FAIL"))
A16: Recons | BS
A17: LineKey | B17: $'000 | C17: TB Account No. | D17: Source value | E17: Databook value | F17: Variance | G17: Explanation | H17: Check (=0) | I17: Status
A18: R_BS_TA | B18: Total assets | D18: ='Combined | BS'!G16 | E18: ='Combined | BS'!G16 | F18: =IF(OR(D18="",E18=""),"",E18-D18) | H18: =IF(F18="","",F18) | I18: =IF(H18="","",IF(ABS(H18)<=0.01,"PASS","FAIL"))
A19: R_BS_TL | B19: Total liabilities | D19: ='Combined | BS'!G21 | E19: ='Combined | BS'!G21 | F19: =IF(OR(D19="",E19=""),"",E19-D19) | H19: =IF(F19="","",F19) | I19: =IF(H19="","",IF(ABS(H19)<=0.01,"PASS","FAIL"))
A20: R_BS_EQ | B20: Equity | D20: ='Combined | BS'!G22 | E20: ='Combined | BS'!G22 | F20: =IF(OR(D20="",E20=""),"",E20-D20) | H20: =IF(F20="","",F20) | I20: =IF(H20="","",IF(ABS(H20)<=0.01,"PASS","FAIL"))
A21: R_BS_TLE | B21: Liabilities + equity | D21: ='Combined | BS'!G23 | E21: ='Combined | BS'!G23 | F21: =IF(OR(D21="",E21=""),"",E21-D21) | H21: =IF(F21="","",F21) | I21: =IF(H21="","",IF(ABS(H21)<=0.01,"PASS","FAIL"))
A22: R_BS_OTHER | B22: Other BS line | D22: ='Combined | BS'!G10 | E22: ='Combined | BS'!G10 | F22: =IF(OR(D22="",E22=""),"",E22-D22) | H22: =IF(F22="","",F22) | I22: =IF(H22="","",IF(ABS(H22)<=0.01,"PASS","FAIL"))
A25: Recons | CF
A26: LineKey | B26: $'000 | C26: TB Account No. | D26: Source value | E26: Databook value | F26: Variance | G26: Explanation | H26: Check (=0) | I26: Status
A27: R_CF_NET | B27: Net cash flow | D27: ='Combined | CF'!G13 | E27: ='Combined | CF'!G13 | F27: =IF(OR(D27="",E27=""),"",E27-D27) | H27: =IF(F27="","",F27) | I27: =IF(H27="","",IF(ABS(H27)<=0.01,"PASS","FAIL"))
A28: R_CF_OP | B28: Operating cash flow | D28: ='Combined | CF'!G9 | E28: ='Combined | CF'!G9 | F28: =IF(OR(D28="",E28=""),"",E28-D28) | H28: =IF(F28="","",F28) | I28: =IF(H28="","",IF(ABS(H28)<=0.01,"PASS","FAIL"))
A29: R_CF_INV | B29: Investing cash flow | D29: ='Combined | CF'!G11 | E29: ='Combined | CF'!G11 | F29: =IF(OR(D29="",E29=""),"",E29-D29) | H29: =IF(F29="","",F29) | I29: =IF(H29="","",IF(ABS(H29)<=0.01,"PASS","FAIL"))
A30: R_CF_FIN | B30: Financing cash flow | D30: ='Combined | CF'!G12 | E30: ='Combined | CF'!G12 | F30: =IF(OR(D30="",E30=""),"",E30-D30) | H30: =IF(F30="","",F30) | I30: =IF(H30="","",IF(ABS(H30)<=0.01,"PASS","FAIL"))
A31: R_CF_OTHER | B31: Other CF line | D31: ='Combined | CF'!G10 | E31: ='Combined | CF'!G10 | F31: =IF(OR(D31="",E31=""),"",E31-D31) | H31: =IF(F31="","",F31) | I31: =IF(H31="","",IF(ABS(H31)<=0.01,"PASS","FAIL"))
A34: Recons | Other
A35: LineKey | B35: $'000 | C35: TB Account No. | D35: Source value | E35: Databook value | F35: Variance | G35: Explanation | H35: Check (=0) | I35: Status
A36: R_OTH_AR | B36: AR aging to BS | D36: ='Agings'!J15 | E36: ='Agings'!J18 | F36: =IF(OR(D36="",E36=""),"",E36-D36) | H36: =IF(F36="","",F36) | I36: =IF(H36="","",IF(ABS(H36)<=0.01,"PASS","FAIL"))
A37: R_OTH_AP | B37: AP aging to BS | D37: ='Agings'!J31 | E37: ='Agings'!J34 | F37: =IF(OR(D37="",E37=""),"",E37-D37) | H37: =IF(F37="","",F37) | I37: =IF(H37="","",IF(ABS(H37)<=0.01,"PASS","FAIL"))
A38: R_OTH_NWC | B38: NWC Summary to NWC Detail | D38: ='NWC | Summary'!G12 | E38: ='NWC | Detail'!G14 | F38: =IF(OR(D38="",E38=""),"",E38-D38) | H38: =IF(F38="","",F38) | I38: =IF(H38="","",IF(ABS(H38)<=0.01,"PASS","FAIL"))
A39: R_OTH_ND | B39: Net debt to Stratified BS | D39: ='Net_debt'!G12 | E39: ='Net_debt'!G12 | F39: =IF(OR(D39="",E39=""),"",E39-D39) | H39: =IF(F39="","",F39) | I39: =IF(H39="","",IF(ABS(H39)<=0.01,"PASS","FAIL"))
A40: R_OTH_MISC | B40: Other tie-out | D40: 0 | E40: 0 | F40: =IF(OR(D40="",E40=""),"",E40-D40) | H40: =IF(F40="","",F40) | I40: =IF(H40="","",IF(ABS(H40)<=0.01,"PASS","FAIL"))
A43: RECONS_CHECKS
A44: Open recon fails (should be 0) | H44: =COUNTIF(I9:I40,"FAIL") | I44: =IF(H44=0,"PASS","FAIL")
A45: Absolute variance sum (should be 0) | H45: =SUMPRODUCT(ABS(F9:F40)) | I45: =IF(H45=0,"PASS","FAIL")
