Workbook
Name ctl_monthly_period_count: '_Sys|Config'!$B$2
Name ctl_month_start: '_Sys|Config'!$B$3
Name ctl_tolerance_abs: '_Sys|Config'!$B$4
Name ctl_tolerance_pct: '_Sys|Config'!$B$5
Name ctl_project_name: '_Sys|Config'!$B$6

Sheet Project North >>>
C4: KPMG
C11: =MID(MID(CELL("filename",C2),FIND("]",CELL("filename",C2))+1,256),1,LEN(MID(CELL("filename",C2),FIND("]",CELL("filename",C2))+1,256))-4)
C16: DRAFT
C17: Financial due diligence assistance
C20: =TODAY()
C23: PRIVATE AND CONFIDENTIAL
N24: VA

Sheet Disclaimer
C1: Notice and disclaimer
C3: Context and scope of work
C5: This Excel workbook is provided to Client Company Payment Services Inc. (“Client” or “You”) on a confidential basis pursuant to our engagement letter dated May 20, 2024 (“Engagement Letter”) and is subject in all respects to the terms and conditions of the Engagement Letter, including restrictions on use of this report by third parties.
C7: If this Excel Workbook is received by any party other than Client, the recipient is placed on notice that this report has been prepared solely for Client’s benefit and its own use. KPMG LLP (“KPMG”) does not authorize recipient or any other party to rely on this report and any such reliance shall be at recipient’s sole risk. Therefore, KPMG shall have no liability or responsibility in respect of the advice, recommendations, or other information in this report to recipient or any other party other than Client. Further, this report and its contents may not be shared with or disclosed by the recipient to any party without the express written consent of Client and KPMG.
C9: KPMG approach
C11: Our Excel workbook makes reference to ‘KPMG Analysis’; this indicates only that we have (where specified) undertaken certain analytical activities on the underlying data to arrive at the information presented; we do not accept responsibility for the underlying data. The analysis of 'normalized'/'underlying‘ earnings and working capital is for indicative purposes only. We have sought to illustrate the effect on EBITDA/working capital of adjusting for those items identified in the course of our work that may be considered to be 'non-recurring' or 'exceptional' using criteria established by the Client. However the selection and quantification of such adjustments are necessarily judgmental. Because there is no authoritative literature or common standard with respect to the calculation of 'normalized'/'underlying' earnings/working capital, there is no basis to state whether all appropriate and comparable adjustments have been made. In addition, while the adjustments may indeed relate to items which are 'non-recurring' or 'exceptional' or otherwise unrepresentative of the trend, it is possible that earnings/working capital for future periods may be affected by such items, which may be different from the historical items.
C13: The trailing twelve months ("TTM") run rate analysis has been prepared for illustrative purposes. There is no authoritative literature or common standard with respect to the calculation of 'run rate' EBITDA, and therefore there is no basis on which to state whether, in the illustrative analysis of 'run rate‘ EBITDA, all appropriate and comparable adjustments have been made. We have set out in our report the basis on which items have been included in or excluded from the run rate calculations for particular years. It is for you to satisfy yourselves as to whether the items included or excluded are appropriate for your purposes. The decision as to what items should be included in or excluded from the calculation of 'run rate' EBITDA is highly judgmental; you may choose to interpret the information presented differently.
C15: The procedures we performed do not constitute an audit, examination or review in accordance with standards established by the Auditing and Assurance Standards Board (“AASB”) in Canada, and we have not otherwise verified the information we obtained or presented in this report. We express no opinion or any other form of assurance on Client’s internal control over financial reporting or on the information presented in our report and make no representations concerning its accuracy or completeness.
C17: We have not compiled, examined, or applied other procedures in accordance with the Assurance and Related Services Guidelines issued by the AASB to prospective information contained in this document and, accordingly, express no opinion or any other form of assurance or representations concerning the accuracy, completeness or presentation format of such prospective information. There will usually be differences between projected and actual results, because events and circumstances frequently do not occur as expected, and those differences may be material.
C19: The data included in this report was received from May 20, 2024 to August 8, 2024. Since many aspects of the prospective transaction have either not been finalized or are not yet documented, changes may occur that materially affect the financial and other information we received and reported to you. We have no obligation to update our report or to revise the information contained herein to reflect events and transactions occurring after August 8, 2024. We have reviewed this report with Management for the purpose of confirming the factual accuracy of the information we presented.
C21: Because of its special nature, this report is not suited for any purpose other than to assist Client in its evaluation of the business and, as such and as agreed in the Engagement Agreement, this report may be provided to any prospective purchaser parties on a non-reliance basis and does not in any way involve advice or recommendations to any prospective purchaser party as to whether to proceed with a transaction. Accordingly, KPMG does not accept any liability or responsibility to any third party who may use or place reliance on our report.

Sheet QofE >>

Sheet QofE | Bridge
B1: Project Name
B2: =C7
B3: Source: TBD
B4: WORKING DRAFT
C7: Quality of earnings | Bridge | AI7: Comments
E8: TTM Apr-24 (As of Apr-24) | K8: Jun-24 roll-forward change | Q8: TTM Jun-24 (YTD Apr-24 run-rate) | W8: YTD Jun-24 run-rate change | AC8: TTM Jun-24 (As of Jun-24)
C9: $'000 | D9: Ref | E9: FY21 | F9: FY22 | G9: FY23 | H9: TTM Apr-24 | I9: TTM Jun-24 | K9: FY21 | L9: FY22 | M9: FY23 | N9: TTM Apr-24 | O9: TTM Jun-24 | Q9: FY21 | R9: FY22 | S9: FY23 | T9: TTM Apr-24 | U9: TTM Jun-24 | W9: FY21 | X9: FY22 | Y9: FY23 | Z9: TTM Apr-24 | AA9: TTM Jun-24 | AC9: FY21 | AD9: FY22 | AE9: FY23 | AF9: TTM Apr-24 | AG9: TTM Jun-24
C10: Revenue, reported
C11: Due diligence adjustments
C12: =C49 | D12: =D49
C13: =C50 | D13: =D50
C14: =C51 | D14: =D51
C15: Due diligence adjustments
C16: Revenue, due diligence adjusted
C17: Pro forma adjustments
C18: =C71 | D18: =D71
C19: =C72 | D19: =D72
C20: =C73 | D20: =D73
C21: =C74 | D21: =D74
C22: =C75 | D22: =D75
C23: =C76 | D23: =D76
C24: =C77 | D24: =D77
C25: =C78 | D25: =D78
C26: =C79 | D26: =D79
C27: =C80 | D27: =D80
C28: =C81 | D28: =D81
C29: =C82 | D29: =D82
... C31: =C84 | D31: =D84
C32: =C87 | D32: =D87
C33: =C89 | D33: =D89
C34: =C90 | D34: =D90
C35: =C91 | D35: =D91
C36: =C92 | D36: =D92
C37: Pro forma adjustments
C38: Revenue, pro forma adjusted
C39: Revenue, pro forma adjusted growth rate
C41: Net income, reported
C42: Add/(deduct)
C43: Interest, net
C44: Depreciation & amortization
C45: Other comprehensive income
C46: Income taxes
C47: EBITDA, reported
C48: Due diligence adjustments
D49: 1
C50: Settlement interest income | D50: =D49+1
C51: Settlement services dispute | D51: =D50+1
D52: a
D53: b
C54: Out of period entries | D54: =D51+1
D55: =D54+1
D56: =D55+1
D57: =D56+1
D58: =D57+1
D59: =D58+1
D60: =D59+1
C61: Loss on fixed asset disposal | D61: a
C62: Foreign exchange expense | D62: b
D63: =D60+1
D64: =D63+1
C65: Canada emergency wage subsidy | D65: a
C66: Canada emergency rent subsidy | D66: b
D67: =D64+1
C68: Due diligence adjustments
C69: EBITDA, due diligence adjusted
C70: Pro forma adjustments
D71: a
D72: b
C73: Net new/lost customers | D73: =D67+1
D74: a
D75: b
D76: c
D77: d
D78: e
D79: f
D80: g
D81: h
D82: i
D83: j
C84: Credit union MSA | D84: =+D73+1
D85: =+D84+1
D86: =D85+1
D87: =D86+1
D88: =+D87+1
C89: New products, cards | D89: =+D88+1
C90: New products, fraud management | D90: =+D89+1
D91: =D90+1
D92: =D91+1
D93: =D92+1
C94: Pro forma adjustments
C95: EBITDA, pro forma adjusted
C96: EBITDA margin, pro forma adjusted
C98: Key performance indicators
C99: EBITDA margin, due diligence adjusted
C101: Source- QofE | Detail tab
C102: Check | AC102: =AC101-AC95 | AD102: =AD101-AD95 | AE102: =AE101-AE95 | AF102: =AF101-AF95 | AG102: =AG101-AG95
C104: Source - 21-Jul-24 databook
C105: Check | E105: =E104-E95 | F105: =F104-F95 | G105: =G104-G95 | H105: =H104-H95
C110: Other considerations
E111: TTM Apr-24 Draft (21-Jul-24) | K111: Variance | Q111: TTM Jun-24 (YTD Apr-24 run-rate) | W111: Variance | AC111: TTM Jun-24 (YTD Jun-24 run-rate)
...

Sheet QofE | Summary
B1: Project Name
B2: =C7
B3: Source: TBD
B4: WORKING DRAFT
C7: Quality of earnings
C8: $'000 | D8: ='QofE | Detail'!AU8 | E8: ='QofE | Detail'!AV8 | F8: ='QofE | Detail'!AW8 | G8: ='QofE | Detail'!AX8 | H8: ='QofE | Detail'!AY8
C9: Revenue, reported | D9: ='QofE | Detail'!AU9 | E9: ='QofE | Detail'!AV9 | F9: ='QofE | Detail'!AW9 | G9: ='QofE | Detail'!AX9 | H9: ='QofE | Detail'!AY9
C10: Due diligence adjustments | D10: ='QofE | Detail'!AU14
C11: Pro forma adjustments | D11: ='QofE | Detail'!AU36
C12: Revenue, pro forma adjusted | D12: =SUM(D9:D11)
C13: Revenue, pro forma adjusted growth rate
C15: Net income, reported | D15: ='QofE | Detail'!AU40
C16: Add/(deduct)
C17: Interest, net | D17: ='QofE | Detail'!AU42
C18: Depreciation & amortization | D18: ='QofE | Detail'!AU43
C19: Other comprehensive income | D19: ='QofE | Detail'!AU44
C20: Income taxes | D20: ='QofE | Detail'!AU45
C21: EBITDA, reported | D21: =SUM(D15:D20)
C22: Due diligence adjustments | D22: ='QofE | Detail'!AU67
C23: Pro forma adjustments | D23: ='QofE | Detail'!AU93
C24: EBITDA, pro forma adjusted | D24: =SUM(D21:D23)
C25: EBITDA margin, pro forma adjusted | D25: =IFERROR(D24/D12,0)
C27: Check | D27: ='QofE | Detail'!AU94-D24 | E27: ='QofE | Detail'!AV94-E24 | F27: ='QofE | Detail'!AW94-F24 | G27: ='QofE | Detail'!AX94-G24 | H27: ='QofE | Detail'!AY94-H24

Sheet QofE | Detail
B1: Project Name
B2: =C7
B3: Source: TBD
B4: WORKING DRAFT
C7: Quality of earnings | BA7: Comments
C8: $'000 | D8: Ref | E8: =ctl_month_start | F8: =EDATE(ctl_month_start,1) | G8: =EDATE(ctl_month_start,2) | H8: =EDATE(ctl_month_start,3) | I8: =EDATE(ctl_month_start,4) | J8: =EDATE(ctl_month_start,5) | K8: =EDATE(ctl_month_start,6) | L8: =EDATE(ctl_month_start,7) | M8: =EDATE(ctl_month_start,8) | N8: =EDATE(ctl_month_start,9) | O8: =EDATE(ctl_month_start,10) | P8: =EDATE(ctl_month_start,11) | Q8: =EDATE(ctl_month_start,12) | R8: =EDATE(ctl_month_start,13) | S8: =EDATE(ctl_month_start,14) | T8: =EDATE(ctl_month_start,15) | U8: =EDATE(ctl_month_start,16) | V8: =EDATE(ctl_month_start,17) | W8: =EDATE(ctl_month_start,18) | X8: =EDATE(ctl_month_start,19) | Y8: =EDATE(ctl_month_start,20) | Z8: =EDATE(ctl_month_start,21) | AA8: =EDATE(ctl_month_start,22) | AB8: =EDATE(ctl_month_start,23) | AC8: =EDATE(ctl_month_start,24) | AD8: =EDATE(ctl_month_start,25) | AE8: =EDATE(ctl_month_start,26) | AF8: =EDATE(ctl_month_start,27) | AG8: =EDATE(ctl_month_start,28) | AH8: =EDATE(ctl_month_start,29) | AI8: =EDATE(ctl_month_start,30) | AJ8: =EDATE(ctl_month_start,31) | AK8: =EDATE(ctl_month_start,32) | AL8: =EDATE(ctl_month_start,33) | AM8: =EDATE(ctl_month_start,34) | AN8: =EDATE(ctl_month_start,35)
C9: Revenue, reported | AO9: ='Income statement'!AP117 | AP9: ='Income statement'!AQ117 | AQ9: ='Income statement'!AR117 | AR9: ='Income statement'!AS117 | AS9: ='Income statement'!AT117 | AT9: ='Income statement'!AU117 | AU9: =SUM(E9:P9) | AV9: =SUM(Q9:AB9) | AW9: =SUM(AC9:AN9) | AX9: =SUM(AG9:AR9) | AY9: =SUM(AI9:AT9)
C10: Due diligence adjustments
C11: =C48 | D11: =D48 | AO11: =AO48 | AP11: =AP48 | AQ11: =AQ48 | AR11: =AR48 | AS11: =AS48 | AT11: =AT48 | AU11: =SUM(E11:P11) | AV11: =SUM(Q11:AB11) | AW11: =SUM(AC11:AN11) | AX11: =SUM(AG11:AR11) | AY11: =SUM(AI11:AT11)
C12: =C49 | D12: =D49 | AU12: =SUM(E12:P12) | AV12: =SUM(Q12:AB12) | AW12: =SUM(AC12:AN12) | AX12: =SUM(AG12:AR12) | AY12: =SUM(AI12:AT12)
C13: =C50 | D13: =D50 | AO13: =AO50 | AP13: =AP50 | AQ13: =AQ50 | AR13: =AR50 | AS13: =AS50 | AT13: =AT50 | AU13: =SUM(E13:P13) | AV13: =SUM(Q13:AB13) | AW13: =SUM(AC13:AN13) | AX13: =SUM(AG13:AR13) | AY13: =SUM(AI13:AT13)
C14: Due diligence adjustments | AO14: =SUM(AO11:AO13) | AP14: =SUM(AP11:AP13) | AQ14: =SUM(AQ11:AQ13) | AR14: =SUM(AR11:AR13) | AS14: =SUM(AS11:AS13) | AT14: =SUM(AT11:AT13) | AU14: =SUM(AU11:AU13) | AV14: =SUM(AV11:AV13) | ... AY14: =SUM(AY11:AY13)
C15: Revenue, due diligence adjusted | AO15: =SUM(AO14,AO9) | AP15: =SUM(AP14,AP9) | AQ15: =SUM(AQ14,AQ9) | AR15: =SUM(AR14,AR9) | AS15: =SUM(AS14,AS9) | AT15: =SUM(AT14,AT9) | AU15: =SUM(AU14,AU9) | AV15: =SUM(AV14,AV9) | ... AY15: =SUM(AY14,AY9)
C16: Pro forma adjustments
C17: =C70 | D17: =D70 | AU17: =SUM(E17:P17) | AV17: =SUM(Q17:AB17) | AW17: =SUM(AC17:AN17) | AX17: =SUM(AG17:AR17) | AY17: =SUM(AI17:AT17)
C18: =C71 | D18: =D71 | AU18: =SUM(E18:P18) | AV18: =SUM(Q18:AB18) | AW18: =SUM(AC18:AN18) | AX18: =SUM(AG18:AR18) | AY18: =SUM(AI18:AT18)
C19: =C72 | D19: =D72 | AO19: =SUM(AO17:AO18) | AP19: =SUM(AP17:AP18) | AQ19: =SUM(AQ17:AQ18) | AR19: =SUM(AR17:AR18) | AS19: =SUM(AS17:AS18) | AT19: =SUM(AT17:AT18) | AU19: =SUM(AU17:AU18) | AV19: =SUM(AV17:AV18) | ... AY19: =SUM(AY17:AY18)
C20: =C73 | D20: =D73 | AU20: =SUM(E20:P20) | AV20: =SUM(Q20:AB20) | AW20: =SUM(AC20:AN20) | AX20: =SUM(AG20:AR20) | AY20: =SUM(AI20:AT20)
C21: =C74 | D21: =D74 | AU21: =SUM(E21:P21) | AV21: =SUM(Q21:AB21) | AW21: =SUM(AC21:AN21) | AX21: =SUM(AG21:AR21) | AY21: =SUM(AI21:AT21)
C22: =C75 | D22: =D75 | AU22: =SUM(E22:P22) | AV22: =SUM(Q22:AB22) | AW22: =SUM(AC22:AN22) | AX22: =SUM(AG22:AR22) | AY22: =SUM(AI22:AT22)
C23: =C76 | D23: =D76 | AU23: =SUM(E23:P23) | AV23: =SUM(Q23:AB23) | AW23: =SUM(AC23:AN23) | AX23: =SUM(AG23:AR23) | AY23: =SUM(AI23:AT23)
C24: =C77 | D24: =D77 | AU24: =SUM(E24:P24) | AV24: =SUM(Q24:AB24) | AW24: =SUM(AC24:AN24) | AX24: =SUM(AG24:AR24) | AY24: =SUM(AI24:AT24)
C25: =C78 | D25: =D78 | AU25: =SUM(E25:P25) | AV25: =SUM(Q25:AB25) | AW25: =SUM(AC25:AN25) | AX25: =SUM(AG25:AR25) | AY25: =SUM(AI25:AT25)
C26: =C79 | D26: =D79 | AU26: =SUM(E26:P26) | AV26: =SUM(Q26:AB26) | AW26: =SUM(AC26:AN26) | AX26: =SUM(AG26:AR26) | AY26: =SUM(AI26:AT26)
C27: =C80 | D27: =D80 | AU27: =SUM(E27:P27) | AV27: =SUM(Q27:AB27) | AW27: =SUM(AC27:AN27) | AX27: =SUM(AG27:AR27) | AY27: =SUM(AI27:AT27)
C28: =C81 | D28: =D81 | AU28: =SUM(E28:P28) | AV28: =SUM(Q28:AB28) | AW28: =SUM(AC28:AN28) | AX28: =SUM(AG28:AR28) | AY28: =SUM(AI28:AT28)
C29: =C82 | D29: =D82 | AU29: =SUM(E29:P29) | AV29: =SUM(Q29:AB29) | AW29: =SUM(AC29:AN29) | AX29: =SUM(AG29:AR29) | AY29: =SUM(AI29:AT29)
C30: =C83 | D30: =D83 | AO30: =SUM(AO20:AO29) | AP30: =SUM(AP20:AP29) | AQ30: =SUM(AQ20:AQ29) | AR30: =SUM(AR20:AR29) | AS30: =SUM(AS20:AS29) | AT30: =SUM(AT20:AT29) | AU30: =SUM(AU20:AU29) | AV30: =SUM(AV20:AV29) | ... AY30: =SUM(AY20:AY29)
C31: =C86 | D31: =D86 | AU31: =SUM(E31:P31) | AV31: =SUM(Q31:AB31) | AW31: =SUM(AC31:AN31) | AX31: =SUM(AG31:AR31) | AY31: =SUM(AI31:AT31)
C32: =C88 | D32: =D88 | AU32: =SUM(E32:P32) | AV32: =SUM(Q32:AB32) | AW32: =SUM(AC32:AN32) | AX32: =SUM(AG32:AR32) | AY32: =SUM(AI32:AT32)
C33: =C89 | D33: =D89 | AU33: =SUM(E33:P33) | AV33: =SUM(Q33:AB33) | AW33: =SUM(AC33:AN33) | AX33: =SUM(AG33:AR33) | AY33: =SUM(AI33:AT33)
C34: =C90 | D34: =D90 | AO34: =AO90 | AP34: =AP90 | AQ34: =AQ90 | AR34: =AR90 | AS34: =AS90 | AT34: =AT90 | AU34: =SUM(E34:P34) | AV34: =SUM(Q34:AB34) | AW34: =SUM(AC34:AN34) | AX34: =SUM(AG34:AR34) | AY34: =SUM(AI34:AT34)
C35: =C91 | D35: =D91 | AU35: =SUM(E35:P35) | AV35: =SUM(Q35:AB35) | AW35: =SUM(AC35:AN35) | AX35: =SUM(AG35:AR35) | AY35: =SUM(AI35:AT35)
C36: Pro forma adjustments | AO36: =SUM(AO30:AO35,AO19) | AP36: =SUM(AP30:AP35,AP19) | AQ36: =SUM(AQ30:AQ35,AQ19) | AR36: =SUM(AR30:AR35,AR19) | AS36: =SUM(AS30:AS35,AS19) | AT36: =SUM(AT30:AT35,AT19) | AU36: =SUM(AU30:AU35,AU19) | AV36: =SUM(AV30:AV35,AV19) | ... AY36: =SUM(AY30:AY35,AY19)
C37: Revenue, pro forma adjusted | AO37: =SUM(AO36,AO15) | AP37: =SUM(AP36,AP15) | AQ37: =SUM(AQ36,AQ15) | AR37: =SUM(AR36,AR15) | AS37: =SUM(AS36,AS15) | AT37: =SUM(AT36,AT15) | AU37: =SUM(AU36,AU15) | AV37: =SUM(AV36,AV15) | ... AY37: =SUM(AY36,AY15)
C38: Revenue, pro forma adjusted growth rate | AO38: =(AO37/AN37)-1 | AP38: =(AP37/AO37)-1 | AQ38: =(AQ37/AP37)-1 | AR38: =(AR37/AQ37)-1 | AS38: =(AS37/AR37)-1 | AT38: =(AT37/AS37)-1 | AV38: =(AV37/AU37)-1 | AW38: =(AW37/AV37)-1 | AX38: =(AX37/AW37)-1 | AY38: =(AY37/AW37)-1
C40: Net income, reported | AO40: ='Income statement'!AP353 | AP40: ='Income statement'!AQ353 | AQ40: ='Income statement'!AR353 | AR40: ='Income statement'!AS353 | AS40: ='Income statement'!AT353 | AT40: ='Income statement'!AU353 | AU40: =SUM(E40:P40) | AV40: =SUM(Q40:AB40) | AW40: =SUM(AC40:AN40) | AX40: =SUM(AG40:AR40) | AY40: =SUM(AI40:AT40)
C41: Add/(deduct)
C42: Interest, net | AO42: ='Income statement'!AP356 | AP42: ='Income statement'!AQ356 | AQ42: ='Income statement'!AR356 | AR42: ='Income statement'!AS356 | AS42: ='Income statement'!AT356 | AT42: ='Income statement'!AU356 | AU42: =SUM(E42:P42) | AV42: =SUM(Q42:AB42) | AW42: =SUM(AC42:AN42) | AX42: =SUM(AG42:AR42) | AY42: =SUM(AI42:AT42)
C43: Depreciation & amortization | AO43: ='Income statement'!AP354 | AP43: ='Income statement'!AQ354 | AQ43: ='Income statement'!AR354 | AR43: ='Income statement'!AS354 | AS43: ='Income statement'!AT354 | AT43: ='Income statement'!AU354 | AU43: =SUM(E43:P43) | AV43: =SUM(Q43:AB43) | AW43: =SUM(AC43:AN43) | AX43: =SUM(AG43:AR43) | AY43: =SUM(AI43:AT43)
C44: Other comprehensive income | AO44: ='Income statement'!AP357 | AP44: ='Income statement'!AQ357 | AQ44: ='Income statement'!AR357 | AR44: ='Income statement'!AS357 | AS44: ='Income statement'!AT357 | AT44: ='Income statement'!AU357 | AU44: =SUM(E44:P44) | AV44: =SUM(Q44:AB44) | AW44: =SUM(AC44:AN44) | AX44: =SUM(AG44:AR44) | AY44: =SUM(AI44:AT44)
C45: Income taxes | AO45: ='Income statement'!AP355 | AP45: ='Income statement'!AQ355 | AQ45: ='Income statement'!AR355 | AR45: ='Income statement'!AS355 | AS45: ='Income statement'!AT355 | AT45: ='Income statement'!AU355 | AU45: =SUM(E45:P45) | AV45: =SUM(Q45:AB45) | AW45: =SUM(AC45:AN45) | AX45: =SUM(AG45:AR45) | AY45: =SUM(AI45:AT45)
C46: EBITDA, reported | AO46: =SUM(AO40:AO45) | AP46: =SUM(AP40:AP45) | AQ46: =SUM(AQ40:AQ45) | AR46: =SUM(AR40:AR45) | AS46: =SUM(AS40:AS45) | AT46: =SUM(AT40:AT45) | AU46: =SUM(AU40:AU45) | AV46: =SUM(AV40:AV45) | ... AY46: =SUM(AY40:AY45)
C47: Due diligence adjustments
D48: 1 | AU48: =SUM(E48:P48) | AV48: =SUM(Q48:AB48) | AW48: =SUM(AC48:AN48) | AX48: =SUM(AG48:AR48) | AY48: =SUM(AI48:AT48)
C49: Settlement interest income | D49: =D48+1 | AU49: =SUM(E49:P49) | AV49: =SUM(Q49:AB49) | AW49: =SUM(AC49:AN49) | AX49: =SUM(AG49:AR49) | AY49: =SUM(AI49:AT49)
D50: =D49+1 | AU50: =SUM(E50:P50) | AV50: =SUM(Q50:AB50) | AW50: =SUM(AC50:AN50) | AX50: =SUM(AG50:AR50) | AY50: =SUM(AI50:AT50)
D51: a | AU51: =SUM(E51:P51) | AV51: =SUM(Q51:AB51) | AW51: =SUM(AC51:AN51) | AX51: =SUM(AG51:AR51) | AY51: =SUM(AI51:AT51)
D52: b | AU52: =SUM(E52:P52) | AV52: =SUM(Q52:AB52) | AW52: =SUM(AC52:AN52) | AX52: =SUM(AG52:AR52) | AY52: =SUM(AI52:AT52)
C53: Out of period entries | D53: =D50+1 | AO53: =SUM(AO51:AO52) | AP53: =SUM(AP51:AP52) | AQ53: =SUM(AQ51:AQ52) | AR53: =SUM(AR51:AR52) | AS53: =SUM(AS51:AS52) | AT53: =SUM(AT51:AT52) | AU53: =SUM(AU51:AU52) | AV53: =SUM(AV51:AV52) | ... AY53: =SUM(AY51:AY52)
D54: =D53+1 | AU54: =SUM(E54:P54) | AV54: =SUM(Q54:AB54) | AW54: =SUM(AC54:AN54) | AX54: =SUM(AG54:AR54) | AY54: =SUM(AI54:AT54)
D55: =D54+1 | AU55: =SUM(E55:P55) | AV55: =SUM(Q55:AB55) | AW55: =SUM(AC55:AN55) | AX55: =SUM(AG55:AR55) | AY55: =SUM(AI55:AT55)
D56: =D55+1 | AU56: =SUM(E56:P56) | AV56: =SUM(Q56:AB56) | AW56: =SUM(AC56:AN56) | AX56: =SUM(AG56:AR56) | AY56: =SUM(AI56:AT56)
D57: =D56+1 | AU57: =SUM(E57:P57) | AV57: =SUM(Q57:AB57) | AW57: =SUM(AC57:AN57) | AX57: =SUM(AG57:AR57) | AY57: =SUM(AI57:AT57)
D58: =D57+1 | AU58: =SUM(E58:P58) | AV58: =SUM(Q58:AB58) | AW58: =SUM(AC58:AN58) | AX58: =SUM(AG58:AR58) | AY58: =SUM(AI58:AT58)
D59: =D58+1 | AU59: =SUM(E59:P59) | AV59: =SUM(Q59:AB59) | AW59: =SUM(AC59:AN59) | AX59: =SUM(AG59:AR59) | AY59: =SUM(AI59:AT59)
C60: Loss on fixed asset disposal | D60: a | AU60: =SUM(E60:P60) | AV60: =SUM(Q60:AB60) | AW60: =SUM(AC60:AN60) | AX60: =SUM(AG60:AR60) | AY60: =SUM(AI60:AT60)
C61: Foreign exchange expense | D61: b | AU61: =SUM(E61:P61) | AV61: =SUM(Q61:AB61) | AW61: =SUM(AC61:AN61) | AX61: =SUM(AG61:AR61) | AY61: =SUM(AI61:AT61)
D62: =D59+1 | AO62: =SUM(AO60:AO61) | AP62: =SUM(AP60:AP61) | AQ62: =SUM(AQ60:AQ61) | AR62: =SUM(AR60:AR61) | AS62: =SUM(AS60:AS61) | AT62: =SUM(AT60:AT61) | AU62: =SUM(AU60:AU61) | AV62: =SUM(AV60:AV61) | ... AY62: =SUM(AY60:AY61)
D63: =D62+1 | AU63: =SUM(E63:P63) | AV63: =SUM(Q63:AB63) | AW63: =SUM(AC63:AN63) | AX63: =SUM(AG63:AR63) | AY63: =SUM(AI63:AT63)
C64: Canada emergency wage subsidy | D64: a | AU64: =SUM(E64:P64) | AV64: =SUM(Q64:AB64) | AW64: =SUM(AC64:AN64) | AX64: =SUM(AG64:AR64) | AY64: =SUM(AI64:AT64)
C65: Canada emergency rent subsidy | D65: b | AU65: =SUM(E65:P65) | AV65: =SUM(Q65:AB65) | AW65: =SUM(AC65:AN65) | AX65: =SUM(AG65:AR65) | AY65: =SUM(AI65:AT65)
D66: =D63+1 | AO66: =SUM(AO64:AO65) | AP66: =SUM(AP64:AP65) | AQ66: =SUM(AQ64:AQ65) | AR66: =SUM(AR64:AR65) | AS66: =SUM(AS64:AS65) | AT66: =SUM(AT64:AT65) | AU66: =SUM(AU64:AU65) | AV66: =SUM(AV64:AV65) | ... AY66: =SUM(AY64:AY65)
C67: Due diligence adjustments | AO67: =SUM(AO66,AO62:AO63,AO53:AO59,AO48:AO50) | AP67: =SUM(AP66,AP62:AP63,AP53:AP59,AP48:AP50) | AQ67: =SUM(AQ66,AQ62:AQ63,AQ53:AQ59,AQ48:AQ50) | AR67: =SUM(AR66,AR62:AR63,AR53:AR59,AR48:AR50) | AS67: =SUM(AS66,AS62:AS63,AS53:AS59,AS48:AS50) | AT67: =SUM(AT66,AT62:AT63,AT53:AT59,AT48:AT50) | AU67: =SUM(AU66,AU62:AU63,AU53:AU59,AU48:AU50) | AV67: =SUM(AV66,AV62:AV63,AV53:AV59,AV48:AV50) | ... AY67: =SUM(AY66,AY62:AY63,AY53:AY59,AY48:AY50)
C68: EBITDA, due diligence adjusted | AO68: =SUM(AO67,AO46) | AP68: =SUM(AP67,AP46) | AQ68: =SUM(AQ67,AQ46) | AR68: =SUM(AR67,AR46) | AS68: =SUM(AS67,AS46) | AT68: =SUM(AT67,AT46) | AU68: =SUM(AU67,AU46) | AV68: =SUM(AV67,AV46) | ... AY68: =SUM(AY67,AY46)
C69: Pro forma adjustments
D70: a | AU70: =SUM(E70:P70) | AV70: =SUM(Q70:AB70) | AW70: =SUM(AC70:AN70) | AX70: =SUM(AG70:AR70) | AY70: =SUM(AI70:AT70)
D71: b | AU71: =SUM(E71:P71) | AV71: =SUM(Q71:AB71) | AW71: =SUM(AC71:AN71) | AX71: =SUM(AG71:AR71) | AY71: =SUM(AI71:AT71)
C72: Net new/lost customers | D72: =D66+1 | AO72: =SUM(AO70:AO71) | AP72: =SUM(AP70:AP71) | AQ72: =SUM(AQ70:AQ71) | AR72: =SUM(AR70:AR71) | AS72: =SUM(AS70:AS71) | AT72: =SUM(AT70:AT71) | AU72: =SUM(AU70:AU71) | AV72: =SUM(AV70:AV71) | ... AY72: =SUM(AY70:AY71)
D73: a | AU73: =SUM(E73:P73) | AV73: =SUM(Q73:AB73) | AW73: =SUM(AC73:AN73) | AX73: =SUM(AG73:AR73) | AY73: =SUM(AI73:AT73)
D74: b | AU74: =SUM(E74:P74) | AV74: =SUM(Q74:AB74) | AW74: =SUM(AC74:AN74) | AX74: =SUM(AG74:AR74) | AY74: =SUM(AI74:AT74)
D75: c | AU75: =SUM(E75:P75) | AV75: =SUM(Q75:AB75) | AW75: =SUM(AC75:AN75) | AX75: =SUM(AG75:AR75) | AY75: =SUM(AI75:AT75)
D76: d | AU76: =SUM(E76:P76) | AV76: =SUM(Q76:AB76) | AW76: =SUM(AC76:AN76) | AX76: =SUM(AG76:AR76) | AY76: =SUM(AI76:AT76)
D77: e | AU77: =SUM(E77:P77) | AV77: =SUM(Q77:AB77) | AW77: =SUM(AC77:AN77) | AX77: =SUM(AG77:AR77) | AY77: =SUM(AI77:AT77)
D78: f | AU78: =SUM(E78:P78) | AV78: =SUM(Q78:AB78) | AW78: =SUM(AC78:AN78) | AX78: =SUM(AG78:AR78) | AY78: =SUM(AI78:AT78)
D79: g | AU79: =SUM(E79:P79) | AV79: =SUM(Q79:AB79) | AW79: =SUM(AC79:AN79) | AX79: =SUM(AG79:AR79) | AY79: =SUM(AI79:AT79)
D80: h | AU80: =SUM(E80:P80) | AV80: =SUM(Q80:AB80) | AW80: =SUM(AC80:AN80) | AX80: =SUM(AG80:AR80) | AY80: =SUM(AI80:AT80)
D81: i | AU81: =SUM(E81:P81) | AV81: =SUM(Q81:AB81) | AW81: =SUM(AC81:AN81) | AX81: =SUM(AG81:AR81) | AY81: =SUM(AI81:AT81)
D82: j | AU82: =SUM(E82:P82) | AV82: =SUM(Q82:AB82) | AW82: =SUM(AC82:AN82) | AX82: =SUM(AG82:AR82) | AY82: =SUM(AI82:AT82)
C83: Credit union MSA | D83: =+D72+1 | AO83: =SUM(AO73:AO82) | AP83: =SUM(AP73:AP82) | AQ83: =SUM(AQ73:AQ82) | AR83: =SUM(AR73:AR82) | AS83: =SUM(AS73:AS82) | AT83: =SUM(AT73:AT82) | AU83: =SUM(AU73:AU82) | AV83: =SUM(AV73:AV82) | ... AY83: =SUM(AY73:AY82)
D84: =+D83+1 | AU84: =SUM(E84:P84) | AV84: =SUM(Q84:AB84) | AW84: =SUM(AC84:AN84) | AX84: =SUM(AG84:AR84) | AY84: =SUM(AI84:AT84)
D85: =D84+1 | AU85: =SUM(E85:P85) | AV85: =SUM(Q85:AB85) | AW85: =SUM(AC85:AN85) | AX85: =SUM(AG85:AR85) | AY85: =SUM(AI85:AT85)
D86: =D85+1 | AU86: =SUM(E86:P86) | AV86: =SUM(Q86:AB86) | AW86: =SUM(AC86:AN86) | AX86: =SUM(AG86:AR86) | AY86: =SUM(AI86:AT86)
D87: =+D86+1 | AU87: =SUM(E87:P87) | AV87: =SUM(Q87:AB87) | AW87: =SUM(AC87:AN87) | AX87: =SUM(AG87:AR87) | AY87: =SUM(AI87:AT87)
C88: New products, cards | D88: =+D87+1 | AU88: =SUM(E88:P88) | AV88: =SUM(Q88:AB88) | AW88: =SUM(AC88:AN88) | AX88: =SUM(AG88:AR88) | AY88: =SUM(AI88:AT88)
C89: New products, fraud management | D89: =+D88+1 | AU89: =SUM(E89:P89) | AV89: =SUM(Q89:AB89) | AW89: =SUM(AC89:AN89) | AX89: =SUM(AG89:AR89) | AY89: =SUM(AI89:AT89)
D90: =D89+1 | AU90: =SUM(E90:P90) | AV90: =SUM(Q90:AB90) | AW90: =SUM(AC90:AN90) | AX90: =SUM(AG90:AR90) | AY90: =SUM(AI90:AT90)
D91: =D90+1 | AU91: =SUM(E91:P91) | AV91: =SUM(Q91:AB91) | AW91: =SUM(AC91:AN91) | AX91: =SUM(AG91:AR91) | AY91: =SUM(AI91:AT91)
D92: =D91+1 | AU92: =SUM(E92:P92) | AV92: =SUM(Q92:AB92) | AW92: =SUM(AC92:AN92) | AX92: =SUM(AG92:AR92) | AY92: =SUM(AI92:AT92)
C93: Pro forma adjustments | AO93: =SUM(AO83:AO92,AO72) | AP93: =SUM(AP83:AP92,AP72) | AQ93: =SUM(AQ83:AQ92,AQ72) | AR93: =SUM(AR83:AR92,AR72) | AS93: =SUM(AS83:AS92,AS72) | AT93: =SUM(AT83:AT92,AT72) | AU93: =SUM(AU83:AU92,AU72) | AV93: =SUM(AV83:AV92,AV72) | ... AY93: =SUM(AY83:AY92,AY72)
C94: EBITDA, pro forma adjusted | AO94: =SUM(AO93,AO68) | AP94: =SUM(AP93,AP68) | AQ94: =SUM(AQ93,AQ68) | AR94: =SUM(AR93,AR68) | AS94: =SUM(AS93,AS68) | AT94: =SUM(AT93,AT68) | AU94: =SUM(AU93,AU68) | AV94: =SUM(AV93,AV68) | ... AY94: =SUM(AY93,AY68)
C95: EBITDA margin, pro forma adjusted | AO95: =IFERROR(AO94/AO37,0) | AP95: =IFERROR(AP94/AP37,0) | AQ95: =IFERROR(AQ94/AQ37,0) | AR95: =IFERROR(AR94/AR37,0) | AS95: =IFERROR(AS94/AS37,0) | AT95: =IFERROR(AT94/AT37,0) | AU95: =IFERROR(AU94/AU37,0) | AV95: =IFERROR(AV94/AV37,0) | ... AY95: =IFERROR(AY94/AY37,0)
C97: Key performance indicators
C98: EBITDA margin, due diligence adjusted | AO98: =AO68/AO15 | AP98: =AP68/AP15 | AQ98: =AQ68/AQ15 | AR98: =AR68/AR15 | AS98: =AS68/AS15 | AT98: =AT68/AT15 | AU98: =AU68/AU15 | AV98: =AV68/AV15 | ... AY98: =AY68/AY15
C100: Source- Revenue pro forma adjusted | AU100: =SUM(E100:P100) | AV100: =SUM(Q100:AB100) | AW100: =SUM(AC100:AN100) | AX100: =SUM(AG100:AR100) | AY100: =SUM(AI100:AT100)
C101: Check | E101: =E100-E37 | F101: =F100-F37 | G101: =G100-G37 | H101: =H100-H37 | I101: =I100-I37 | J101: =J100-J37 | K101: =K100-K37 | L101: =L100-L37 | ... AY101: =AY100-AY37
C102: Source - EBITDA reported | AU102: =SUM(E102:P102) | AV102: =SUM(Q102:AB102) | AW102: =SUM(AC102:AN102) | AX102: =SUM(AG102:AR102) | AY102: =SUM(AI102:AT102)
C103: Check | E103: =E46-E102 | F103: =F46-F102 | G103: =G46-G102 | H103: =H46-H102 | I103: =I46-I102 | J103: =J46-J102 | K103: =K46-K102 | L103: =L46-L102 | ... AT103: =AT46-AT102 | AU103: =AU102-AU46 | AV103: =AV102-AV46 | AW103: =AW102-AW46 | AX103: =AX102-AX46 | AY103: =AY102-AY46
C104: Source - EBITDA diligence adjusted | AU104: =SUM(E104:P104) | AV104: =SUM(Q104:AB104) | AW104: =SUM(AC104:AN104) | AX104: =SUM(AG104:AR104) | AY104: =SUM(AI104:AT104)
C105: Check | E105: =E104-E68 | F105: =F104-F68 | G105: =G104-G68 | H105: =H104-H68 | I105: =I104-I68 | J105: =J104-J68 | K105: =K104-K68 | L105: =L104-L68 | ... AY105: =AY104-AY68
...

Sheet Net debt>>

Sheet Net debt
B1: Project Name
B2: =C7
B3: Source: TBD
B4: WORKING DRAFT
C7: Net cash/(debt) | M7: Comments
E8: As at
C9: $'000 | D9: Ref | E9: =ctl_month_start | F9: =EDATE(ctl_month_start,1) | G9: =EDATE(ctl_month_start,2) | H9: =EDATE(ctl_month_start,3) | I9: =EDATE(ctl_month_start,4) | J9: =EDATE(ctl_month_start,5) | K9: =EDATE(ctl_month_start,6) | L9: =EDATE(ctl_month_start,7) | N9: =EDATE(ctl_month_start,9) | O9: =EDATE(ctl_month_start,10) | P9: =EDATE(ctl_month_start,11) | Q9: =EDATE(ctl_month_start,12) | R9: =EDATE(ctl_month_start,13) | S9: =EDATE(ctl_month_start,14) | T9: =EDATE(ctl_month_start,15) | U9: =EDATE(ctl_month_start,16) | V9: =EDATE(ctl_month_start,17) | W9: =EDATE(ctl_month_start,18) | X9: =EDATE(ctl_month_start,19) | Y9: =EDATE(ctl_month_start,20) | Z9: =EDATE(ctl_month_start,21) | AA9: =EDATE(ctl_month_start,22) | AB9: =EDATE(ctl_month_start,23) | AC9: =EDATE(ctl_month_start,24) | AD9: =EDATE(ctl_month_start,25) | AE9: =EDATE(ctl_month_start,26) | AF9: =EDATE(ctl_month_start,27) | AG9: =EDATE(ctl_month_start,28) | AH9: =EDATE(ctl_month_start,29) | AI9: =EDATE(ctl_month_start,30) | AJ9: =EDATE(ctl_month_start,31) | AK9: =EDATE(ctl_month_start,32) | AL9: =EDATE(ctl_month_start,33) | AM9: =EDATE(ctl_month_start,34) | AN9: =EDATE(ctl_month_start,35)
C10: Cash-CAD - operating | K10: ✓
C11: Cash - operating CAD | K11: ✓
C12: Cash USD - 079 | K12: ✓
C13: Cash USD - BMO harris 137 | K13: ✓
C14: Cash CAD - 095 | K14: ✓
C15: Cash and cash equivalents | D15: 1 | K15: ✓
C16: Finance lease obligations | D16: =+D15+1 | K16: ✓
C17: Current income tax liability-federal and prov | D17: a | K17: ✓
C18: Curr income tax liab IFRS adj- IFRS15 | D18: b | K18: ✓
C19: Income tax payable | D19: =D16+1 | K19: ✓
C20: Deferred compensation payable (SERP) | D20: =+D19+1 | K20: ✓
C21: Return of cap - co-op payable | D21: =+D20+1 | K21: ✓
C22: Return of cap payable - celero | D22: =+D21+1 | K22: ✓
C23: Shareholder return of capital payable | D23: =+D20+1 | K23: ✓
C24: Net cash/(debt), reported
C25: Adjustments
C26: Current maturity - prop lease | D26: i | K26: ✓
C27: Long term - property lease | D27: ii | K27: ✓
C28: Finance lease obligation - property lease | D28: b | K28: ✓
C29: Current maturities - finance lease | D29: i | K29: ✓
C30: Long term - finance lease obligations | D30: ii | K30: ✓
C31: Finance lease obligation - leased equipment | D31: a | K31: ✓
C32: Non-resident witholding tax payable | D32: =D23+1 | K32: ✓
C33: Adjustments
C34: Net cash/(debt), adjusted
C36: Check - Stratified BS
C37: Variance

Sheet Financials>>

Sheet Income statement
B1: Project Name
B2: =C7
B3: Source: TBD
B4: WORKING DRAFT
C7: Income statement
BB8: As a % of Revenue | BN8: As a % of Revenue | BZ8: As a % of Revenue | CL8: As a % of Revenue | CR8: As a % of Revenue
C9: $'000 | D9: Code | E9: Concatenate | F9: =ctl_month_start | G9: =EDATE(ctl_month_start,1) | H9: =EDATE(ctl_month_start,2) | I9: =EDATE(ctl_month_start,3) | J9: =EDATE(ctl_month_start,4) | K9: =EDATE(ctl_month_start,5) | L9: =EDATE(ctl_month_start,6) | M9: =EDATE(ctl_month_start,7) | N9: =EDATE(ctl_month_start,8) | O9: =EDATE(ctl_month_start,9) | P9: =EDATE(ctl_month_start,10) | Q9: =EDATE(ctl_month_start,11) | R9: =EDATE(ctl_month_start,12) | S9: =EDATE(ctl_month_start,13) | T9: =EDATE(ctl_month_start,14) | U9: =EDATE(ctl_month_start,15) | V9: =EDATE(ctl_month_start,16) | W9: =EDATE(ctl_month_start,17) | X9: =EDATE(ctl_month_start,18) | Y9: =EDATE(ctl_month_start,19) | Z9: =EDATE(ctl_month_start,20) | AA9: =EDATE(ctl_month_start,21) | AB9: =EDATE(ctl_month_start,22) | AC9: =EDATE(ctl_month_start,23) | AD9: =EDATE(ctl_month_start,24) | AE9: =EDATE(ctl_month_start,25) | AF9: =EDATE(ctl_month_start,26) | AG9: =EDATE(ctl_month_start,27) | AH9: =EDATE(ctl_month_start,28) | AI9: =EDATE(ctl_month_start,29) | AJ9: =EDATE(ctl_month_start,30) | AK9: =EDATE(ctl_month_start,31) | AL9: =EDATE(ctl_month_start,32) | AM9: =EDATE(ctl_month_start,33) | AN9: =EDATE(ctl_month_start,34) | AO9: =EDATE(ctl_month_start,35)
C10: Mobile tsp transactions pos- | D10: 411110 | E10: =CONCATENATE(D10," - ",C10) | AP10: 1180.3076 | AQ10: 1205.4039 | AR10: 1317.5891 | AS10: 1379.2225 | AT10: 1529.493 | AU10: 1505.7267 | AV10: =SUM(F10:Q10) | AW10: =SUM(R10:AC10) | AX10: =SUM(AD10:AO10) | AY10: =SUM(AH10:AS10) | AZ10: =SUM(AJ10:AU10) | BB10: =IFERROR(F10/F$117,0) | BC10: =IFERROR(G10/G$117,0) | BD10: =IFERROR(H10/H$117,0) | BE10: =IFERROR(I10/I$117,0) | BF10: =IFERROR(J10/J$117,0) | BG10: =IFERROR(K10/K$117,0) | BH10: =IFERROR(L10/L$117,0) | BI10: =IFERROR(M10/M$117,0) | ... CV10: =IFERROR(AZ10/AZ$117,0) | CX10: 5877.6973
C11: Png transactions revenue - pos | D11: 411101 | E11: =CONCATENATE(D11," - ",C11) | AP11: 728.33166 | AQ11: 725.70095 | AR11: 803.04041 | AS11: 809.89996 | AT11: 937.54038 | AU11: 912.18298 | AV11: =SUM(F11:Q11) | AW11: =SUM(R11:AC11) | AX11: =SUM(AD11:AO11) | AY11: =SUM(AH11:AS11) | AZ11: =SUM(AJ11:AU11) | BB11: =IFERROR(F11/F$117,0) | BC11: =IFERROR(G11/G$117,0) | BD11: =IFERROR(H11/H$117,0) | BE11: =IFERROR(I11/I$117,0) | BF11: =IFERROR(J11/J$117,0) | BG11: =IFERROR(K11/K$117,0) | BH11: =IFERROR(L11/L$117,0) | BI11: =IFERROR(M11/M$117,0) | ... CV11: =IFERROR(AZ11/AZ$117,0) | CX11: 8174.7092
C12: Merchant services debit transaction revenue | D12: 411103 | E12: =CONCATENATE(D12," - ",C12) | AP12: 281.37015 | AQ12: 305.48489 | AR12: 352.35083 | AS12: 354.12246 | AT12: 403.47647 | AU12: 412.9241 | AV12: =SUM(F12:Q12) | AW12: =SUM(R12:AC12) | AX12: =SUM(AD12:AO12) | AY12: =SUM(AH12:AS12) | AZ12: =SUM(AJ12:AU12) | BB12: =IFERROR(F12/F$117,0) | BC12: =IFERROR(G12/G$117,0) | BD12: =IFERROR(H12/H$117,0) | BE12: =IFERROR(I12/I$117,0) | BF12: =IFERROR(J12/J$117,0) | BG12: =IFERROR(K12/K$117,0) | BH12: =IFERROR(L12/L$117,0) | BI12: =IFERROR(M12/M$117,0) | ... CV12: =IFERROR(AZ12/AZ$117,0) | CX12: 1201.2717
C13: Ifrs 15 adj to processing | D13: 411119 | E13: =CONCATENATE(D13," - ",C13) | AP13: 154 | AQ13: 148 | AR13: 165 | AS13: -6 | AT13: -5 | AU13: -6 | AV13: =SUM(F13:Q13) | AW13: =SUM(R13:AC13) | AX13: =SUM(AD13:AO13) | AY13: =SUM(AH13:AS13) | AZ13: =SUM(AJ13:AU13) | BB13: =IFERROR(F13/F$117,0) | BC13: =IFERROR(G13/G$117,0) | BD13: =IFERROR(H13/H$117,0) | BE13: =IFERROR(I13/I$117,0) | BF13: =IFERROR(J13/J$117,0) | BG13: =IFERROR(K13/K$117,0) | BH13: =IFERROR(L13/L$117,0) | BI13: =IFERROR(M13/M$117,0) | ... CV13: =IFERROR(AZ13/AZ$117,0) | CX13: -1165.6463
C14: Mobile provisioning & lcm-transaction fees | D14: 411116 | E14: =CONCATENATE(D14," - ",C14) | AP14: 115.33668 | AQ14: 149.83268 | AR14: 119.67113 | AS14: 139.75918 | AT14: 125.22612 | AU14: 128.09291 | AV14: =SUM(F14:Q14) | AW14: =SUM(R14:AC14) | AX14: =SUM(AD14:AO14) | AY14: =SUM(AH14:AS14) | AZ14: =SUM(AJ14:AU14) | BB14: =IFERROR(F14/F$117,0) | BC14: =IFERROR(G14/G$117,0) | BD14: =IFERROR(H14/H$117,0) | BE14: =IFERROR(I14/I$117,0) | BF14: =IFERROR(J14/J$117,0) | BG14: =IFERROR(K14/K$117,0) | BH14: =IFERROR(L14/L$117,0) | BI14: =IFERROR(M14/M$117,0) | ... CV14: =IFERROR(AZ14/AZ$117,0) | CX14: 893.60288
C15: Interest income-other | D15: ADJ | E15: =CONCATENATE(D15," - ",C15) | AP15: 0 | AQ15: 0 | AR15: 0 | AS15: 0 | AT15: 0 | AU15: 0 | AV15: =SUM(F15:Q15) | AW15: =SUM(R15:AC15) | AX15: =SUM(AD15:AO15) | AY15: =SUM(AH15:AS15) | AZ15: =SUM(AJ15:AU15) | BB15: =IFERROR(F15/F$117,0) | BC15: =IFERROR(G15/G$117,0) | BD15: =IFERROR(H15/H$117,0) | BE15: =IFERROR(I15/I$117,0) | BF15: =IFERROR(J15/J$117,0) | BG15: =IFERROR(K15/K$117,0) | BH15: =IFERROR(L15/L$117,0) | BI15: =IFERROR(M15/M$117,0) | ... CV15: =IFERROR(AZ15/AZ$117,0) | CX15: 0
C16: Png transactions revenue - scd | D16: 411102 | E16: =CONCATENATE(D16," - ",C16) | AP16: 88.06383 | AQ16: 86.56468 | AR16: 95.66202 | AS16: 98.0696 | AT16: 106.39485 | AU16: 102.30183 | AV16: =SUM(F16:Q16) | AW16: =SUM(R16:AC16) | AX16: =SUM(AD16:AO16) | AY16: =SUM(AH16:AS16) | AZ16: =SUM(AJ16:AU16) | BB16: =IFERROR(F16/F$117,0) | BC16: =IFERROR(G16/G$117,0) | BD16: =IFERROR(H16/H$117,0) | BE16: =IFERROR(I16/I$117,0) | BF16: =IFERROR(J16/J$117,0) | BG16: =IFERROR(K16/K$117,0) | BH16: =IFERROR(L16/L$117,0) | BI16: =IFERROR(M16/M$117,0) | ... CV16: =IFERROR(AZ16/AZ$117,0) | CX16: 1224.1593
C17: Caf revenue | D17: 411106 | E17: =CONCATENATE(D17," - ",C17) | AP17: 69.43003 | AQ17: 67.88132 | AR17: 68.78232 | AS17: 69.37502 | AT17: 76.40918 | AU17: 74.28575 | AV17: =SUM(F17:Q17) | AW17: =SUM(R17:AC17) | AX17: =SUM(AD17:AO17) | AY17: =SUM(AH17:AS17) | AZ17: =SUM(AJ17:AU17) | BB17: =IFERROR(F17/F$117,0) | BC17: =IFERROR(G17/G$117,0) | BD17: =IFERROR(H17/H$117,0) | BE17: =IFERROR(I17/I$117,0) | BF17: =IFERROR(J17/J$117,0) | BG17: =IFERROR(K17/K$117,0) | BH17: =IFERROR(L17/L$117,0) | BI17: =IFERROR(M17/M$117,0) | ... CV17: =IFERROR(AZ17/AZ$117,0) | CX17: 755.79962
C18: Reporting & other fees | D18: 411107 | E18: =CONCATENATE(D18," - ",C18) | AP18: 51.54635 | AQ18: 69.06635 | AR18: 58.06635 | AS18: 58.06635 | AT18: 70.04335 | AU18: 71.83735 | AV18: =SUM(F18:Q18) | AW18: =SUM(R18:AC18) | AX18: =SUM(AD18:AO18) | AY18: =SUM(AH18:AS18) | AZ18: =SUM(AJ18:AU18) | BB18: =IFERROR(F18/F$117,0) | BC18: =IFERROR(G18/G$117,0) | BD18: =IFERROR(H18/H$117,0) | BE18: =IFERROR(I18/I$117,0) | BF18: =IFERROR(J18/J$117,0) | BG18: =IFERROR(K18/K$117,0) | BH18: =IFERROR(L18/L$117,0) | BI18: =IFERROR(M18/M$117,0) | ... CV18: =IFERROR(AZ18/AZ$117,0) | CX18: 426.52635
C19: Host connection revenue | D19: 411114 | E19: =CONCATENATE(D19," - ",C19) | AP19: 35.4445 | AQ19: 35.4445 | AR19: 36.3445 | AS19: 35.4445 | AT19: 42.8945 | AU19: 42.8945 | AV19: =SUM(F19:Q19) | AW19: =SUM(R19:AC19) | AX19: =SUM(AD19:AO19) | AY19: =SUM(AH19:AS19) | AZ19: =SUM(AJ19:AU19) | BB19: =IFERROR(F19/F$117,0) | BC19: =IFERROR(G19/G$117,0) | BD19: =IFERROR(H19/H$117,0) | BE19: =IFERROR(I19/I$117,0) | BF19: =IFERROR(J19/J$117,0) | BG19: =IFERROR(K19/K$117,0) | BH19: =IFERROR(L19/L$117,0) | BI19: =IFERROR(M19/M$117,0) | ... CV19: =IFERROR(AZ19/AZ$117,0) | CX19: 489.934
C20: Merchant services credit transaction revenue | D20: 411104 | E20: =CONCATENATE(D20," - ",C20) | AP20: 28.96289 | AQ20: 31.63188 | AR20: 33.07393 | AS20: 31.66428 | AT20: 34.05895 | AU20: 31.34656 | AV20: =SUM(F20:Q20) | AW20: =SUM(R20:AC20) | AX20: =SUM(AD20:AO20) | AY20: =SUM(AH20:AS20) | AZ20: =SUM(AJ20:AU20) | BB20: =IFERROR(F20/F$117,0) | BC20: =IFERROR(G20/G$117,0) | BD20: =IFERROR(H20/H$117,0) | BE20: =IFERROR(I20/I$117,0) | BF20: =IFERROR(J20/J$117,0) | BG20: =IFERROR(K20/K$117,0) | BH20: =IFERROR(L20/L$117,0) | BI20: =IFERROR(M20/M$117,0) | ... CV20: =IFERROR(AZ20/AZ$117,0) | CX20: 124.66668
C21: E hub money transfer | D21: 411102 | E21: =CONCATENATE(D21," - ",C21) | AP21: 51.26563 | AQ21: 56.11116 | AR21: 70.15838 | AS21: 53.22705 | AT21: 102.35467 | AU21: 93.21207 | AV21: =SUM(F21:Q21) | AW21: =SUM(R21:AC21) | AX21: =SUM(AD21:AO21) | AY21: =SUM(AH21:AS21) | AZ21: =SUM(AJ21:AU21) | BB21: =IFERROR(F21/F$117,0) | BC21: =IFERROR(G21/G$117,0) | BD21: =IFERROR(H21/H$117,0) | BE21: =IFERROR(I21/I$117,0) | BF21: =IFERROR(J21/J$117,0) | BG21: =IFERROR(K21/K$117,0) | BH21: =IFERROR(L21/L$117,0) | BI21: =IFERROR(M21/M$117,0) | ... CV21: =IFERROR(AZ21/AZ$117,0) | CX21: 0
C22: Switch fee - in-app transactions | D22: 411110 | E22: =CONCATENATE(D22," - ",C22) | AP22: 10.31596 | AQ22: 9.119 | AR22: 9.98405 | AS22: 9.83068 | AT22: 9.77906 | AU22: 9.80628 | AV22: =SUM(F22:Q22) | AW22: =SUM(R22:AC22) | AX22: =SUM(AD22:AO22) | AY22: =SUM(AH22:AS22) | AZ22: =SUM(AJ22:AU22) | BB22: =IFERROR(F22/F$117,0) | BC22: =IFERROR(G22/G$117,0) | BD22: =IFERROR(H22/H$117,0) | BE22: =IFERROR(I22/I$117,0) | BF22: =IFERROR(J22/J$117,0) | BG22: =IFERROR(K22/K$117,0) | BH22: =IFERROR(L22/L$117,0) | BI22: =IFERROR(M22/M$117,0) | ... CV22: =IFERROR(AZ22/AZ$117,0) | CX22: 57.49521
C23: White-label atm transaction revenue (2018-) | D23: 411102 | E23: =CONCATENATE(D23," - ",C23) | AP23: 3.23509 | AQ23: 3.12583 | AR23: 3.44118 | AS23: 3.34088 | AT23: 3.55673 | AU23: 3.37948 | AV23: =SUM(F23:Q23) | AW23: =SUM(R23:AC23) | AX23: =SUM(AD23:AO23) | AY23: =SUM(AH23:AS23) | AZ23: =SUM(AJ23:AU23) | BB23: =IFERROR(F23/F$117,0) | BC23: =IFERROR(G23/G$117,0) | BD23: =IFERROR(H23/H$117,0) | BE23: =IFERROR(I23/I$117,0) | BF23: =IFERROR(J23/J$117,0) | BG23: =IFERROR(K23/K$117,0) | BH23: =IFERROR(L23/L$117,0) | BI23: =IFERROR(M23/M$117,0) | ... CV23: =IFERROR(AZ23/AZ$117,0) | CX23: 148.01661
C24: Other transaction related revenue | D24: 411105 | E24: =CONCATENATE(D24," - ",C24) | AP24: 1.99202 | AQ24: 2.75449 | AR24: 2.73307 | AS24: 2.06804 | AT24: 1.12552 | AU24: 2.11906 | AV24: =SUM(F24:Q24) | AW24: =SUM(R24:AC24) | AX24: =SUM(AD24:AO24) | AY24: =SUM(AH24:AS24) | AZ24: =SUM(AJ24:AU24) | BB24: =IFERROR(F24/F$117,0) | BC24: =IFERROR(G24/G$117,0) | BD24: =IFERROR(H24/H$117,0) | BE24: =IFERROR(I24/I$117,0) | BF24: =IFERROR(J24/J$117,0) | BG24: =IFERROR(K24/K$117,0) | BH24: =IFERROR(L24/L$117,0) | BI24: =IFERROR(M24/M$117,0) | ... CV24: =IFERROR(AZ24/AZ$117,0) | CX24: 116.4272
C25: Contractual minimum fees | D25: 411109 | E25: =CONCATENATE(D25," - ",C25) | AP25: 4.41285 | AQ25: 5.89969 | AR25: 3.73611 | AS25: 4.04702 | AT25: 7.12328 | AU25: 7.85363 | AV25: =SUM(F25:Q25) | AW25: =SUM(R25:AC25) | AX25: =SUM(AD25:AO25) | AY25: =SUM(AH25:AS25) | AZ25: =SUM(AJ25:AU25) | BB25: =IFERROR(F25/F$117,0) | BC25: =IFERROR(G25/G$117,0) | BD25: =IFERROR(H25/H$117,0) | BE25: =IFERROR(I25/I$117,0) | BF25: =IFERROR(J25/J$117,0) | BG25: =IFERROR(K25/K$117,0) | BH25: =IFERROR(L25/L$117,0) | BI25: =IFERROR(M25/M$117,0) | ... CV25: =IFERROR(AZ25/AZ$117,0) | CX25: 39.8584
C26: Merchant batch close fees | D26: 411111 | E26: =CONCATENATE(D26," - ",C26) | AP26: 0.0005 | AQ26: -5e-05 | AR26: 0 | AS26: 0 | AT26: 0 | AU26: 0 | AV26: =SUM(F26:Q26) | AW26: =SUM(R26:AC26) | AX26: =SUM(AD26:AO26) | AY26: =SUM(AH26:AS26) | AZ26: =SUM(AJ26:AU26) | BB26: =IFERROR(F26/F$117,0) | BC26: =IFERROR(G26/G$117,0) | BD26: =IFERROR(H26/H$117,0) | BE26: =IFERROR(I26/I$117,0) | BF26: =IFERROR(J26/J$117,0) | BG26: =IFERROR(K26/K$117,0) | BH26: =IFERROR(L26/L$117,0) | BI26: =IFERROR(M26/M$117,0) | ... CV26: =IFERROR(AZ26/AZ$117,0) | CX26: 6.70943
C27: Merchant residual revenue - square | D27: 411138 | E27: =CONCATENATE(D27," - ",C27) | AP27: 0 | AQ27: 0 | AR27: 0 | AS27: 0 | AT27: 0 | AU27: 0 | AV27: =SUM(F27:Q27) | AW27: =SUM(R27:AC27) | AX27: =SUM(AD27:AO27) | AY27: =SUM(AH27:AS27) | AZ27: =SUM(AJ27:AU27) | BB27: =IFERROR(F27/F$117,0) | BC27: =IFERROR(G27/G$117,0) | BD27: =IFERROR(H27/H$117,0) | BE27: =IFERROR(I27/I$117,0) | BF27: =IFERROR(J27/J$117,0) | BG27: =IFERROR(K27/K$117,0) | BH27: =IFERROR(L27/L$117,0) | BI27: =IFERROR(M27/M$117,0) | ... CV27: =IFERROR(AZ27/AZ$117,0) | CX27: 0.77818
... C29: Settlement services | D29: 411112 | E29: =CONCATENATE(D29," - ",C29) | AP29: 24.475 | AQ29: 24.2375 | AR29: 24.3125 | AS29: 24.3125 | AT29: 24.425 | AU29: 24.6125 | AV29: =SUM(F29:Q29) | AW29: =SUM(R29:AC29) | AX29: =SUM(AD29:AO29) | AY29: =SUM(AH29:AS29) | AZ29: =SUM(AJ29:AU29) | BB29: =IFERROR(F29/F$117,0) | BC29: =IFERROR(G29/G$117,0) | BD29: =IFERROR(H29/H$117,0) | BE29: =IFERROR(I29/I$117,0) | BF29: =IFERROR(J29/J$117,0) | BG29: =IFERROR(K29/K$117,0) | BH29: =IFERROR(L29/L$117,0) | BI29: =IFERROR(M29/M$117,0) | ... CV29: =IFERROR(AZ29/AZ$117,0) | CX29: 195.76774
C30: Processing services revenue | AP30: =SUM(AP10:AP29) | AQ30: =SUM(AQ10:AQ29) | AR30: =SUM(AR10:AR29) | AS30: =SUM(AS10:AS29) | AT30: =SUM(AT10:AT29) | AU30: =SUM(AU10:AU29) | AV30: =SUM(AV10:AV29) | AW30: =SUM(AW10:AW29) | ... AZ30: =SUM(AZ10:AZ29) | BB30: =IFERROR(F30/F$117,0) | BC30: =IFERROR(G30/G$117,0) | BD30: =IFERROR(H30/H$117,0) | BE30: =IFERROR(I30/I$117,0) | BF30: =IFERROR(J30/J$117,0) | BG30: =IFERROR(K30/K$117,0) | BH30: =IFERROR(L30/L$117,0) | BI30: =IFERROR(M30/M$117,0) | ... CV30: =IFERROR(AZ30/AZ$117,0) | CX30: =SUM(CX10:CX29)
C31: Card manufacture for fi - cci | D31: 411229 | E31: =CONCATENATE(D31," - ",C31) | AP31: 646.50429 | AQ31: 1201.2549 | AR31: 189.04252 | AS31: 369.16721 | AT31: 215.71517 | AU31: 278.77138 | AV31: =SUM(F31:Q31) | AW31: =SUM(R31:AC31) | AX31: =SUM(AD31:AO31) | AY31: =SUM(AH31:AS31) | AZ31: =SUM(AJ31:AU31) | BB31: =IFERROR(F31/F$117,0) | BC31: =IFERROR(G31/G$117,0) | BD31: =IFERROR(H31/H$117,0) | BE31: =IFERROR(I31/I$117,0) | BF31: =IFERROR(J31/J$117,0) | BG31: =IFERROR(K31/K$117,0) | BH31: =IFERROR(L31/L$117,0) | BI31: =IFERROR(M31/M$117,0) | ... CV31: =IFERROR(AZ31/AZ$117,0) | CX31: 2892.7684
C32: Card personalization revenue | D32: 411228 | E32: =CONCATENATE(D32," - ",C32) | AP32: 102.58528 | AQ32: 145.02828 | AR32: 76.33061 | AS32: 128.66676 | AT32: 188.5095 | AU32: 109.32997 | AV32: =SUM(F32:Q32) | AW32: =SUM(R32:AC32) | AX32: =SUM(AD32:AO32) | AY32: =SUM(AH32:AS32) | AZ32: =SUM(AJ32:AU32) | BB32: =IFERROR(F32/F$117,0) | BC32: =IFERROR(G32/G$117,0) | BD32: =IFERROR(H32/H$117,0) | BE32: =IFERROR(I32/I$117,0) | BF32: =IFERROR(J32/J$117,0) | BG32: =IFERROR(K32/K$117,0) | BH32: =IFERROR(L32/L$117,0) | BI32: =IFERROR(M32/M$117,0) | ... CV32: =IFERROR(AZ32/AZ$117,0) | CX32: 528.75455
C33: Card collateral & pin mailer | D33: 411227 | E33: =CONCATENATE(D33," - ",C33) | AP33: 51.5036 | AQ33: 50.89901 | AR33: 40.20927 | AS33: 66.18783 | AT33: 128.89512 | AU33: 57.44058 | AV33: =SUM(F33:Q33) | AW33: =SUM(R33:AC33) | AX33: =SUM(AD33:AO33) | AY33: =SUM(AH33:AS33) | AZ33: =SUM(AJ33:AU33) | BB33: =IFERROR(F33/F$117,0) | BC33: =IFERROR(G33/G$117,0) | BD33: =IFERROR(H33/H$117,0) | BE33: =IFERROR(I33/I$117,0) | BF33: =IFERROR(J33/J$117,0) | BG33: =IFERROR(K33/K$117,0) | BH33: =IFERROR(L33/L$117,0) | BI33: =IFERROR(M33/M$117,0) | ... CV33: =IFERROR(AZ33/AZ$117,0) | CX33: 374.82141
C34: Cards order processing & report fee | D34: 411226 | E34: =CONCATENATE(D34," - ",C34) | AP34: 1.29789 | AQ34: 12.29592 | AR34: 12.29592 | AS34: 12.29592 | AT34: 12.29592 | AU34: 12.29592 | AV34: =SUM(F34:Q34) | AW34: =SUM(R34:AC34) | AX34: =SUM(AD34:AO34) | AY34: =SUM(AH34:AS34) | AZ34: =SUM(AJ34:AU34) | BB34: =IFERROR(F34/F$117,0) | BC34: =IFERROR(G34/G$117,0) | BD34: =IFERROR(H34/H$117,0) | BE34: =IFERROR(I34/I$117,0) | BF34: =IFERROR(J34/J$117,0) | BG34: =IFERROR(K34/K$117,0) | BH34: =IFERROR(L34/L$117,0) | BI34: =IFERROR(M34/M$117,0) | ... CV34: =IFERROR(AZ34/AZ$117,0) | CX34: 175.94402
C35: Cards ancillary services | D35: 411224 | E35: =CONCATENATE(D35," - ",C35) | AP35: 10.03042 | AQ35: 4.39082 | AR35: 3.19735 | AS35: 5.70818 | AT35: 2.38351 | AU35: 4.62558 | AV35: =SUM(F35:Q35) | AW35: =SUM(R35:AC35) | AX35: =SUM(AD35:AO35) | AY35: =SUM(AH35:AS35) | AZ35: =SUM(AJ35:AU35) | BB35: =IFERROR(F35/F$117,0) | BC35: =IFERROR(G35/G$117,0) | BD35: =IFERROR(H35/H$117,0) | BE35: =IFERROR(I35/I$117,0) | BF35: =IFERROR(J35/J$117,0) | BG35: =IFERROR(K35/K$117,0) | BH35: =IFERROR(L35/L$117,0) | BI35: =IFERROR(M35/M$117,0) | ... CV35: =IFERROR(AZ35/AZ$117,0) | CX35: 2.715
C36: Dma - program fee | D36: 411222 | E36: =CONCATENATE(D36," - ",C36) | AP36: 31.24389 | AQ36: 4.99909 | AR36: 4.99983 | AS36: 6.66465 | AT36: 5.83225 | AU36: 6.24882 | AV36: =SUM(F36:Q36) | AW36: =SUM(R36:AC36) | AX36: =SUM(AD36:AO36) | AY36: =SUM(AH36:AS36) | AZ36: =SUM(AJ36:AU36) | BB36: =IFERROR(F36/F$117,0) | BC36: =IFERROR(G36/G$117,0) | BD36: =IFERROR(H36/H$117,0) | BE36: =IFERROR(I36/I$117,0) | BF36: =IFERROR(J36/J$117,0) | BG36: =IFERROR(K36/K$117,0) | BH36: =IFERROR(L36/L$117,0) | BI36: =IFERROR(M36/M$117,0) | ... CV36: =IFERROR(AZ36/AZ$117,0) | CX36: 0
C37: Card services ifrs15 py adj- cards | D37: 411217 | E37: =CONCATENATE(D37," - ",C37) | AP37: 0 | AQ37: 0 | AR37: 0 | AS37: 0 | AT37: 0 | AU37: 0 | AV37: =SUM(F37:Q37) | AW37: =SUM(R37:AC37) | AX37: =SUM(AD37:AO37) | AY37: =SUM(AH37:AS37) | AZ37: =SUM(AJ37:AU37) | BB37: =IFERROR(F37/F$117,0) | BC37: =IFERROR(G37/G$117,0) | BD37: =IFERROR(H37/H$117,0) | BE37: =IFERROR(I37/I$117,0) | BF37: =IFERROR(J37/J$117,0) | BG37: =IFERROR(K37/K$117,0) | BH37: =IFERROR(L37/L$117,0) | BI37: =IFERROR(M37/M$117,0) | ... CV37: =IFERROR(AZ37/AZ$117,0) | CX37: 30.54996
C38: Card issuance revenue - cards | AP38: =SUM(AP31:AP37) | AQ38: =SUM(AQ31:AQ37) | AR38: =SUM(AR31:AR37) | AS38: =SUM(AS31:AS37) | AT38: =SUM(AT31:AT37) | AU38: =SUM(AU31:AU37) | AV38: =SUM(AV31:AV37) | AW38: =SUM(AW31:AW37) | ... AZ38: =SUM(AZ31:AZ37) | BB38: =IFERROR(F38/F$117,0) | BC38: =IFERROR(G38/G$117,0) | BD38: =IFERROR(H38/H$117,0) | BE38: =IFERROR(I38/I$117,0) | BF38: =IFERROR(J38/J$117,0) | BG38: =IFERROR(K38/K$117,0) | BH38: =IFERROR(L38/L$117,0) | BI38: =IFERROR(M38/M$117,0) | ... CV38: =IFERROR(AZ38/AZ$117,0) | CX38: =SUM(CX31:CX37)
C39: Dma - mastercard network interchange & switch fees | D39: 483122 | E39: =CONCATENATE(D39," - ",C39) | AP39: 194.23424 | AQ39: 285.20116 | AR39: 147.54237 | AS39: 154.83058 | AT39: 147.54907 | AU39: 175.47059 | AV39: =SUM(F39:Q39) | AW39: =SUM(R39:AC39) | AX39: =SUM(AD39:AO39) | AY39: =SUM(AH39:AS39) | AZ39: =SUM(AJ39:AU39) | BB39: =IFERROR(F39/F$117,0) | BC39: =IFERROR(G39/G$117,0) | BD39: =IFERROR(H39/H$117,0) | BE39: =IFERROR(I39/I$117,0) | BF39: =IFERROR(J39/J$117,0) | BG39: =IFERROR(K39/K$117,0) | BH39: =IFERROR(L39/L$117,0) | BI39: =IFERROR(M39/M$117,0) | ... CV39: =IFERROR(AZ39/AZ$117,0) | CX39: 0
C40: Reimbursed exp - mastercard interchg & switch fees | D40: 483106 | E40: =CONCATENATE(D40," - ",C40) | AP40: 103.22214 | AQ40: 111.2833 | AR40: 108.69878 | AS40: 86.98942 | AT40: 80.81704 | AU40: 73.01641 | AV40: =SUM(F40:Q40) | AW40: =SUM(R40:AC40) | AX40: =SUM(AD40:AO40) | AY40: =SUM(AH40:AS40) | AZ40: =SUM(AJ40:AU40) | BB40: =IFERROR(F40/F$117,0) | BC40: =IFERROR(G40/G$117,0) | BD40: =IFERROR(H40/H$117,0) | BE40: =IFERROR(I40/I$117,0) | BF40: =IFERROR(J40/J$117,0) | BG40: =IFERROR(K40/K$117,0) | BH40: =IFERROR(L40/L$117,0) | BI40: =IFERROR(M40/M$117,0) | ... CV40: =IFERROR(AZ40/AZ$117,0) | CX40: 717.68944
C41: Reimbursed expenses - postage | D41: 483102 | E41: =CONCATENATE(D41," - ",C41) | AP41: 62.19036 | AQ41: 41.49228 | AR41: 42.53087 | AS41: 53.98862 | AT41: 49.99818 | AU41: 66.60064 | AV41: =SUM(F41:Q41) | AW41: =SUM(R41:AC41) | AX41: =SUM(AD41:AO41) | AY41: =SUM(AH41:AS41) | AZ41: =SUM(AJ41:AU41) | BB41: =IFERROR(F41/F$117,0) | BC41: =IFERROR(G41/G$117,0) | BD41: =IFERROR(H41/H$117,0) | BE41: =IFERROR(I41/I$117,0) | BF41: =IFERROR(J41/J$117,0) | BG41: =IFERROR(K41/K$117,0) | BH41: =IFERROR(L41/L$117,0) | BI41: =IFERROR(M41/M$117,0) | ... CV41: =IFERROR(AZ41/AZ$117,0) | CX41: 403.81841
C42: Reimbursed expenses - freight | D42: 483103 | E42: =CONCATENATE(D42," - ",C42) | AP42: 51.96329 | AQ42: 39.69755 | AR42: 63.51417 | AS42: 42.43311 | AT42: 43.62154 | AU42: 41.46473 | AV42: =SUM(F42:Q42) | AW42: =SUM(R42:AC42) | AX42: =SUM(AD42:AO42) | AY42: =SUM(AH42:AS42) | AZ42: =SUM(AJ42:AU42) | BB42: =IFERROR(F42/F$117,0) | BC42: =IFERROR(G42/G$117,0) | BD42: =IFERROR(H42/H$117,0) | BE42: =IFERROR(I42/I$117,0) | BF42: =IFERROR(J42/J$117,0) | BG42: =IFERROR(K42/K$117,0) | BH42: =IFERROR(L42/L$117,0) | BI42: =IFERROR(M42/M$117,0) | ... CV42: =IFERROR(AZ42/AZ$117,0) | CX42: 254.74278
C43: Reimbursed exp - network interchg & swich fees | D43: 483106 | E43: =CONCATENATE(D43," - ",C43) | AP43: 68.69943 | AQ43: 67.85021 | AR43: 81.48068 | AS43: 84.52141 | AT43: 123.10139 | AU43: 121.53339 | AV43: =SUM(F43:Q43) | AW43: =SUM(R43:AC43) | AX43: =SUM(AD43:AO43) | AY43: =SUM(AH43:AS43) | AZ43: =SUM(AJ43:AU43) | BB43: =IFERROR(F43/F$117,0) | BC43: =IFERROR(G43/G$117,0) | BD43: =IFERROR(H43/H$117,0) | BE43: =IFERROR(I43/I$117,0) | BF43: =IFERROR(J43/J$117,0) | BG43: =IFERROR(K43/K$117,0) | BH43: =IFERROR(L43/L$117,0) | BI43: =IFERROR(M43/M$117,0) | ... CV43: =IFERROR(AZ43/AZ$117,0) | CX43: 90.31485
C44: Dma - admin fees for reimbursed exp | D44: 483120 | E44: =CONCATENATE(D44," - ",C44) | AP44: 51.58747 | AQ44: 75.19483 | AR44: 40.75415 | AS44: 42.01718 | AT44: 39.80821 | AU44: 52.27275 | AV44: =SUM(F44:Q44) | AW44: =SUM(R44:AC44) | AX44: =SUM(AD44:AO44) | AY44: =SUM(AH44:AS44) | AZ44: =SUM(AJ44:AU44) | BB44: =IFERROR(F44/F$117,0) | BC44: =IFERROR(G44/G$117,0) | BD44: =IFERROR(H44/H$117,0) | BE44: =IFERROR(I44/I$117,0) | BF44: =IFERROR(J44/J$117,0) | BG44: =IFERROR(K44/K$117,0) | BH44: =IFERROR(L44/L$117,0) | BI44: =IFERROR(M44/M$117,0) | ... CV44: =IFERROR(AZ44/AZ$117,0) | CX44: 0
C45: Admin fees for reimbursed exp | D45: 483109 | E45: =CONCATENATE(D45," - ",C45) | AP45: 28.18649 | AQ45: 29.96856 | AR45: 30.72195 | AS45: 24.66541 | AT45: 23.15324 | AU45: 22.57789 | AV45: =SUM(F45:Q45) | AW45: =SUM(R45:AC45) | AX45: =SUM(AD45:AO45) | AY45: =SUM(AH45:AS45) | AZ45: =SUM(AJ45:AU45) | BB45: =IFERROR(F45/F$117,0) | BC45: =IFERROR(G45/G$117,0) | BD45: =IFERROR(H45/H$117,0) | BE45: =IFERROR(I45/I$117,0) | BF45: =IFERROR(J45/J$117,0) | BG45: =IFERROR(K45/K$117,0) | BH45: =IFERROR(L45/L$117,0) | BI45: =IFERROR(M45/M$117,0) | ... CV45: =IFERROR(AZ45/AZ$117,0) | CX45: 212.47777
C46: Reimbursed expenses - mc membership fees | D46: 483112 | E46: =CONCATENATE(D46," - ",C46) | AP46: 18.47521 | AQ46: 18.6752 | AR46: 18.71882 | AS46: 18.84242 | AT46: 18.85223 | AU46: 27.52974 | AV46: =SUM(F46:Q46) | AW46: =SUM(R46:AC46) | AX46: =SUM(AD46:AO46) | AY46: =SUM(AH46:AS46) | AZ46: =SUM(AJ46:AU46) | BB46: =IFERROR(F46/F$117,0) | BC46: =IFERROR(G46/G$117,0) | BD46: =IFERROR(H46/H$117,0) | BE46: =IFERROR(I46/I$117,0) | BF46: =IFERROR(J46/J$117,0) | BG46: =IFERROR(K46/K$117,0) | BH46: =IFERROR(L46/L$117,0) | BI46: =IFERROR(M46/M$117,0) | ... CV46: =IFERROR(AZ46/AZ$117,0) | CX46: 240.56873
C47: Reimbured exp - csp fees exch- ficanex | D47: 483105 | E47: =CONCATENATE(D47," - ",C47) | AP47: 16.20229 | AQ47: 16.30745 | AR47: 17.90153 | AS47: 18.01065 | AT47: 19.11838 | AU47: 18.50089 | AV47: =SUM(F47:Q47) | AW47: =SUM(R47:AC47) | AX47: =SUM(AD47:AO47) | AY47: =SUM(AH47:AS47) | AZ47: =SUM(AJ47:AU47) | BB47: =IFERROR(F47/F$117,0) | BC47: =IFERROR(G47/G$117,0) | BD47: =IFERROR(H47/H$117,0) | BE47: =IFERROR(I47/I$117,0) | BF47: =IFERROR(J47/J$117,0) | BG47: =IFERROR(K47/K$117,0) | BH47: =IFERROR(L47/L$117,0) | BI47: =IFERROR(M47/M$117,0) | ... CV47: =IFERROR(AZ47/AZ$117,0) | CX47: 255.43595
C48: Vda - program onboardingi fee icici | D48: 483132 | E48: =CONCATENATE(D48," - ",C48) | AP48: 29.86524 | AQ48: 22.58642 | AR48: 28.48113 | AS48: 14.13374 | AT48: 28.00443 | AU48: 23.46979 | AV48: =SUM(F48:Q48) | AW48: =SUM(R48:AC48) | AX48: =SUM(AD48:AO48) | AY48: =SUM(AH48:AS48) | AZ48: =SUM(AJ48:AU48) | BB48: =IFERROR(F48/F$117,0) | BC48: =IFERROR(G48/G$117,0) | BD48: =IFERROR(H48/H$117,0) | BE48: =IFERROR(I48/I$117,0) | BF48: =IFERROR(J48/J$117,0) | BG48: =IFERROR(K48/K$117,0) | BH48: =IFERROR(L48/L$117,0) | BI48: =IFERROR(M48/M$117,0) | ... CV48: =IFERROR(AZ48/AZ$117,0) | CX48: 0
C49: Reimbursed expenses - others | D49: 483113 | E49: =CONCATENATE(D49," - ",C49) | AP49: 0.66454 | AQ49: 0.6683 | AR49: 0.67023 | AS49: 22.85901 | AT49: 5.67667 | AU49: 2.1785 | AV49: =SUM(F49:Q49) | AW49: =SUM(R49:AC49) | AX49: =SUM(AD49:AO49) | AY49: =SUM(AH49:AS49) | AZ49: =SUM(AJ49:AU49) | BB49: =IFERROR(F49/F$117,0) | BC49: =IFERROR(G49/G$117,0) | BD49: =IFERROR(H49/H$117,0) | BE49: =IFERROR(I49/I$117,0) | BF49: =IFERROR(J49/J$117,0) | BG49: =IFERROR(K49/K$117,0) | BH49: =IFERROR(L49/L$117,0) | BI49: =IFERROR(M49/M$117,0) | ... CV49: =IFERROR(AZ49/AZ$117,0) | CX49: 83.43153
C50: Dma - membership fee | D50: 483124 | E50: =CONCATENATE(D50," - ",C50) | AP50: 0 | AQ50: 81.5 | AR50: 12.54167 | AS50: 0 | AT50: 0 | AU50: 0 | AV50: =SUM(F50:Q50) | AW50: =SUM(R50:AC50) | AX50: =SUM(AD50:AO50) | AY50: =SUM(AH50:AS50) | AZ50: =SUM(AJ50:AU50) | BB50: =IFERROR(F50/F$117,0) | BC50: =IFERROR(G50/G$117,0) | BD50: =IFERROR(H50/H$117,0) | BE50: =IFERROR(I50/I$117,0) | BF50: =IFERROR(J50/J$117,0) | BG50: =IFERROR(K50/K$117,0) | BH50: =IFERROR(L50/L$117,0) | BI50: =IFERROR(M50/M$117,0) | ... CV50: =IFERROR(AZ50/AZ$117,0) | CX50: 0
... C62: Flash interchange tier fee | D62: 483104 | E62: =CONCATENATE(D62," - ",C62) | AP62: 0.00105 | AQ62: 0.00259 | AR62: 0.02482 | AS62: 0.08097 | AT62: 0.04396 | AU62: 0.05261 | AV62: =SUM(F62:Q62) | AW62: =SUM(R62:AC62) | AX62: =SUM(AD62:AO62) | AY62: =SUM(AH62:AS62) | AZ62: =SUM(AJ62:AU62) | BB62: =IFERROR(F62/F$117,0) | BC62: =IFERROR(G62/G$117,0) | BD62: =IFERROR(H62/H$117,0) | BE62: =IFERROR(I62/I$117,0) | BF62: =IFERROR(J62/J$117,0) | BG62: =IFERROR(K62/K$117,0) | BH62: =IFERROR(L62/L$117,0) | BI62: =IFERROR(M62/M$117,0) | ... CV62: =IFERROR(AZ62/AZ$117,0) | CX62: -5.86233
C63: Pass thru revenue | AP63: =SUM(AP39:AP62) | AQ63: =SUM(AQ39:AQ62) | AR63: =SUM(AR39:AR62) | AS63: =SUM(AS39:AS62) | AT63: =SUM(AT39:AT62) | AU63: =SUM(AU39:AU62) | AV63: =SUM(AV39:AV62) | AW63: =SUM(AW39:AW62) | ... AZ63: =SUM(AZ39:AZ62) | BB63: =IFERROR(F63/F$117,0) | BC63: =IFERROR(G63/G$117,0) | BD63: =IFERROR(H63/H$117,0) | BE63: =IFERROR(I63/I$117,0) | BF63: =IFERROR(J63/J$117,0) | BG63: =IFERROR(K63/K$117,0) | BH63: =IFERROR(L63/L$117,0) | BI63: =IFERROR(M63/M$117,0) | ... CV63: =IFERROR(AZ63/AZ$117,0) | CX63: =SUM(CX39:CX62)
C64: Professional service fees revenue | D64: 425101 | E64: =CONCATENATE(D64," - ",C64) | AP64: 116.54162 | AQ64: 182.58973 | AR64: 355.73413 | AS64: 284.14774 | AT64: 193.82576 | AU64: 259.26189 | AV64: =SUM(F64:Q64) | AW64: =SUM(R64:AC64) | AX64: =SUM(AD64:AO64) | AY64: =SUM(AH64:AS64) | AZ64: =SUM(AJ64:AU64) | BB64: =IFERROR(F64/F$117,0) | BC64: =IFERROR(G64/G$117,0) | BD64: =IFERROR(H64/H$117,0) | BE64: =IFERROR(I64/I$117,0) | BF64: =IFERROR(J64/J$117,0) | BG64: =IFERROR(K64/K$117,0) | BH64: =IFERROR(L64/L$117,0) | BI64: =IFERROR(M64/M$117,0) | ... CV64: =IFERROR(AZ64/AZ$117,0) | CX64: 2377.7729
C65: Professional service fees - major projects | D65: 425103 | E65: =CONCATENATE(D65," - ",C65) | AP65: 42.69456 | AQ65: 51.54425 | AR65: 56.43038 | AS65: 75.85172 | AT65: 84.11632 | AU65: 27.30781 | AV65: =SUM(F65:Q65) | AW65: =SUM(R65:AC65) | AX65: =SUM(AD65:AO65) | AY65: =SUM(AH65:AS65) | AZ65: =SUM(AJ65:AU65) | BB65: =IFERROR(F65/F$117,0) | BC65: =IFERROR(G65/G$117,0) | BD65: =IFERROR(H65/H$117,0) | BE65: =IFERROR(I65/I$117,0) | BF65: =IFERROR(J65/J$117,0) | BG65: =IFERROR(K65/K$117,0) | BH65: =IFERROR(L65/L$117,0) | BI65: =IFERROR(M65/M$117,0) | ... CV65: =IFERROR(AZ65/AZ$117,0) | CX65: 531.64608
C66: Dma - program onboarding fee | D66: 425110 | E66: =CONCATENATE(D66," - ",C66) | AP66: 0 | AQ66: 0 | AR66: 0 | AS66: 0 | AT66: 0 | AU66: 0 | AV66: =SUM(F66:Q66) | AW66: =SUM(R66:AC66) | AX66: =SUM(AD66:AO66) | AY66: =SUM(AH66:AS66) | AZ66: =SUM(AJ66:AU66) | BB66: =IFERROR(F66/F$117,0) | BC66: =IFERROR(G66/G$117,0) | BD66: =IFERROR(H66/H$117,0) | BE66: =IFERROR(I66/I$117,0) | BF66: =IFERROR(J66/J$117,0) | BG66: =IFERROR(K66/K$117,0) | BH66: =IFERROR(L66/L$117,0) | BI66: =IFERROR(M66/M$117,0) | ... CV66: =IFERROR(AZ66/AZ$117,0) | CX66: 25
C67: Visa debit affiliate - implementation fee | D67: 425112 | E67: =CONCATENATE(D67," - ",C67) | AP67: 0 | AQ67: 0 | AR67: 0 | AS67: 0 | AT67: 0 | AU67: 0 | AV67: =SUM(F67:Q67) | AW67: =SUM(R67:AC67) | AX67: =SUM(AD67:AO67) | AY67: =SUM(AH67:AS67) | AZ67: =SUM(AJ67:AU67) | BB67: =IFERROR(F67/F$117,0) | BC67: =IFERROR(G67/G$117,0) | BD67: =IFERROR(H67/H$117,0) | BE67: =IFERROR(I67/I$117,0) | BF67: =IFERROR(J67/J$117,0) | BG67: =IFERROR(K67/K$117,0) | BH67: =IFERROR(L67/L$117,0) | BI67: =IFERROR(M67/M$117,0) | ... CV67: =IFERROR(AZ67/AZ$117,0) | CX67: 0
C68: Professional services revenue | AP68: =SUM(AP64:AP67) | AQ68: =SUM(AQ64:AQ67) | AR68: =SUM(AR64:AR67) | AS68: =SUM(AS64:AS67) | AT68: =SUM(AT64:AT67) | AU68: =SUM(AU64:AU67) | AV68: =SUM(AV64:AV67) | AW68: =SUM(AW64:AW67) | ... AZ68: =SUM(AZ64:AZ67) | BB68: =IFERROR(F68/F$117,0) | BC68: =IFERROR(G68/G$117,0) | BD68: =IFERROR(H68/H$117,0) | BE68: =IFERROR(I68/I$117,0) | BF68: =IFERROR(J68/J$117,0) | BG68: =IFERROR(K68/K$117,0) | BH68: =IFERROR(L68/L$117,0) | BI68: =IFERROR(M68/M$117,0) | ... CV68: =IFERROR(AZ68/AZ$117,0) | CX68: =SUM(CX64:CX67)
C69: Atm express | D69: 414106 | E69: =CONCATENATE(D69," - ",C69) | AP69: 119.21931 | AQ69: 121.00431 | AR69: 119.81431 | AS69: 205.32763 | AT69: 129.2438 | AU69: 136.92603 | AV69: =SUM(F69:Q69) | AW69: =SUM(R69:AC69) | AX69: =SUM(AD69:AO69) | AY69: =SUM(AH69:AS69) | AZ69: =SUM(AJ69:AU69) | BB69: =IFERROR(F69/F$117,0) | BC69: =IFERROR(G69/G$117,0) | BD69: =IFERROR(H69/H$117,0) | BE69: =IFERROR(I69/I$117,0) | BF69: =IFERROR(J69/J$117,0) | BG69: =IFERROR(K69/K$117,0) | BH69: =IFERROR(L69/L$117,0) | BI69: =IFERROR(M69/M$117,0) | ... CV69: =IFERROR(AZ69/AZ$117,0) | CX69: 275.71101
C70: Atm incident management (im) | D70: 414104 | E70: =CONCATENATE(D70," - ",C70) | AP70: 78.82532 | AQ70: 78.83249 | AR70: 78.89695 | AS70: 78.43867 | AT70: 86.5695 | AU70: 86.51625 | AV70: =SUM(F70:Q70) | AW70: =SUM(R70:AC70) | AX70: =SUM(AD70:AO70) | AY70: =SUM(AH70:AS70) | AZ70: =SUM(AJ70:AU70) | BB70: =IFERROR(F70/F$117,0) | BC70: =IFERROR(G70/G$117,0) | BD70: =IFERROR(H70/H$117,0) | BE70: =IFERROR(I70/I$117,0) | BF70: =IFERROR(J70/J$117,0) | BG70: =IFERROR(K70/K$117,0) | BH70: =IFERROR(L70/L$117,0) | BI70: =IFERROR(M70/M$117,0) | ... CV70: =IFERROR(AZ70/AZ$117,0) | CX70: 893.2462
C71: Atm monitoring | D71: 414105 | E71: =CONCATENATE(D71," - ",C71) | AP71: 59.867 | AQ71: 59.867 | AR71: 59.46475 | AS71: 59.66475 | AT71: 75.929 | AU71: 50.7465 | AV71: =SUM(F71:Q71) | AW71: =SUM(R71:AC71) | AX71: =SUM(AD71:AO71) | AY71: =SUM(AH71:AS71) | AZ71: =SUM(AJ71:AU71) | BB71: =IFERROR(F71/F$117,0) | BC71: =IFERROR(G71/G$117,0) | BD71: =IFERROR(H71/H$117,0) | BE71: =IFERROR(I71/I$117,0) | BF71: =IFERROR(J71/J$117,0) | BG71: =IFERROR(K71/K$117,0) | BH71: =IFERROR(L71/L$117,0) | BI71: =IFERROR(M71/M$117,0) | ... CV71: =IFERROR(AZ71/AZ$117,0) | CX71: 780.71925
C72: Atm electronic journal | D72: 414102 | E72: =CONCATENATE(D72," - ",C72) | AP72: 23.24895 | AQ72: 23.46855 | AR72: 23.32635 | AS72: 23.08605 | AT72: 27.6519 | AU72: 23.6123 | AV72: =SUM(F72:Q72) | AW72: =SUM(R72:AC72) | AX72: =SUM(AD72:AO72) | AY72: =SUM(AH72:AS72) | AZ72: =SUM(AJ72:AU72) | BB72: =IFERROR(F72/F$117,0) | BC72: =IFERROR(G72/G$117,0) | BD72: =IFERROR(H72/H$117,0) | BE72: =IFERROR(I72/I$117,0) | BF72: =IFERROR(J72/J$117,0) | BG72: =IFERROR(K72/K$117,0) | BH72: =IFERROR(L72/L$117,0) | BI72: =IFERROR(M72/M$117,0) | ... CV72: =IFERROR(AZ72/AZ$117,0) | CX72: 224.9143
C73: Visa vap - atm monthly fee | D73: 414107 | E73: =CONCATENATE(D73," - ",C73) | AP73: 22.709 | AQ73: 22.192 | AR73: 22.25 | AS73: 22.072 | AT73: 21.987 | AU73: 22.005 | AV73: =SUM(F73:Q73) | AW73: =SUM(R73:AC73) | AX73: =SUM(AD73:AO73) | AY73: =SUM(AH73:AS73) | AZ73: =SUM(AJ73:AU73) | BB73: =IFERROR(F73/F$117,0) | BC73: =IFERROR(G73/G$117,0) | BD73: =IFERROR(H73/H$117,0) | BE73: =IFERROR(I73/I$117,0) | BF73: =IFERROR(J73/J$117,0) | BG73: =IFERROR(K73/K$117,0) | BH73: =IFERROR(L73/L$117,0) | BI73: =IFERROR(M73/M$117,0) | ... CV73: =IFERROR(AZ73/AZ$117,0) | CX73: 280.569
C74: Atm driving | D74: 414103 | E74: =CONCATENATE(D74," - ",C74) | AP74: 19.47375 | AQ74: 19.47375 | AR74: 19.438 | AS74: 19.358 | AT74: 21.05375 | AU74: 21.02075 | AV74: =SUM(F74:Q74) | AW74: =SUM(R74:AC74) | AX74: =SUM(AD74:AO74) | AY74: =SUM(AH74:AS74) | AZ74: =SUM(AJ74:AU74) | BB74: =IFERROR(F74/F$117,0) | BC74: =IFERROR(G74/G$117,0) | BD74: =IFERROR(H74/H$117,0) | BE74: =IFERROR(I74/I$117,0) | BF74: =IFERROR(J74/J$117,0) | BG74: =IFERROR(K74/K$117,0) | BH74: =IFERROR(L74/L$117,0) | BI74: =IFERROR(M74/M$117,0) | ... CV74: =IFERROR(AZ74/AZ$117,0) | CX74: 231.83675
C75: Atm - cdrs fees | D75: 414112 | E75: =CONCATENATE(D75," - ",C75) | AP75: 5.02084 | AQ75: 5.02084 | AR75: 5.02084 | AS75: 5.02084 | AT75: 5.02084 | AU75: 5.02084 | AV75: =SUM(F75:Q75) | AW75: =SUM(R75:AC75) | AX75: =SUM(AD75:AO75) | AY75: =SUM(AH75:AS75) | AZ75: =SUM(AJ75:AU75) | BB75: =IFERROR(F75/F$117,0) | BC75: =IFERROR(G75/G$117,0) | BD75: =IFERROR(H75/H$117,0) | BE75: =IFERROR(I75/I$117,0) | BF75: =IFERROR(J75/J$117,0) | BG75: =IFERROR(K75/K$117,0) | BH75: =IFERROR(L75/L$117,0) | BI75: =IFERROR(M75/M$117,0) | ... CV75: =IFERROR(AZ75/AZ$117,0) | CX75: 0
C76: Atm rkl | D76: 414101 | E76: =CONCATENATE(D76," - ",C76) | AP76: 4.318 | AQ76: 3.8855 | AR76: 3.914 | AS76: 7.248 | AT76: 7.1815 | AU76: 4.3795 | AV76: =SUM(F76:Q76) | AW76: =SUM(R76:AC76) | AX76: =SUM(AD76:AO76) | AY76: =SUM(AH76:AS76) | AZ76: =SUM(AJ76:AU76) | BB76: =IFERROR(F76/F$117,0) | BC76: =IFERROR(G76/G$117,0) | BD76: =IFERROR(H76/H$117,0) | BE76: =IFERROR(I76/I$117,0) | BF76: =IFERROR(J76/J$117,0) | BG76: =IFERROR(K76/K$117,0) | BH76: =IFERROR(L76/L$117,0) | BI76: =IFERROR(M76/M$117,0) | ... CV76: =IFERROR(AZ76/AZ$117,0) | CX76: 42.727
C77: Atm other | D77: 414120 | E77: =CONCATENATE(D77," - ",C77) | AP77: 2.364 | AQ77: 2.664 | AR77: 2.664 | AS77: 2.664 | AT77: 2.664 | AU77: 2.664 | AV77: =SUM(F77:Q77) | AW77: =SUM(R77:AC77) | AX77: =SUM(AD77:AO77) | AY77: =SUM(AH77:AS77) | AZ77: =SUM(AJ77:AU77) | BB77: =IFERROR(F77/F$117,0) | BC77: =IFERROR(G77/G$117,0) | BD77: =IFERROR(H77/H$117,0) | BE77: =IFERROR(I77/I$117,0) | BF77: =IFERROR(J77/J$117,0) | BG77: =IFERROR(K77/K$117,0) | BH77: =IFERROR(L77/L$117,0) | BI77: =IFERROR(M77/M$117,0) | ... CV77: =IFERROR(AZ77/AZ$117,0) | CX77: 36.21
C78: Vynamic view user fees | D78: 414111 | E78: =CONCATENATE(D78," - ",C78) | AP78: 0.1725 | AQ78: 0.1725 | AR78: 0.1725 | AS78: 0.1725 | AT78: 0.1725 | AU78: 0.1725 | AV78: =SUM(F78:Q78) | AW78: =SUM(R78:AC78) | AX78: =SUM(AD78:AO78) | AY78: =SUM(AH78:AS78) | AZ78: =SUM(AJ78:AU78) | BB78: =IFERROR(F78/F$117,0) | BC78: =IFERROR(G78/G$117,0) | BD78: =IFERROR(H78/H$117,0) | BE78: =IFERROR(I78/I$117,0) | BF78: =IFERROR(J78/J$117,0) | BG78: =IFERROR(K78/K$117,0) | BH78: =IFERROR(L78/L$117,0) | BI78: =IFERROR(M78/M$117,0) | ... CV78: =IFERROR(AZ78/AZ$117,0) | CX78: 2.461
C79: Atm managed services revenue | AP79: =SUM(AP69:AP78) | AQ79: =SUM(AQ69:AQ78) | AR79: =SUM(AR69:AR78) | AS79: =SUM(AS69:AS78) | AT79: =SUM(AT69:AT78) | AU79: =SUM(AU69:AU78) | AV79: =SUM(AV69:AV78) | AW79: =SUM(AW69:AW78) | ... AZ79: =SUM(AZ69:AZ78) | BB79: =IFERROR(F79/F$117,0) | BC79: =IFERROR(G79/G$117,0) | BD79: =IFERROR(H79/H$117,0) | BE79: =IFERROR(I79/I$117,0) | BF79: =IFERROR(J79/J$117,0) | BG79: =IFERROR(K79/K$117,0) | BH79: =IFERROR(L79/L$117,0) | BI79: =IFERROR(M79/M$117,0) | ... CV79: =IFERROR(AZ79/AZ$117,0) | CX79: =SUM(CX69:CX78)
C80: Fraud services revenue - aci prm revenue | D80: 411325 | E80: =CONCATENATE(D80," - ",C80) | AP80: 176.98753 | AQ80: 174.42525 | AR80: 175.37224 | AS80: 175.67638 | AT80: 178.68712 | AU80: 177.18716 | AV80: =SUM(F80:Q80) | AW80: =SUM(R80:AC80) | AX80: =SUM(AD80:AO80) | AY80: =SUM(AH80:AS80) | AZ80: =SUM(AJ80:AU80) | BB80: =IFERROR(F80/F$117,0) | BC80: =IFERROR(G80/G$117,0) | BD80: =IFERROR(H80/H$117,0) | BE80: =IFERROR(I80/I$117,0) | BF80: =IFERROR(J80/J$117,0) | BG80: =IFERROR(K80/K$117,0) | BH80: =IFERROR(L80/L$117,0) | BI80: =IFERROR(M80/M$117,0) | ... CV80: =IFERROR(AZ80/AZ$117,0) | CX80: 1477.72
C81: Fraud services revenue -online scoring | D81: 411326 | E81: =CONCATENATE(D81," - ",C81) | AP81: 31 | AQ81: 31 | AR81: 32.25 | AS81: 34.75 | AT81: 34.75 | AU81: 33.5 | AV81: =SUM(F81:Q81) | AW81: =SUM(R81:AC81) | AX81: =SUM(AD81:AO81) | AY81: =SUM(AH81:AS81) | AZ81: =SUM(AJ81:AU81) | BB81: =IFERROR(F81/F$117,0) | BC81: =IFERROR(G81/G$117,0) | BD81: =IFERROR(H81/H$117,0) | BE81: =IFERROR(I81/I$117,0) | BF81: =IFERROR(J81/J$117,0) | BG81: =IFERROR(K81/K$117,0) | BH81: =IFERROR(L81/L$117,0) | BI81: =IFERROR(M81/M$117,0) | ... CV81: =IFERROR(AZ81/AZ$117,0) | CX81: 60
C82: Fraud services revenue - hot card | D82: 411337 | E82: =CONCATENATE(D82," - ",C82) | AP82: 23.5486 | AQ82: 24.05695 | AR82: 22.3344 | AS82: 26.4708 | AT82: 30.1025 | AU82: 32.15305 | AV82: =SUM(F82:Q82) | AW82: =SUM(R82:AC82) | AX82: =SUM(AD82:AO82) | AY82: =SUM(AH82:AS82) | AZ82: =SUM(AJ82:AU82) | BB82: =IFERROR(F82/F$117,0) | BC82: =IFERROR(G82/G$117,0) | BD82: =IFERROR(H82/H$117,0) | BE82: =IFERROR(I82/I$117,0) | BF82: =IFERROR(J82/J$117,0) | BG82: =IFERROR(K82/K$117,0) | BH82: =IFERROR(L82/L$117,0) | BI82: =IFERROR(M82/M$117,0) | ... CV82: =IFERROR(AZ82/AZ$117,0) | CX82: 281.3816
C83: Fraud services revenue - lock n block | D83: 411335 | E83: =CONCATENATE(D83," - ",C83) | AP83: 17.95 | AQ83: 17.95 | AR83: 17.95 | AS83: 17.95 | AT83: 35.95 | AU83: 19.95 | AV83: =SUM(F83:Q83) | AW83: =SUM(R83:AC83) | AX83: =SUM(AD83:AO83) | AY83: =SUM(AH83:AS83) | AZ83: =SUM(AJ83:AU83) | BB83: =IFERROR(F83/F$117,0) | BC83: =IFERROR(G83/G$117,0) | BD83: =IFERROR(H83/H$117,0) | BE83: =IFERROR(I83/I$117,0) | BF83: =IFERROR(J83/J$117,0) | BG83: =IFERROR(K83/K$117,0) | BH83: =IFERROR(L83/L$117,0) | BI83: =IFERROR(M83/M$117,0) | ... CV83: =IFERROR(AZ83/AZ$117,0) | CX83: 226.99992
C84: Fraud services revenue - country block | D84: 411338 | E84: =CONCATENATE(D84," - ",C84) | AP84: 9.4766 | AQ84: 9.5501 | AR84: 9.49637 | AS84: 9.4047 | AT84: 9.41571 | AU84: 8.96779 | AV84: =SUM(F84:Q84) | AW84: =SUM(R84:AC84) | AX84: =SUM(AD84:AO84) | AY84: =SUM(AH84:AS84) | AZ84: =SUM(AJ84:AU84) | BB84: =IFERROR(F84/F$117,0) | BC84: =IFERROR(G84/G$117,0) | BD84: =IFERROR(H84/H$117,0) | BE84: =IFERROR(I84/I$117,0) | BF84: =IFERROR(J84/J$117,0) | BG84: =IFERROR(K84/K$117,0) | BH84: =IFERROR(L84/L$117,0) | BI84: =IFERROR(M84/M$117,0) | ... CV84: =IFERROR(AZ84/AZ$117,0) | CX84: 111.36885
C85: Fraud services revenue - coop vcas | D85: 411320 | E85: =CONCATENATE(D85," - ",C85) | AP85: 10.58342 | AQ85: 9.16505 | AR85: 10.11568 | AS85: 11.43121 | AT85: 12.31679 | AU85: 10.96875 | AV85: =SUM(F85:Q85) | AW85: =SUM(R85:AC85) | AX85: =SUM(AD85:AO85) | AY85: =SUM(AH85:AS85) | AZ85: =SUM(AJ85:AU85) | BB85: =IFERROR(F85/F$117,0) | BC85: =IFERROR(G85/G$117,0) | BD85: =IFERROR(H85/H$117,0) | BE85: =IFERROR(I85/I$117,0) | BF85: =IFERROR(J85/J$117,0) | BG85: =IFERROR(K85/K$117,0) | BH85: =IFERROR(L85/L$117,0) | BI85: =IFERROR(M85/M$117,0) | ... CV85: =IFERROR(AZ85/AZ$117,0) | CX85: 0
C86: Fraud services revenue - others | D86: 411339 | E86: =CONCATENATE(D86," - ",C86) | AP86: 7.75 | AQ86: 7.545 | AR86: 7.62 | AS86: 7.95 | AT86: 7.95 | AU86: 7.92 | AV86: =SUM(F86:Q86) | AW86: =SUM(R86:AC86) | AX86: =SUM(AD86:AO86) | AY86: =SUM(AH86:AS86) | AZ86: =SUM(AJ86:AU86) | BB86: =IFERROR(F86/F$117,0) | BC86: =IFERROR(G86/G$117,0) | BD86: =IFERROR(H86/H$117,0) | BE86: =IFERROR(I86/I$117,0) | BF86: =IFERROR(J86/J$117,0) | BG86: =IFERROR(K86/K$117,0) | BH86: =IFERROR(L86/L$117,0) | BI86: =IFERROR(M86/M$117,0) | ... CV86: =IFERROR(AZ86/AZ$117,0) | CX86: 98.03776
C87: Fraud services revenue -mobile alerts | D87: 411327 | E87: =CONCATENATE(D87," - ",C87) | AP87: 3.56965 | AQ87: 4.9195 | AR87: 4.2304 | AS87: 4.2795 | AT87: 4.5085 | AU87: 4.4695 | AV87: =SUM(F87:Q87) | AW87: =SUM(R87:AC87) | AX87: =SUM(AD87:AO87) | AY87: =SUM(AH87:AS87) | AZ87: =SUM(AJ87:AU87) | BB87: =IFERROR(F87/F$117,0) | BC87: =IFERROR(G87/G$117,0) | BD87: =IFERROR(H87/H$117,0) | BE87: =IFERROR(I87/I$117,0) | BF87: =IFERROR(J87/J$117,0) | BG87: =IFERROR(K87/K$117,0) | BH87: =IFERROR(L87/L$117,0) | BI87: =IFERROR(M87/M$117,0) | ... CV87: =IFERROR(AZ87/AZ$117,0) | CX87: 0.20888
C88: Fraud Services Enterprise Monitoring | D88: 411323 | E88: =CONCATENATE(D88," - ",C88) | AP88: 0 | AQ88: 0 | AR88: 0 | AS88: 0 | AT88: 0 | AU88: 2.57928 | AV88: =SUM(F88:Q88) | AW88: =SUM(R88:AC88) | AX88: =SUM(AD88:AO88) | AY88: =SUM(AH88:AS88) | AZ88: =SUM(AJ88:AU88) | BB88: =IFERROR(F88/F$117,0) | BC88: =IFERROR(G88/G$117,0) | BD88: =IFERROR(H88/H$117,0) | BE88: =IFERROR(I88/I$117,0) | BF88: =IFERROR(J88/J$117,0) | BG88: =IFERROR(K88/K$117,0) | BH88: =IFERROR(L88/L$117,0) | BI88: =IFERROR(M88/M$117,0) | ... CV88: =IFERROR(AZ88/AZ$117,0) | CX88: 0
C89: Fraud services -lnb sms alerts messages | D89: 411336 | E89: =CONCATENATE(D89," - ",C89) | AP89: 0.01475 | AQ89: 0.0157 | AR89: 0.0177 | AS89: 0.0226 | AT89: 0.02955 | AU89: 0.03 | AV89: =SUM(F89:Q89) | AW89: =SUM(R89:AC89) | AX89: =SUM(AD89:AO89) | AY89: =SUM(AH89:AS89) | AZ89: =SUM(AJ89:AU89) | BB89: =IFERROR(F89/F$117,0) | BC89: =IFERROR(G89/G$117,0) | BD89: =IFERROR(H89/H$117,0) | BE89: =IFERROR(I89/I$117,0) | BF89: =IFERROR(J89/J$117,0) | BG89: =IFERROR(K89/K$117,0) | BH89: =IFERROR(L89/L$117,0) | BI89: =IFERROR(M89/M$117,0) | ... CV89: =IFERROR(AZ89/AZ$117,0) | CX89: 0
C90: Fraud management revenue | AP90: =SUM(AP80:AP89) | AQ90: =SUM(AQ80:AQ89) | AR90: =SUM(AR80:AR89) | AS90: =SUM(AS80:AS89) | AT90: =SUM(AT80:AT89) | AU90: =SUM(AU80:AU89) | AV90: =SUM(AV80:AV89) | AW90: =SUM(AW80:AW89) | ... AZ90: =SUM(AZ80:AZ89) | BB90: =IFERROR(F90/F$117,0) | BC90: =IFERROR(G90/G$117,0) | BD90: =IFERROR(H90/H$117,0) | BE90: =IFERROR(I90/I$117,0) | BF90: =IFERROR(J90/J$117,0) | BG90: =IFERROR(K90/K$117,0) | BH90: =IFERROR(L90/L$117,0) | BI90: =IFERROR(M90/M$117,0) | ... CV90: =IFERROR(AZ90/AZ$117,0) | CX90: =SUM(CX80:CX89)
C91: Optional issuer fee revenue - cirrus & plus | D91: 411140 | E91: =CONCATENATE(D91," - ",C91) | AP91: 94.75907 | AQ91: 102.80226 | AR91: 92.65 | AS91: 61.56849 | AT91: 45.97223 | AU91: 39.06553 | AV91: =SUM(F91:Q91) | AW91: =SUM(R91:AC91) | AX91: =SUM(AD91:AO91) | AY91: =SUM(AH91:AS91) | AZ91: =SUM(AJ91:AU91) | BB91: =IFERROR(F91/F$117,0) | BC91: =IFERROR(G91/G$117,0) | BD91: =IFERROR(H91/H$117,0) | BE91: =IFERROR(I91/I$117,0) | BF91: =IFERROR(J91/J$117,0) | BG91: =IFERROR(K91/K$117,0) | BH91: =IFERROR(L91/L$117,0) | BI91: =IFERROR(M91/M$117,0) | ... CV91: =IFERROR(AZ91/AZ$117,0) | CX91: 629.47136
C92: Issuer interchange - co-badged- debit mc | D92: 411148 | E92: =CONCATENATE(D92," - ",C92) | AP92: 35.99257 | AQ92: 17.1001 | AR92: 32.46535 | AS92: 31.685 | AT92: 44.7716 | AU92: 26.62719 | AV92: =SUM(F92:Q92) | AW92: =SUM(R92:AC92) | AX92: =SUM(AD92:AO92) | AY92: =SUM(AH92:AS92) | AZ92: =SUM(AJ92:AU92) | BB92: =IFERROR(F92/F$117,0) | BC92: =IFERROR(G92/G$117,0) | BD92: =IFERROR(H92/H$117,0) | BE92: =IFERROR(I92/I$117,0) | BF92: =IFERROR(J92/J$117,0) | BG92: =IFERROR(K92/K$117,0) | BH92: =IFERROR(L92/L$117,0) | BI92: =IFERROR(M92/M$117,0) | ... CV92: =IFERROR(AZ92/AZ$117,0) | CX92: 0
C93: Issuer interchange - co-badged- visa debit | D93: 411144 | E93: =CONCATENATE(D93," - ",C93) | AP93: 16.02343 | AQ93: 26.12078 | AR93: 19.61633 | AS93: 19.702 | AT93: 20.55433 | AU93: 19.6097 | AV93: =SUM(F93:Q93) | AW93: =SUM(R93:AC93) | AX93: =SUM(AD93:AO93) | AY93: =SUM(AH93:AS93) | AZ93: =SUM(AJ93:AU93) | BB93: =IFERROR(F93/F$117,0) | BC93: =IFERROR(G93/G$117,0) | BD93: =IFERROR(H93/H$117,0) | BE93: =IFERROR(I93/I$117,0) | BF93: =IFERROR(J93/J$117,0) | BG93: =IFERROR(K93/K$117,0) | BH93: =IFERROR(L93/L$117,0) | BI93: =IFERROR(M93/M$117,0) | ... CV93: =IFERROR(AZ93/AZ$117,0) | CX93: 0
C94: Optional issuer fee revenue - dma | D94: 411149 | E94: =CONCATENATE(D94," - ",C94) | AP94: 19.78337 | AQ94: 20.35154 | AR94: 20.35154 | AS94: 7.28538 | AT94: 41.58015 | AU94: 18.57777 | AV94: =SUM(F94:Q94) | AW94: =SUM(R94:AC94) | AX94: =SUM(AD94:AO94) | AY94: =SUM(AH94:AS94) | AZ94: =SUM(AJ94:AU94) | BB94: =IFERROR(F94/F$117,0) | BC94: =IFERROR(G94/G$117,0) | BD94: =IFERROR(H94/H$117,0) | BE94: =IFERROR(I94/I$117,0) | BF94: =IFERROR(J94/J$117,0) | BG94: =IFERROR(K94/K$117,0) | BH94: =IFERROR(L94/L$117,0) | BI94: =IFERROR(M94/M$117,0) | ... CV94: =IFERROR(AZ94/AZ$117,0) | CX94: 0
C95: Optional issuer fee revenue - maestro | D95: 411141 | E95: =CONCATENATE(D95," - ",C95) | AP95: 9.46507 | AQ95: 10.6718 | AR95: 12.131 | AS95: 11.02484 | AT95: 9.52895 | AU95: 8.18448 | AV95: =SUM(F95:Q95) | AW95: =SUM(R95:AC95) | AX95: =SUM(AD95:AO95) | AY95: =SUM(AH95:AS95) | AZ95: =SUM(AJ95:AU95) | BB95: =IFERROR(F95/F$117,0) | BC95: =IFERROR(G95/G$117,0) | BD95: =IFERROR(H95/H$117,0) | BE95: =IFERROR(I95/I$117,0) | BF95: =IFERROR(J95/J$117,0) | BG95: =IFERROR(K95/K$117,0) | BH95: =IFERROR(L95/L$117,0) | BI95: =IFERROR(M95/M$117,0) | ... CV95: =IFERROR(AZ95/AZ$117,0) | CX95: 47.44071
C96: Optional issuer fee revenue - dmc | D96: 411142 | E96: =CONCATENATE(D96," - ",C96) | AP96: 10.70728 | AQ96: 12.60981 | AR96: 11.625 | AS96: 28.62018 | AT96: -14.16543 | AU96: 4.95508 | AV96: =SUM(F96:Q96) | AW96: =SUM(R96:AC96) | AX96: =SUM(AD96:AO96) | AY96: =SUM(AH96:AS96) | AZ96: =SUM(AJ96:AU96) | BB96: =IFERROR(F96/F$117,0) | BC96: =IFERROR(G96/G$117,0) | BD96: =IFERROR(H96/H$117,0) | BE96: =IFERROR(I96/I$117,0) | BF96: =IFERROR(J96/J$117,0) | BG96: =IFERROR(K96/K$117,0) | BH96: =IFERROR(L96/L$117,0) | BI96: =IFERROR(M96/M$117,0) | ... CV96: =IFERROR(AZ96/AZ$117,0) | CX96: 38.41831
C97: Atm cirrus surcharge sharing | D97: 411145 | E97: =CONCATENATE(D97," - ",C97) | AP97: 6.6137 | AQ97: 7.30368 | AR97: 8.53708 | AS97: 8.3932 | AT97: 9.09324 | AU97: 9.34497 | AV97: =SUM(F97:Q97) | AW97: =SUM(R97:AC97) | AX97: =SUM(AD97:AO97) | AY97: =SUM(AH97:AS97) | AZ97: =SUM(AJ97:AU97) | BB97: =IFERROR(F97/F$117,0) | BC97: =IFERROR(G97/G$117,0) | BD97: =IFERROR(H97/H$117,0) | BE97: =IFERROR(I97/I$117,0) | BF97: =IFERROR(J97/J$117,0) | BG97: =IFERROR(K97/K$117,0) | BH97: =IFERROR(L97/L$117,0) | BI97: =IFERROR(M97/M$117,0) | ... CV97: =IFERROR(AZ97/AZ$117,0) | CX97: 63.80503
C98: Optional issuer fee revenue - visa | D98: 411147 | E98: =CONCATENATE(D98," - ",C98) | AP98: 3.55581 | AQ98: 3.22513 | AR98: 2.665 | AS98: 8.71886 | AT98: 5.85425 | AU98: 5.02346 | AV98: =SUM(F98:Q98) | AW98: =SUM(R98:AC98) | AX98: =SUM(AD98:AO98) | AY98: =SUM(AH98:AS98) | AZ98: =SUM(AJ98:AU98) | BB98: =IFERROR(F98/F$117,0) | BC98: =IFERROR(G98/G$117,0) | BD98: =IFERROR(H98/H$117,0) | BE98: =IFERROR(I98/I$117,0) | BF98: =IFERROR(J98/J$117,0) | BG98: =IFERROR(K98/K$117,0) | BH98: =IFERROR(L98/L$117,0) | BI98: =IFERROR(M98/M$117,0) | ... CV98: =IFERROR(AZ98/AZ$117,0) | CX98: 0
C99: Atm visa plus surcharge | D99: 411146 | E99: =CONCATENATE(D99," - ",C99) | AP99: 1.40079 | AQ99: 1.45329 | AR99: 1.81767 | AS99: 1.6731 | AT99: 2.19365 | AU99: 2.42636 | AV99: =SUM(F99:Q99) | AW99: =SUM(R99:AC99) | AX99: =SUM(AD99:AO99) | AY99: =SUM(AH99:AS99) | AZ99: =SUM(AJ99:AU99) | BB99: =IFERROR(F99/F$117,0) | BC99: =IFERROR(G99/G$117,0) | BD99: =IFERROR(H99/H$117,0) | BE99: =IFERROR(I99/I$117,0) | BF99: =IFERROR(J99/J$117,0) | BG99: =IFERROR(K99/K$117,0) | BH99: =IFERROR(L99/L$117,0) | BI99: =IFERROR(M99/M$117,0) | ... CV99: =IFERROR(AZ99/AZ$117,0) | CX99: 11.91539
C100: Dynamic currency conversion-atm | D100: 411143 | E100: =CONCATENATE(D100," - ",C100) | AP100: 1.07787 | AQ100: 0.80396 | AR100: 0.99701 | AS100: 1.0797 | AT100: 1.29763 | AU100: 1.15478 | AV100: =SUM(F100:Q100) | AW100: =SUM(R100:AC100) | AX100: =SUM(AD100:AO100) | AY100: =SUM(AH100:AS100) | AZ100: =SUM(AJ100:AU100) | BB100: =IFERROR(F100/F$117,0) | BC100: =IFERROR(G100/G$117,0) | BD100: =IFERROR(H100/H$117,0) | BE100: =IFERROR(I100/I$117,0) | BF100: =IFERROR(J100/J$117,0) | BG100: =IFERROR(K100/K$117,0) | BH100: =IFERROR(L100/L$117,0) | BI100: =IFERROR(M100/M$117,0) | ... CV100: =IFERROR(AZ100/AZ$117,0) | CX100: 16.06594
C101: Optional issuer fee , dcc & surcharge | AP101: =SUM(AP91:AP100) | AQ101: =SUM(AQ91:AQ100) | AR101: =SUM(AR91:AR100) | AS101: =SUM(AS91:AS100) | AT101: =SUM(AT91:AT100) | AU101: =SUM(AU91:AU100) | AV101: =SUM(AV91:AV100) | AW101: =SUM(AW91:AW100) | ... AZ101: =SUM(AZ91:AZ100) | BB101: =IFERROR(F101/F$117,0) | BC101: =IFERROR(G101/G$117,0) | BD101: =IFERROR(H101/H$117,0) | BE101: =IFERROR(I101/I$117,0) | BF101: =IFERROR(J101/J$117,0) | BG101: =IFERROR(K101/K$117,0) | BH101: =IFERROR(L101/L$117,0) | BI101: =IFERROR(M101/M$117,0) | ... CV101: =IFERROR(AZ101/AZ$117,0) | CX101: =SUM(CX91:CX100)
C102: Telecom customer revenue | D102: 411350 | E102: =CONCATENATE(D102," - ",C102) | AP102: 94.65123 | AQ102: 101.34443 | AR102: 94.6034 | AS102: 114.03621 | AT102: 101.53025 | AU102: 103.03193 | AV102: =SUM(F102:Q102) | AW102: =SUM(R102:AC102) | AX102: =SUM(AD102:AO102) | AY102: =SUM(AH102:AS102) | AZ102: =SUM(AJ102:AU102) | BB102: =IFERROR(F102/F$117,0) | BC102: =IFERROR(G102/G$117,0) | BD102: =IFERROR(H102/H$117,0) | BE102: =IFERROR(I102/I$117,0) | BF102: =IFERROR(J102/J$117,0) | BG102: =IFERROR(K102/K$117,0) | BH102: =IFERROR(L102/L$117,0) | BI102: =IFERROR(M102/M$117,0) | ... CV102: =IFERROR(AZ102/AZ$117,0) | CX102: 1167.9813
C103: Telecom shared recovery revenue | D103: 411351 | E103: =CONCATENATE(D103," - ",C103) | AP103: 28.75 | AQ103: 28.74999 | AR103: 28.75003 | AS103: 28.75001 | AT103: 28.75001 | AU103: 28.75003 | AV103: =SUM(F103:Q103) | AW103: =SUM(R103:AC103) | AX103: =SUM(AD103:AO103) | AY103: =SUM(AH103:AS103) | AZ103: =SUM(AJ103:AU103) | BB103: =IFERROR(F103/F$117,0) | BC103: =IFERROR(G103/G$117,0) | BD103: =IFERROR(H103/H$117,0) | BE103: =IFERROR(I103/I$117,0) | BF103: =IFERROR(J103/J$117,0) | BG103: =IFERROR(K103/K$117,0) | BH103: =IFERROR(L103/L$117,0) | BI103: =IFERROR(M103/M$117,0) | ... CV103: =IFERROR(AZ103/AZ$117,0) | CX103: 345.00001
C104: Telecomm recovery | AP104: =SUM(AP102:AP103) | AQ104: =SUM(AQ102:AQ103) | AR104: =SUM(AR102:AR103) | AS104: =SUM(AS102:AS103) | AT104: =SUM(AT102:AT103) | AU104: =SUM(AU102:AU103) | AV104: =SUM(AV102:AV103) | AW104: =SUM(AW102:AW103) | ... AZ104: =SUM(AZ102:AZ103) | BB104: =IFERROR(F104/F$117,0) | BC104: =IFERROR(G104/G$117,0) | BD104: =IFERROR(H104/H$117,0) | BE104: =IFERROR(I104/I$117,0) | BF104: =IFERROR(J104/J$117,0) | BG104: =IFERROR(K104/K$117,0) | BH104: =IFERROR(L104/L$117,0) | BI104: =IFERROR(M104/M$117,0) | ... CV104: =IFERROR(AZ104/AZ$117,0) | CX104: =SUM(CX102:CX103)
C105: Equipment maintenance revenue | D105: 435801 | E105: =CONCATENATE(D105," - ",C105) | AP105: 11 | AQ105: 11.94037 | AR105: 11.47019 | AS105: 11.86205 | AT105: 11.47019 | AU105: 11.47019 | AV105: =SUM(F105:Q105) | AW105: =SUM(R105:AC105) | AX105: =SUM(AD105:AO105) | AY105: =SUM(AH105:AS105) | AZ105: =SUM(AJ105:AU105) | BB105: =IFERROR(F105/F$117,0) | BC105: =IFERROR(G105/G$117,0) | BD105: =IFERROR(H105/H$117,0) | BE105: =IFERROR(I105/I$117,0) | BF105: =IFERROR(J105/J$117,0) | BG105: =IFERROR(K105/K$117,0) | BH105: =IFERROR(L105/L$117,0) | BI105: =IFERROR(M105/M$117,0) | ... CV105: =IFERROR(AZ105/AZ$117,0) | CX105: 142.95464
C106: Printer driving | D106: 435802 | E106: =CONCATENATE(D106," - ",C106) | AP106: 0 | AQ106: 0 | AR106: 0 | AS106: 0 | AT106: 0 | AU106: 0 | AV106: =SUM(F106:Q106) | AW106: =SUM(R106:AC106) | AX106: =SUM(AD106:AO106) | AY106: =SUM(AH106:AS106) | AZ106: =SUM(AJ106:AU106) | BB106: =IFERROR(F106/F$117,0) | BC106: =IFERROR(G106/G$117,0) | BD106: =IFERROR(H106/H$117,0) | BE106: =IFERROR(I106/I$117,0) | BF106: =IFERROR(J106/J$117,0) | BG106: =IFERROR(K106/K$117,0) | BH106: =IFERROR(L106/L$117,0) | BI106: =IFERROR(M106/M$117,0) | ... CV106: =IFERROR(AZ106/AZ$117,0) | CX106: 58.4
C107: Pin station - driving | D107: 435803 | E107: =CONCATENATE(D107," - ",C107) | AP107: 15.94 | AQ107: 13.835 | AR107: 13.79 | AS107: 13.835 | AT107: 13.835 | AU107: 13.805 | AV107: =SUM(F107:Q107) | AW107: =SUM(R107:AC107) | AX107: =SUM(AD107:AO107) | AY107: =SUM(AH107:AS107) | AZ107: =SUM(AJ107:AU107) | BB107: =IFERROR(F107/F$117,0) | BC107: =IFERROR(G107/G$117,0) | BD107: =IFERROR(H107/H$117,0) | BE107: =IFERROR(I107/I$117,0) | BF107: =IFERROR(J107/J$117,0) | BG107: =IFERROR(K107/K$117,0) | BH107: =IFERROR(L107/L$117,0) | BI107: =IFERROR(M107/M$117,0) | ... CV107: =IFERROR(AZ107/AZ$117,0) | CX107: 171.41
C108: Pin station - rental | D108: 435805 | E108: =CONCATENATE(D108," - ",C108) | AP108: 53.29 | AQ108: 51.15 | AR108: 51.82 | AS108: 52.83 | AT108: 52.01 | AU108: 52.601 | AV108: =SUM(F108:Q108) | AW108: =SUM(R108:AC108) | AX108: =SUM(AD108:AO108) | AY108: =SUM(AH108:AS108) | AZ108: =SUM(AJ108:AU108) | BB108: =IFERROR(F108/F$117,0) | BC108: =IFERROR(G108/G$117,0) | BD108: =IFERROR(H108/H$117,0) | BE108: =IFERROR(I108/I$117,0) | BF108: =IFERROR(J108/J$117,0) | BG108: =IFERROR(K108/K$117,0) | BH108: =IFERROR(L108/L$117,0) | BI108: =IFERROR(M108/M$117,0) | ... CV108: =IFERROR(AZ108/AZ$117,0) | CX108: 580.945
C109: Equipment revenue - recurring | AP109: =SUM(AP105:AP108) | AQ109: =SUM(AQ105:AQ108) | AR109: =SUM(AR105:AR108) | AS109: =SUM(AS105:AS108) | AT109: =SUM(AT105:AT108) | AU109: =SUM(AU105:AU108) | AV109: =SUM(AV105:AV108) | AW109: =SUM(AW105:AW108) | ... AZ109: =SUM(AZ105:AZ108) | BB109: =IFERROR(F109/F$117,0) | BC109: =IFERROR(G109/G$117,0) | BD109: =IFERROR(H109/H$117,0) | BE109: =IFERROR(I109/I$117,0) | BF109: =IFERROR(J109/J$117,0) | BG109: =IFERROR(K109/K$117,0) | BH109: =IFERROR(L109/L$117,0) | BI109: =IFERROR(M109/M$117,0) | ... CV109: =IFERROR(AZ109/AZ$117,0) | CX109: =SUM(CX105:CX108)
C110: Equipment sales - pos & pin stations | D110: 435101 | E110: =CONCATENATE(D110," - ",C110) | AP110: 5.41525 | AQ110: 1.17525 | AR110: 8.39025 | AS110: 1.23 | AT110: 1.04025 | AU110: 65.045 | AV110: =SUM(F110:Q110) | AW110: =SUM(R110:AC110) | AX110: =SUM(AD110:AO110) | AY110: =SUM(AH110:AS110) | AZ110: =SUM(AJ110:AU110) | BB110: =IFERROR(F110/F$117,0) | BC110: =IFERROR(G110/G$117,0) | BD110: =IFERROR(H110/H$117,0) | BE110: =IFERROR(I110/I$117,0) | BF110: =IFERROR(J110/J$117,0) | BG110: =IFERROR(K110/K$117,0) | BH110: =IFERROR(L110/L$117,0) | BI110: =IFERROR(M110/M$117,0) | ... CV110: =IFERROR(AZ110/AZ$117,0) | CX110: 83.35525
C111: Atm express hardware | D111: 435116 | E111: =CONCATENATE(D111," - ",C111) | AP111: 0 | AQ111: 85.60716 | AR111: 0 | AS111: 0 | AT111: 89.52 | AU111: 0 | AV111: =SUM(F111:Q111) | AW111: =SUM(R111:AC111) | AX111: =SUM(AD111:AO111) | AY111: =SUM(AH111:AS111) | AZ111: =SUM(AJ111:AU111) | BB111: =IFERROR(F111/F$117,0) | BC111: =IFERROR(G111/G$117,0) | BD111: =IFERROR(H111/H$117,0) | BE111: =IFERROR(I111/I$117,0) | BF111: =IFERROR(J111/J$117,0) | BG111: =IFERROR(K111/K$117,0) | BH111: =IFERROR(L111/L$117,0) | BI111: =IFERROR(M111/M$117,0) | ... CV111: =IFERROR(AZ111/AZ$117,0) | CX111: 234.34037
C112: Equipment revenue - re-sale | AP112: =SUM(AP110:AP111) | AQ112: =SUM(AQ110:AQ111) | AR112: =SUM(AR110:AR111) | AS112: =SUM(AS110:AS111) | AT112: =SUM(AT110:AT111) | AU112: =SUM(AU110:AU111) | AV112: =SUM(AV110:AV111) | AW112: =SUM(AW110:AW111) | ... AZ112: =SUM(AZ110:AZ111) | BB112: =IFERROR(F112/F$117,0) | BC112: =IFERROR(G112/G$117,0) | BD112: =IFERROR(H112/H$117,0) | BE112: =IFERROR(I112/I$117,0) | BF112: =IFERROR(J112/J$117,0) | BG112: =IFERROR(K112/K$117,0) | BH112: =IFERROR(L112/L$117,0) | BI112: =IFERROR(M112/M$117,0) | ... CV112: =IFERROR(AZ112/AZ$117,0) | CX112: =SUM(CX110:CX111)
C113: Prof services ifrs 15 adjust | D113: 425115 | E113: =CONCATENATE(D113," - ",C113) | AP113: -70 | AQ113: -196.3405 | AR113: -315.0012 | AS113: -304.49325 | AT113: -144.39538 | AU113: 7.34998 | AV113: =SUM(F113:Q113) | AW113: =SUM(R113:AC113) | AX113: =SUM(AD113:AO113) | AY113: =SUM(AH113:AS113) | AZ113: =SUM(AJ113:AU113) | BB113: =IFERROR(F113/F$117,0) | BC113: =IFERROR(G113/G$117,0) | BD113: =IFERROR(H113/H$117,0) | BE113: =IFERROR(I113/I$117,0) | BF113: =IFERROR(J113/J$117,0) | BG113: =IFERROR(K113/K$117,0) | BH113: =IFERROR(L113/L$117,0) | BI113: =IFERROR(M113/M$117,0) | ... CV113: =IFERROR(AZ113/AZ$117,0) | CX113: -1434.3456
C114: Prof serv ifrs15 cy amort | D114: 426115 | E114: =CONCATENATE(D114," - ",C114) | AP114: 2 | AQ114: -0.60086 | AR114: 8.13019 | AS114: 6.92217 | AT114: 6.92217 | AU114: 15.42685 | AV114: =SUM(F114:Q114) | AW114: =SUM(R114:AC114) | AX114: =SUM(AD114:AO114) | AY114: =SUM(AH114:AS114) | AZ114: =SUM(AJ114:AU114) | BB114: =IFERROR(F114/F$117,0) | BC114: =IFERROR(G114/G$117,0) | BD114: =IFERROR(H114/H$117,0) | BE114: =IFERROR(I114/I$117,0) | BF114: =IFERROR(J114/J$117,0) | BG114: =IFERROR(K114/K$117,0) | BH114: =IFERROR(L114/L$117,0) | BI114: =IFERROR(M114/M$117,0) | ... CV114: =IFERROR(AZ114/AZ$117,0) | CX114: 0
...

Sheet Balance sheet
B1: Project Name
B2: =C7
B3: Source: TBD
B4: WORKING DRAFT
C7: Balance sheet
AV8: As at | BA8: Average
C9: $'000 | D9: Code | E9: Concatenate | F9: =ctl_month_start | G9: =EDATE(ctl_month_start,1) | H9: =EDATE(ctl_month_start,2) | I9: =EDATE(ctl_month_start,3) | J9: =EDATE(ctl_month_start,4) | K9: =EDATE(ctl_month_start,5) | L9: =EDATE(ctl_month_start,6) | M9: =EDATE(ctl_month_start,7) | N9: =EDATE(ctl_month_start,8) | O9: =EDATE(ctl_month_start,9) | P9: =EDATE(ctl_month_start,10) | Q9: =EDATE(ctl_month_start,11) | R9: =EDATE(ctl_month_start,12) | S9: =EDATE(ctl_month_start,13) | T9: =EDATE(ctl_month_start,14) | U9: =EDATE(ctl_month_start,15) | V9: =EDATE(ctl_month_start,16) | W9: =EDATE(ctl_month_start,17) | X9: =EDATE(ctl_month_start,18) | Y9: =EDATE(ctl_month_start,19) | Z9: =EDATE(ctl_month_start,20) | AA9: =EDATE(ctl_month_start,21) | AB9: =EDATE(ctl_month_start,22) | AC9: =EDATE(ctl_month_start,23) | AD9: =EDATE(ctl_month_start,24) | AE9: =EDATE(ctl_month_start,25) | AF9: =EDATE(ctl_month_start,26) | AG9: =EDATE(ctl_month_start,27) | AH9: =EDATE(ctl_month_start,28) | AI9: =EDATE(ctl_month_start,29) | AJ9: =EDATE(ctl_month_start,30) | AK9: =EDATE(ctl_month_start,31) | AL9: =EDATE(ctl_month_start,32) | AM9: =EDATE(ctl_month_start,33) | AN9: =EDATE(ctl_month_start,34) | AO9: =EDATE(ctl_month_start,35)
C10: Assets
C11: Cash-CAD - operating | D11: 100210 | E11: 100210 - Cash-CAD - Operating | AP11: 13156.221 | AQ11: 6914.205 | AR11: 6163.993 | AS11: 8149.643 | AT11: 7522.4572 | AU11: 11960.892 | AV11: =Q11 | AW11: =AC11 | AX11: =AO11 | AY11: =AS11 | AZ11: =AU11 | BA11: =AVERAGE(F11:Q11) | BB11: =AVERAGE(R11:AC11) | BC11: =AVERAGE(AD11:AO11) | BD11: =AVERAGE(AH11:AS11) | BE11: =AVERAGE(AJ11:AU11) | BG11: 12220.529
C12: Cash - operating CAD | D12: 100215 | E12: 100215 - CASH - Operating CAD | AP12: 437.838 | AQ12: 187.216 | AR12: 131.674 | AS12: 285.295 | AT12: 246.89383 | AU12: 46.82403 | AV12: =Q12 | AW12: =AC12 | AX12: =AO12 | AY12: =AS12 | AZ12: =AU12 | BA12: =AVERAGE(F12:Q12) | BB12: =AVERAGE(R12:AC12) | BC12: =AVERAGE(AD12:AO12) | BD12: =AVERAGE(AH12:AS12) | BE12: =AVERAGE(AJ12:AU12) | BG12: 0
C13: Cash USD - 079 | D13: 100416 | E13: 100416 - Cash USD - 079 | AP13: 212.855 | AQ13: 8.819 | AR13: 273.321 | AS13: 277.491 | AT13: 19.16881 | AU13: 306.60843 | AV13: =Q13 | AW13: =AC13 | AX13: =AO13 | AY13: =AS13 | AZ13: =AU13 | BA13: =AVERAGE(F13:Q13) | BB13: =AVERAGE(R13:AC13) | BC13: =AVERAGE(AD13:AO13) | BD13: =AVERAGE(AH13:AS13) | BE13: =AVERAGE(AJ13:AU13) | BG13: 390.447
C14: Cash USD - BMO harris 137 | D14: 100417 | E14: 100417 - Cash USD - BMO Harris 137 | AP14: 41.355 | AQ14: 329.688 | AR14: 75.617 | AS14: 206.174 | AT14: 304.29252 | AU14: 114.4629 | AV14: =Q14 | AW14: =AC14 | AX14: =AO14 | AY14: =AS14 | AZ14: =AU14 | BA14: =AVERAGE(F14:Q14) | BB14: =AVERAGE(R14:AC14) | BC14: =AVERAGE(AD14:AO14) | BD14: =AVERAGE(AH14:AS14) | BE14: =AVERAGE(AJ14:AU14) | BG14: 178.012
C15: Cash CAD - 095 | D15: 100211 | E15: 100211 - Cash CAD - 095 | AP15: 15.981 | AQ15: 11.6 | AR15: 12.58 | AS15: 5.686 | AT15: 10.55675 | AU15: 13.90124 | AV15: =Q15 | AW15: =AC15 | AX15: =AO15 | AY15: =AS15 | AZ15: =AU15 | BA15: =AVERAGE(F15:Q15) | BB15: =AVERAGE(R15:AC15) | BC15: =AVERAGE(AD15:AO15) | BD15: =AVERAGE(AH15:AS15) | BE15: =AVERAGE(AJ15:AU15) | BG15: 6.858
C16: Cash and cash equivalents | AP16: =SUM(AP11:AP15) | AQ16: =SUM(AQ11:AQ15) | AR16: =SUM(AR11:AR15) | AS16: =SUM(AS11:AS15) | AT16: =SUM(AT11:AT15) | AU16: =SUM(AU11:AU15) | AV16: =SUM(AV11:AV15) | AW16: =SUM(AW11:AW15) | ... BE16: =SUM(BE11:BE15) | BG16: =SUM(BG11:BG15)
C17: Cash settlement - pos desjardin 147 | D17: 100370 | E17: 100370 - Cash Settlement - POS Desjardin 147 | AP17: 20013.443 | AQ17: 23209.703 | AR17: 33328.156 | AS17: 27168.531 | AT17: 38601.277 | AU17: 43082.789 | AV17: =Q17 | AW17: =AC17 | AX17: =AO17 | AY17: =AS17 | AZ17: =AU17 | BA17: =AVERAGE(F17:Q17) | BB17: =AVERAGE(R17:AC17) | BC17: =AVERAGE(AD17:AO17) | BD17: =AVERAGE(AH17:AS17) | BE17: =AVERAGE(AJ17:AU17) | BG17: 3594.054
C18: Cash settlement scd desjardin 139 | D18: 100488 | E18: 100488 - Cash Settlement SCD Desjardin 139 | AP18: 48.28 | AQ18: -871.374 | AR18: 1075.313 | AS18: 7857.143 | AT18: -1151.1836 | AU18: -1134.4438 | AV18: =Q18 | AW18: =AC18 | AX18: =AO18 | AY18: =AS18 | AZ18: =AU18 | BA18: =AVERAGE(F18:Q18) | BB18: =AVERAGE(R18:AC18) | BC18: =AVERAGE(AD18:AO18) | BD18: =AVERAGE(AH18:AS18) | BE18: =AVERAGE(AJ18:AU18) | BG18: 2914.632
C19: Icici bank settlement CAD6932- for visa debit | D19: 100350 | E19: 100350 - ICICI Bank Settlement CAD6932- For Visa Debit | AP19: 538.144 | AQ19: 558.762 | AR19: 615.808 | AS19: 660.633 | AT19: 685.99913 | AU19: 685.99913 | AV19: =Q19 | AW19: =AC19 | AX19: =AO19 | AY19: =AS19 | AZ19: =AU19 | BA19: =AVERAGE(F19:Q19) | BB19: =AVERAGE(R19:AC19) | BC19: =AVERAGE(AD19:AO19) | BD19: =AVERAGE(AH19:AS19) | BE19: =AVERAGE(AJ19:AU19) | BG19: 0
C20: Cash settlement e-transfer desj suspense 067 | D20: 100367 | E20: 100367 - Cash Settlement E-Transfer Desj Suspense 067 | AP20: 62.262 | AQ20: 71.183 | AR20: 116.118 | AS20: 69.606 | AT20: 158.82134 | AU20: 132.76535 | AV20: =Q20 | AW20: =AC20 | AX20: =AO20 | AY20: =AS20 | AZ20: =AU20 | BA20: =AVERAGE(F20:Q20) | BB20: =AVERAGE(R20:AC20) | BC20: =AVERAGE(AD20:AO20) | BD20: =AVERAGE(AH20:AS20) | BE20: =AVERAGE(AJ20:AU20) | BG20: 0
C21: Cash settlement 178 | D21: 100489 | E21: 100489 - Cash Settlement 178 | AP21: 26.706 | AQ21: 26.845 | AR21: 25.794 | AS21: 29.618 | AT21: -148.32566 | AU21: 121.90942 | AV21: =Q21 | AW21: =AC21 | AX21: =AO21 | AY21: =AS21 | AZ21: =AU21 | BA21: =AVERAGE(F21:Q21) | BB21: =AVERAGE(R21:AC21) | BC21: =AVERAGE(AD21:AO21) | BD21: =AVERAGE(AH21:AS21) | BE21: =AVERAGE(AJ21:AU21) | BG21: 32.511
C22: Cash settlement - pos 10403- 1154 | D22: 100373 | E22: TBD | AP22: 2.123 | AQ22: 1.635 | AR22: 2.445 | AS22: 1.636 | AT22: 2.63766 | AU22: 2.3727 | AV22: =Q22 | AW22: =AC22 | AX22: =AO22 | AY22: =AS22 | AZ22: =AU22 | BA22: =AVERAGE(F22:Q22) | BB22: =AVERAGE(R22:AC22) | BC22: =AVERAGE(AD22:AO22) | BD22: =AVERAGE(AH22:AS22) | BE22: =AVERAGE(AJ22:AU22) | BG22: 0
C23: Cash settlement desj etransf 1162 | D23: 100380 | E23: 100380 - Cash Settlement Desj Etransf 1162 | AP23: 0.015 | AQ23: 0.015 | AR23: 0.015 | AS23: 0.015 | AT23: 0.01483 | AU23: 0.01483 | AV23: =Q23 | AW23: =AC23 | AX23: =AO23 | AY23: =AS23 | AZ23: =AU23 | BA23: =AVERAGE(F23:Q23) | BB23: =AVERAGE(R23:AC23) | BC23: =AVERAGE(AD23:AO23) | BD23: =AVERAGE(AH23:AS23) | BE23: =AVERAGE(AJ23:AU23) | BG23: 0
C24: Cash USD - settlement td bank, n.a 154 | D24: 100418 | E24: 100418 - Cash USD - Settlement TD Bank, N.A 154 | AP24: 0 | AQ24: 0 | AR24: 0 | AS24: 0 | AT24: 0 | AU24: 1e-05 | AV24: =Q24 | AW24: =AC24 | AX24: =AO24 | AY24: =AS24 | AZ24: =AU24 | BA24: =AVERAGE(F24:Q24) | BB24: =AVERAGE(R24:AC24) | BC24: =AVERAGE(AD24:AO24) | BD24: =AVERAGE(AH24:AS24) | BE24: =AVERAGE(AJ24:AU24) | BG24: 0
C25: Cash settlement e-transfer 059 | D25: 100359 | E25: TBD | AP25: 0.549 | AQ25: 0 | AR25: 0 | AS25: 0 | AT25: 1e-05 | AU25: 0 | AV25: =Q25 | AW25: =AC25 | AX25: =AO25 | AY25: =AS25 | AZ25: =AU25 | BA25: =AVERAGE(F25:Q25) | BB25: =AVERAGE(R25:AC25) | BC25: =AVERAGE(AD25:AO25) | BD25: =AVERAGE(AH25:AS25) | BE25: =AVERAGE(AJ25:AU25) | BG25: 0
C26: Items in transit | AP26: =SUM(AP17:AP25) | AQ26: =SUM(AQ17:AQ25) | AR26: =SUM(AR17:AR25) | AS26: =SUM(AS17:AS25) | AT26: =SUM(AT17:AT25) | AU26: =SUM(AU17:AU25) | AV26: =SUM(AV17:AV25) | AW26: =SUM(AW17:AW25) | ... BE26: =SUM(BE17:BE25) | BG26: =SUM(BG17:BG25)
C27: A/R billings-subledger | D27: 120101 | E27: 120101 - A/R Billings-Subledger | AP27: 10153.072 | AQ27: 5012.974 | AR27: 7273.266 | AS27: 6359.375 | AT27: 8141.7196 | AU27: 5418.3691 | AV27: =Q27 | AW27: =AC27 | AX27: =AO27 | AY27: =AS27 | AZ27: =AU27 | BA27: =AVERAGE(F27:Q27) | BB27: =AVERAGE(R27:AC27) | BC27: =AVERAGE(AD27:AO27) | BD27: =AVERAGE(AH27:AS27) | BE27: =AVERAGE(AJ27:AU27) | BG27: 3616.041
C28: A/R-trade accrual | D28: 120201 | E28: 120201 - A/R-Trade Accrual | AP28: 4970.669 | AQ28: 5970.482 | AR28: 5259.959 | AS28: 5730.494 | AT28: 5723.6653 | AU28: 5814.5333 | AV28: =Q28 | AW28: =AC28 | AX28: =AO28 | AY28: =AS28 | AZ28: =AU28 | BA28: =AVERAGE(F28:Q28) | BB28: =AVERAGE(R28:AC28) | BC28: =AVERAGE(AD28:AO28) | BD28: =AVERAGE(AH28:AS28) | BE28: =AVERAGE(AJ28:AU28) | BG28: 3261.941
C29: Accrued merchant services fees | D29: 120301 | E29: 120301 - Accrued Merchant Services Fees | AP29: 340.102 | AQ29: 371.563 | AR29: 422.474 | AS29: 422.408 | AT29: 474.22416 | AU29: 481.02878 | AV29: =Q29 | AW29: =AC29 | AX29: =AO29 | AY29: =AS29 | AZ29: =AU29 | BA29: =AVERAGE(F29:Q29) | BB29: =AVERAGE(R29:AC29) | BC29: =AVERAGE(AD29:AO29) | BD29: =AVERAGE(AH29:AS29) | BE29: =AVERAGE(AJ29:AU29) | BG29: 200.524
C30: Accrued other receivable | D30: 120401 | E30: 120401 - Accrued Other Receivable | AP30: 236.533 | AQ30: 219.783 | AR30: 235.088 | AS30: 235.286 | AT30: 234.59109 | AU30: 234.49109 | AV30: =Q30 | AW30: =AC30 | AX30: =AO30 | AY30: =AS30 | AZ30: =AU30 | BA30: =AVERAGE(F30:Q30) | BB30: =AVERAGE(R30:AC30) | BC30: =AVERAGE(AD30:AO30) | BD30: =AVERAGE(AH30:AS30) | BE30: =AVERAGE(AJ30:AU30) | BG30: 155.917
C31: Sales tax receivables - HST/GST | D31: 130301 | E31: 130301 - Sales Tax Receivables - HST/GST | AP31: 166.579 | AQ31: 304.994 | AR31: 288.599 | AS31: 193.459 | AT31: 151.69733 | AU31: 175.55522 | AV31: =Q31 | AW31: =AC31 | AX31: =AO31 | AY31: =AS31 | AZ31: =AU31 | BA31: =AVERAGE(F31:Q31) | BB31: =AVERAGE(R31:AC31) | BC31: =AVERAGE(AD31:AO31) | BD31: =AVERAGE(AH31:AS31) | BE31: =AVERAGE(AJ31:AU31) | BG31: 99.07
C32: Interest receivables | D32: 130101 | E32: 130101 - Interest Receivables | AP32: 92.015 | AQ32: 88.057 | AR32: 115.707 | AS32: 120.436 | AT32: 138.18024 | AU32: 137.03295 | AV32: =Q32 | AW32: =AC32 | AX32: =AO32 | AY32: =AS32 | AZ32: =AU32 | BA32: =AVERAGE(F32:Q32) | BB32: =AVERAGE(R32:AC32) | BC32: =AVERAGE(AD32:AO32) | BD32: =AVERAGE(AH32:AS32) | BE32: =AVERAGE(AJ32:AU32) | BG32: 0
C33: Sales tax receivables - QST | D33: 130300 | E33: 130300 - Sales Tax Receivables - QST | AP33: 0.827 | AQ33: 0.827 | AR33: 1.334 | AS33: 0.533 | AT33: 0.53267 | AU33: 0.53267 | AV33: =Q33 | AW33: =AC33 | AX33: =AO33 | AY33: =AS33 | AZ33: =AU33 | BA33: =AVERAGE(F33:Q33) | BB33: =AVERAGE(R33:AC33) | BC33: =AVERAGE(AD33:AO33) | BD33: =AVERAGE(AH33:AS33) | BE33: =AVERAGE(AJ33:AU33) | BG33: 0.037
C34: IFRS15 adjustment to accr A/R | D34: 120215 | E34: 120215 - -IFRS15 Adjustment to Accr AR- | AP34: 0 | AQ34: 0 | AR34: 0 | AS34: 0 | AT34: 0 | AU34: 0 | AV34: =Q34 | AW34: =AC34 | AX34: =AO34 | AY34: =AS34 | AZ34: =AU34 | BA34: =AVERAGE(F34:Q34) | BB34: =AVERAGE(R34:AC34) | BC34: =AVERAGE(AD34:AO34) | BD34: =AVERAGE(AH34:AS34) | BE34: =AVERAGE(AJ34:AU34) | BG34: 0
C35: Corporate card payments suspense | D35: 143102 | E35: 143102 - Corporate Card Payments Suspense | AP35: 0 | AQ35: 0 | AR35: 0 | AS35: 0 | AT35: -0.00515 | AU35: 9.69549 | AV35: =Q35 | AW35: =AC35 | AX35: =AO35 | AY35: =AS35 | AZ35: =AU35 | BA35: =AVERAGE(F35:Q35) | BB35: =AVERAGE(R35:AC35) | BC35: =AVERAGE(AD35:AO35) | BD35: =AVERAGE(AH35:AS35) | BE35: =AVERAGE(AJ35:AU35) | BG35: 0
C36: Allowances for customers A/R | D36: 125101 | E36: 125101 - Allowances for Customers A/R | AP36: -62.419 | AQ36: -62.419 | AR36: -62.419 | AS36: -62.419 | AT36: -62.41876 | AU36: -62.41876 | AV36: =Q36 | AW36: =AC36 | AX36: =AO36 | AY36: =AS36 | AZ36: =AU36 | BA36: =AVERAGE(F36:Q36) | BB36: =AVERAGE(R36:AC36) | BC36: =AVERAGE(AD36:AO36) | BD36: =AVERAGE(AH36:AS36) | BE36: =AVERAGE(AJ36:AU36) | BG36: -116.407
C37: Accounts receivable and other receivables | AP37: =SUM(AP27:AP36) | AQ37: =SUM(AQ27:AQ36) | AR37: =SUM(AR27:AR36) | AS37: =SUM(AS27:AS36) | AT37: =SUM(AT27:AT36) | AU37: =SUM(AU27:AU36) | AV37: =SUM(AV27:AV36) | AW37: =SUM(AW27:AW36) | ... BE37: =SUM(BE27:BE36) | BG37: =SUM(BG27:BG36)
C38: Inventory - prepaid COGS | D38: 142113 | E38: 142113 - Inventory - Prepaid COGS | AP38: 624.985 | AQ38: 635.789 | AR38: 780.971 | AS38: 809.919 | AT38: 733.1211 | AU38: 678.26014 | AV38: =Q38 | AW38: =AC38 | AX38: =AO38 | AY38: =AS38 | AZ38: =AU38 | BA38: =AVERAGE(F38:Q38) | BB38: =AVERAGE(R38:AC38) | BC38: =AVERAGE(AD38:AO38) | BD38: =AVERAGE(AH38:AS38) | BE38: =AVERAGE(AJ38:AU38) | BG38: 321.696
C39: Inventory | D39: 142101 | E39: 142101 - Inventory | AP39: 428.38 | AQ39: 428.38 | AR39: 428.38 | AS39: 433.789 | AT39: 433.83963 | AU39: 422.28133 | AV39: =Q39 | AW39: =AC39 | AX39: =AO39 | AY39: =AS39 | AZ39: =AU39 | BA39: =AVERAGE(F39:Q39) | BB39: =AVERAGE(R39:AC39) | BC39: =AVERAGE(AD39:AO39) | BD39: =AVERAGE(AH39:AS39) | BE39: =AVERAGE(AJ39:AU39) | BG39: 122.314
C40: Inventory - rental units | D40: 142112 | E40: 142112 - Inventory - Rental Units | AP40: -282.064 | AQ40: -292.064 | AR40: -302.064 | AS40: -312.064 | AT40: -322.06411 | AU40: -332.06411 | AV40: =Q40 | AW40: =AC40 | AX40: =AO40 | AY40: =AS40 | AZ40: =AU40 | BA40: =AVERAGE(F40:Q40) | BB40: =AVERAGE(R40:AC40) | BC40: =AVERAGE(AD40:AO40) | BD40: =AVERAGE(AH40:AS40) | BE40: =AVERAGE(AJ40:AU40) | BG40: -67.064
C41: Inventory | AP41: =SUM(AP38:AP40) | AQ41: =SUM(AQ38:AQ40) | AR41: =SUM(AR38:AR40) | AS41: =SUM(AS38:AS40) | AT41: =SUM(AT38:AT40) | AU41: =SUM(AU38:AU40) | AV41: =SUM(AV38:AV40) | AW41: =SUM(AW38:AW40) | ... BE41: =SUM(BE38:BE40) | BG41: =SUM(BG38:BG40)
C42: Prepaid SW license fees | D42: 141511 | E42: 141511 - Prepaid SW License Fees | AP42: 1991.456 | AQ42: 2127.768 | AR42: 1851.546 | AS42: 1692.646 | AT42: 1558.5565 | AU42: 1298.7882 | AV42: =Q42 | AW42: =AC42 | AX42: =AO42 | AY42: =AS42 | AZ42: =AU42 | BA42: =AVERAGE(F42:Q42) | BB42: =AVERAGE(R42:AC42) | BC42: =AVERAGE(AD42:AO42) | BD42: =AVERAGE(AH42:AS42) | BE42: =AVERAGE(AJ42:AU42) | BG42: 1321.887
C43: Prepaid SW maintenance | D43: 141204 | E43: 141204 - Prepaid SW Maintenance | AP43: 525.013 | AQ43: 547.835 | AR43: 588.654 | AS43: 633.546 | AT43: 605.18264 | AU43: 655.15641 | AV43: =Q43 | AW43: =AC43 | AX43: =AO43 | AY43: =AS43 | AZ43: =AU43 | BA43: =AVERAGE(F43:Q43) | BB43: =AVERAGE(R43:AC43) | BC43: =AVERAGE(AD43:AO43) | BD43: =AVERAGE(AH43:AS43) | BE43: =AVERAGE(AJ43:AU43) | BG43: 530.977
C44: Prepaid HW maintenance | D44: 141203 | E44: 141203 - Prepaid HW Maintenance | AP44: 293.093 | AQ44: 260.882 | AR44: 267.372 | AS44: 237.432 | AT44: 203.91198 | AU44: 191.3329 | AV44: =Q44 | AW44: =AC44 | AX44: =AO44 | AY44: =AS44 | AZ44: =AU44 | BA44: =AVERAGE(F44:Q44) | BB44: =AVERAGE(R44:AC44) | BC44: =AVERAGE(AD44:AO44) | BD44: =AVERAGE(AH44:AS44) | BE44: =AVERAGE(AJ44:AU44) | BG44: 312.069
C45: Prepaid insurance | D45: 143201 | E45: 143201 - Prepaid Insurance | AP45: 311.021 | AQ45: 246.416 | AR45: 181.811 | AS45: 117.206 | AT45: 52.60135 | AU45: 122.66079 | AV45: =Q45 | AW45: =AC45 | AX45: =AO45 | AY45: =AS45 | AZ45: =AU45 | BA45: =AVERAGE(F45:Q45) | BB45: =AVERAGE(R45:AC45) | BC45: =AVERAGE(AD45:AO45) | BD45: =AVERAGE(AH45:AS45) | BE45: =AVERAGE(AJ45:AU45) | BG45: 92.727
C46: Prepaid rent | D46: 143201 | E46: 143201 - Prepaid Rent | AP46: 58.843 | AQ46: 58.843 | AR46: 58.843 | AS46: 58.843 | AT46: 58.84289 | AU46: 58.84286 | AV46: =Q46 | AW46: =AC46 | AX46: =AO46 | AY46: =AS46 | AZ46: =AU46 | BA46: =AVERAGE(F46:Q46) | BB46: =AVERAGE(R46:AC46) | BC46: =AVERAGE(AD46:AO46) | BD46: =AVERAGE(AH46:AS46) | BE46: =AVERAGE(AJ46:AU46) | BG46: 55.779
C47: Prepaid other miscellaneous | D47: 141501 | E47: 141501 - Prepaid Other Miscellaneous | AP47: 54.932 | AQ47: 84.304 | AR47: 87.555 | AS47: 89.944 | AT47: 81.6555 | AU47: 66.84682 | AV47: =Q47 | AW47: =AC47 | AX47: =AO47 | AY47: =AS47 | AZ47: =AU47 | BA47: =AVERAGE(F47:Q47) | BB47: =AVERAGE(R47:AC47) | BC47: =AVERAGE(AD47:AO47) | BD47: =AVERAGE(AH47:AS47) | BE47: =AVERAGE(AJ47:AU47) | BG47: 59.901
C48: Prepaid marketing & tradeshow | D48: 141502 | E48: 141502 - Prepaid Marketing & Tradeshow | AP48: 3.681 | AQ48: 27.827 | AR48: 27.748 | AS48: 41.704 | AT48: 13.67372 | AU48: 10.56226 | AV48: =Q48 | AW48: =AC48 | AX48: =AO48 | AY48: =AS48 | AZ48: =AU48 | BA48: =AVERAGE(F48:Q48) | BB48: =AVERAGE(R48:AC48) | BC48: =AVERAGE(AD48:AO48) | BD48: =AVERAGE(AH48:AS48) | BE48: =AVERAGE(AJ48:AU48) | BG48: 12.555
C49: Prepaid expenses | AP49: =SUM(AP42:AP48) | AQ49: =SUM(AQ42:AQ48) | AR49: =SUM(AR42:AR48) | AS49: =SUM(AS42:AS48) | AT49: =SUM(AT42:AT48) | AU49: =SUM(AU42:AU48) | AV49: =SUM(AV42:AV48) | AW49: =SUM(AW42:AW48) | ... BE49: =SUM(BE42:BE48) | BG49: =SUM(BG42:BG48)
C50: Contract assets current IFRS15 | D50: 148015 | E50: 148015 - Contract Assets Current IFRS15 | AP50: 557.412 | AQ50: 453.443 | AR50: 440.59 | AS50: 407.388 | AT50: 372.07684 | AU50: 321.22466 | AV50: =Q50 | AW50: =AC50 | AX50: =AO50 | AY50: =AS50 | AZ50: =AU50 | BA50: =AVERAGE(F50:Q50) | BB50: =AVERAGE(R50:AC50) | BC50: =AVERAGE(AD50:AO50) | BD50: =AVERAGE(AH50:AS50) | BE50: =AVERAGE(AJ50:AU50) | BG50: 1010.722
C51: Unbilled revenue | AP51: =SUM(AP50) | AQ51: =SUM(AQ50) | AR51: =SUM(AR50) | AS51: =SUM(AS50) | AT51: =SUM(AT50) | AU51: =SUM(AU50) | AV51: =SUM(AV50) | AW51: =SUM(AW50) | ... BE51: =SUM(BE50) | BG51: =SUM(BG50)
C52: Current assets | AP52: =SUM(AP51,AP49,AP41,AP37,AP26,AP16) | AQ52: =SUM(AQ51,AQ49,AQ41,AQ37,AQ26,AQ16) | AR52: =SUM(AR51,AR49,AR41,AR37,AR26,AR16) | AS52: =SUM(AS51,AS49,AS41,AS37,AS26,AS16) | AT52: =SUM(AT51,AT49,AT41,AT37,AT26,AT16) | AU52: =SUM(AU51,AU49,AU41,AU37,AU26,AU16) | AV52: =SUM(AV51,AV49,AV41,AV37,AV26,AV16) | AW52: =SUM(AW51,AW49,AW41,AW37,AW26,AW16) | ... BE52: =SUM(BE51,BE49,BE41,BE37,BE26,BE16) | BG52: =SUM(BG51,BG49,BG41,BG37,BG26,BG16)
C53: Data processing equipment | D53: 150801 | E53: 150801 - Data Processing Equipment | AP53: 1641.308 | AQ53: 1644.22 | AR53: 1653.481 | AS53: 1653.481 | AT53: 1669.977 | AU53: 1674.6583 | AV53: =Q53 | AW53: =AC53 | AX53: =AO53 | AY53: =AS53 | AZ53: =AU53 | BA53: =AVERAGE(F53:Q53) | BB53: =AVERAGE(R53:AC53) | BC53: =AVERAGE(AD53:AO53) | BD53: =AVERAGE(AH53:AS53) | BE53: =AVERAGE(AJ53:AU53) | BG53: 4609.354
C54: Building - rou asset | D54: 150401 | E54: 150401 - Building - ROU Asset | AP54: 1637.369 | AQ54: 1637.369 | AR54: 1637.369 | AS54: 1637.369 | AT54: 1637.369 | AU54: 1637.369 | AV54: =Q54 | AW54: =AC54 | AX54: =AO54 | AY54: =AS54 | AZ54: =AU54 | BA54: =AVERAGE(F54:Q54) | BB54: =AVERAGE(R54:AC54) | BC54: =AVERAGE(AD54:AO54) | BD54: =AVERAGE(AH54:AS54) | BE54: =AVERAGE(AJ54:AU54) | BG54: 1637.369
C55: Leased asset | D55: 150920 | E55: 150920 - Leased Asset | AP55: 1558.572 | AQ55: 1558.572 | AR55: 1558.572 | AS55: 1558.572 | AT55: 1558.5717 | AU55: 1558.5717 | AV55: =Q55 | AW55: =AC55 | AX55: =AO55 | AY55: =AS55 | AZ55: =AU55 | BA55: =AVERAGE(F55:Q55) | BB55: =AVERAGE(R55:AC55) | BC55: =AVERAGE(AD55:AO55) | BD55: =AVERAGE(AH55:AS55) | BE55: =AVERAGE(AJ55:AU55) | BG55: 0
C56: Leasehold improvements | D56: 150501 | E56: 150501 - Leasehold Improvements | AP56: 1003.479 | AQ56: 1003.479 | AR56: 1003.479 | AS56: 1003.479 | AT56: 1003.479 | AU56: 1003.479 | AV56: =Q56 | AW56: =AC56 | AX56: =AO56 | AY56: =AS56 | AZ56: =AU56 | BA56: =AVERAGE(F56:Q56) | BB56: =AVERAGE(R56:AC56) | BC56: =AVERAGE(AD56:AO56) | BD56: =AVERAGE(AH56:AS56) | BE56: =AVERAGE(AJ56:AU56) | BG56: 1003.479
C57: Capitalize HW implementation | D57: 150901 | E57: 150901 - Capitalize HW Implementation | AP57: 996.476 | AQ57: 996.476 | AR57: 996.476 | AS57: 996.476 | AT57: 996.47612 | AU57: 996.47612 | AV57: =Q57 | AW57: =AC57 | AX57: =AO57 | AY57: =AS57 | AZ57: =AU57 | BA57: =AVERAGE(F57:Q57) | BB57: =AVERAGE(R57:AC57) | BC57: =AVERAGE(AD57:AO57) | BD57: =AVERAGE(AH57:AS57) | BE57: =AVERAGE(AJ57:AU57) | BG57: 0
C58: Network equipment | D58: 150820 | E58: 150820 - Network Equipment | AP58: 340.77 | AQ58: 340.77 | AR58: 343.971 | AS58: 360.686 | AT58: 360.68626 | AU58: 360.68626 | AV58: =Q58 | AW58: =AC58 | AX58: =AO58 | AY58: =AS58 | AZ58: =AU58 | BA58: =AVERAGE(F58:Q58) | BB58: =AVERAGE(R58:AC58) | BC58: =AVERAGE(AD58:AO58) | BD58: =AVERAGE(AH58:AS58) | BE58: =AVERAGE(AJ58:AU58) | BG58: 0
C59: Furniture and fixtures | D59: 150601 | E59: 150601 - Furniture and Fixtures | AP59: 191.006 | AQ59: 191.006 | AR59: 191.006 | AS59: 191.006 | AT59: 191.00522 | AU59: 191.00522 | AV59: =Q59 | AW59: =AC59 | AX59: =AO59 | AY59: =AS59 | AZ59: =AU59 | BA59: =AVERAGE(F59:Q59) | BB59: =AVERAGE(R59:AC59) | BC59: =AVERAGE(AD59:AO59) | BD59: =AVERAGE(AH59:AS59) | BE59: =AVERAGE(AJ59:AU59) | BG59: 193.575
C60: Purchased fixed assets - WIP | D60: 151101 | E60: 151101 - Purchased Fixed Assets - WIP | AP60: 18.912 | AQ60: 24.604 | AR60: 68.845 | AS60: 77.656 | AT60: 70.06461 | AU60: 110.08588 | AV60: =Q60 | AW60: =AC60 | AX60: =AO60 | AY60: =AS60 | AZ60: =AU60 | BA60: =AVERAGE(F60:Q60) | BB60: =AVERAGE(R60:AC60) | BC60: =AVERAGE(AD60:AO60) | BD60: =AVERAGE(AH60:AS60) | BE60: =AVERAGE(AJ60:AU60) | BG60: 77.375
C61: Office equipment | D61: 150701 | E61: 150701 - Office Equipment | AP61: 52.645 | AQ61: 52.645 | AR61: 52.645 | AS61: 52.645 | AT61: 52.64392 | AU61: 52.64392 | AV61: =Q61 | AW61: =AC61 | AX61: =AO61 | AY61: =AS61 | AZ61: =AU61 | BA61: =AVERAGE(F61:Q61) | BB61: =AVERAGE(R61:AC61) | BC61: =AVERAGE(AD61:AO61) | BD61: =AVERAGE(AH61:AS61) | BE61: =AVERAGE(AJ61:AU61) | BG61: 50.407
C62: Network equipment - WIP | D62: 151120 | E62: 151120 - Network Equipment - WIP | AP62: 9.603 | AQ62: 9.603 | AR62: 30.92 | AS62: 27.718 | AT62: 27.7184 | AU62: 27.7184 | AV62: =Q62 | AW62: =AC62 | AX62: =AO62 | AY62: =AS62 | AZ62: =AU62 | BA62: =AVERAGE(F62:Q62) | BB62: =AVERAGE(R62:AC62) | BC62: =AVERAGE(AD62:AO62) | BD62: =AVERAGE(AH62:AS62) | BE62: =AVERAGE(AJ62:AU62) | BG62: 0
C63: Cap HW implementation - WIP | D63: 151105 | E63: 151105 - Cap HW implementation - WIP | AP63: 0 | AQ63: 0 | AR63: 0 | AS63: 0 | AT63: 0 | AU63: 0 | AV63: =Q63 | AW63: =AC63 | AX63: =AO63 | AY63: =AS63 | AZ63: =AU63 | BA63: =AVERAGE(F63:Q63) | BB63: =AVERAGE(R63:AC63) | BC63: =AVERAGE(AD63:AO63) | BD63: =AVERAGE(AH63:AS63) | BE63: =AVERAGE(AJ63:AU63) | BG63: 0
C64: Accum dep - office equipment | D64: 155701 | E64: 155701 - Accum Dep - Office Equipment | AP64: -51.845 | AQ64: -51.918 | AR64: -51.991 | AS64: -52.043 | AT64: -52.09438 | AU64: -52.14646 | AV64: =Q64 | AW64: =AC64 | AX64: =AO64 | AY64: =AS64 | AZ64: =AU64 | BA64: =AVERAGE(F64:Q64) | BB64: =AVERAGE(R64:AC64) | BC64: =AVERAGE(AD64:AO64) | BD64: =AVERAGE(AH64:AS64) | BE64: =AVERAGE(AJ64:AU64) | BG64: -45.43
... C71: Accum dep - data processing equipment | D71: 155801 | E71: 155801 - Accum Dep - Data Processing Equipment | AP71: -1341.517 | AQ71: -1352.438 | AR71: -1363.585 | AS71: -1374.513 | AT71: -1386.6632 | AU71: -1397.789 | AV71: =Q71 | AW71: =AC71 | AX71: =AO71 | AY71: =AS71 | AZ71: =AU71 | BA71: =AVERAGE(F71:Q71) | BB71: =AVERAGE(R71:AC71) | BC71: =AVERAGE(AD71:AO71) | BD71: =AVERAGE(AH71:AS71) | BE71: =AVERAGE(AJ71:AU71) | BG71: -3406.95
C72: Property & equipment | AP72: =SUM(AP53:AP71) | AQ72: =SUM(AQ53:AQ71) | AR72: =SUM(AR53:AR71) | AS72: =SUM(AS53:AS71) | AT72: =SUM(AT53:AT71) | AU72: =SUM(AU53:AU71) | AV72: =SUM(AV53:AV71) | AW72: =SUM(AW53:AW71) | ... BE72: =SUM(BE53:BE71) | BG72: =SUM(BG53:BG71)
C73: IDSW - capitalized projects | D73: 170801 | E73: 170801 - IDSW - Capitalized Projects | AP73: 24177.843 | AQ73: 24177.843 | AR73: 24249.356 | AS73: 24249.356 | AT73: 24249.356 | AU73: 24249.356 | AV73: =Q73 | AW73: =AC73 | AX73: =AO73 | AY73: =AS73 | AZ73: =AU73 | BA73: =AVERAGE(F73:Q73) | BB73: =AVERAGE(R73:AC73) | BC73: =AVERAGE(AD73:AO73) | BD73: =AVERAGE(AH73:AS73) | BE73: =AVERAGE(AJ73:AU73) | BG73: 21900.692
C74: IDSW capitalized projects WIP | D74: 170805 | E74: 170805 - IDSW Capitalized Projects WIP | AP74: 2135.395 | AQ74: 2307.427 | AR74: 2426.145 | AS74: 2606.737 | AT74: 2821.5055 | AU74: 3016.7906 | AV74: =Q74 | AW74: =AC74 | AX74: =AO74 | AY74: =AS74 | AZ74: =AU74 | BA74: =AVERAGE(F74:Q74) | BB74: =AVERAGE(R74:AC74) | BC74: =AVERAGE(AD74:AO74) | BD74: =AVERAGE(AH74:AS74) | BE74: =AVERAGE(AJ74:AU74) | BG74: 986.027
C75: Accum amort - IDSW capitalized projects | D75: 175801 | E75: 175801 - Accum Amort - IDSW Capitalized Projects | AP75: -22988.201 | AQ75: -23056.952 | AR75: -23125.702 | AS75: -23194.453 | AT75: -23263.204 | AU75: -23298.702 | AV75: =Q75 | AW75: =AC75 | AX75: =AO75 | AY75: =AS75 | AZ75: =AU75 | BA75: =AVERAGE(F75:Q75) | BB75: =AVERAGE(R75:AC75) | BC75: =AVERAGE(AD75:AO75) | BD75: =AVERAGE(AH75:AS75) | BE75: =AVERAGE(AJ75:AU75) | BG75: -20555.299
C76: Capitalized development | AP76: =SUM(AP73:AP75) | AQ76: =SUM(AQ73:AQ75) | AR76: =SUM(AR73:AR75) | AS76: =SUM(AS73:AS75) | AT76: =SUM(AT73:AT75) | AU76: =SUM(AU73:AU75) | AV76: =SUM(AV73:AV75) | AW76: =SUM(AW73:AW75) | ... BE76: =SUM(BE73:BE75) | BG76: =SUM(BG73:BG75)
C77: Purchased software | D77: 170101 | E77: 170101 - Purchased Software | AP77: 10761.903 | AQ77: 10926.103 | AR77: 10926.103 | AS77: 10926.103 | AT77: 10926.103 | AU77: 10933.303 | AV77: =Q77 | AW77: =AC77 | AX77: =AO77 | AY77: =AS77 | AZ77: =AU77 | BA77: =AVERAGE(F77:Q77) | BB77: =AVERAGE(R77:AC77) | BC77: =AVERAGE(AD77:AO77) | BD77: =AVERAGE(AH77:AS77) | BE77: =AVERAGE(AJ77:AU77) | BG77: 11152.515
C78: Purchased software - WIP | D78: 170151 | E78: 170151 - Purchased Software - WIP | AP78: 2176.029 | AQ78: 2013.859 | AR78: 2046.981 | AS78: 2065.36 | AT78: 2083.2309 | AU78: 2100.6668 | AV78: =Q78 | AW78: =AC78 | AX78: =AO78 | AY78: =AS78 | AZ78: =AU78 | BA78: =AVERAGE(F78:Q78) | BB78: =AVERAGE(R78:AC78) | BC78: =AVERAGE(AD78:AO78) | BD78: =AVERAGE(AH78:AS78) | BE78: =AVERAGE(AJ78:AU78) | BG78: 524.314
C79: System software purchased- infrastructure | D79: 170121 | E79: 170121 - System Software Purchased- Infrastructure | AP79: 1147.966 | AQ79: 1147.966 | AR79: 1147.966 | AS79: 1147.966 | AT79: 1147.9656 | AU79: 1147.9656 | AV79: =Q79 | AW79: =AC79 | AX79: =AO79 | AY79: =AS79 | AZ79: =AU79 | BA79: =AVERAGE(F79:Q79) | BB79: =AVERAGE(R79:AC79) | BC79: =AVERAGE(AD79:AO79) | BD79: =AVERAGE(AH79:AS79) | BE79: =AVERAGE(AJ79:AU79) | BG79: 1345.444
C80: Accum amort - system software- infrastructure | D80: 175121 | E80: 175121 - Accum Amort - System Software- Infrastructure | AP80: -753.467 | AQ80: -764.351 | AR80: -775.236 | AS80: -786.121 | AT80: -797.00588 | AU80: -807.89069 | AV80: =Q80 | AW80: =AC80 | AX80: =AO80 | AY80: =AS80 | AZ80: =AU80 | BA80: =AVERAGE(F80:Q80) | BB80: =AVERAGE(R80:AC80) | BC80: =AVERAGE(AD80:AO80) | BD80: =AVERAGE(AH80:AS80) | BE80: =AVERAGE(AJ80:AU80) | BG80: -572.569
C81: Accum amort - purchased software | D81: 175101 | E81: 175101 - Accum Amort - Purchased Software | AP81: -8214.416 | AQ81: -8309.505 | AR81: -8404.591 | AS81: -8499.679 | AT81: -8594.5972 | AU81: -8689.8307 | AV81: =Q81 | AW81: =AC81 | AX81: =AO81 | AY81: =AS81 | AZ81: =AU81 | BA81: =AVERAGE(F81:Q81) | BB81: =AVERAGE(R81:AC81) | BC81: =AVERAGE(AD81:AO81) | BD81: =AVERAGE(AH81:AS81) | BE81: =AVERAGE(AJ81:AU81) | BG81: -8047.459
C82: Purchased software assets | AP82: =SUM(AP77:AP81) | AQ82: =SUM(AQ77:AQ81) | AR82: =SUM(AR77:AR81) | AS82: =SUM(AS77:AS81) | AT82: =SUM(AT77:AT81) | AU82: =SUM(AU77:AU81) | AV82: =SUM(AV77:AV81) | AW82: =SUM(AW77:AW81) | ... BE82: =SUM(BE77:BE81) | BG82: =SUM(BG77:BG81)
C83: Goodwill | D83: 160101 | E83: 160101 - Goodwill | AP83: 7695.101 | AQ83: 7695.101 | AR83: 7695.101 | AS83: 7695.101 | AT83: 7695.101 | AU83: 7695.101 | AV83: =Q83 | AW83: =AC83 | AX83: =AO83 | AY83: =AS83 | AZ83: =AU83 | BA83: =AVERAGE(F83:Q83) | BB83: =AVERAGE(R83:AC83) | BC83: =AVERAGE(AD83:AO83) | BD83: =AVERAGE(AH83:AS83) | BE83: =AVERAGE(AJ83:AU83) | BG83: 7695.101
C84: Goodwill | AP84: =SUM(AP83) | AQ84: =SUM(AQ83) | AR84: =SUM(AR83) | AS84: =SUM(AS83) | AT84: =SUM(AT83) | AU84: =SUM(AU83) | AV84: =SUM(AV83) | AW84: =SUM(AW83) | ... BE84: =SUM(BE83) | BG84: =SUM(BG83)
C85: Investment in shares | D85: 180101 | E85: 180101 - Investment in Shares | AP85: 940.538 | AQ85: 940.538 | AR85: 940.538 | AS85: 940.538 | AT85: 940.53762 | AU85: 940.53762 | AV85: =Q85 | AW85: =AC85 | AX85: =AO85 | AY85: =AS85 | AZ85: =AU85 | BA85: =AVERAGE(F85:Q85) | BB85: =AVERAGE(R85:AC85) | BC85: =AVERAGE(AD85:AO85) | BD85: =AVERAGE(AH85:AS85) | BE85: =AVERAGE(AJ85:AU85) | BG85: 686.933
C86: Investment in | AP86: =SUM(AP85) | AQ86: =SUM(AQ85) | AR86: =SUM(AR85) | AS86: =SUM(AS85) | AT86: =SUM(AT85) | AU86: =SUM(AU85) | AV86: =SUM(AV85) | AW86: =SUM(AW85) | ... BE86: =SUM(BE85) | BG86: =SUM(BG85)
C87: Contract assets - lT IFRS15 | D87: 191515 | E87: 191515 - CONTRACT ASSETS - LT IFRS15 | AP87: 530.309 | AQ87: 630.309 | AR87: 666.059 | AS87: 701.309 | AT87: 743.57121 | AU87: 756.1712 | AV87: =Q87 | AW87: =AC87 | AX87: =AO87 | AY87: =AS87 | AZ87: =AU87 | BA87: =AVERAGE(F87:Q87) | BB87: =AVERAGE(R87:AC87) | BC87: =AVERAGE(AD87:AO87) | BD87: =AVERAGE(AH87:AS87) | BE87: =AVERAGE(AJ87:AU87) | BG87: 1204.859
C88: Deferred implementation costs - non-current | AP88: =SUM(AP87) | AQ88: =SUM(AQ87) | AR88: =SUM(AR87) | AS88: =SUM(AS87) | AT88: =SUM(AT87) | AU88: =SUM(AU87) | AV88: =SUM(AV87) | AW88: =SUM(AW87) | ... BE88: =SUM(BE87) | BG88: =SUM(BG87)
C89: Long-term prepayments | D89: 192201 | E89: 192201 - Long-Term Prepayments | AP89: 590.741 | AQ89: 590.741 | AR89: 505.565 | AS89: 505.565 | AT89: 505.56633 | AU89: 420.39192 | AV89: =Q89 | AW89: =AC89 | AX89: =AO89 | AY89: =AS89 | AZ89: =AU89 | BA89: =AVERAGE(F89:Q89) | BB89: =AVERAGE(R89:AC89) | BC89: =AVERAGE(AD89:AO89) | BD89: =AVERAGE(AH89:AS89) | BE89: =AVERAGE(AJ89:AU89) | BG89: 2414.843
C90: Long-term security deposit | D90: 192202 | E90: 192202 - Long-Term Security Deposit | AP90: 42.593 | AQ90: 42.593 | AR90: 42.593 | AS90: 38.88 | AT90: 35.16705 | AU90: 42.59295 | AV90: =Q90 | AW90: =AC90 | AX90: =AO90 | AY90: =AS90 | AZ90: =AU90 | BA90: =AVERAGE(F90:Q90) | BB90: =AVERAGE(R90:AC90) | BC90: =AVERAGE(AD90:AO90) | BD90: =AVERAGE(AH90:AS90) | BE90: =AVERAGE(AJ90:AU90) | BG90: 50.019
C91: Long term COGS lock n block | D91: 192203 | E91: 192203 - Long Term COGS Lock N Block | AP91: 0 | AQ91: 0 | AR91: 0 | AS91: 0 | AT91: 0 | AU91: 0 | AV91: =Q91 | AW91: =AC91 | AX91: =AO91 | AY91: =AS91 | AZ91: =AU91 | BA91: =AVERAGE(F91:Q91) | BB91: =AVERAGE(R91:AC91) | BC91: =AVERAGE(AD91:AO91) | BD91: =AVERAGE(AH91:AS91) | BE91: =AVERAGE(AJ91:AU91) | BG91: 32.634
C92: Long-term sec deposit IFRS adj-corp | D92: 192216 | E92: 192216 - Long-Term Sec Deposit IFRS ADJ-Corp | AP92: -27.864 | AQ92: -27.864 | AR92: -27.864 | AS92: -27.864 | AT92: -27.86375 | AU92: -27.86375 | AV92: =Q92 | AW92: =AC92 | AX92: =AO92 | AY92: =AS92 | AZ92: =AU92 | BA92: =AVERAGE(F92:Q92) | BB92: =AVERAGE(R92:AC92) | BC92: =AVERAGE(AD92:AO92) | BD92: =AVERAGE(AH92:AS92) | BE92: =AVERAGE(AJ92:AU92) | BG92: -27.864
C93: Prepaid contractual payments - non-current | AP93: =SUM(AP89:AP92) | AQ93: =SUM(AQ89:AQ92) | AR93: =SUM(AR89:AR92) | AS93: =SUM(AS89:AS92) | AT93: =SUM(AT89:AT92) | AU93: =SUM(AU89:AU92) | AV93: =SUM(AV89:AV92) | AW93: =SUM(AW89:AW92) | ... BE93: =SUM(BE89:BE92) | BG93: =SUM(BG89:BG92)
C94: Non current assets | AP94: =SUM(AP72,AP76,AP82,AP84,AP86,AP88,AP93) | AQ94: =SUM(AQ72,AQ76,AQ82,AQ84,AQ86,AQ88,AQ93) | AR94: =SUM(AR72,AR76,AR82,AR84,AR86,AR88,AR93) | AS94: =SUM(AS72,AS76,AS82,AS84,AS86,AS88,AS93) | AT94: =SUM(AT72,AT76,AT82,AT84,AT86,AT88,AT93) | AU94: =SUM(AU72,AU76,AU82,AU84,AU86,AU88,AU93) | AV94: =SUM(AV72,AV76,AV82,AV84,AV86,AV88,AV93) | AW94: =SUM(AW72,AW76,AW82,AW84,AW86,AW88,AW93) | ... BE94: =SUM(BE72,BE76,BE82,BE84,BE86,BE88,BE93) | BG94: =SUM(BG72,BG76,BG82,BG84,BG86,BG88,BG93)
C95: Assets | AP95: =SUM(AP94,AP52) | AQ95: =SUM(AQ94,AQ52) | AR95: =SUM(AR94,AR52) | AS95: =SUM(AS94,AS52) | AT95: =SUM(AT94,AT52) | AU95: =SUM(AU94,AU52) | AV95: =SUM(AV94,AV52) | AW95: =SUM(AW94,AW52) | ... BE95: =SUM(BE94,BE52) | BG95: =SUM(BG94,BG52)
C96: Liabilities and equity
C97: Trade accounts payable - CAD | D97: 200101 | E97: 200101 - Trade Accounts Payable - CAD | AP97: -961.078 | AQ97: -1824.389 | AR97: -1899.984 | AS97: -1834.813 | AT97: -1263.7598 | AU97: -999.53627 | AV97: =Q97 | AW97: =AC97 | AX97: =AO97 | AY97: =AS97 | AZ97: =AU97 | BA97: =AVERAGE(F97:Q97) | BB97: =AVERAGE(R97:AC97) | BC97: =AVERAGE(AD97:AO97) | BD97: =AVERAGE(AH97:AS97) | BE97: =AVERAGE(AJ97:AU97) | BG97: -431.77
C98: Trade accounts payable - USD | D98: 200101 | E98: 200101 - Trade Accounts Payable - USD | AP98: 8.099 | AQ98: -45.914 | AR98: 12.93 | AS98: -10.666 | AT98: -50.03399 | AU98: -4.68756 | AV98: =Q98 | AW98: =AC98 | AX98: =AO98 | AY98: =AS98 | AZ98: =AU98 | BA98: =AVERAGE(F98:Q98) | BB98: =AVERAGE(R98:AC98) | BC98: =AVERAGE(AD98:AO98) | BD98: =AVERAGE(AH98:AS98) | BE98: =AVERAGE(AJ98:AU98) | BG98: 0
C99: Trade accounts payable | AP99: =SUM(AP97:AP98) | AQ99: =SUM(AQ97:AQ98) | AR99: =SUM(AR97:AR98) | AS99: =SUM(AS97:AS98) | AT99: =SUM(AT97:AT98) | AU99: =SUM(AU97:AU98) | AV99: =SUM(AV97:AV98) | AW99: =SUM(AW97:AW98) | ... BE99: =SUM(BE97:BE98) | BG99: =SUM(BG97:BG98)
C100: Accrued liabilities - COGS | D100: 214102 | E100: 214102 - Accrued Liabilities - COGS | AP100: -1624.425 | AQ100: -1716.643 | AR100: -1197.721 | AS100: -1340.494 | AT100: -1628.2556 | AU100: -1832.549 | AV100: =Q100 | AW100: =AC100 | AX100: =AO100 | AY100: =AS100 | AZ100: =AU100 | BA100: =AVERAGE(F100:Q100) | BB100: =AVERAGE(R100:AC100) | BC100: =AVERAGE(AD100:AO100) | BD100: =AVERAGE(AH100:AS100) | BE100: =AVERAGE(AJ100:AU100) | BG100: -627.9
C101: Accrued liabilites - general | D101: 214101 | E101: 214101 - Accrued Liabilites - General | AP101: -835.079 | AQ101: -793.889 | AR101: -682.958 | AS101: -735.789 | AT101: -783.91359 | AU101: -1171.703 | AV101: =Q101 | AW101: =AC101 | AX101: =AO101 | AY101: =AS101 | AZ101: =AU101 | BA101: =AVERAGE(F101:Q101) | BB101: =AVERAGE(R101:AC101) | BC101: =AVERAGE(AD101:AO101) | BD101: =AVERAGE(AH101:AS101) | BE101: =AVERAGE(AJ101:AU101) | BG101: -385.733
C102: Accrued liaibilites -c2c conversions team | D102: 214101 | E102: 214101 - Accrued Liaibilites -C2C Conversions Team | AP102: -0.063 | AQ102: -0.062 | AR102: 0 | AS102: 0 | AT102: 0 | AU102: 0 | AV102: =Q102 | AW102: =AC102 | AX102: =AO102 | AY102: =AS102 | AZ102: =AU102 | BA102: =AVERAGE(F102:Q102) | BB102: =AVERAGE(R102:AC102) | BC102: =AVERAGE(AD102:AO102) | BD102: =AVERAGE(AH102:AS102) | BE102: =AVERAGE(AJ102:AU102) | BG102: -0.049
C103: Accrued liabilities - celero and cu centrals | D103: 214103 | E103: 214103 - Accrued Liabilities - Celero and CU Centrals | AP103: -304.679 | AQ103: -324.134 | AR103: -207.45 | AS103: -207.575 | AT103: -207.69952 | AU103: -213.78716 | AV103: =Q103 | AW103: =AC103 | AX103: =AO103 | AY103: =AS103 | AZ103: =AU103 | BA103: =AVERAGE(F103:Q103) | BB103: =AVERAGE(R103:AC103) | BC103: =AVERAGE(AD103:AO103) | BD103: =AVERAGE(AH103:AS103) | BE103: =AVERAGE(AJ103:AU103) | BG103: -33.001
C104: Accrued liabilities -intercompany - co-op vcas | D104: 249850 | E104: 249850 - Accrued Liabilities -Intercompany - Co-Op VCAS | AP104: -34.714 | AQ104: -37.504 | AR104: -47.536 | AS104: -46.118 | AT104: -48.73962 | AU104: -59.94911 | AV104: =Q104 | AW104: =AC104 | AX104: =AO104 | AY104: =AS104 | AZ104: =AU104 | BA104: =AVERAGE(F104:Q104) | BB104: =AVERAGE(R104:AC104) | BC104: =AVERAGE(AD104:AO104) | BD104: =AVERAGE(AH104:AS104) | BE104: =AVERAGE(AJ104:AU104) | BG104: 0
C105: Accrued liabilities - fixed assets | D105: 214105 | E105: 214105 - Accrued Liabilities - Fixed Assets | AP105: -32.023 | AQ105: -24.702 | AR105: -18.169 | AS105: -23.979 | AT105: -24.20678 | AU105: -15.73428 | AV105: =Q105 | AW105: =AC105 | AX105: =AO105 | AY105: =AS105 | AZ105: =AU105 | BA105: =AVERAGE(F105:Q105) | BB105: =AVERAGE(R105:AC105) | BC105: =AVERAGE(AD105:AO105) | BD105: =AVERAGE(AH105:AS105) | BE105: =AVERAGE(AJ105:AU105) | BG105: -4.233
C106: Accrued liabilities | AP106: =SUM(AP100:AP105) | AQ106: =SUM(AQ100:AQ105) | AR106: =SUM(AR100:AR105) | AS106: =SUM(AS100:AS105) | AT106: =SUM(AT100:AT105) | AU106: =SUM(AU100:AU105) | AV106: =SUM(AV100:AV105) | AW106: =SUM(AW100:AW105) | ... BE106: =SUM(BE100:BE105) | BG106: =SUM(BG100:BG105)
C107: Sales tax payable - PST BC | D107: 208323 | E107: 208323 - Sales Tax Payable - PST BC | AP107: -66.4 | AQ107: -68.412 | AR107: -100.924 | AS107: -68.237 | AT107: -71.41061 | AU107: -69.97694 | AV107: =Q107 | AW107: =AC107 | AX107: =AO107 | AY107: =AS107 | AZ107: =AU107 | BA107: =AVERAGE(F107:Q107) | BB107: =AVERAGE(R107:AC107) | BC107: =AVERAGE(AD107:AO107) | BD107: =AVERAGE(AH107:AS107) | BE107: =AVERAGE(AJ107:AU107) | BG107: -26.877
C108: Sales tax payable - HST/GST | D108: 208319 | E108: 208319 - Sales Tax Payable - HST/GST | AP108: -490.25 | AQ108: -527.836 | AR108: -571.048 | AS108: -492.086 | AT108: -524.35599 | AU108: -538.06905 | AV108: =Q108 | AW108: =AC108 | AX108: =AO108 | AY108: =AS108 | AZ108: =AU108 | BA108: =AVERAGE(F108:Q108) | BB108: =AVERAGE(R108:AC108) | BC108: =AVERAGE(AD108:AO108) | BD108: =AVERAGE(AH108:AS108) | BE108: =AVERAGE(AJ108:AU108) | BG108: -289.329
...

Sheet Cash flow
B1: Project Name
B2: =C7
B3: Source: TBD
B4: WORKING DRAFT
C7: Cash flow
C8: $'000 | D8: Code | E8: Concatenate | F8: 44197 | G8: =EOMONTH(F8,1) | H8: =EOMONTH(G8,1) | I8: =EOMONTH(H8,1) | J8: =EOMONTH(I8,1) | K8: =EOMONTH(J8,1) | L8: =EOMONTH(K8,1) | M8: =EOMONTH(L8,1) | N8: =EOMONTH(M8,1) | ... AU8: =EOMONTH(AT8,1) | AV8: FY21 | AW8: FY22 | AX8: FY23 | AY8: TTM Apr-24 | AZ8: TTM Jun-24 | BB8: FY21
C9: Operating
C10: Net income
C11: Depreciation - software | D11: 707101 | E11: 707101 - Depreciation - software
C12: Depreciation - system software- infrastructure | D12: 707121 | E12: 707121 - Depreciation - system software- infrastructure
C13: Amortization expense-software
C14: Amortization expense - idsw | D14: 708201 | E14: 708201 - Amortization expense - idsw
C15: Amortization expense - internal development
C16: Depreciation - leasehold imp | D16: 705401 | E16: 705401 - Depreciation - leasehold imp
C17: Depreciation - furniture and fixtures | D17: 705501 | E17: 705501 - Depreciation - furniture and fixtures
C18: Depreciation - office equipment | D18: 705601 | E18: 705601 - Depreciation - office equipment
C19: Depreciation - data processing equipment | D19: 705701 | E19: 705701 - Depreciation - data processing equipment
C20: Depreciation - network equipment | D20: 705820 | E20: 705820 - Depreciation - network equipment
C21: Depreciation - capitalized hw implementation | D21: 705901 | E21: 705901 - Depreciation - capitalized hw implementation
C22: Depreciation - leased asset | D22: 705920 | E22: 705920 - Depreciation - leased asset
C23: Depreciation expense
C24: Depreciation - building rou asset | D24: 705301 | E24: 705301 - Depreciation - building rou asset
C25: Depreciation expense - property right of use
C26: Depreciation and amortization expense
C27: Deferred tax liability | D27: 260101 | E27: 260101 - Deferred Tax Liability
C28: Deferred tax liability IFRS- IFRS adjusted | D28: 260115 | E28: 260115 - Deferred Tax Liability IFRS- IFRS Adjusted
C29: Deferred tax liabilities
C30: Non cash items
C31: Change in working capital
C32: Cash settlement - pos desjardin 147
C33: Cash settlement scd desjardin 139
C34: Icici bank settlement CAD6932- for visa debit
C35: Cash settlement e-transfer desj suspense 067
C36: Cash settlement 178
C37: Cash settlement - pos 10403- 1154
C38: Cash settlement desj etransf 1162
C39: Cash USD - settlement td bank, n.a 154
C40: Cash settlement e-transfer 059
C41: Items in transit
C42: A/R billings-subledger | D42: 120101 | E42: 120101 - A/R Billings-Subledger
C43: A/R-trade accrual | D43: 120201 | E43: 120201 - A/R-Trade Accrual
C44: Accrued merchant services fees | D44: 120301 | E44: 120301 - Accrued Merchant Services Fees
C45: Accrued other receivable | D45: 120401 | E45: 120401 - Accrued Other Receivable
C46: Sales tax receivables - HST/GST | D46: 130301 | E46: 130301 - Sales Tax Receivables - HST/GST
C47: Interest receivables | D47: 130101 | E47: 130101 - Interest Receivables
C48: Sales tax receivables - QST | D48: 130300 | E48: 130300 - Sales Tax Receivables - QST
C49: IFRS15 adjustment to accr A/R | D49: 120215 | E49: 120215 - -IFRS15 Adjustment to Accr AR-
C50: Corporate card payments suspense | D50: 143102 | E50: 143102 - Corporate Card Payments Suspense
C51: Allowances for customers A/R | D51: 125101 | E51: 125101 - Allowances for Customers A/R
C52: Accounts receivable and other receivables
C53: Inventory - prepaid COGS | D53: 142113 | E53: 142113 - Inventory - Prepaid COGS
C54: Inventory | D54: 142101 | E54: 142101 - Inventory
C55: Inventory - rental units | D55: 142112 | E55: 142112 - Inventory - Rental Units
C56: Inventory
C57: Prepaid SW license fees | D57: 141511 | E57: 141511 - Prepaid SW License Fees
C58: Prepaid SW maintenance | D58: 141204 | E58: 141204 - Prepaid SW Maintenance
C59: Prepaid HW maintenance | D59: 141203 | E59: 141203 - Prepaid HW Maintenance
C60: Prepaid insurance | D60: 143201 | E60: 143201 - Prepaid Insurance
C61: Prepaid rent | D61: 143201 | E61: 143201 - Prepaid Rent
C62: Prepaid other miscellaneous | D62: 141501 | E62: 141501 - Prepaid Other Miscellaneous
C63: Prepaid marketing & tradeshow | D63: 141502 | E63: 141502 - Prepaid Marketing & Tradeshow
C64: Prepaid expenses
C65: Long-term prepayments | D65: 192201 | E65: 192201 - Long-Term Prepayments
C66: Long-term security deposit | D66: 192202 | E66: 192202 - Long-Term Security Deposit
C67: Long term COGS lock n block | D67: 192203 | E67: 192203 - Long Term COGS Lock N Block
C68: Long-term sec deposit IFRS adj-corp | D68: 192216 | E68: 192216 - Long-Term Sec Deposit IFRS ADJ-Corp
C69: Prepaid contractual payments - non-current
C70: Prepaid expenses and other assets
C71: Contract assets current IFRS15 | D71: 148015 | E71: 148015 - Contract Assets Current IFRS15
C72: Unbilled revenue - current
C73: Contract assets - lT IFRS15 | D73: 148015 | E73: 148015 - Contract Assets Current IFRS15
C74: Unbilled revenue - non current
C75: Unbilled revenue
C76: Trade accounts payable - CAD | D76: 200101 | E76: 200101 - Trade Accounts Payable - CAD
C77: Trade accounts payable - USD | D77: 200101 | E77: 200101 - Trade Accounts Payable - USD
C78: Trade accounts payable
C79: Accrued liabilities - COGS | D79: 214102 | E79: 214102 - Accrued Liabilities - COGS
C80: Accrued liabilites - general | D80: 214101 | E80: 214101 - Accrued Liabilites - General
C81: Accrued liaibilites -c2c conversions team | D81: 214101 | E81: 214101 - Accrued Liaibilites -C2C Conversions Team
C82: Accrued liabilities - celero and cu centrals | D82: 214103 | E82: 214103 - Accrued Liabilities - Celero and CU Centrals
C83: Accrued liabilities -intercompany - co-op vcas | D83: 249850 | E83: 249850 - Accrued Liabilities -Intercompany - Co-Op VCAS
C84: Accrued liabilities - fixed assets | D84: 214105 | E84: 214105 - Accrued Liabilities - Fixed Assets
C85: Accrued liabilities
C86: Sales tax payable - PST BC | D86: 208323 | E86: 208323 - Sales Tax Payable - PST BC
C87: Sales tax payable - HST/GST | D87: 208319 | E87: 208319 - Sales Tax Payable - HST/GST
C88: Sales tax payable - PST MB | D88: 208320 | E88: 208320 - Sales Tax Payable - PST MB
C89: Sales tax payable - PST SK | D89: 208321 | E89: 208321 - Sales Tax Payable - PST SK
C90: Sales tax payable - PST QST | D90: 208322 | E90: 208322 - Sales Tax Payable - PST QST
C91: Sales tax payable
C92: Accrued merchant residuals- chase | D92: 214112 | E92: 214112 - Accrued Merchant Residuals- CHASE
C93: Inter-company fis mv invoices | D93: 249851 | E93: 249851 - Inter-Company FIS MV Invoices
C94: Non-resident witholding tax payable | D94: 208305 | E94: 208305 - Non-resident Witholding Tax Payable
C95: Accounts payable and accrued liabilities
C96: Settlement payables - pos | D96: 225101 | E96: 225101 - Settlement Payables - POS
C97: Settlement payables - scd | D97: 225102 | E97: 225102 - Settlement Payables - SCD
C98: Settlement payables - ICICI CAD for vda | D98: 225108 | E98: 225108 - Settlement Payables - ICICI CAD for VDA
C99: Settlement etrans susp 067 | D99: 225167 | E99: TBD
C100: Unclaimed settlement | D100: 225199 | E100: 225199 - Unclaimed Settlement
C101: Settlement payables - 178 | D101: 225103 | E101: 225103 - Settlement Payables - 178
C102: Settlement payables - 10403- 1154 | D102: 225105 | E102: TBD
...

Sheet Personnel>>

Sheet IS | Payroll costs
B1: Project Name
B2: =C7
B3: Source: TBD
B4: WORKING DRAFT
C7: Personnel analysis | Reported
C8: $'000 | D8: Code | E8: Mapping | F8: 44197 | G8: =EOMONTH(F8,1) | H8: =EOMONTH(G8,1) | I8: =EOMONTH(H8,1) | J8: =EOMONTH(I8,1) | K8: =EOMONTH(J8,1) | L8: =EOMONTH(K8,1) | M8: =EOMONTH(L8,1) | N8: =EOMONTH(M8,1) | ... AU8: =EOMONTH(AT8,1) | AV8: FY21 | AW8: FY22 | AX8: FY23 | AY8: TTM Apr-24 | AZ8: TTM Jun-24
C9: Salaries & benefits per Income statement
C10: Salaries - general | D10: 531101 | E10: Salaries
C11: Salaries - ncsc | D11: 531101 | E11: Salaries
C12: Salaries - overtime & on-call | D12: 531102 | E12: Salaries
C13: Vacation pay | D13: 531104 | E13: Salaries
C14: Salary compensation
C15: Bonus - short term | D15: 531204 | E15: Bonus
C16: Bonus - long term incentive- corp | D16: 531209 | E16: Bonus
C17: Bonus compensation
C18: Canada pension plan(cpp)expe | D18: 533203 | E18: Taxes
C19: Canadian employer health tax | D19: 533205 | E19: Taxes
C20: Canadian employment ins (ei) | D20: 533204 | E20: Taxes
C21: Worker's compensation | D21: 533401 | E21: Taxes
C22: Employer taxes
C23: Disability and life insurance | D23: 532104 | E23: Benefits
C24: Cooperative employee css pension | D24: 532303 | E24: Benefits
C25: Medical insurance | D25: 532101 | E25: Benefits
C26: Dental insurance | D26: 532102 | E26: Benefits
C27: Health spending account | D27: 532103 | E27: Benefits
C28: Supplement exec retire plan- exec office | D28: 532304 | E28: Benefits
C29: Employee miscellaneous incentives | D29: 532306 | E29: Benefits
C30: Employee benefits - gas allowances | D30: 532308 | E30: Benefits
C31: Employee - other compensation | D31: 532309 | E31: Benefits
C32: Benefits
C33: Salaries - severance | D33: 531105 | E33: Salaries
C34: Severance & related costs
C35: Other payroll tax | D35: 533501 | E35: Salaries
C36: Canada emergency wage subsidy
C37: Compensation
C38: Summary
C39: Salaries
C40: Benefits
C41: Taxes
C42: Bonus
C43: Salaries & benefits
C44: As a % of total compensation
C45: Salaries
C46: Benefits
C47: Taxes
C48: Bonus
C49: Total | F49: =IFERROR(F43/F$43,0) | G49: =IFERROR(G43/G$43,0) | H49: =IFERROR(H43/H$43,0) | I49: =IFERROR(I43/I$43,0) | J49: =IFERROR(J43/J$43,0) | K49: =IFERROR(K43/K$43,0) | L49: =IFERROR(L43/L$43,0) | M49: =IFERROR(M43/M$43,0) | ... AZ49: =IFERROR(AZ43/AZ$43,0)
C50: As a % of salaries
C51: Salaries
C52: Benefits
C53: Taxes
C54: Bonus
C55: Total | F55: =IFERROR(F43/F$39,0) | G55: =IFERROR(G43/G$39,0) | H55: =IFERROR(H43/H$39,0) | I55: =IFERROR(I43/I$39,0) | J55: =IFERROR(J43/J$39,0) | K55: =IFERROR(K43/K$39,0) | L55: =IFERROR(L43/L$39,0) | M55: =IFERROR(M43/M$39,0) | ... AZ55: =IFERROR(AZ43/AZ$39,0)
C56: As a % of revenue
C57: Revenue
C58: Salaries
C59: Benefits
C60: Taxes
C61: Bonus
C62: Total | F62: =IFERROR(F43/F$57,0) | G62: =IFERROR(G43/G$57,0) | H62: =IFERROR(H43/H$57,0) | I62: =IFERROR(I43/I$57,0) | J62: =IFERROR(J43/J$57,0) | K62: =IFERROR(K43/K$57,0) | L62: =IFERROR(L43/L$57,0) | M62: =IFERROR(M43/M$57,0) | ... AZ62: =IFERROR(AZ43/AZ$57,0)
C63: Average cost per employee ($'000)
C64: Headcount
C65: Salaries
C66: Benefits
C67: Taxes
C68: Bonus
C69: Total | F69: =IFERROR(F43/F$64,0) | G69: =IFERROR(G43/G$64,0) | H69: =IFERROR(H43/H$64,0) | I69: =IFERROR(I43/I$64,0) | J69: =IFERROR(J43/J$64,0) | K69: =IFERROR(K43/K$64,0) | L69: =IFERROR(L43/L$64,0) | M69: =IFERROR(M43/M$64,0) | ... AZ69: =IFERROR(AZ43/AZ$64,0)
C71: Per IS
C72: Check | F72: =F71-F37 | G72: =G71-G37 | H72: =H71-H37 | I72: =I71-I37 | J72: =J71-J37 | K72: =K71-K37 | L72: =L71-L37 | M72: =M71-M37 | ... AZ72: =AZ71-AZ37
C73: % YoY Change in total salaries | AW73: =AW39/AV39-1 | AX73: =AX39/AW39-1 | AY73: =AY39/AX39-1 | AZ73: =AZ39/AX39-1
C74: % YoY Change in average salaries per employee

Sheet Headcount census
B1: Project Name
B2: =C8
B3: Source: TBD
B4: WORKING DRAFT
C8: Payroll and headcount analysis
J9: Annualized salary | P9: FTE | V9: Headcount FTE | AH9: =V9 | AT9: =AH9 | BF9: =AT9 | BL9: =BF9
C10: # | D10: Employee ID | E10: Hire Date | F10: Service Date | G10: Term. Date | H10: Birth date | I10: Gender | J10: FY21 | K10: FY22 | L10: FY23 | P10: FY21 | Q10: FY22 | R10: FY23 | BL10: FY21 | BM10: FY22 | BN10: FY23 | BO10: TTM Apr-24 | BP10: TTM Jun-24
C11: [Redacted] | D11: 11086 | I11: M
C12: [Redacted] | D12: 11319 | I12: M
C13: [Redacted] | D13: 11027 | I13: M
C14: [Redacted] | D14: 11253 | I14: M
C15: [Redacted] | D15: 11064 | I15: M
C16: [Redacted] | D16: 11352 | I16: M
C17: [Redacted] | D17: 11231 | I17: F
C18: [Redacted] | D18: 11338 | I18: M
C19: [Redacted] | D19: 11323 | I19: M
C20: [Redacted] | D20: 11351 | I20: F
C21: [Redacted] | D21: 11058 | I21: M
C22: [Redacted] | D22: 11123 | I22: F
... C107: [Redacted] | D107: 11296 | I107: M
C108: [Redacted] | D108: 11381 | I108: F | BR108: >>This employee is terminated in Feb-24 but included in May-24 headcount source.
C109: [Redacted] | D109: 11335 | I109: F
C110: [Redacted] | D110: 11256 | I110: F
C111: [Redacted] | D111: 11160 | I111: M
C112: [Redacted] | D112: 11223 | I112: M
C113: [Redacted] | D113: 11349 | I113: M
C114: [Redacted] | D114: 11235 | I114: M
C115: [Redacted] | D115: 11383 | I115: M
C116: [Redacted] | D116: 11364 | I116: M
C117: [Redacted] | D117: 11369 | I117: M
C118: [Redacted] | D118: 11380 | I118: F
C119: [Redacted] | D119: 11343 | I119: F
C120: [Redacted] | D120: 11255 | I120: F
... C127: [Redacted] | D127: 11372 | I127: F
C128: [Redacted] | D128: 11243 | I128: M | BR128: >>This employee is terminated in Jan-24 but included in May-24 headcount source.
C129: [Redacted] | D129: 11387 | I129: M
C130: [Redacted] | D130: 11377 | I130: M
C131: [Redacted] | D131: 11382 | I131: M
C132: [Redacted] | D132: 11385 | I132: F
C133: [Redacted] | D133: 11384 | I133: F
C134: [Redacted] | D134: 11325 | I134: M
C135: [Redacted] | D135: 11167 | I135: M
C136: [Redacted] | D136: 11236 | I136: M
C137: [Redacted] | D137: 11300 | I137: F
C138: [Redacted] | D138: 11032 | I138: F
C139: [Redacted] | D139: 11009 | I139: M | BR139: >>Employee is terminated in 29-Dec-22. Manually included headcount for Dec-22 as active for majority of the year,
C140: [Redacted] | D140: 11126 | I140: M
C141: [Redacted] | D141: 11246 | I141: F
C142: [Redacted] | D142: 11283 | I142: F
C143: [Redacted] | D143: 11357 | I143: F
C144: [Redacted] | D144: 11014 | I144: M
C145: [Redacted] | D145: 11291 | I145: F
C146: [Redacted] | D146: 11068 | I146: F | BR146: >>Termination date is missing for this employee. Assumed Nov-23 as excluded from Dec-23 headcount
C147: [Redacted] | D147: 11308 | I147: M | BR147: >>Termination date is missing for this employee. Assumed Nov-23 as excluded from Dec-23 headcount
C148: [Redacted] | D148: 11274 | I148: F
C149: [Redacted] | D149: 11333 | I149: M
C150: [Redacted] | D150: 11251 | I150: M
C151: [Redacted] | D151: 11091 | I151: F
C152: [Redacted] | D152: 11307 | I152: M
C153: [Redacted] | D153: 11277 | I153: M
C154: [Redacted] | D154: 11019 | I154: M
C155: [Redacted] | D155: 11278 | I155: M
C156: [Redacted] | D156: 11282 | I156: M
C157: [Redacted] | D157: 11281 | I157: F
C158: [Redacted] | D158: 11358 | I158: M
C159: [Redacted] | D159: 11302 | I159: M
... C173: [Redacted] | D173: 11279 | I173: F
C174: [Redacted] | D174: 11289
C175: [Redacted] | D175: 11201
C176: [Redacted] | D176: 11315
C177: [Redacted] | D177: 11045
C178: [Redacted] | D178: 11259
C179: [Redacted] | D179: 11266
C180: [Redacted] | D180: 11222
C181: [Redacted] | D181: 11191
C182: [Redacted] | D182: 11261
C183: [Redacted] | D183: 11303
C184: [Redacted] | D184: 11154
C185: [Redacted] | D185: 11208
... C187: [Redacted] | D187: 11292
C188: [Redacted] | D188: 11342 | BR188: <<Employee included in Termination file but not headcount. Excluded from analysis.
C189: [Redacted] | D189: 11373 | BR189: <<Employee included in Termination file but not headcount. Excluded from analysis.
C190: [Redacted] | D190: 11375 | BR190: <<Employee included in Termination file but not headcount. Excluded from analysis.
C191: [Redacted] | D191: 11348 | I191: M
C192: [Redacted] | D192: 11393 | I192: M
C193: [Redacted] | D193: 11392 | I193: F
C194: [Redacted] | D194: 11391 | I194: M
C195: [Redacted] | D195: 11394 | I195: M
C196: [Redacted] | D196: 11395 | I196: M
C197: [Redacted] | D197: 11398 | I197: F
C198: [Redacted] | D198: 11396 | I198: F
C199: Total | J199: =SUM(J11:J198) | K199: =SUM(K11:K198) | L199: =SUM(L11:L198) | M199: =SUM(M11:M198) | N199: =SUM(N11:N198) | P199: =SUM(P11:P198) | Q199: =SUM(Q11:Q198) | R199: =SUM(R11:R198) | S199: =SUM(S11:S198) | T199: =SUM(T11:T198) | V199: =SUM(V11:V198) | W199: =SUM(W11:W198) | X199: =SUM(X11:X198) | Y199: =SUM(Y11:Y198) | Z199: =SUM(Z11:Z198) | AA199: =SUM(AA11:AA198) | AB199: =SUM(AB11:AB198) | AC199: =SUM(AC11:AC198) | ... BP199: =SUM(BP11:BP198)
C201: Source (Termination folder > Turnover files)
C202: Check | J202: =J201-J199 | K202: =K201-K199 | L202: =L201-L199 | M202: =M201-M199 | N202: =N201-N199 | AG202: =AG201-AG199 | AS202: =AS201-AS199 | BE202: =BE201-BE199 | BJ202: =BJ201-BJ199
K203: >>Variance as annualized salary is equated to previous year salary for employees terminated during the year

Sheet Other analysis>>

Sheet Top customers
B1: Project Name
B2: =C7
B3: Source: TBD
B4: WORKING DRAFT
C7: Top customers
C8: # | D8: Customer | E8: Annual revenue | F8: Maturity date | G8: Existing Termination, Change of Control and/or Assignment Rights
C9: 1 | D9: Mobile TSP | E9: $12.5M+ | F9: 45869 | G9: Change of Control clause exists
C10: =C9+1 | D10: Credit Union MSA | E10: $15M+ | G10: Change of Control clause exists
C11: =C10+1 | D11: Square | E11: $1.7M
C12: =C11+1 | D12: Adyen | E12: $1.6M
C13: =C12+1 | D13: Laurentian Bank | E13: $700K+
C14: =C13+1 | D14: Stripe | E14: $450K+
C15: =C14+1 | D15: Monex | E15: $375K+ | F15: Jul-24 | G15: Currently in contract renewal discussions but client wants change of control rights in amended agreement
C16: =C15+1 | D16: Manulife Bank | E16: $285K+
C17: =C16+1 | D17: ICICI Bank | E17: $200K+ | F17: Oct-24
C18: =C17+1 | D18: Canadian Tire Bank | E18: $150K+ | F18: Jun-22
C21: Contract maturity waterfall
C22: Switch clients | D22: Annual volumes | E22: Expiry date | F22: Risk level to renew | G22: Present status
C23: Credit Union MSA
C24: Over 200 credit unions coast to coast | D24: 600M+ | E24: April, 2031 | F24: Low | G24: Recently renewed MSA for a 7-year term plus a 3-year option.
C26: (Mobile TSP) | D26: 1.2B | E26: July, 2025 | F26: Low | G26: In the process of contract renewal discussions.
C27: (NYCE POS) | D27: 285K | E27: Auto-renewal | F27: Low | G27: Currently have auto-renewal clause, but working on a 3-year new renewal to include new business terms on price and compliance.
C28: (CUP) | D28: 400K | E28: Auto-renewal | F28: Low | G28: Currently have auto-renewal clause, but working on a 3-year new renewal to include new business terms on price and compliance.
C29: (PULSE) | D29: 32K | E29: Auto-renewal | F29: Low | G29: Currently have auto-renewal clause, but working on a 3-year new renewal to include new business terms on price and compliance.
C30: Banks
C31: Laurentian Bank | D31: 24M | E31: June 30, 2024 | F31: Low | G31: Currently in discussions for a 3-year renewal
C32: Canadian Western Bank | D32: 2.8M | E32: March, 2025 | F32: Low | G32: Currently in auto-renewal, working on a 3-year new renewal to include new business terms on price and compliance.
C33: Manulife Bank | D33: 9.6M | E33: January 31, 2025 | F33: Low | G33: Confirm status with Oliver & Anthony
C34: ICICI Bank | D34: 1.2M | E34: October, 2024 | F34: Low | G34: Currently have auto-renewal clause, but working on a 3-year new renewal to include new business terms on price and compliance.
C35: First Nations Bank | D35: 240K | E35: December, 2024 | F35: Low | G35: Currently have auto-renewal clause, but working on a 3-year new renewal to include new business terms on price and compliance.
C36: Shinhan Bank | D36: 100K | E36: March, 2025 | F36: Low | G36: Currently have auto-renewal clause, but working on a 3-year new renewal to include new business terms on price and compliance.
C37: KEB Bank | D37: 240K | E37: August, 2024 | F37: Low | G37: Currently have auto-renewal clause, but working on a 3-year new renewal to include new business terms on price and compliance.
C38: State Bank of India | D38: 100K | E38: July, 2024 | F38: Low | G38: Currently have auto-renewal clause, but working on a 3-year new renewal to include new business terms on price and compliance.
C39: Host to Host, ISO Clients & Acquirers
C40: Adyen | D40: 100M | E40: December, 2026 | F40: Low | G40: Recently renewed agreement in December 2023.
C41: Monex | D41: 21M | E41: July, 2024 | F41: Low | G41: Currently in discussions with the client for a 3-year term.
C42: Square | D42: 130M | E42: October, 2025 | F42: Low
C43: WorldPay | D43: 4M | E43: October, 2024 | F43: High | G43: TBD
C44: PSP Services | D44: 1.6M | E44: August, 2026 | F44: Low | G44: No foreseeable challenges or risks
C45: Stanley Security (Manulife) | D45: 2M | E45: June, 2024 | F45: Low | G45: This agreement is currently in auto-renewal. We are opening up the agreement to amend pricing to address increasing costs in the service.
C46: Stanley Security (Whitelabel) | D46: 160K | E46: June, 2024 | F46: Low | G46: This agreement is currently in auto-renewal. We are opening up the agreement to amend pricing to address increasing costs in the service.

Sheet Revenue by customer group
B1: Project Name
B2: =C7
B3: Source: TBD
B4: WORKING DRAFT
C7: Billings by customer group
D8: Billings | P8: Billings | AB8: Billings | AN8: Billings | AT8: Billings | AZ8: As a % of total | BL8: As a % of total | BX8: As a % of total | CJ8: As a % of total | CP8: As a % of total
C9: Line of business | D9: 44227 | E9: =EOMONTH(D9,1) | F9: =EOMONTH(E9,1) | G9: =EOMONTH(F9,1) | H9: =EOMONTH(G9,1) | I9: =EOMONTH(H9,1) | J9: =EOMONTH(I9,1) | K9: =EOMONTH(J9,1) | L9: =EOMONTH(K9,1) | ... AS9: =EOMONTH(AR9,1) | AT9: FY21 | AU9: FY22 | AV9: FY23 | AW9: TTM Apr-24 | AX9: TTM Jun-24 | AZ9: 44227 | BA9: 44255 | BB9: 44286 | BC9: 44316 | BD9: 44347 | BE9: 44377 | BF9: 44408 | BG9: 44439 | BH9: 44469 | BI9: 44500 | BJ9: 44530 | BK9: 44561 | BL9: 44592 | BM9: 44620 | BN9: 44651 | BO9: 44681 | BP9: 44712 | BQ9: 44742 | BR9: 44773 | BS9: 44804 | BT9: 44834 | BU9: 44865 | BV9: 44895 | BW9: 44926 | BX9: 44957 | BY9: 44985 | BZ9: 45016 | CA9: 45046 | CB9: 45077 | CC9: 45107 | CD9: 45138 | CE9: 45169 | CF9: 45199 | CG9: 45230 | CH9: 45260 | CI9: 45291 | CJ9: 45322 | CK9: 45351 | CL9: 45382 | CM9: 45412 | CN9: 45443 | CO9: =EOMONTH(CN9,1) | CP9: FY21 | CQ9: FY22 | CR9: FY23 | CS9: TTM Apr-24 | CT9: TTM Jun-24
C10: Credit union | D10: 2047.3404
D11: 645.28246
C12: Retail host-to-host | D12: 305.29657
C13: Banks | D13: 296.85858
C14: Partners serving customer | D14: 2.56536
C15: Retail ISO | D15: 51.15826
C16: Digital | D16: 0
C17: White label ATM | D17: 20.76152
C18: Sublet of office space | D18: 0
C19: Banks other | D19: 0
C20: Other | D20: =SUM(D18:D19)
C21: Total | D21: =SUM(D10:D17,D20) | E21: =SUM(E10:E17,E20) | F21: =SUM(F10:F17,F20) | G21: =SUM(G10:G17,G20) | H21: =SUM(H10:H17,H20) | I21: =SUM(I10:I17,I20) | J21: =SUM(J10:J17,J20) | K21: =SUM(K10:K17,K20) | ... AX21: =SUM(AX10:AX17,AX20) | AZ21: =IFERROR(D21/D$21,0) | BA21: =IFERROR(E21/E$21,0) | BB21: =IFERROR(F21/F$21,0) | BC21: =IFERROR(G21/G$21,0) | BD21: =IFERROR(H21/H$21,0) | BE21: =IFERROR(I21/I$21,0) | BF21: =IFERROR(J21/J$21,0) | BG21: =IFERROR(K21/K$21,0) | ... CT21: =IFERROR(AX21/AX$21,0)
C23: Per source | D23: 3369.2632
C24: Check | D24: =D23-D21 | E24: =E23-E21 | F24: =F23-F21 | G24: =G23-G21 | H24: =H23-H21 | I24: =I23-I21 | J24: =J23-J21 | K24: =K23-K21 | ... AX24: =AX23-AX21
B1320: Customer
B1321: Uni Financial Services and Technology Inc.
B1322: Uni Financial Services and Technology Inc.
B1323: Uni Financial Services and Technology Inc.
B1324: Uni Financial Services and Technology Inc.
B1325: Uni Financial Services and Technology Inc.
B1326: Uni Financial Services and Technology Inc.
B1327: Uni Financial Services and Technology Inc.
B1328: Uni Financial Services and Technology Inc.
B1329: Uni Financial Services and Technology Inc.
B1330: Uni Financial Services and Technology Inc.
B1331: Uni Financial Services and Technology Inc.
... B1583: Healthcare & Municipal Employees’ Credit Union

Sheet Recons >>

Sheet Recons | IS
B1: Project Name
B2: =C7
B3: Source: TBD
B4: WORKING DRAFT
C7: Income statement reconciliation
D8: FY21 | G8: FY22 | J8: FY23
C9: $'000 | D9: Audited financial statements | E9: Internal financial statements | F9: Variance | G9: Audited financial statements | H9: Internal financial statements | I9: Variance | J9: Audited financial statements | K9: Internal financial statements | L9: Variance
C10: Revenue | D10: 40398
C11: Compensation | D11: -12443
C12: Cost of goods sold | D12: -7600
C13: Data processing and equipment | D13: -5720
C14: Contracted staffing and services | D14: -1807
C15: Occupancy and office | D15: -617
C16: Marketing, travel and other | D16: -551
C17: Amortization of property and equipment | D17: -1406
C18: Amortization of intangible assets | D18: -1971
C19: Capitalized Development Costs | D19: 0
C20: Interest expense on leases | D20: -108
C21: Operating expenses | D21: =SUM(D11:D20)
C22: Operating income | D22: =SUM(D21,D10)
C23: Interest income | D23: 23
C24: Income before income tax | D24: =SUM(D23,D22)
C25: Income tax expense | D25: -2150
C26: Net income for the year | D26: =SUM(D24:D25)
C28: Other comprehensive income
C29: Increase in fair value through other comprehensive income | D29: 179
C30: Related income tax expense | D30: -24
C31: Equity investments measured at FVTOCI | D31: =SUM(D29:D30)
C32: Net income and comprehensive income for the year | D32: =SUM(D31,D26)
C33: Notes:
C34: TBD
C35: TBD
C37: Net income as per source | D37: 6048
C38: Check | D38: =D37-D26 | E38: =E37-E26 | F38: =F37-F26 | G38: =G37-G26 | H38: =H37-H26 | I38: =I37-I26 | J38: =J37-J26 | K38: =K37-K26 | L38: =L37-L26

Sheet Recons | BS
B1: Project Name
B2: =C7
B3: Source: TBD
B4: WORKING DRAFT
C7: Balance sheet reconciliation
D8: 44561 | G8: 44926 | J8: 45291
C9: $'000 | D9: Audited financial statements | E9: Internal financial statements | F9: Variance | G9: Audited financial statements | H9: Internal financial statements | I9: Variance | J9: Audited financial statements | K9: Internal financial statements | L9: Variance | N9: Management Comments
C10: Assets
C11: Cash and cash equivalents | D11: 10743
C12: Items in transit | D12: 12326
C13: Accounts receivable and other receivables | D13: 8044
C14: Unbilled revenue | D14: 934
C15: Prepaid and other assets | D15: 3653
C16: Current assets | D16: =SUM(D11:D15)
C17: Intangible assets | D17: 8092
C18: Property and equipment | D18: 4217
C19: Deferred implementation costs | D19: 980
C20: Prepaid and other assets | D20: 2211
C21: Investments | D21: 941
C22: Goodwill | D22: 7695
C23: Non-current assets | D23: =SUM(D17:D22)
C24: Assets | D24: =SUM(D23,D16)
C25: Liabilities and Shareholder's equity
C26: Accounts payable and accrued liabilities | D26: -4281
C27: Payments held for third-party remittance | D27: -12260
C28: Contract liabilities | D28: -2183
C29: Current tax liability | D29: -359
C30: Current portion of lease liabilities | D30: -1164
C31: Shareholder dividends payable | D31: 0
C32: Current liabilities | D32: =SUM(D26:D31)
C33: Deferred tax liabilities | D33: -1695
C34: Lease liabilities | D34: -3595
C35: Long-term employee benefits | D35: -328
C36: Contract liabilities | D36: -4037
C37: Non-current liabilities | D37: =SUM(D33:D36)
C38: Liabilities | D38: =SUM(D37,D32)
C39: Shareholders' deficiency | D39: -29934
C40: Liabilities and shareholders' deficiency | D40: =SUM(D38:D39)
C42: Audit check | D42: =D40+D24 | E42: =E40+E24 | F42: =E42-D42 | G42: =G40+G24 | H42: =H40+H24 | I42: =H42-G42 | J42: =J40+J24 | K42: =K40+K24 | L42: =K42-J42
C43: Assets as per source | D43: 59836
C44: Check | D44: =D43-D24 | E44: =E43-E24 | F44: =E44-D44 | G44: =G43-G24 | H44: =H43-H24 | I44: =I43-I24 | J44: =J43-J24 | K44: =K43-K24

Sheet Recon | Cash flow
B1: Project Name
B2: =C7
B3: Source: TBD
B4: WORKING DRAFT
C6: Pending commentary on FY21 reclass adjustments from Management
AF7: Questions/Comments
E8: FY21 | Q8: FY22 | Y8: FY23
D9: [A] | E9: [B] | N9: [C] | O9: [A-(B+C)] | P9: [A] | Q9: [B] | V9: [C] | W9: [A-(B+C)] | X9: [A] | Y9: [B] | AC9: [C] | AD9: [A-(B+C)]
D10: Audited financial statements | E10: Internal financial statements | F10: 1. Reclass loss on disposal of PPE | G10: 2. Reclass change in AP for PPE | H10: 3. Reclass items in transit | I10: 4. Reclass amortization of PPE and intangibles | J10: 5. Reclass Deferred revenue to employee benefits | K10: 6. Reclass capitalized development costs to intangible assets | L10: 7. Reclass OCI on shares | M10: 8. Reclass acquisition of assets, prepaids, and lease liabilities | N10: Reclass entries | O10: Variance | P10: Audited financial statements | Q10: Internal financial statements | R10: 1. Reclass loss on disposal of PPE | S10: 2. Reclass change in AP for PPE | T10: 3. Reclass items in transit | U10: 4. Reclass PPE and intangibles | V10: Reclass entries | W10: Variance | X10: Audited financial statements | Y10: Internal financial statements | Z10: 1. Reclass loss on disposal of PPE | AA10: 2. Reclass change in AP for PPE | AB10: 3. Reclass items in transit | AC10: Reclass entries | AD10: Variance
D12: 6048
D14: 1406
D15: 1971
D16: -82
D17: 1
D19: -827
D20: 584
D21: 303
D22: 352
D23: 114
D24: 147
D25: 492
D26: 5733
D27: =SUM(D19:D26)
D28: =SUM(D27,D12:D17)
D30: -3724
D31: -628
D32: 0
D33: -75
D34: 100
D35: =SUM(D30:D34)
D37: -1183
D38: -5650
D39: -1350
D40: =SUM(D37:D39)
D41: =SUM(D40,D35,D28)
D42: 19337
D43: =SUM(D41:D42)
D45: 23069
D46: =D43-D45 | E46: =E43-E45 | N46: =N43-N45 | O46: =O43-O45 | P46: =P43-P45 | Q46: =Q43-Q45 | V46: =V43-V45 | W46: =W43-W45 | X46: =X43-X45 | Y46: =Y43-Y45 | AC46: =AC43-AC45 | AD46: =AD43-AD45

Sheet Recon | Billings
B1: Project Name
B2: =C7
B3: Source: TBD
B4: WORKING DRAFT
C7: Billing report reconciliation | BB7: Comments
C8: $'000 | D8: Revenue Type | E8: GL Account | F8: =ctl_month_start | G8: =EDATE(ctl_month_start,1) | H8: =EDATE(ctl_month_start,2) | I8: =EDATE(ctl_month_start,3) | J8: =EDATE(ctl_month_start,4) | K8: =EDATE(ctl_month_start,5) | L8: =EDATE(ctl_month_start,6) | M8: =EDATE(ctl_month_start,7) | N8: =EDATE(ctl_month_start,8) | O8: =EDATE(ctl_month_start,9) | P8: =EDATE(ctl_month_start,10) | Q8: =EDATE(ctl_month_start,11) | R8: =EDATE(ctl_month_start,12) | S8: =EDATE(ctl_month_start,13) | T8: =EDATE(ctl_month_start,14) | U8: =EDATE(ctl_month_start,15) | V8: =EDATE(ctl_month_start,16) | W8: =EDATE(ctl_month_start,17) | X8: =EDATE(ctl_month_start,18) | Y8: =EDATE(ctl_month_start,19) | Z8: =EDATE(ctl_month_start,20) | AA8: =EDATE(ctl_month_start,21) | AB8: =EDATE(ctl_month_start,22) | AC8: =EDATE(ctl_month_start,23) | AD8: =EDATE(ctl_month_start,24) | AE8: =EDATE(ctl_month_start,25) | AF8: =EDATE(ctl_month_start,26) | AG8: =EDATE(ctl_month_start,27) | AH8: =EDATE(ctl_month_start,28) | AI8: =EDATE(ctl_month_start,29) | AJ8: =EDATE(ctl_month_start,30) | AK8: =EDATE(ctl_month_start,31) | AL8: =EDATE(ctl_month_start,32) | AM8: =EDATE(ctl_month_start,33) | AN8: =EDATE(ctl_month_start,34) | AO8: =EDATE(ctl_month_start,35)
C9: Revenue from Billing Invoices & Credits | D9: billing | E9: various | AP9: 5734.2531 | AQ9: 5860.7753 | AR9: 6592.4271 | AS9: 5780.079 | AT9: 6260.6559 | AU9: 6237.6501 | AV9: =SUM(F9:Q9) | AW9: =SUM(R9:AC9) | AX9: =SUM(AD9:AO9) | AY9: =SUM(AH9:AS9) | AZ9: =SUM(AJ9:AU9)
C10: Unreconcilable differences | AP10: -0.6 | AQ10: 0 | AR10: 0 | AS10: 3.11295 | AT10: 9.46802 | AU10: -5.65255 | AV10: =SUM(F10:Q10) | AW10: =SUM(R10:AC10) | AX10: =SUM(AD10:AO10) | AY10: =SUM(AH10:AS10) | AZ10: =SUM(AJ10:AU10)
C11: Adjustment to billing in Great Plains G/L | AP11: 0 | AQ11: 0 | AR11: 0 | AS11: 0 | AT11: 0 | AU11: -2.77773 | AV11: =SUM(F11:Q11) | AW11: =SUM(R11:AC11) | AX11: =SUM(AD11:AO11) | AY11: =SUM(AH11:AS11) | AZ11: =SUM(AJ11:AU11)
C12: Chase residuals applied to A/R for CHASE ISO's | D12: Chase Residual | E12: 3025-411139-1012-301 | AP12: 0 | AQ12: 0 | AR12: 0 | AS12: 0 | AT12: 0 | AU12: 0 | AV12: =SUM(F12:Q12) | AW12: =SUM(R12:AC12) | AX12: =SUM(AD12:AO12) | AY12: =SUM(AH12:AS12) | AZ12: =SUM(AJ12:AU12)
C13: Billed revenue | AP13: =SUM(AP9:AP12) | AQ13: =SUM(AQ9:AQ12) | AR13: =SUM(AR9:AR12) | AS13: =SUM(AS9:AS12) | AT13: =SUM(AT9:AT12) | AU13: =SUM(AU9:AU12) | AV13: =SUM(AV9:AV12) | AW13: =SUM(AW9:AW12) | ... AZ13: =SUM(AZ9:AZ12)
C14: OIF (cirrus, plus, visa) transferred in | D14: OIF Revenue | E14: 3025-411140-1014-601 | AP14: 79.36412 | AQ14: 94.75907 | AR14: 102.80226 | AS14: 92.64949 | AT14: 61.56961 | AU14: 45.97162 | AV14: =SUM(F14:Q14) | AW14: =SUM(R14:AC14) | AX14: =SUM(AD14:AO14) | AY14: =SUM(AH14:AS14) | AZ14: =SUM(AJ14:AU14)
C15: OIF (maestro) transferred in | D15: OIF Revenue | E15: 3025-411141-1014-601 | AP15: 10.57025 | AQ15: 9.46507 | AR15: 10.6718 | AS15: 12.13184 | AT15: 11.02461 | AU15: 9.52834 | AV15: =SUM(F15:Q15) | AW15: =SUM(R15:AC15) | AX15: =SUM(AD15:AO15) | AY15: =SUM(AH15:AS15) | AZ15: =SUM(AJ15:AU15)
C16: DCC (Dynamic Currency conversion) | D16: DCC Revenue | E16: 3025-411143-1017-201 | AP16: 1.28488 | AQ16: 1.07785 | AR16: 0.80397 | AS16: 0.9967 | AT16: 1.07978 | AU16: 1.29786 | AV16: =SUM(F16:Q16) | AW16: =SUM(R16:AC16) | AX16: =SUM(AD16:AO16) | AY16: =SUM(AH16:AS16) | AZ16: =SUM(AJ16:AU16)
C17: Debit Mastercard Maestro Fees | D17: DMC OIF | E17: 3025-411142-1014-601 | AP17: 9.27732 | AQ17: 10.70728 | AR17: 12.60981 | AS17: 11.62518 | AT17: 8.68172 | AU17: 5.77285 | AV17: =SUM(F17:Q17) | AW17: =SUM(R17:AC17) | AX17: =SUM(AD17:AO17) | AY17: =SUM(AH17:AS17) | AZ17: =SUM(AJ17:AU17)
C18: Interchange Revenue | D18: Revenue Issuer Interchange - Co-badged- Visa Debit and MC | E18: 3025-411144-1014-601 | AP18: 28.33276 | AQ18: 25.47204 | AR18: 16.67217 | AS18: 19.61633 | AT18: 19.70171 | AU18: 20.55462 | AV18: =SUM(F18:Q18) | AW18: =SUM(R18:AC18) | AX18: =SUM(AD18:AO18) | AY18: =SUM(AH18:AS18) | AZ18: =SUM(AJ18:AU18)
C19: DMA OIF Revenue | D19: DMA OIF Revenue | E19: 3025-411149-1014-601 | AP19: 17.9535 | AQ19: 19.78337 | AR19: 20.35154 | AS19: 24.55392 | AT19: 23.02233 | AU19: 21.64082 | AV19: =SUM(F19:Q19) | AW19: =SUM(R19:AC19) | AX19: =SUM(AD19:AO19) | AY19: =SUM(AH19:AS19) | AZ19: =SUM(AJ19:AU19)
C20: Debit Visa | D20: Debit Visa | E20: 3025-411147-1014-601 | AP20: 2.59426 | AQ20: 2.97035 | AR20: 3.22513 | AS20: 5.12286 | AT20: 6.2616 | AU20: 5.85365 | AV20: =SUM(F20:Q20) | AW20: =SUM(R20:AC20) | AX20: =SUM(AD20:AO20) | AY20: =SUM(AH20:AS20) | AZ20: =SUM(AJ20:AU20)
C21: Issuer Interchange - Co-badged- Debit MC | D21: Issuer Interchange - Co-badged- Debit MC | E21: 3025-411148-1014-601 | AP21: 31.23219 | AQ21: 26.54396 | AR21: 26.54871 | AS21: 32.46535 | AT21: 31.51868 | AU21: 35.97752 | AV21: =SUM(F21:Q21) | AW21: =SUM(R21:AC21) | AX21: =SUM(AD21:AO21) | AY21: =SUM(AH21:AS21) | AZ21: =SUM(AJ21:AU21)
C22: MAP Program fees collected from Merchants | D22: MAP Revenue | E22: 3025-411103-1012-301/411104-1012-301/411107-1012-301/483104-1012-301 | AP22: 0 | AQ22: 0 | AR22: 0 | AS22: 0 | AT22: 0 | AU22: 0 | AV22: =SUM(F22:Q22) | AW22: =SUM(R22:AC22) | AX22: =SUM(AD22:AO22) | AY22: =SUM(AH22:AS22) | AZ22: =SUM(AJ22:AU22)
C23: Revenue Issuer Interchange - Co-badged- Visa Debit and MC | E23: 3025-411144-1014-601 | AP23: 0 | AQ23: 0 | AR23: 0 | AS23: 0 | AT23: 0 | AU23: 0 | AV23: =SUM(F23:Q23) | AW23: =SUM(R23:AC23) | AX23: =SUM(AD23:AO23) | AY23: =SUM(AH23:AS23) | AZ23: =SUM(AJ23:AU23)
C24: OIF, Interchange, DCC | AP24: =SUM(AP14:AP23) | AQ24: =SUM(AQ14:AQ23) | AR24: =SUM(AR14:AR23) | AS24: =SUM(AS14:AS23) | AT24: =SUM(AT14:AT23) | AU24: =SUM(AU14:AU23) | AV24: =SUM(AV14:AV23) | AW24: =SUM(AW14:AW23) | ... AZ24: =SUM(AZ14:AZ23)
C25: Flash Interchange (net) transferred in (received) | D25: Flash Revenue | E25: 3025-483104-10xx-xxx | AP25: -603.15072 | AQ25: -485.22279 | AR25: -516.32093 | AS25: -600.1333 | AT25: -594.86176 | AU25: -668.56398 | AV25: =SUM(F25:Q25) | AW25: =SUM(R25:AC25) | AX25: =SUM(AD25:AO25) | AY25: =SUM(AH25:AS25) | AZ25: =SUM(AJ25:AU25)
C26: Flash Revenue - Adjustment for Square/Block back-billing | D26: Flash Revenue - Adjustment for Square/Block back-billing | AP26: 0 | AQ26: 0 | AR26: 0 | AS26: 0 | AT26: 0 | AU26: 0 | AV26: =SUM(F26:Q26) | AW26: =SUM(R26:AC26) | AX26: =SUM(AD26:AO26) | AY26: =SUM(AH26:AS26) | AZ26: =SUM(AJ26:AU26)
C27: flash and In-app interchange | AP27: =SUM(AP25:AP26) | AQ27: =SUM(AQ25:AQ26) | AR27: =SUM(AR25:AR26) | AS27: =SUM(AS25:AS26) | AT27: =SUM(AT25:AT26) | AU27: =SUM(AU25:AU26) | AV27: =SUM(AV25:AV26) | AW27: =SUM(AW25:AW26) | ... AZ27: =SUM(AZ25:AZ26)
C28: Revenue from settlement1 | AP28: =SUM(AP27,AP24) | AQ28: =SUM(AQ27,AQ24) | AR28: =SUM(AR27,AR24) | AS28: =SUM(AS27,AS24) | AT28: =SUM(AT27,AT24) | AU28: =SUM(AU27,AU24) | AV28: =SUM(AV27,AV24) | AW28: =SUM(AW27,AW24) | ... AZ28: =SUM(AZ27,AZ24)
C29: Subtract Increase in Total Deferred Rev | D29: Deferred Revenue | E29: 3025-240101-10xx-xxx | AP29: 16.74751 | AQ29: -237.52999 | AR29: -225.11889 | AS29: -93.72734 | AT29: 206.90202 | AU29: 77.71222 | AV29: =SUM(F29:Q29) | AW29: =SUM(R29:AC29) | AX29: =SUM(AD29:AO29) | AY29: =SUM(AH29:AS29) | AZ29: =SUM(AJ29:AU29)
C30: Subtract Increase in Total Contract Liability ST | D30: Contract Liability | E30: 3025-241515-10xx-xxx | AP30: 151.72657 | AQ30: 217.23089 | AR30: -28.48575 | AS30: 259.58413 | AT30: 88.90243 | AU30: 577.08376 | AV30: =SUM(F30:Q30) | AW30: =SUM(R30:AC30) | AX30: =SUM(AD30:AO30) | AY30: =SUM(AH30:AS30) | AZ30: =SUM(AJ30:AU30)
C31: Subtract Increase in Total Contract Liability LT | D31: Contract Liability-non current | E31: 3025-281515-xxx | AP31: 104 | AQ31: -7.94568 | AR31: 66.86716 | AS31: -360.42034 | AT31: -106.51567 | AU31: -474.72778 | AV31: =SUM(F31:Q31) | AW31: =SUM(R31:AC31) | AX31: =SUM(AD31:AO31) | AY31: =SUM(AH31:AS31) | AZ31: =SUM(AJ31:AU31)
C32: Cost Amort 18&PY Q1 (JE#113011) not part of revenue | E32: 241515-1011-101 | AP32: 0 | AQ32: 0 | AR32: 14.26491 | AS32: 4.75497 | AT32: 4.75497 | AU32: 0 | AV32: =SUM(F32:Q32) | AW32: =SUM(R32:AC32) | AX32: =SUM(AD32:AO32) | AY32: =SUM(AH32:AS32) | AZ32: =SUM(AJ32:AU32)
C33: Square Rebate accrued in COGS-1012 | AP33: 0 | AQ33: 0 | AR33: 0 | AS33: 0 | AT33: 0 | AU33: 0 | AV33: =SUM(F33:Q33) | AW33: =SUM(R33:AC33) | AX33: =SUM(AD33:AO33) | AY33: =SUM(AH33:AS33) | AZ33: =SUM(AJ33:AU33)
C34: Contract Assets - re: IFRS15 Entries for 2018 | D34: Contract Assets Current IFRS15 | E34: 3025-148015-1011/1017/1019 | AP34: 0 | AQ34: 0 | AR34: 0 | AS34: 0 | AT34: 0 | AU34: 0 | AV34: =SUM(F34:Q34) | AW34: =SUM(R34:AC34) | AX34: =SUM(AD34:AO34) | AY34: =SUM(AH34:AS34) | AZ34: =SUM(AJ34:AU34)
C35: Revenue from deferred revenue | AP35: =SUM(AP29:AP34) | AQ35: =SUM(AQ29:AQ34) | AR35: =SUM(AR29:AR34) | AS35: =SUM(AS29:AS34) | AT35: =SUM(AT29:AT34) | AU35: =SUM(AU29:AU34) | AV35: =SUM(AV29:AV34) | AW35: =SUM(AW29:AW34) | ... AZ35: =SUM(AZ29:AZ34)
C36: Add Total Increase to Accrued A/R | D36: Accruals for CU & Banks | E36: various revenue a/c OR 3025-120201-1003-999 | AP36: 86.1676 | AQ36: 999.8139 | AR36: -707.93738 | AS36: 470.53656 | AT36: -6.8002 | AU36: 135.53362 | AV36: =SUM(F36:Q36) | AW36: =SUM(R36:AC36) | AX36: =SUM(AD36:AO36) | AY36: =SUM(AH36:AS36) | AZ36: =SUM(AJ36:AU36)
C37: Less: Threshold EXC Interchange | AP37: 0 | AQ37: 0 | AR37: 0 | AS37: 0 | AT37: 0 | AU37: 0 | AV37: =SUM(F37:Q37) | AW37: =SUM(R37:AC37) | AX37: =SUM(AD37:AO37) | AY37: =SUM(AH37:AS37) | AZ37: =SUM(AJ37:AU37)
C38: Less: Reclass & adj | D38: IFRS15 ADJ to Revenue Accrued | E38: 120201-1000, 120201-1001, 120215-1015 | AP38: 0 | AQ38: 0 | AR38: 0 | AS38: 0 | AT38: 0 | AU38: 0 | AV38: =SUM(F38:Q38) | AW38: =SUM(R38:AC38) | AX38: =SUM(AD38:AO38) | AY38: =SUM(AH38:AS38) | AZ38: =SUM(AJ38:AU38)
C39: Add Increase to Accrued Merchant Services | D39: Accruals for ISO | E39: various revenue a/c / 3025-120301-1012-301 | AP39: -69.81782 | AQ39: 32.26076 | AR39: 50.9113 | AS39: -0.06563 | AT39: 51.81592 | AU39: 6.80462 | AV39: =SUM(F39:Q39) | AW39: =SUM(R39:AC39) | AX39: =SUM(AD39:AO39) | AY39: =SUM(AH39:AS39) | AZ39: =SUM(AJ39:AU39)
C40: Add Increase to Chase Annual Fees | AP40: 0 | AQ40: 0 | AR40: 0 | AS40: 0 | AT40: 0 | AU40: 0 | AV40: =SUM(F40:Q40) | AW40: =SUM(R40:AC40) | AX40: =SUM(AD40:AO40) | AY40: =SUM(AH40:AS40) | AZ40: =SUM(AJ40:AU40)
C41: Add Increase to Chase Residuals Recv. | D41: Chase Residual | AP41: 0 | AQ41: 0 | AR41: 0 | AS41: 0 | AT41: 0 | AU41: 0 | AV41: =SUM(F41:Q41) | AW41: =SUM(R41:AC41) | AX41: =SUM(AD41:AO41) | AY41: =SUM(AH41:AS41) | AZ41: =SUM(AJ41:AU41)
C42: Add Increase to ACCR Chase referral rev Q2-2 | AP42: 0 | AQ42: 0 | AR42: 0 | AS42: 0 | AT42: 0 | AU42: 0 | AV42: =SUM(F42:Q42) | AW42: =SUM(R42:AC42) | AX42: =SUM(AD42:AO42) | AY42: =SUM(AH42:AS42) | AZ42: =SUM(AJ42:AU42)
C43: Add Increase to Accrued CHASE Receivable - to pay | D43: Chase Residual | AP43: 0 | AQ43: 0 | AR43: 0 | AS43: 0 | AT43: 0 | AU43: 0 | AV43: =SUM(F43:Q43) | AW43: =SUM(R43:AC43) | AX43: =SUM(AD43:AO43) | AY43: =SUM(AH43:AS43) | AZ43: =SUM(AJ43:AU43)
C44: Residual - Entegra rejects | D44: Chase Residual | AP44: 0 | AQ44: 0.06185 | AR44: 0 | AS44: 0 | AT44: 0 | AU44: 0 | AV44: =SUM(F44:Q44) | AW44: =SUM(R44:AC44) | AX44: =SUM(AD44:AO44) | AY44: =SUM(AH44:AS44) | AZ44: =SUM(AJ44:AU44)
C45: Adjustment to Other Accrued A/R | AP45: 0 | AQ45: 0 | AR45: 0 | AS45: 0 | AT45: 0 | AU45: 0 | AV45: =SUM(F45:Q45) | AW45: =SUM(R45:AC45) | AX45: =SUM(AD45:AO45) | AY45: =SUM(AH45:AS45) | AZ45: =SUM(AJ45:AU45)
C46: Subtract Residuals paying Accrued A/R | D46: Chase Residual | AP46: 0 | AQ46: 0 | AR46: 0 | AS46: 0 | AT46: 0 | AU46: 0 | AV46: =SUM(F46:Q46) | AW46: =SUM(R46:AC46) | AX46: =SUM(AD46:AO46) | AY46: =SUM(AH46:AS46) | AZ46: =SUM(AJ46:AU46)
C47: Revenue - accrued accounts receivable accounts | AP47: =SUM(AP36:AP46) | AQ47: =SUM(AQ36:AQ46) | AR47: =SUM(AR36:AR46) | AS47: =SUM(AS36:AS46) | AT47: =SUM(AT36:AT46) | AU47: =SUM(AU36:AU46) | AV47: =SUM(AV36:AV46) | AW47: =SUM(AW36:AW46) | ... AZ47: =SUM(AZ36:AZ46)
C48: Add Cash received from Chase | D48: Chase Residual | E48: 3025-411139-1012-301 | AP48: 0 | AQ48: 0 | AR48: 0 | AS48: 0 | AT48: 2.43246 | AU48: 0 | AV48: =SUM(F48:Q48) | AW48: =SUM(R48:AC48) | AX48: =SUM(AD48:AO48) | AY48: =SUM(AH48:AS48) | AZ48: =SUM(AJ48:AU48)
C49: Referral fee Q4 2023 | D49: Chase Residual | AP49: 0 | AQ49: 1.93586 | AR49: 0.69881 | AS49: 0 | AT49: 0 | AU49: -0.82591 | AV49: =SUM(F49:Q49) | AW49: =SUM(R49:AC49) | AX49: =SUM(AD49:AO49) | AY49: =SUM(AH49:AS49) | AZ49: =SUM(AJ49:AU49)
C50: Subtract cash paid out to ISO's & CU's- residuals | D50: Chase Residual | E50: 3025-411139-1012-301 | AP50: 0 | AQ50: 0 | AR50: -0.69883 | AS50: 0 | AT50: 0 | AU50: 0 | AV50: =SUM(F50:Q50) | AW50: =SUM(R50:AC50) | AX50: =SUM(AD50:AO50) | AY50: =SUM(AH50:AS50) | AZ50: =SUM(AJ50:AU50)
C51: Add Old Accrued Liability for CHASE (see column A&B) | D51: Chase Residual | E51: 3025-411139-1012-301 in 214112 | AP51: 0 | AQ51: 2e-05 | AR51: 0 | AS51: 0 | AT51: 0 | AU51: 1.62381 | AV51: =SUM(F51:Q51) | AW51: =SUM(R51:AC51) | AX51: =SUM(AD51:AO51) | AY51: =SUM(AH51:AS51) | AZ51: =SUM(AJ51:AU51)
C52: Subtract New Accrued Liability for Chase (see column A&B) | D52: Chase Residual | E52: 3025-411139-1012-301 in 214112 | AP52: 0 | AQ52: -2.10434 | AR52: 0 | AS52: 0 | AT52: -1.62381 | AU52: -0.79792 | AV52: =SUM(F52:Q52) | AW52: =SUM(R52:AC52) | AX52: =SUM(AD52:AO52) | AY52: =SUM(AH52:AS52) | AZ52: =SUM(AJ52:AU52)
C53: Reclass sales tax on chase | D53: Chase Residual | E53: 3025-411139-1012-301 | AP53: 0 | AQ53: 0 | AR53: 0 | AS53: 0 | AT53: 0 | AU53: 0 | AV53: =SUM(F53:Q53) | AW53: =SUM(R53:AC53) | AX53: =SUM(AD53:AO53) | AY53: =SUM(AH53:AS53) | AZ53: =SUM(AJ53:AU53)
C54: Chase residual | AP54: =SUM(AP48:AP53) | AQ54: =SUM(AQ48:AQ53) | AR54: =SUM(AR48:AR53) | AS54: =SUM(AS48:AS53) | AT54: =SUM(AT48:AT53) | AU54: =SUM(AU48:AU53) | AV54: =SUM(AV48:AV53) | AW54: =SUM(AW48:AW53) | ... AZ54: =SUM(AZ48:AZ53)
C55: OIF Rev Change in month in Settlement Accrual | D55: OIF Revenue, DCC (ACCR DCC, CIR,DMC, VDA, ICI VISA) exclude VISA accruals and DMA FEE | E55: 3025-411140-1014-601/3025-411141-1014-601 | AP55: 20.68259 | AQ55: 10.24 | AR55: -10.94403 | AS55: -49.31054 | AT55: -1.62986 | AU55: -10.92999 | AV55: =SUM(F55:Q55) | AW55: =SUM(R55:AC55) | AX55: =SUM(AD55:AO55) | AY55: =SUM(AH55:AS55) | AZ55: =SUM(AJ55:AU55)
C56: =D56 | D56: OIF Revenue, MAE, Visa, DMA, VDA, ICI VISA | AP56: -9.9274 | AQ56: -7.33361 | AR56: 9.75987 | AS56: 19.83332 | AT56: -5.83647 | AU56: -12.4693 | AV56: =SUM(F56:Q56) | AW56: =SUM(R56:AC56) | AX56: =SUM(AD56:AO56) | AY56: =SUM(AH56:AS56) | AZ56: =SUM(AJ56:AU56)
C57: Revenue accruals in settlement liability | AP57: =SUM(AP55:AP56) | AQ57: =SUM(AQ55:AQ56) | AR57: =SUM(AR55:AR56) | AS57: =SUM(AS55:AS56) | AT57: =SUM(AT55:AT56) | AU57: =SUM(AU55:AU56) | AV57: =SUM(AV55:AV56) | AW57: =SUM(AW55:AW56) | ... AZ57: =SUM(AZ55:AZ56)
C58: Plus: Writeoffs to AR Provision | E58: various revenue a/c / 3025-125101-1003-999 | AP58: 0 | AQ58: 0 | AR58: 0 | AS58: 0 | AT58: 0 | AU58: 0 | AV58: =SUM(F58:Q58) | AW58: =SUM(R58:AC58) | AX58: =SUM(AD58:AO58) | AY58: =SUM(AH58:AS58) | AZ58: =SUM(AJ58:AU58)
C59: Misc Adjustments | D59: Reclass between Def Rev & Accrued A/P | E59: 3025-214102-1017-201 | AP59: 0 | AQ59: 0 | AR59: 0 | AS59: 0 | AT59: 0 | AU59: 0 | AV59: =SUM(F59:Q59) | AW59: =SUM(R59:AC59) | AX59: =SUM(AD59:AO59) | AY59: =SUM(AH59:AS59) | AZ59: =SUM(AJ59:AU59)
C60: Credit received from ACI for Mobile outage | AP60: 0 | AQ60: 0 | AR60: 0 | AS60: 0 | AT60: 0 | AU60: 0 | AV60: =SUM(F60:Q60) | AW60: =SUM(R60:AC60) | AX60: =SUM(AD60:AO60) | AY60: =SUM(AH60:AS60) | AZ60: =SUM(AJ60:AU60)
C61: Adjustments per accounts receivable provision | AP61: =SUM(AP58:AP60) | AQ61: =SUM(AQ58:AQ60) | AR61: =SUM(AR58:AR60) | AS61: =SUM(AS58:AS60) | AT61: =SUM(AT58:AT60) | AU61: =SUM(AU58:AU60) | AV61: =SUM(AV58:AV60) | AW61: =SUM(AW58:AW60) | ... AZ61: =SUM(AZ58:AZ60)
C62: Revenue recognized per biilling details | AP62: =SUM(AP47,AP35,AP57,AP28,AP54,AP61,AP13) | AQ62: =SUM(AQ47,AQ35,AQ57,AQ28,AQ54,AQ61,AQ13) | AR62: =SUM(AR47,AR35,AR57,AR28,AR54,AR61,AR13) | AS62: =SUM(AS47,AS35,AS57,AS28,AS54,AS61,AS13) | AT62: =SUM(AT47,AT35,AT57,AT28,AT54,AT61,AT13) | AU62: =SUM(AU47,AU35,AU57,AU28,AU54,AU61,AU13) | AV62: =SUM(AV47,AV35,AV57,AV28,AV54,AV61,AV13) | AW62: =SUM(AW47,AW35,AW57,AW28,AW54,AW61,AW13) | ... AZ62: =SUM(AZ47,AZ35,AZ57,AZ28,AZ54,AZ61,AZ13)
C63: Revenue from financials & revenue by LOB | AP63: ='Income statement'!AP117 | AQ63: ='Income statement'!AQ117 | AR63: ='Income statement'!AR117 | AS63: ='Income statement'!AS117 | AT63: ='Income statement'!AT117 | AU63: ='Income statement'!AU117 | AV63: =SUM(F63:Q63) | AW63: =SUM(R63:AC63) | AX63: =SUM(AD63:AO63) | AY63: =SUM(AH63:AS63) | AZ63: =SUM(AJ63:AU63)
C64: Unreconcilable differences2 | AP64: =AP10 | AQ64: =AQ10 | AR64: =AR10 | AS64: =AS10 | AT64: =AT10 | AU64: =AU10 | AV64: =SUM(F64:Q64) | AW64: =SUM(R64:AC64) | AX64: =SUM(AD64:AO64) | AY64: =SUM(AH64:AS64) | AZ64: =SUM(AJ64:AU64)
C65: Variance | F65: {=SUM(F62,-F63:F64)} | G65: {=SUM(G62,-G63:G64)} | H65: {=SUM(H62,-H63:H64)} | I65: {=SUM(I62,-I63:I64)} | J65: {=SUM(J62,-J63:J64)} | K65: {=SUM(K62,-K63:K64)} | L65: {=SUM(L62,-L63:L64)} | M65: {=SUM(M62,-M63:M64)} | ... AZ65: {=SUM(AZ62,-AZ63:AZ64)}
C66: TBD
C67: Per source | AP67: 5611.2907 | AQ67: 6572.9612 | AR67: 5439.1087 | AS67: 5630.2925 | AT67: 6061.056 | AU67: 6011.9128 | AV67: =SUM(F67:Q67) | AW67: =SUM(R67:AC67) | AX67: =SUM(AD67:AO67) | AY67: =SUM(AH67:AS67) | AZ67: =SUM(AJ67:AU67)
C68: Check | F68: =F67-F62 | G68: =G67-G62 | H68: =H67-H62 | I68: =I67-I62 | J68: =J67-J62 | K68: =K67-K62 | L68: =L67-L62 | M68: =M67-M62 | ... AZ68: =AZ67-AZ62
C69: Revenue by LOB | AV69: =SUM(F69:Q69) | AW69: =SUM(R69:AC69) | AX69: =SUM(AD69:AO69)
C70: Check | F70: =F69-F63 | G70: =G69-G63 | H70: =H69-H63 | I70: =I69-I63 | J70: =J69-J63 | K70: =K69-K63 | L70: =L69-L63 | M70: =M69-M63 | ... AO70: =AO69-AO63 | AV70: =SUM(F70:Q70) | AW70: =SUM(R70:AC70) | AX70: =SUM(AD70:AO70)
C71: Billed revenue extract - PBI | AP71: 5733.6531 | AQ71: 5860.7753 | AR71: 6592.4271 | AS71: 5783.1919 | AT71: 6270.1239 | AU71: 6229.2198 | AV71: =SUM(F71:Q71) | AW71: =SUM(R71:AC71) | AX71: =SUM(AD71:AO71) | AY71: =SUM(AH71:AS71) | AZ71: =SUM(AJ71:AU71)
C72: Check | F72: =F71-F13 | G72: =G71-G13 | H72: =H71-H13 | I72: =I71-I13 | J72: =J71-J13 | K72: =K71-K13 | L72: =L71-L13 | M72: =M71-M13 | ... AU72: =AU71-AU13 | AV72: =SUM(F72:Q72) | AW72: =SUM(R72:AC72) | AX72: =SUM(AD72:AO72) | AY72: =SUM(AH72:AS72) | AZ72: =SUM(AJ72:AU72)
C73: Revenue - income statement | AP73: ='Income statement'!AP117 | AQ73: ='Income statement'!AQ117 | AR73: ='Income statement'!AR117 | AS73: ='Income statement'!AS117 | AT73: ='Income statement'!AT117 | AU73: ='Income statement'!AU117 | AV73: =SUM(F73:Q73) | AW73: =SUM(R73:AC73) | AX73: =SUM(AD73:AO73) | AY73: =SUM(AH73:AS73) | AZ73: =SUM(AJ73:AU73)
C74: Check | F74: =F73-F63 | G74: =G73-G63 | H74: =H73-H63 | I74: =I73-I63 | J74: =J73-J63 | K74: =K73-K63 | L74: =L73-L63 | M74: =M73-M63 | ... AU74: =AU73-AU63 | AV74: =SUM(F74:Q74) | AW74: =SUM(R74:AC74) | AX74: =SUM(AD74:AO74) | AY74: =SUM(AH74:AS74) | AZ74: =SUM(AJ74:AU74)
C75: Billed revenue - Internal check | AV75: =SUM(F75:Q75) | AW75: =SUM(R75:AC75) | AX75: =SUM(AD75:AO75) | AY75: =SUM(AH75:AS75) | AZ75: =SUM(AJ75:AU75)
C76: Check | F76: =F75-F13 | G76: =G75-G13 | H76: =H75-H13 | I76: =I75-I13 | J76: =J75-J13 | K76: =K75-K13 | L76: =L75-L13 | M76: =M75-M13 | ... AZ76: =AZ75-AZ13

Sheet Checks>>
A1: Checks>>

Sheet Checks | Core
B1: Project North
B2: Checks | Core
B3: Source: System generated
B4: WORKING DRAFT
C7: Checks | Core
C9: Check_ID | D9: Description | E9: Status | F9: Actual | G9: Expected | H9: Severity | I9: Linked_Tab
C10: CHK-001 | D10: Control values populated | E10: =IF(F10=G10,"PASS","FAIL") | F10: =COUNTBLANK('_Sys|Config'!$B$2:$B$5) | G10: 0 | H10: HIGH | I10: _Sys|Config
C11: CHK-002 | D11: Unmapped TB rows | E11: =IF(F11=G11,"PASS","WARN") | F11: =COUNTIF('_Sys|Trial_Balance'!$I$2:$I$5000,"MISSING")+COUNTIF('_Sys|Trial_Balance'!$L$2:$L$5000,"MISSING") | G11: 0 | H11: HIGH | I11: _Sys|Trial_Balance
C12: CHK-003 | D12: No forbidden formulas in governed tabs | E12: =IF(F12=G12,"PASS","WARN") | F12: =COUNTIF('_Sys|Tab_Manifest'!$A:$A,">0") | G12: =COUNTIF('_Sys|Tab_Manifest'!$A:$A,">0") | H12: HIGH | I12: Core
C13: CHK-MON-001 | D13: 36-month contiguous header | Income statement | E13: =IF(F13=G13,"PASS","FAIL") | F13: =IF(AND(COUNT('Income statement'!$F$9:$AO$9)=36,SUMPRODUCT(--('Income statement'!$F$9:$AO$9=EDATE('Income statement'!$F$9,COLUMN('Income statement'!$F$9:$AO$9)-COLUMN('Income statement'!$F$9))))=36),1,0) | G13: 1 | H13: HIGH | I13: Income statement
C14: CHK-MON-002 | D14: 36-month contiguous header | Balance sheet | E14: =IF(F14=G14,"PASS","FAIL") | F14: =IF(AND(COUNT('Balance sheet'!$F$9:$AO$9)=36,SUMPRODUCT(--('Balance sheet'!$F$9:$AO$9=EDATE('Balance sheet'!$F$9,COLUMN('Balance sheet'!$F$9:$AO$9)-COLUMN('Balance sheet'!$F$9))))=36),1,0) | G14: 1 | H14: HIGH | I14: Balance sheet
C15: CHK-MON-003 | D15: 36-month contiguous header | QofE | Detail | E15: =IF(F15=G15,"PASS","FAIL") | F15: =IF(AND(COUNT('QofE | Detail'!$E$8:$AN$8)=36,SUMPRODUCT(--('QofE | Detail'!$E$8:$AN$8=EDATE('QofE | Detail'!$E$8,COLUMN('QofE | Detail'!$E$8:$AN$8)-COLUMN('QofE | Detail'!$E$8))))=36),1,0) | G15: 1 | H15: HIGH | I15: QofE | Detail
C16: CHK-MON-004 | D16: 36-month contiguous header | Net debt | E16: =IF(F16=G16,"PASS","FAIL") | F16: =IF(AND(COUNT('Net debt'!$E$9:$AN$9)=36,SUMPRODUCT(--('Net debt'!$E$9:$AN$9=EDATE('Net debt'!$E$9,COLUMN('Net debt'!$E$9:$AN$9)-COLUMN('Net debt'!$E$9))))=36),1,0) | G16: 1 | H16: HIGH | I16: Net debt
C17: CHK-MON-005 | D17: 36-month contiguous header | Recon | Billings | E17: =IF(F17=G17,"PASS","FAIL") | F17: =IF(AND(COUNT('Recon | Billings'!$F$8:$AO$8)=36,SUMPRODUCT(--('Recon | Billings'!$F$8:$AO$8=EDATE('Recon | Billings'!$F$8,COLUMN('Recon | Billings'!$F$8:$AO$8)-COLUMN('Recon | Billings'!$F$8))))=36),1,0) | G17: 1 | H17: HIGH | I17: Recon | Billings

Sheet Audit>>
A1: Audit>>

Sheet Audit | Issues_Index
B1: Project North
B2: Audit | Issues_Index
B3: Source: System generated
B4: WORKING_DRAFT
C7: Audit | Issues_Index
C9: issue_id | D9: sheet | E9: cell | F9: severity | G9: message | H9: linked_check | I9: timestamp_utc | J9: status

Sheet Audit | Run_Log
B1: Project North
B2: Audit | Run_Log
B3: Source: System generated
B4: WORKING_DRAFT
C7: Audit | Run_Log
C9: run_id | D9: timestamp_utc | E9: mode | F9: tabs_touched | G9: checks_pass | H9: checks_warn | I9: checks_fail | J9: operator

Sheet _Sys|Trial_Balance
A1: period_end | B1: account_code | C1: account_name | D1: amount | E1: entity | F1: source_file | G1: source_tab | H1: note | I1: map_line | J1: map_sign | K1: signed_amount | L1: map_statement_type
I2: =XLOOKUP(B2,'_Sys|Line_Map'!$A:$A,'_Sys|Line_Map'!$C:$C,"MISSING",0) | J2: =XLOOKUP(B2,'_Sys|Line_Map'!$A:$A,'_Sys|Line_Map'!$D:$D,1,0) | K2: =IF(D2="","",D2*J2) | L2: =XLOOKUP(B2,'_Sys|Line_Map'!$A:$A,'_Sys|Line_Map'!$B:$B,"MISSING",0)
I3: =XLOOKUP(B3,'_Sys|Line_Map'!$A:$A,'_Sys|Line_Map'!$C:$C,"MISSING",0) | J3: =XLOOKUP(B3,'_Sys|Line_Map'!$A:$A,'_Sys|Line_Map'!$D:$D,1,0) | K3: =IF(D3="","",D3*J3) | L3: =XLOOKUP(B3,'_Sys|Line_Map'!$A:$A,'_Sys|Line_Map'!$B:$B,"MISSING",0)
I4: =XLOOKUP(B4,'_Sys|Line_Map'!$A:$A,'_Sys|Line_Map'!$C:$C,"MISSING",0) | J4: =XLOOKUP(B4,'_Sys|Line_Map'!$A:$A,'_Sys|Line_Map'!$D:$D,1,0) | K4: =IF(D4="","",D4*J4) | L4: =XLOOKUP(B4,'_Sys|Line_Map'!$A:$A,'_Sys|Line_Map'!$B:$B,"MISSING",0)
I5: =XLOOKUP(B5,'_Sys|Line_Map'!$A:$A,'_Sys|Line_Map'!$C:$C,"MISSING",0) | J5: =XLOOKUP(B5,'_Sys|Line_Map'!$A:$A,'_Sys|Line_Map'!$D:$D,1,0) | K5: =IF(D5="","",D5*J5) | L5: =XLOOKUP(B5,'_Sys|Line_Map'!$A:$A,'_Sys|Line_Map'!$B:$B,"MISSING",0)
I6: =XLOOKUP(B6,'_Sys|Line_Map'!$A:$A,'_Sys|Line_Map'!$C:$C,"MISSING",0) | J6: =XLOOKUP(B6,'_Sys|Line_Map'!$A:$A,'_Sys|Line_Map'!$D:$D,1,0) | K6: =IF(D6="","",D6*J6) | L6: =XLOOKUP(B6,'_Sys|Line_Map'!$A:$A,'_Sys|Line_Map'!$B:$B,"MISSING",0)
I7: =XLOOKUP(B7,'_Sys|Line_Map'!$A:$A,'_Sys|Line_Map'!$C:$C,"MISSING",0) | J7: =XLOOKUP(B7,'_Sys|Line_Map'!$A:$A,'_Sys|Line_Map'!$D:$D,1,0) | K7: =IF(D7="","",D7*J7) | L7: =XLOOKUP(B7,'_Sys|Line_Map'!$A:$A,'_Sys|Line_Map'!$B:$B,"MISSING",0)
I8: =XLOOKUP(B8,'_Sys|Line_Map'!$A:$A,'_Sys|Line_Map'!$C:$C,"MISSING",0) | J8: =XLOOKUP(B8,'_Sys|Line_Map'!$A:$A,'_Sys|Line_Map'!$D:$D,1,0) | K8: =IF(D8="","",D8*J8) | L8: =XLOOKUP(B8,'_Sys|Line_Map'!$A:$A,'_Sys|Line_Map'!$B:$B,"MISSING",0)
I9: =XLOOKUP(B9,'_Sys|Line_Map'!$A:$A,'_Sys|Line_Map'!$C:$C,"MISSING",0) | J9: =XLOOKUP(B9,'_Sys|Line_Map'!$A:$A,'_Sys|Line_Map'!$D:$D,1,0) | K9: =IF(D9="","",D9*J9) | L9: =XLOOKUP(B9,'_Sys|Line_Map'!$A:$A,'_Sys|Line_Map'!$B:$B,"MISSING",0)
I10: =XLOOKUP(B10,'_Sys|Line_Map'!$A:$A,'_Sys|Line_Map'!$C:$C,"MISSING",0) | J10: =XLOOKUP(B10,'_Sys|Line_Map'!$A:$A,'_Sys|Line_Map'!$D:$D,1,0) | K10: =IF(D10="","",D10*J10) | L10: =XLOOKUP(B10,'_Sys|Line_Map'!$A:$A,'_Sys|Line_Map'!$B:$B,"MISSING",0)
I11: =XLOOKUP(B11,'_Sys|Line_Map'!$A:$A,'_Sys|Line_Map'!$C:$C,"MISSING",0) | J11: =XLOOKUP(B11,'_Sys|Line_Map'!$A:$A,'_Sys|Line_Map'!$D:$D,1,0) | K11: =IF(D11="","",D11*J11) | L11: =XLOOKUP(B11,'_Sys|Line_Map'!$A:$A,'_Sys|Line_Map'!$B:$B,"MISSING",0)
I12: =XLOOKUP(B12,'_Sys|Line_Map'!$A:$A,'_Sys|Line_Map'!$C:$C,"MISSING",0) | J12: =XLOOKUP(B12,'_Sys|Line_Map'!$A:$A,'_Sys|Line_Map'!$D:$D,1,0) | K12: =IF(D12="","",D12*J12) | L12: =XLOOKUP(B12,'_Sys|Line_Map'!$A:$A,'_Sys|Line_Map'!$B:$B,"MISSING",0)
I13: =XLOOKUP(B13,'_Sys|Line_Map'!$A:$A,'_Sys|Line_Map'!$C:$C,"MISSING",0) | J13: =XLOOKUP(B13,'_Sys|Line_Map'!$A:$A,'_Sys|Line_Map'!$D:$D,1,0) | K13: =IF(D13="","",D13*J13) | L13: =XLOOKUP(B13,'_Sys|Line_Map'!$A:$A,'_Sys|Line_Map'!$B:$B,"MISSING",0)
... I5000: =XLOOKUP(B5000,'_Sys|Line_Map'!$A:$A,'_Sys|Line_Map'!$C:$C,"MISSING",0) | J5000: =XLOOKUP(B5000,'_Sys|Line_Map'!$A:$A,'_Sys|Line_Map'!$D:$D,1,0) | K5000: =IF(D5000="","",D5000*J5000) | L5000: =XLOOKUP(B5000,'_Sys|Line_Map'!$A:$A,'_Sys|Line_Map'!$B:$B,"MISSING",0)

Sheet _Sys|Line_Map
A1: account_code | B1: statement_type | C1: report_line | D1: sign_factor | E1: active_flag | F1: notes
A2: 4000 | B2: IS | C2: Revenue | D2: 1 | E2: Y | F2: seed mapping
A3: 5000 | B3: IS | C3: COGS | D3: -1 | E3: Y | F3: seed mapping
A4: 6100 | B4: IS | C4: Personnel_Costs | D4: -1 | E4: Y | F4: seed mapping
A5: 1000 | B5: BS | C5: Cash | D5: 1 | E5: Y | F5: seed mapping
A6: 2000 | B6: BS | C6: AP | D6: -1 | E6: Y | F6: seed mapping

Sheet _Sys|Tab_Manifest
A1: tab_name | B1: is_visible_scope | C1: is_monthly_enforced | D1: period_header_row | E1: period_start_col | F1: period_count_required | G1: comments_header_cell | H1: write_scope
A2: Project North >>> | B2: TRUE | C2: FALSE | H2: comments-only
A3: Disclaimer | B3: TRUE | C3: FALSE | H3: comments-only
A4: QofE >> | B4: TRUE | C4: FALSE | H4: comments-only
A5: QofE | Bridge | B5: TRUE | C5: FALSE | G5: AI7 | H5: comments-only
A6: QofE | Summary | B6: TRUE | C6: FALSE | H6: comments-only
A7: QofE | Detail | B7: TRUE | C7: TRUE | D7: 8 | E7: E | F7: 36 | G7: BA7 | H7: monthly-grid + comments
A8: Net debt>> | B8: TRUE | C8: FALSE | H8: comments-only
A9: Net debt | B9: TRUE | C9: TRUE | D9: 9 | E9: E | F9: 36 | G9: M7 | H9: monthly-grid + comments
A10: Financials>> | B10: TRUE | C10: FALSE | H10: comments-only
A11: Income statement | B11: TRUE | C11: TRUE | D11: 9 | E11: F | F11: 36 | H11: monthly-grid + comments
A12: Balance sheet | B12: TRUE | C12: TRUE | D12: 9 | E12: F | F12: 36 | H12: monthly-grid + comments
A13: Cash flow | B13: TRUE | C13: FALSE | H13: comments-only
A14: Personnel>> | B14: TRUE | C14: FALSE | H14: comments-only
A15: IS | Payroll costs | B15: TRUE | C15: FALSE | H15: comments-only
A16: Headcount census | B16: TRUE | C16: FALSE | H16: comments-only
A17: Other analysis>> | B17: TRUE | C17: FALSE | H17: comments-only
A18: Top customers | B18: TRUE | C18: FALSE | H18: comments-only
A19: Revenue by customer group | B19: TRUE | C19: FALSE | H19: comments-only
A20: Recons >> | B20: TRUE | C20: FALSE | H20: comments-only
A21: Recons | IS | B21: TRUE | C21: FALSE | H21: comments-only
A22: Recons | BS | B22: TRUE | C22: FALSE | H22: comments-only
A23: Recon | Cash flow | B23: TRUE | C23: FALSE | G23: AF7 | H23: comments-only
A24: Recon | Billings | B24: TRUE | C24: TRUE | D24: 8 | E24: F | F24: 36 | G24: BB7 | H24: monthly-grid + comments
A25: Checks>> | B25: TRUE | C25: FALSE | H25: comments-only
A26: Checks | Core | B26: TRUE | C26: FALSE
A27: Audit>> | B27: TRUE | C27: FALSE | H27: comments-only
A28: Audit | Issues_Index | B28: TRUE | C28: FALSE | H28: C10:J5000
A29: Audit | Run_Log | B29: TRUE | C29: FALSE | H29: C10:J5000
A30: _Sys|Trial_Balance | B30: FALSE | C30: FALSE | H30: A2:H5000
A31: _Sys|Line_Map | B31: FALSE | C31: FALSE | H31: A2:F5000
A32: _Sys|Tab_Manifest | B32: FALSE | C32: FALSE
A33: _Sys|Config | B33: FALSE | C33: FALSE

Sheet _Sys|Config
A1: config_key | B1: config_value
A2: ctl_monthly_period_count | B2: 36
A3: ctl_month_start | B3: 44227
A4: ctl_tolerance_abs | B4: 1
A5: ctl_tolerance_pct | B5: 0.001
A6: ctl_project_name | B6: Project Name
