Workbook
Name Button_429: "LeaseCalc_Lease_Data_List"
Name CellAbove: INDIRECT(ADDRESS(ROW()-1,COLUMN()))
Name CIT: #N/A
Name IQ_CH: 110000
Name IQ_CQ: 5000
Name IQ_CY: 10000
Name IQ_DAILY: 500000
Name IQ_FH: 100000
Name IQ_FQ: 500
Name IQ_FY: 1000
Name IQ_LTM: 2000
Name IQ_MONTH: 15000
Name IQ_NTM: 6000
Name IQ_WEEK: 50000
Name IQ_YTD: 3000
Name TM1REBUILDOPTION: 1

Sheet Adjusted IS
B1: Project North
B2: =C7
B3: Source:Everlink P&L IFRS1516 All Months Statements
B4: WORKING DRAFT
C7: Adjusted income statement
F8: Reported | R8: =F8 | AD8: =R8 | AP8: =AD8 | AV8: =AP8 | BB8: Definitional adjustments | BN8: =BB8 | BZ8: =BN8 | CL8: =BZ8 | CR8: =CL8 | CX8: EBITDA | DJ8: =CX8 | DV8: =DJ8 | EH8: =DV8 | EN8: =EH8 | ET8: Due diligence adjustments | FF8: =ET8 | FR8: =FF8 | GD8: =FR8 | GJ8: =GD8 | GP8: Diligence adjusted EBITDA | HB8: =GP8 | HN8: =HB8 | HZ8: =HN8 | IF8: =HZ8 | IL8: Pro forma adjustments | IX8: =IL8 | JJ8: =IX8 | JV8: =JJ8 | KB8: =JV8 | KH8: Pro forma adjusted EBITDA | KT8: =KH8 | LF8: =KT8 | LR8: =LF8 | LX8: =LR8 | MD8: As a % of Revenue | MP8: As a % of Revenue | NB8: As a % of Revenue | NN8: As a % of Revenue | NT8: As a % of Revenue | NZ8: Change | OE8: Adjusted IS Mapping
C9: $'000 | D9: Code | E9: Concatenate | F9: 44197 | G9: =EOMONTH(F9,1) | H9: =EOMONTH(G9,1) | I9: =EOMONTH(H9,1) | J9: =EOMONTH(I9,1) | K9: =EOMONTH(J9,1) | L9: =EOMONTH(K9,1) | M9: =EOMONTH(L9,1) | N9: =EOMONTH(M9,1) | ... AU9: =EOMONTH(AT9,1) | AV9: FY21 | AW9: FY22 | AX9: FY23 | AY9: TTM Apr-24 | AZ9: TTM Jun-24 | BB9: 44197 | BC9: =EOMONTH(BB9,1) | BD9: =EOMONTH(BC9,1) | BE9: =EOMONTH(BD9,1) | BF9: =EOMONTH(BE9,1) | BG9: =EOMONTH(BF9,1) | BH9: =EOMONTH(BG9,1) | BI9: =EOMONTH(BH9,1) | BJ9: =EOMONTH(BI9,1) | ... CQ9: =EOMONTH(CP9,1) | CR9: FY21 | CS9: FY22 | CT9: FY23 | CU9: TTM Apr-24 | CV9: TTM Jun-24 | CX9: 44197 | CY9: =EOMONTH(CX9,1) | CZ9: =EOMONTH(CY9,1) | DA9: =EOMONTH(CZ9,1) | DB9: =EOMONTH(DA9,1) | DC9: =EOMONTH(DB9,1) | DD9: =EOMONTH(DC9,1) | DE9: =EOMONTH(DD9,1) | DF9: =EOMONTH(DE9,1) | ... EM9: =EOMONTH(EL9,1) | EN9: FY21 | EO9: FY22 | EP9: FY23 | EQ9: TTM Apr-24 | ER9: TTM Jun-24 | ET9: 44197 | EU9: =EOMONTH(ET9,1) | EV9: =EOMONTH(EU9,1) | EW9: =EOMONTH(EV9,1) | EX9: =EOMONTH(EW9,1) | EY9: =EOMONTH(EX9,1) | EZ9: =EOMONTH(EY9,1) | FA9: =EOMONTH(EZ9,1) | FB9: =EOMONTH(FA9,1) | ... GI9: =EOMONTH(GH9,1) | GJ9: FY21 | GK9: FY22 | GL9: FY23 | GM9: TTM Apr-24 | GN9: TTM Jun-24 | GP9: 44197 | GQ9: =EOMONTH(GP9,1) | GR9: =EOMONTH(GQ9,1) | GS9: =EOMONTH(GR9,1) | GT9: =EOMONTH(GS9,1) | GU9: =EOMONTH(GT9,1) | GV9: =EOMONTH(GU9,1) | GW9: =EOMONTH(GV9,1) | GX9: =EOMONTH(GW9,1) | ... IE9: =EOMONTH(ID9,1) | IF9: FY21 | IG9: FY22 | IH9: FY23 | II9: TTM Apr-24 | IJ9: TTM Jun-24 | IL9: 44197 | IM9: =EOMONTH(IL9,1) | IN9: =EOMONTH(IM9,1) | IO9: =EOMONTH(IN9,1) | IP9: =EOMONTH(IO9,1) | IQ9: =EOMONTH(IP9,1) | IR9: =EOMONTH(IQ9,1) | IS9: =EOMONTH(IR9,1) | IT9: =EOMONTH(IS9,1) | ... KA9: =EOMONTH(JZ9,1) | KB9: FY21 | KC9: FY22 | KD9: FY23 | KE9: TTM Apr-24 | KF9: TTM Jun-24 | KH9: 44197 | KI9: =EOMONTH(KH9,1) | KJ9: =EOMONTH(KI9,1) | KK9: =EOMONTH(KJ9,1) | KL9: =EOMONTH(KK9,1) | KM9: =EOMONTH(KL9,1) | KN9: =EOMONTH(KM9,1) | KO9: =EOMONTH(KN9,1) | KP9: =EOMONTH(KO9,1) | ... LW9: =EOMONTH(LV9,1) | LX9: FY21 | LY9: FY22 | LZ9: FY23 | MA9: TTM Apr-24 | MB9: TTM Jun-24 | MD9: 44197 | ME9: =EOMONTH(MD9,1) | MF9: =EOMONTH(ME9,1) | MG9: =EOMONTH(MF9,1) | MH9: =EOMONTH(MG9,1) | MI9: =EOMONTH(MH9,1) | MJ9: =EOMONTH(MI9,1) | MK9: =EOMONTH(MJ9,1) | ML9: =EOMONTH(MK9,1) | ... NS9: =EOMONTH(NR9,1) | NT9: FY21 | NU9: FY22 | NV9: FY23 | NW9: TTM Apr-24 | NX9: TTM Jun-24 | NZ9: FY22 vs FY21 | OA9: FY23 vs FY22 | OB9: TTM Apr-24 vs FY23 | OC9: TTM Jun-24 vs FY23 | OE9: FY22 vs FY21 | OF9: FY23 vs FY22 | OG9: TTM Apr-24 vs FY23
C10: Mobile tsp transactions pos- | D10: 411110 | E10: =CONCATENATE(D10," - ",C10) | F10: ='Income statement'!F10 | G10: ='Income statement'!G10 | H10: ='Income statement'!H10 | I10: ='Income statement'!I10 | J10: ='Income statement'!J10 | K10: ='Income statement'!K10 | L10: ='Income statement'!L10 | M10: ='Income statement'!M10 | ... AU10: ='Income statement'!AU10 | AV10: =SUM(F10:Q10) | AW10: =SUM(R10:AC10) | AX10: =SUM(AD10:AO10) | AY10: =SUM(AH10:AS10) | AZ10: =SUM(AJ10:AU10) | BB10: =SUMIFS('QofE Def adjustments'!F:F,'QofE Def adjustments'!$E:$E,'Adjusted IS'!$E10) | BC10: =SUMIFS('QofE Def adjustments'!G:G,'QofE Def adjustments'!$E:$E,'Adjusted IS'!$E10) | BD10: =SUMIFS('QofE Def adjustments'!H:H,'QofE Def adjustments'!$E:$E,'Adjusted IS'!$E10) | BE10: =SUMIFS('QofE Def adjustments'!I:I,'QofE Def adjustments'!$E:$E,'Adjusted IS'!$E10) | BF10: =SUMIFS('QofE Def adjustments'!J:J,'QofE Def adjustments'!$E:$E,'Adjusted IS'!$E10) | BG10: =SUMIFS('QofE Def adjustments'!K:K,'QofE Def adjustments'!$E:$E,'Adjusted IS'!$E10) | BH10: =SUMIFS('QofE Def adjustments'!L:L,'QofE Def adjustments'!$E:$E,'Adjusted IS'!$E10) | BI10: =SUMIFS('QofE Def adjustments'!M:M,'QofE Def adjustments'!$E:$E,'Adjusted IS'!$E10) | BJ10: =SUMIFS('QofE Def adjustments'!N:N,'QofE Def adjustments'!$E:$E,'Adjusted IS'!$E10) | BK10: =SUMIFS('QofE Def adjustments'!O:O,'QofE Def adjustments'!$E:$E,'Adjusted IS'!$E10) | BL10: =SUMIFS('QofE Def adjustments'!P:P,'QofE Def adjustments'!$E:$E,'Adjusted IS'!$E10) | BM10: =SUMIFS('QofE Def adjustments'!Q:Q,'QofE Def adjustments'!$E:$E,'Adjusted IS'!$E10) | BN10: =SUMIFS('QofE Def adjustments'!R:R,'QofE Def adjustments'!$E:$E,'Adjusted IS'!$E10) | BO10: =SUMIFS('QofE Def adjustments'!S:S,'QofE Def adjustments'!$E:$E,'Adjusted IS'!$E10) | BP10: =SUMIFS('QofE Def adjustments'!T:T,'QofE Def adjustments'!$E:$E,'Adjusted IS'!$E10) | BQ10: =SUMIFS('QofE Def adjustments'!U:U,'QofE Def adjustments'!$E:$E,'Adjusted IS'!$E10) | BR10: =SUMIFS('QofE Def adjustments'!V:V,'QofE Def adjustments'!$E:$E,'Adjusted IS'!$E10) | BS10: =SUMIFS('QofE Def adjustments'!W:W,'QofE Def adjustments'!$E:$E,'Adjusted IS'!$E10) | BT10: =SUMIFS('QofE Def adjustments'!X:X,'QofE Def adjustments'!$E:$E,'Adjusted IS'!$E10) | BU10: =SUMIFS('QofE Def adjustments'!Y:Y,'QofE Def adjustments'!$E:$E,'Adjusted IS'!$E10) | BV10: =SUMIFS('QofE Def adjustments'!Z:Z,'QofE Def adjustments'!$E:$E,'Adjusted IS'!$E10) | BW10: =SUMIFS('QofE Def adjustments'!AA:AA,'QofE Def adjustments'!$E:$E,'Adjusted IS'!$E10) | BX10: =SUMIFS('QofE Def adjustments'!AB:AB,'QofE Def adjustments'!$E:$E,'Adjusted IS'!$E10) | BY10: =SUMIFS('QofE Def adjustments'!AC:AC,'QofE Def adjustments'!$E:$E,'Adjusted IS'!$E10) | BZ10: =SUMIFS('QofE Def adjustments'!AD:AD,'QofE Def adjustments'!$E:$E,'Adjusted IS'!$E10) | CA10: =SUMIFS('QofE Def adjustments'!AE:AE,'QofE Def adjustments'!$E:$E,'Adjusted IS'!$E10) | CB10: =SUMIFS('QofE Def adjustments'!AF:AF,'QofE Def adjustments'!$E:$E,'Adjusted IS'!$E10) | CC10: =SUMIFS('QofE Def adjustments'!AG:AG,'QofE Def adjustments'!$E:$E,'Adjusted IS'!$E10) | CD10: =SUMIFS('QofE Def adjustments'!AH:AH,'QofE Def adjustments'!$E:$E,'Adjusted IS'!$E10) | CE10: =SUMIFS('QofE Def adjustments'!AI:AI,'QofE Def adjustments'!$E:$E,'Adjusted IS'!$E10) | CF10: =SUMIFS('QofE Def adjustments'!AJ:AJ,'QofE Def adjustments'!$E:$E,'Adjusted IS'!$E10) | CG10: =SUMIFS('QofE Def adjustments'!AK:AK,'QofE Def adjustments'!$E:$E,'Adjusted IS'!$E10) | CH10: =SUMIFS('QofE Def adjustments'!AL:AL,'QofE Def adjustments'!$E:$E,'Adjusted IS'!$E10) | CI10: =SUMIFS('QofE Def adjustments'!AM:AM,'QofE Def adjustments'!$E:$E,'Adjusted IS'!$E10) | CJ10: =SUMIFS('QofE Def adjustments'!AN:AN,'QofE Def adjustments'!$E:$E,'Adjusted IS'!$E10) | CK10: =SUMIFS('QofE Def adjustments'!AO:AO,'QofE Def adjustments'!$E:$E,'Adjusted IS'!$E10) | CL10: =SUMIFS('QofE Def adjustments'!AP:AP,'QofE Def adjustments'!$E:$E,'Adjusted IS'!$E10) | CM10: =SUMIFS('QofE Def adjustments'!AQ:AQ,'QofE Def adjustments'!$E:$E,'Adjusted IS'!$E10) | CN10: =SUMIFS('QofE Def adjustments'!AR:AR,'QofE Def adjustments'!$E:$E,'Adjusted IS'!$E10) | CO10: =SUMIFS('QofE Def adjustments'!AS:AS,'QofE Def adjustments'!$E:$E,'Adjusted IS'!$E10) | CP10: =SUMIFS('QofE Def adjustments'!AT:AT,'QofE Def adjustments'!$E:$E,'Adjusted IS'!$E10) | CQ10: =SUMIFS('QofE Def adjustments'!AU:AU,'QofE Def adjustments'!$E:$E,'Adjusted IS'!$E10) | CR10: =SUM(BB10:BM10) | CS10: =SUM(BN10:BY10) | CT10: =SUM(BZ10:CK10) | CU10: =SUM(CD10:CO10) | CV10: =SUM(CF10:CQ10) | CX10: =SUM(BB10,F10) | CY10: =SUM(BC10,G10) | CZ10: =SUM(BD10,H10) | DA10: =SUM(BE10,I10) | DB10: =SUM(BF10,J10) | DC10: =SUM(BG10,K10) | DD10: =SUM(BH10,L10) | DE10: =SUM(BI10,M10) | ... EM10: =SUM(CQ10,AU10) | EN10: =SUM(CX10:DI10) | EO10: =SUM(DJ10:DU10) | EP10: =SUM(DV10:EG10) | EQ10: =SUM(DZ10:EK10) | ER10: =SUM(EB10:EM10) | ET10: =SUMIFS('QofE DD adjustments'!F:F,'QofE DD adjustments'!$E:$E,'Adjusted IS'!$E10) | EU10: =SUMIFS('QofE DD adjustments'!G:G,'QofE DD adjustments'!$E:$E,'Adjusted IS'!$E10) | EV10: =SUMIFS('QofE DD adjustments'!H:H,'QofE DD adjustments'!$E:$E,'Adjusted IS'!$E10) | EW10: =SUMIFS('QofE DD adjustments'!I:I,'QofE DD adjustments'!$E:$E,'Adjusted IS'!$E10) | EX10: =SUMIFS('QofE DD adjustments'!J:J,'QofE DD adjustments'!$E:$E,'Adjusted IS'!$E10) | EY10: =SUMIFS('QofE DD adjustments'!K:K,'QofE DD adjustments'!$E:$E,'Adjusted IS'!$E10) | EZ10: =SUMIFS('QofE DD adjustments'!L:L,'QofE DD adjustments'!$E:$E,'Adjusted IS'!$E10) | FA10: =SUMIFS('QofE DD adjustments'!M:M,'QofE DD adjustments'!$E:$E,'Adjusted IS'!$E10) | FB10: =SUMIFS('QofE DD adjustments'!N:N,'QofE DD adjustments'!$E:$E,'Adjusted IS'!$E10) | FC10: =SUMIFS('QofE DD adjustments'!O:O,'QofE DD adjustments'!$E:$E,'Adjusted IS'!$E10) | FD10: =SUMIFS('QofE DD adjustments'!P:P,'QofE DD adjustments'!$E:$E,'Adjusted IS'!$E10) | FE10: =SUMIFS('QofE DD adjustments'!Q:Q,'QofE DD adjustments'!$E:$E,'Adjusted IS'!$E10) | FF10: =SUMIFS('QofE DD adjustments'!R:R,'QofE DD adjustments'!$E:$E,'Adjusted IS'!$E10) | FG10: =SUMIFS('QofE DD adjustments'!S:S,'QofE DD adjustments'!$E:$E,'Adjusted IS'!$E10) | FH10: =SUMIFS('QofE DD adjustments'!T:T,'QofE DD adjustments'!$E:$E,'Adjusted IS'!$E10) | FI10: =SUMIFS('QofE DD adjustments'!U:U,'QofE DD adjustments'!$E:$E,'Adjusted IS'!$E10) | FJ10: =SUMIFS('QofE DD adjustments'!V:V,'QofE DD adjustments'!$E:$E,'Adjusted IS'!$E10) | FK10: =SUMIFS('QofE DD adjustments'!W:W,'QofE DD adjustments'!$E:$E,'Adjusted IS'!$E10) | FL10: =SUMIFS('QofE DD adjustments'!X:X,'QofE DD adjustments'!$E:$E,'Adjusted IS'!$E10) | FM10: =SUMIFS('QofE DD adjustments'!Y:Y,'QofE DD adjustments'!$E:$E,'Adjusted IS'!$E10) | FN10: =SUMIFS('QofE DD adjustments'!Z:Z,'QofE DD adjustments'!$E:$E,'Adjusted IS'!$E10) | FO10: =SUMIFS('QofE DD adjustments'!AA:AA,'QofE DD adjustments'!$E:$E,'Adjusted IS'!$E10) | FP10: =SUMIFS('QofE DD adjustments'!AB:AB,'QofE DD adjustments'!$E:$E,'Adjusted IS'!$E10) | FQ10: =SUMIFS('QofE DD adjustments'!AC:AC,'QofE DD adjustments'!$E:$E,'Adjusted IS'!$E10) | FR10: =SUMIFS('QofE DD adjustments'!AD:AD,'QofE DD adjustments'!$E:$E,'Adjusted IS'!$E10) | FS10: =SUMIFS('QofE DD adjustments'!AE:AE,'QofE DD adjustments'!$E:$E,'Adjusted IS'!$E10) | FT10: =SUMIFS('QofE DD adjustments'!AF:AF,'QofE DD adjustments'!$E:$E,'Adjusted IS'!$E10) | FU10: =SUMIFS('QofE DD adjustments'!AG:AG,'QofE DD adjustments'!$E:$E,'Adjusted IS'!$E10) | FV10: =SUMIFS('QofE DD adjustments'!AH:AH,'QofE DD adjustments'!$E:$E,'Adjusted IS'!$E10) | FW10: =SUMIFS('QofE DD adjustments'!AI:AI,'QofE DD adjustments'!$E:$E,'Adjusted IS'!$E10) | FX10: =SUMIFS('QofE DD adjustments'!AJ:AJ,'QofE DD adjustments'!$E:$E,'Adjusted IS'!$E10) | FY10: =SUMIFS('QofE DD adjustments'!AK:AK,'QofE DD adjustments'!$E:$E,'Adjusted IS'!$E10) | FZ10: =SUMIFS('QofE DD adjustments'!AL:AL,'QofE DD adjustments'!$E:$E,'Adjusted IS'!$E10) | GA10: =SUMIFS('QofE DD adjustments'!AM:AM,'QofE DD adjustments'!$E:$E,'Adjusted IS'!$E10) | GB10: =SUMIFS('QofE DD adjustments'!AN:AN,'QofE DD adjustments'!$E:$E,'Adjusted IS'!$E10) | GC10: =SUMIFS('QofE DD adjustments'!AO:AO,'QofE DD adjustments'!$E:$E,'Adjusted IS'!$E10) | GD10: =SUMIFS('QofE DD adjustments'!AP:AP,'QofE DD adjustments'!$E:$E,'Adjusted IS'!$E10) | GE10: =SUMIFS('QofE DD adjustments'!AQ:AQ,'QofE DD adjustments'!$E:$E,'Adjusted IS'!$E10) | GF10: =SUMIFS('QofE DD adjustments'!AR:AR,'QofE DD adjustments'!$E:$E,'Adjusted IS'!$E10) | GG10: =SUMIFS('QofE DD adjustments'!AS:AS,'QofE DD adjustments'!$E:$E,'Adjusted IS'!$E10) | GH10: =SUMIFS('QofE DD adjustments'!AT:AT,'QofE DD adjustments'!$E:$E,'Adjusted IS'!$E10) | GI10: =SUMIFS('QofE DD adjustments'!AU:AU,'QofE DD adjustments'!$E:$E,'Adjusted IS'!$E10) | GJ10: =SUM(ET10:FE10) | GK10: =SUM(FF10:FQ10) | GL10: =SUM(FR10:GC10) | GM10: =SUM(FV10:GG10) | GN10: =SUM(FX10:GI10) | GP10: =SUM(ET10,CX10) | GQ10: =SUM(EU10,CY10) | GR10: =SUM(EV10,CZ10) | GS10: =SUM(EW10,DA10) | GT10: =SUM(EX10,DB10) | GU10: =SUM(EY10,DC10) | GV10: =SUM(EZ10,DD10) | GW10: =SUM(FA10,DE10) | ... IE10: =SUM(GI10,EM10) | IF10: =SUM(GP10:HA10) | IG10: =SUM(HB10:HM10) | IH10: =SUM(HN10:HY10) | II10: =SUM(HR10:IC10) | IJ10: =SUM(HT10:IE10) | IL10: =SUMIFS('QofE PF adjustments'!F:F,'QofE PF adjustments'!$E:$E,'Adjusted IS'!$E10) | IM10: =SUMIFS('QofE PF adjustments'!G:G,'QofE PF adjustments'!$E:$E,'Adjusted IS'!$E10) | IN10: =SUMIFS('QofE PF adjustments'!H:H,'QofE PF adjustments'!$E:$E,'Adjusted IS'!$E10) | IO10: =SUMIFS('QofE PF adjustments'!I:I,'QofE PF adjustments'!$E:$E,'Adjusted IS'!$E10) | IP10: =SUMIFS('QofE PF adjustments'!J:J,'QofE PF adjustments'!$E:$E,'Adjusted IS'!$E10) | IQ10: =SUMIFS('QofE PF adjustments'!K:K,'QofE PF adjustments'!$E:$E,'Adjusted IS'!$E10) | IR10: =SUMIFS('QofE PF adjustments'!L:L,'QofE PF adjustments'!$E:$E,'Adjusted IS'!$E10) | IS10: =SUMIFS('QofE PF adjustments'!M:M,'QofE PF adjustments'!$E:$E,'Adjusted IS'!$E10) | IT10: =SUMIFS('QofE PF adjustments'!N:N,'QofE PF adjustments'!$E:$E,'Adjusted IS'!$E10) | IU10: =SUMIFS('QofE PF adjustments'!O:O,'QofE PF adjustments'!$E:$E,'Adjusted IS'!$E10) | IV10: =SUMIFS('QofE PF adjustments'!P:P,'QofE PF adjustments'!$E:$E,'Adjusted IS'!$E10) | IW10: =SUMIFS('QofE PF adjustments'!Q:Q,'QofE PF adjustments'!$E:$E,'Adjusted IS'!$E10) | IX10: =SUMIFS('QofE PF adjustments'!R:R,'QofE PF adjustments'!$E:$E,'Adjusted IS'!$E10) | IY10: =SUMIFS('QofE PF adjustments'!S:S,'QofE PF adjustments'!$E:$E,'Adjusted IS'!$E10) | IZ10: =SUMIFS('QofE PF adjustments'!T:T,'QofE PF adjustments'!$E:$E,'Adjusted IS'!$E10) | JA10: =SUMIFS('QofE PF adjustments'!U:U,'QofE PF adjustments'!$E:$E,'Adjusted IS'!$E10) | JB10: =SUMIFS('QofE PF adjustments'!V:V,'QofE PF adjustments'!$E:$E,'Adjusted IS'!$E10) | JC10: =SUMIFS('QofE PF adjustments'!W:W,'QofE PF adjustments'!$E:$E,'Adjusted IS'!$E10) | JD10: =SUMIFS('QofE PF adjustments'!X:X,'QofE PF adjustments'!$E:$E,'Adjusted IS'!$E10) | JE10: =SUMIFS('QofE PF adjustments'!Y:Y,'QofE PF adjustments'!$E:$E,'Adjusted IS'!$E10) | JF10: =SUMIFS('QofE PF adjustments'!Z:Z,'QofE PF adjustments'!$E:$E,'Adjusted IS'!$E10) | JG10: =SUMIFS('QofE PF adjustments'!AA:AA,'QofE PF adjustments'!$E:$E,'Adjusted IS'!$E10) | JH10: =SUMIFS('QofE PF adjustments'!AB:AB,'QofE PF adjustments'!$E:$E,'Adjusted IS'!$E10) | JI10: =SUMIFS('QofE PF adjustments'!AC:AC,'QofE PF adjustments'!$E:$E,'Adjusted IS'!$E10) | JJ10: =SUMIFS('QofE PF adjustments'!AD:AD,'QofE PF adjustments'!$E:$E,'Adjusted IS'!$E10) | JK10: =SUMIFS('QofE PF adjustments'!AE:AE,'QofE PF adjustments'!$E:$E,'Adjusted IS'!$E10) | JL10: =SUMIFS('QofE PF adjustments'!AF:AF,'QofE PF adjustments'!$E:$E,'Adjusted IS'!$E10) | JM10: =SUMIFS('QofE PF adjustments'!AG:AG,'QofE PF adjustments'!$E:$E,'Adjusted IS'!$E10) | JN10: =SUMIFS('QofE PF adjustments'!AH:AH,'QofE PF adjustments'!$E:$E,'Adjusted IS'!$E10) | JO10: =SUMIFS('QofE PF adjustments'!AI:AI,'QofE PF adjustments'!$E:$E,'Adjusted IS'!$E10) | JP10: =SUMIFS('QofE PF adjustments'!AJ:AJ,'QofE PF adjustments'!$E:$E,'Adjusted IS'!$E10) | JQ10: =SUMIFS('QofE PF adjustments'!AK:AK,'QofE PF adjustments'!$E:$E,'Adjusted IS'!$E10) | JR10: =SUMIFS('QofE PF adjustments'!AL:AL,'QofE PF adjustments'!$E:$E,'Adjusted IS'!$E10) | JS10: =SUMIFS('QofE PF adjustments'!AM:AM,'QofE PF adjustments'!$E:$E,'Adjusted IS'!$E10) | JT10: =SUMIFS('QofE PF adjustments'!AN:AN,'QofE PF adjustments'!$E:$E,'Adjusted IS'!$E10) | JU10: =SUMIFS('QofE PF adjustments'!AO:AO,'QofE PF adjustments'!$E:$E,'Adjusted IS'!$E10) | JV10: =SUMIFS('QofE PF adjustments'!AP:AP,'QofE PF adjustments'!$E:$E,'Adjusted IS'!$E10) | JW10: =SUMIFS('QofE PF adjustments'!AQ:AQ,'QofE PF adjustments'!$E:$E,'Adjusted IS'!$E10) | JX10: =SUMIFS('QofE PF adjustments'!AR:AR,'QofE PF adjustments'!$E:$E,'Adjusted IS'!$E10) | JY10: =SUMIFS('QofE PF adjustments'!AS:AS,'QofE PF adjustments'!$E:$E,'Adjusted IS'!$E10) | JZ10: =SUMIFS('QofE PF adjustments'!AT:AT,'QofE PF adjustments'!$E:$E,'Adjusted IS'!$E10) | KA10: =SUMIFS('QofE PF adjustments'!AU:AU,'QofE PF adjustments'!$E:$E,'Adjusted IS'!$E10) | KB10: =SUM(IL10:IW10) | KC10: =SUM(IX10:JI10) | KD10: =SUM(JJ10:JU10) | KE10: =SUM(JN10:JY10) | KF10: =SUM(JP10:KA10) | KH10: =SUM(IL10,GP10) | KI10: =SUM(IM10,GQ10) | KJ10: =SUM(IN10,GR10) | KK10: =SUM(IO10,GS10) | KL10: =SUM(IP10,GT10) | KM10: =SUM(IQ10,GU10) | KN10: =SUM(IR10,GV10) | KO10: =SUM(IS10,GW10) | ... LW10: =SUM(KA10,IE10) | LX10: =SUM(KH10:KS10) | LY10: =SUM(KT10:LE10) | LZ10: =SUM(LF10:LQ10) | MA10: =SUM(LJ10:LU10) | MB10: =SUM(LL10:LW10) | MD10: =IFERROR(KH10/KH$117,0) | ME10: =IFERROR(KI10/KI$117,0) | MF10: =IFERROR(KJ10/KJ$117,0) | MG10: =IFERROR(KK10/KK$117,0) | MH10: =IFERROR(KL10/KL$117,0) | MI10: =IFERROR(KM10/KM$117,0) | MJ10: =IFERROR(KN10/KN$117,0) | MK10: =IFERROR(KO10/KO$117,0) | ... NX10: =IFERROR(MB10/MB$117,0) | NZ10: =LY10-LX10 | OA10: =LZ10-LY10 | OB10: =MA10-LZ10 | OC10: =MB10-LZ10 | OE10: Processing services revenue | OF10: Processing services revenue | OG10: Processing services revenue
C11: Png transactions revenue - pos | D11: 411101 | E11: =CONCATENATE(D11," - ",C11) | F11: ='Income statement'!F11 | G11: ='Income statement'!G11 | H11: ='Income statement'!H11 | I11: ='Income statement'!I11 | J11: ='Income statement'!J11 | K11: ='Income statement'!K11 | L11: ='Income statement'!L11 | M11: ='Income statement'!M11 | ... AU11: ='Income statement'!AU11 | AV11: =SUM(F11:Q11) | AW11: =SUM(R11:AC11) | AX11: =SUM(AD11:AO11) | AY11: =SUM(AH11:AS11) | AZ11: =SUM(AJ11:AU11) | BB11: =SUMIFS('QofE Def adjustments'!F:F,'QofE Def adjustments'!$E:$E,'Adjusted IS'!$E11) | BC11: =SUMIFS('QofE Def adjustments'!G:G,'QofE Def adjustments'!$E:$E,'Adjusted IS'!$E11) | BD11: =SUMIFS('QofE Def adjustments'!H:H,'QofE Def adjustments'!$E:$E,'Adjusted IS'!$E11) | BE11: =SUMIFS('QofE Def adjustments'!I:I,'QofE Def adjustments'!$E:$E,'Adjusted IS'!$E11) | BF11: =SUMIFS('QofE Def adjustments'!J:J,'QofE Def adjustments'!$E:$E,'Adjusted IS'!$E11) | BG11: =SUMIFS('QofE Def adjustments'!K:K,'QofE Def adjustments'!$E:$E,'Adjusted IS'!$E11) | BH11: =SUMIFS('QofE Def adjustments'!L:L,'QofE Def adjustments'!$E:$E,'Adjusted IS'!$E11) | BI11: =SUMIFS('QofE Def adjustments'!M:M,'QofE Def adjustments'!$E:$E,'Adjusted IS'!$E11) | BJ11: =SUMIFS('QofE Def adjustments'!N:N,'QofE Def adjustments'!$E:$E,'Adjusted IS'!$E11) | BK11: =SUMIFS('QofE Def adjustments'!O:O,'QofE Def adjustments'!$E:$E,'Adjusted IS'!$E11) | BL11: =SUMIFS('QofE Def adjustments'!P:P,'QofE Def adjustments'!$E:$E,'Adjusted IS'!$E11) | BM11: =SUMIFS('QofE Def adjustments'!Q:Q,'QofE Def adjustments'!$E:$E,'Adjusted IS'!$E11) | BN11: =SUMIFS('QofE Def adjustments'!R:R,'QofE Def adjustments'!$E:$E,'Adjusted IS'!$E11) | BO11: =SUMIFS('QofE Def adjustments'!S:S,'QofE Def adjustments'!$E:$E,'Adjusted IS'!$E11) | BP11: =SUMIFS('QofE Def adjustments'!T:T,'QofE Def adjustments'!$E:$E,'Adjusted IS'!$E11) | BQ11: =SUMIFS('QofE Def adjustments'!U:U,'QofE Def adjustments'!$E:$E,'Adjusted IS'!$E11) | BR11: =SUMIFS('QofE Def adjustments'!V:V,'QofE Def adjustments'!$E:$E,'Adjusted IS'!$E11) | BS11: =SUMIFS('QofE Def adjustments'!W:W,'QofE Def adjustments'!$E:$E,'Adjusted IS'!$E11) | BT11: =SUMIFS('QofE Def adjustments'!X:X,'QofE Def adjustments'!$E:$E,'Adjusted IS'!$E11) | BU11: =SUMIFS('QofE Def adjustments'!Y:Y,'QofE Def adjustments'!$E:$E,'Adjusted IS'!$E11) | BV11: =SUMIFS('QofE Def adjustments'!Z:Z,'QofE Def adjustments'!$E:$E,'Adjusted IS'!$E11) | BW11: =SUMIFS('QofE Def adjustments'!AA:AA,'QofE Def adjustments'!$E:$E,'Adjusted IS'!$E11) | BX11: =SUMIFS('QofE Def adjustments'!AB:AB,'QofE Def adjustments'!$E:$E,'Adjusted IS'!$E11) | BY11: =SUMIFS('QofE Def adjustments'!AC:AC,'QofE Def adjustments'!$E:$E,'Adjusted IS'!$E11) | BZ11: =SUMIFS('QofE Def adjustments'!AD:AD,'QofE Def adjustments'!$E:$E,'Adjusted IS'!$E11) | CA11: =SUMIFS('QofE Def adjustments'!AE:AE,'QofE Def adjustments'!$E:$E,'Adjusted IS'!$E11) | CB11: =SUMIFS('QofE Def adjustments'!AF:AF,'QofE Def adjustments'!$E:$E,'Adjusted IS'!$E11) | CC11: =SUMIFS('QofE Def adjustments'!AG:AG,'QofE Def adjustments'!$E:$E,'Adjusted IS'!$E11) | CD11: =SUMIFS('QofE Def adjustments'!AH:AH,'QofE Def adjustments'!$E:$E,'Adjusted IS'!$E11) | CE11: =SUMIFS('QofE Def adjustments'!AI:AI,'QofE Def adjustments'!$E:$E,'Adjusted IS'!$E11) | CF11: =SUMIFS('QofE Def adjustments'!AJ:AJ,'QofE Def adjustments'!$E:$E,'Adjusted IS'!$E11) | CG11: =SUMIFS('QofE Def adjustments'!AK:AK,'QofE Def adjustments'!$E:$E,'Adjusted IS'!$E11) | CH11: =SUMIFS('QofE Def adjustments'!AL:AL,'QofE Def adjustments'!$E:$E,'Adjusted IS'!$E11) | CI11: =SUMIFS('QofE Def adjustments'!AM:AM,'QofE Def adjustments'!$E:$E,'Adjusted IS'!$E11) | CJ11: =SUMIFS('QofE Def adjustments'!AN:AN,'QofE Def adjustments'!$E:$E,'Adjusted IS'!$E11) | CK11: =SUMIFS('QofE Def adjustments'!AO:AO,'QofE Def adjustments'!$E:$E,'Adjusted IS'!$E11) | CL11: =SUMIFS('QofE Def adjustments'!AP:AP,'QofE Def adjustments'!$E:$E,'Adjusted IS'!$E11) | CM11: =SUMIFS('QofE Def adjustments'!AQ:AQ,'QofE Def adjustments'!$E:$E,'Adjusted IS'!$E11) | CN11: =SUMIFS('QofE Def adjustments'!AR:AR,'QofE Def adjustments'!$E:$E,'Adjusted IS'!$E11) | CO11: =SUMIFS('QofE Def adjustments'!AS:AS,'QofE Def adjustments'!$E:$E,'Adjusted IS'!$E11) | CP11: =SUMIFS('QofE Def adjustments'!AT:AT,'QofE Def adjustments'!$E:$E,'Adjusted IS'!$E11) | CQ11: =SUMIFS('QofE Def adjustments'!AU:AU,'QofE Def adjustments'!$E:$E,'Adjusted IS'!$E11) | CR11: =SUM(BB11:BM11) | CS11: =SUM(BN11:BY11) | CT11: =SUM(BZ11:CK11) | CU11: =SUM(CD11:CO11) | CV11: =SUM(CF11:CQ11) | CX11: =SUM(BB11,F11) | CY11: =SUM(BC11,G11) | CZ11: =SUM(BD11,H11) | DA11: =SUM(BE11,I11) | DB11: =SUM(BF11,J11) | DC11: =SUM(BG11,K11) | DD11: =SUM(BH11,L11) | DE11: =SUM(BI11,M11) | ... EM11: =SUM(CQ11,AU11) | EN11: =SUM(CX11:DI11) | EO11: =SUM(DJ11:DU11) | EP11: =SUM(DV11:EG11) | EQ11: =SUM(DZ11:EK11) | ER11: =SUM(EB11:EM11) | ET11: =SUMIFS('QofE DD adjustments'!F:F,'QofE DD adjustments'!$E:$E,'Adjusted IS'!$E11) | EU11: =SUMIFS('QofE DD adjustments'!G:G,'QofE DD adjustments'!$E:$E,'Adjusted IS'!$E11) | EV11: =SUMIFS('QofE DD adjustments'!H:H,'QofE DD adjustments'!$E:$E,'Adjusted IS'!$E11) | EW11: =SUMIFS('QofE DD adjustments'!I:I,'QofE DD adjustments'!$E:$E,'Adjusted IS'!$E11) | EX11: =SUMIFS('QofE DD adjustments'!J:J,'QofE DD adjustments'!$E:$E,'Adjusted IS'!$E11) | EY11: =SUMIFS('QofE DD adjustments'!K:K,'QofE DD adjustments'!$E:$E,'Adjusted IS'!$E11) | EZ11: =SUMIFS('QofE DD adjustments'!L:L,'QofE DD adjustments'!$E:$E,'Adjusted IS'!$E11) | FA11: =SUMIFS('QofE DD adjustments'!M:M,'QofE DD adjustments'!$E:$E,'Adjusted IS'!$E11) | FB11: =SUMIFS('QofE DD adjustments'!N:N,'QofE DD adjustments'!$E:$E,'Adjusted IS'!$E11) | FC11: =SUMIFS('QofE DD adjustments'!O:O,'QofE DD adjustments'!$E:$E,'Adjusted IS'!$E11) | FD11: =SUMIFS('QofE DD adjustments'!P:P,'QofE DD adjustments'!$E:$E,'Adjusted IS'!$E11) | FE11: =SUMIFS('QofE DD adjustments'!Q:Q,'QofE DD adjustments'!$E:$E,'Adjusted IS'!$E11) | FF11: =SUMIFS('QofE DD adjustments'!R:R,'QofE DD adjustments'!$E:$E,'Adjusted IS'!$E11) | FG11: =SUMIFS('QofE DD adjustments'!S:S,'QofE DD adjustments'!$E:$E,'Adjusted IS'!$E11) | FH11: =SUMIFS('QofE DD adjustments'!T:T,'QofE DD adjustments'!$E:$E,'Adjusted IS'!$E11) | FI11: =SUMIFS('QofE DD adjustments'!U:U,'QofE DD adjustments'!$E:$E,'Adjusted IS'!$E11) | FJ11: =SUMIFS('QofE DD adjustments'!V:V,'QofE DD adjustments'!$E:$E,'Adjusted IS'!$E11) | FK11: =SUMIFS('QofE DD adjustments'!W:W,'QofE DD adjustments'!$E:$E,'Adjusted IS'!$E11) | FL11: =SUMIFS('QofE DD adjustments'!X:X,'QofE DD adjustments'!$E:$E,'Adjusted IS'!$E11) | FM11: =SUMIFS('QofE DD adjustments'!Y:Y,'QofE DD adjustments'!$E:$E,'Adjusted IS'!$E11) | FN11: =SUMIFS('QofE DD adjustments'!Z:Z,'QofE DD adjustments'!$E:$E,'Adjusted IS'!$E11) | FO11: =SUMIFS('QofE DD adjustments'!AA:AA,'QofE DD adjustments'!$E:$E,'Adjusted IS'!$E11) | FP11: =SUMIFS('QofE DD adjustments'!AB:AB,'QofE DD adjustments'!$E:$E,'Adjusted IS'!$E11) | FQ11: =SUMIFS('QofE DD adjustments'!AC:AC,'QofE DD adjustments'!$E:$E,'Adjusted IS'!$E11) | FR11: =SUMIFS('QofE DD adjustments'!AD:AD,'QofE DD adjustments'!$E:$E,'Adjusted IS'!$E11) | FS11: =SUMIFS('QofE DD adjustments'!AE:AE,'QofE DD adjustments'!$E:$E,'Adjusted IS'!$E11) | FT11: =SUMIFS('QofE DD adjustments'!AF:AF,'QofE DD adjustments'!$E:$E,'Adjusted IS'!$E11) | FU11: =SUMIFS('QofE DD adjustments'!AG:AG,'QofE DD adjustments'!$E:$E,'Adjusted IS'!$E11) | FV11: =SUMIFS('QofE DD adjustments'!AH:AH,'QofE DD adjustments'!$E:$E,'Adjusted IS'!$E11) | FW11: =SUMIFS('QofE DD adjustments'!AI:AI,'QofE DD adjustments'!$E:$E,'Adjusted IS'!$E11) | FX11: =SUMIFS('QofE DD adjustments'!AJ:AJ,'QofE DD adjustments'!$E:$E,'Adjusted IS'!$E11) | FY11: =SUMIFS('QofE DD adjustments'!AK:AK,'QofE DD adjustments'!$E:$E,'Adjusted IS'!$E11) | FZ11: =SUMIFS('QofE DD adjustments'!AL:AL,'QofE DD adjustments'!$E:$E,'Adjusted IS'!$E11) | GA11: =SUMIFS('QofE DD adjustments'!AM:AM,'QofE DD adjustments'!$E:$E,'Adjusted IS'!$E11) | GB11: =SUMIFS('QofE DD adjustments'!AN:AN,'QofE DD adjustments'!$E:$E,'Adjusted IS'!$E11) | GC11: =SUMIFS('QofE DD adjustments'!AO:AO,'QofE DD adjustments'!$E:$E,'Adjusted IS'!$E11) | GD11: =SUMIFS('QofE DD adjustments'!AP:AP,'QofE DD adjustments'!$E:$E,'Adjusted IS'!$E11) | GE11: =SUMIFS('QofE DD adjustments'!AQ:AQ,'QofE DD adjustments'!$E:$E,'Adjusted IS'!$E11) | GF11: =SUMIFS('QofE DD adjustments'!AR:AR,'QofE DD adjustments'!$E:$E,'Adjusted IS'!$E11) | GG11: =SUMIFS('QofE DD adjustments'!AS:AS,'QofE DD adjustments'!$E:$E,'Adjusted IS'!$E11) | GH11: =SUMIFS('QofE DD adjustments'!AT:AT,'QofE DD adjustments'!$E:$E,'Adjusted IS'!$E11) | GI11: =SUMIFS('QofE DD adjustments'!AU:AU,'QofE DD adjustments'!$E:$E,'Adjusted IS'!$E11) | GJ11: =SUM(ET11:FE11) | GK11: =SUM(FF11:FQ11) | GL11: =SUM(FR11:GC11) | GM11: =SUM(FV11:GG11) | GN11: =SUM(FX11:GI11) | GP11: =SUM(ET11,CX11) | GQ11: =SUM(EU11,CY11) | GR11: =SUM(EV11,CZ11) | GS11: =SUM(EW11,DA11) | GT11: =SUM(EX11,DB11) | GU11: =SUM(EY11,DC11) | GV11: =SUM(EZ11,DD11) | GW11: =SUM(FA11,DE11) | ... IE11: =SUM(GI11,EM11) | IF11: =SUM(GP11:HA11) | IG11: =SUM(HB11:HM11) | IH11: =SUM(HN11:HY11) | II11: =SUM(HR11:IC11) | IJ11: =SUM(HT11:IE11) | IL11: =SUMIFS('QofE PF adjustments'!F:F,'QofE PF adjustments'!$E:$E,'Adjusted IS'!$E11) | IM11: =SUMIFS('QofE PF adjustments'!G:G,'QofE PF adjustments'!$E:$E,'Adjusted IS'!$E11) | IN11: =SUMIFS('QofE PF adjustments'!H:H,'QofE PF adjustments'!$E:$E,'Adjusted IS'!$E11) | IO11: =SUMIFS('QofE PF adjustments'!I:I,'QofE PF adjustments'!$E:$E,'Adjusted IS'!$E11) | IP11: =SUMIFS('QofE PF adjustments'!J:J,'QofE PF adjustments'!$E:$E,'Adjusted IS'!$E11) | IQ11: =SUMIFS('QofE PF adjustments'!K:K,'QofE PF adjustments'!$E:$E,'Adjusted IS'!$E11) | IR11: =SUMIFS('QofE PF adjustments'!L:L,'QofE PF adjustments'!$E:$E,'Adjusted IS'!$E11) | IS11: =SUMIFS('QofE PF adjustments'!M:M,'QofE PF adjustments'!$E:$E,'Adjusted IS'!$E11) | IT11: =SUMIFS('QofE PF adjustments'!N:N,'QofE PF adjustments'!$E:$E,'Adjusted IS'!$E11) | IU11: =SUMIFS('QofE PF adjustments'!O:O,'QofE PF adjustments'!$E:$E,'Adjusted IS'!$E11) | IV11: =SUMIFS('QofE PF adjustments'!P:P,'QofE PF adjustments'!$E:$E,'Adjusted IS'!$E11) | IW11: =SUMIFS('QofE PF adjustments'!Q:Q,'QofE PF adjustments'!$E:$E,'Adjusted IS'!$E11) | IX11: =SUMIFS('QofE PF adjustments'!R:R,'QofE PF adjustments'!$E:$E,'Adjusted IS'!$E11) | IY11: =SUMIFS('QofE PF adjustments'!S:S,'QofE PF adjustments'!$E:$E,'Adjusted IS'!$E11) | IZ11: =SUMIFS('QofE PF adjustments'!T:T,'QofE PF adjustments'!$E:$E,'Adjusted IS'!$E11) | JA11: =SUMIFS('QofE PF adjustments'!U:U,'QofE PF adjustments'!$E:$E,'Adjusted IS'!$E11) | JB11: =SUMIFS('QofE PF adjustments'!V:V,'QofE PF adjustments'!$E:$E,'Adjusted IS'!$E11) | JC11: =SUMIFS('QofE PF adjustments'!W:W,'QofE PF adjustments'!$E:$E,'Adjusted IS'!$E11) | JD11: =SUMIFS('QofE PF adjustments'!X:X,'QofE PF adjustments'!$E:$E,'Adjusted IS'!$E11) | JE11: =SUMIFS('QofE PF adjustments'!Y:Y,'QofE PF adjustments'!$E:$E,'Adjusted IS'!$E11) | JF11: =SUMIFS('QofE PF adjustments'!Z:Z,'QofE PF adjustments'!$E:$E,'Adjusted IS'!$E11) | JG11: =SUMIFS('QofE PF adjustments'!AA:AA,'QofE PF adjustments'!$E:$E,'Adjusted IS'!$E11) | JH11: =SUMIFS('QofE PF adjustments'!AB:AB,'QofE PF adjustments'!$E:$E,'Adjusted IS'!$E11) | JI11: =SUMIFS('QofE PF adjustments'!AC:AC,'QofE PF adjustments'!$E:$E,'Adjusted IS'!$E11) | JJ11: =SUMIFS('QofE PF adjustments'!AD:AD,'QofE PF adjustments'!$E:$E,'Adjusted IS'!$E11) | JK11: =SUMIFS('QofE PF adjustments'!AE:AE,'QofE PF adjustments'!$E:$E,'Adjusted IS'!$E11) | JL11: =SUMIFS('QofE PF adjustments'!AF:AF,'QofE PF adjustments'!$E:$E,'Adjusted IS'!$E11) | JM11: =SUMIFS('QofE PF adjustments'!AG:AG,'QofE PF adjustments'!$E:$E,'Adjusted IS'!$E11) | JN11: =SUMIFS('QofE PF adjustments'!AH:AH,'QofE PF adjustments'!$E:$E,'Adjusted IS'!$E11) | JO11: =SUMIFS('QofE PF adjustments'!AI:AI,'QofE PF adjustments'!$E:$E,'Adjusted IS'!$E11) | JP11: =SUMIFS('QofE PF adjustments'!AJ:AJ,'QofE PF adjustments'!$E:$E,'Adjusted IS'!$E11) | JQ11: =SUMIFS('QofE PF adjustments'!AK:AK,'QofE PF adjustments'!$E:$E,'Adjusted IS'!$E11) | JR11: =SUMIFS('QofE PF adjustments'!AL:AL,'QofE PF adjustments'!$E:$E,'Adjusted IS'!$E11) | JS11: =SUMIFS('QofE PF adjustments'!AM:AM,'QofE PF adjustments'!$E:$E,'Adjusted IS'!$E11) | JT11: =SUMIFS('QofE PF adjustments'!AN:AN,'QofE PF adjustments'!$E:$E,'Adjusted IS'!$E11) | JU11: =SUMIFS('QofE PF adjustments'!AO:AO,'QofE PF adjustments'!$E:$E,'Adjusted IS'!$E11) | JV11: =SUMIFS('QofE PF adjustments'!AP:AP,'QofE PF adjustments'!$E:$E,'Adjusted IS'!$E11) | JW11: =SUMIFS('QofE PF adjustments'!AQ:AQ,'QofE PF adjustments'!$E:$E,'Adjusted IS'!$E11) | JX11: =SUMIFS('QofE PF adjustments'!AR:AR,'QofE PF adjustments'!$E:$E,'Adjusted IS'!$E11) | JY11: =SUMIFS('QofE PF adjustments'!AS:AS,'QofE PF adjustments'!$E:$E,'Adjusted IS'!$E11) | JZ11: =SUMIFS('QofE PF adjustments'!AT:AT,'QofE PF adjustments'!$E:$E,'Adjusted IS'!$E11) | KA11: =SUMIFS('QofE PF adjustments'!AU:AU,'QofE PF adjustments'!$E:$E,'Adjusted IS'!$E11) | KB11: =SUM(IL11:IW11) | KC11: =SUM(IX11:JI11) | KD11: =SUM(JJ11:JU11) | KE11: =SUM(JN11:JY11) | KF11: =SUM(JP11:KA11) | KH11: =SUM(IL11,GP11) | KI11: =SUM(IM11,GQ11) | KJ11: =SUM(IN11,GR11) | KK11: =SUM(IO11,GS11) | KL11: =SUM(IP11,GT11) | KM11: =SUM(IQ11,GU11) | KN11: =SUM(IR11,GV11) | KO11: =SUM(IS11,GW11) | ... LW11: =SUM(KA11,IE11) | LX11: =SUM(KH11:KS11) | LY11: =SUM(KT11:LE11) | LZ11: =SUM(LF11:LQ11) | MA11: =SUM(LJ11:LU11) | MB11: =SUM(LL11:LW11) | MD11: =IFERROR(KH11/KH$117,0) | ME11: =IFERROR(KI11/KI$117,0) | MF11: =IFERROR(KJ11/KJ$117,0) | MG11: =IFERROR(KK11/KK$117,0) | MH11: =IFERROR(KL11/KL$117,0) | MI11: =IFERROR(KM11/KM$117,0) | MJ11: =IFERROR(KN11/KN$117,0) | MK11: =IFERROR(KO11/KO$117,0) | ... NX11: =IFERROR(MB11/MB$117,0) | NZ11: =LY11-LX11 | OA11: =LZ11-LY11 | OB11: =MA11-LZ11 | OC11: =MB11-LZ11 | OE11: Processing services revenue | OF11: Processing services revenue | OG11: Processing services revenue
C12: Merchant services debit transaction revenue | D12: 411103 | E12: =CONCATENATE(D12," - ",C12) | F12: ='Income statement'!F12 | G12: ='Income statement'!G12 | H12: ='Income statement'!H12 | I12: ='Income statement'!I12 | J12: ='Income statement'!J12 | K12: ='Income statement'!K12 | L12: ='Income statement'!L12 | M12: ='Income statement'!M12 | ... AU12: ='Income statement'!AU12 | AV12: =SUM(F12:Q12) | AW12: =SUM(R12:AC12) | AX12: =SUM(AD12:AO12) | AY12: =SUM(AH12:AS12) | AZ12: =SUM(AJ12:AU12) | BB12: =SUMIFS('QofE Def adjustments'!F:F,'QofE Def adjustments'!$E:$E,'Adjusted IS'!$E12) | BC12: =SUMIFS('QofE Def adjustments'!G:G,'QofE Def adjustments'!$E:$E,'Adjusted IS'!$E12) | BD12: =SUMIFS('QofE Def adjustments'!H:H,'QofE Def adjustments'!$E:$E,'Adjusted IS'!$E12) | BE12: =SUMIFS('QofE Def adjustments'!I:I,'QofE Def adjustments'!$E:$E,'Adjusted IS'!$E12) | BF12: =SUMIFS('QofE Def adjustments'!J:J,'QofE Def adjustments'!$E:$E,'Adjusted IS'!$E12) | BG12: =SUMIFS('QofE Def adjustments'!K:K,'QofE Def adjustments'!$E:$E,'Adjusted IS'!$E12) | BH12: =SUMIFS('QofE Def adjustments'!L:L,'QofE Def adjustments'!$E:$E,'Adjusted IS'!$E12) | BI12: =SUMIFS('QofE Def adjustments'!M:M,'QofE Def adjustments'!$E:$E,'Adjusted IS'!$E12) | BJ12: =SUMIFS('QofE Def adjustments'!N:N,'QofE Def adjustments'!$E:$E,'Adjusted IS'!$E12) | BK12: =SUMIFS('QofE Def adjustments'!O:O,'QofE Def adjustments'!$E:$E,'Adjusted IS'!$E12) | BL12: =SUMIFS('QofE Def adjustments'!P:P,'QofE Def adjustments'!$E:$E,'Adjusted IS'!$E12) | BM12: =SUMIFS('QofE Def adjustments'!Q:Q,'QofE Def adjustments'!$E:$E,'Adjusted IS'!$E12) | BN12: =SUMIFS('QofE Def adjustments'!R:R,'QofE Def adjustments'!$E:$E,'Adjusted IS'!$E12) | BO12: =SUMIFS('QofE Def adjustments'!S:S,'QofE Def adjustments'!$E:$E,'Adjusted IS'!$E12) | BP12: =SUMIFS('QofE Def adjustments'!T:T,'QofE Def adjustments'!$E:$E,'Adjusted IS'!$E12) | BQ12: =SUMIFS('QofE Def adjustments'!U:U,'QofE Def adjustments'!$E:$E,'Adjusted IS'!$E12) | BR12: =SUMIFS('QofE Def adjustments'!V:V,'QofE Def adjustments'!$E:$E,'Adjusted IS'!$E12) | BS12: =SUMIFS('QofE Def adjustments'!W:W,'QofE Def adjustments'!$E:$E,'Adjusted IS'!$E12) | BT12: =SUMIFS('QofE Def adjustments'!X:X,'QofE Def adjustments'!$E:$E,'Adjusted IS'!$E12) | BU12: =SUMIFS('QofE Def adjustments'!Y:Y,'QofE Def adjustments'!$E:$E,'Adjusted IS'!$E12) | BV12: =SUMIFS('QofE Def adjustments'!Z:Z,'QofE Def adjustments'!$E:$E,'Adjusted IS'!$E12) | BW12: =SUMIFS('QofE Def adjustments'!AA:AA,'QofE Def adjustments'!$E:$E,'Adjusted IS'!$E12) | BX12: =SUMIFS('QofE Def adjustments'!AB:AB,'QofE Def adjustments'!$E:$E,'Adjusted IS'!$E12) | BY12: =SUMIFS('QofE Def adjustments'!AC:AC,'QofE Def adjustments'!$E:$E,'Adjusted IS'!$E12) | BZ12: =SUMIFS('QofE Def adjustments'!AD:AD,'QofE Def adjustments'!$E:$E,'Adjusted IS'!$E12) | CA12: =SUMIFS('QofE Def adjustments'!AE:AE,'QofE Def adjustments'!$E:$E,'Adjusted IS'!$E12) | CB12: =SUMIFS('QofE Def adjustments'!AF:AF,'QofE Def adjustments'!$E:$E,'Adjusted IS'!$E12) | CC12: =SUMIFS('QofE Def adjustments'!AG:AG,'QofE Def adjustments'!$E:$E,'Adjusted IS'!$E12) | CD12: =SUMIFS('QofE Def adjustments'!AH:AH,'QofE Def adjustments'!$E:$E,'Adjusted IS'!$E12) | CE12: =SUMIFS('QofE Def adjustments'!AI:AI,'QofE Def adjustments'!$E:$E,'Adjusted IS'!$E12) | CF12: =SUMIFS('QofE Def adjustments'!AJ:AJ,'QofE Def adjustments'!$E:$E,'Adjusted IS'!$E12) | CG12: =SUMIFS('QofE Def adjustments'!AK:AK,'QofE Def adjustments'!$E:$E,'Adjusted IS'!$E12) | CH12: =SUMIFS('QofE Def adjustments'!AL:AL,'QofE Def adjustments'!$E:$E,'Adjusted IS'!$E12) | CI12: =SUMIFS('QofE Def adjustments'!AM:AM,'QofE Def adjustments'!$E:$E,'Adjusted IS'!$E12) | CJ12: =SUMIFS('QofE Def adjustments'!AN:AN,'QofE Def adjustments'!$E:$E,'Adjusted IS'!$E12) | CK12: =SUMIFS('QofE Def adjustments'!AO:AO,'QofE Def adjustments'!$E:$E,'Adjusted IS'!$E12) | CL12: =SUMIFS('QofE Def adjustments'!AP:AP,'QofE Def adjustments'!$E:$E,'Adjusted IS'!$E12) | CM12: =SUMIFS('QofE Def adjustments'!AQ:AQ,'QofE Def adjustments'!$E:$E,'Adjusted IS'!$E12) | CN12: =SUMIFS('QofE Def adjustments'!AR:AR,'QofE Def adjustments'!$E:$E,'Adjusted IS'!$E12) | CO12: =SUMIFS('QofE Def adjustments'!AS:AS,'QofE Def adjustments'!$E:$E,'Adjusted IS'!$E12) | CP12: =SUMIFS('QofE Def adjustments'!AT:AT,'QofE Def adjustments'!$E:$E,'Adjusted IS'!$E12) | CQ12: =SUMIFS('QofE Def adjustments'!AU:AU,'QofE Def adjustments'!$E:$E,'Adjusted IS'!$E12) | CR12: =SUM(BB12:BM12) | CS12: =SUM(BN12:BY12) | CT12: =SUM(BZ12:CK12) | CU12: =SUM(CD12:CO12) | CV12: =SUM(CF12:CQ12) | CX12: =SUM(BB12,F12) | CY12: =SUM(BC12,G12) | CZ12: =SUM(BD12,H12) | DA12: =SUM(BE12,I12) | DB12: =SUM(BF12,J12) | DC12: =SUM(BG12,K12) | DD12: =SUM(BH12,L12) | DE12: =SUM(BI12,M12) | ... EM12: =SUM(CQ12,AU12) | EN12: =SUM(CX12:DI12) | EO12: =SUM(DJ12:DU12) | EP12: =SUM(DV12:EG12) | EQ12: =SUM(DZ12:EK12) | ER12: =SUM(EB12:EM12) | ET12: =SUMIFS('QofE DD adjustments'!F:F,'QofE DD adjustments'!$E:$E,'Adjusted IS'!$E12) | EU12: =SUMIFS('QofE DD adjustments'!G:G,'QofE DD adjustments'!$E:$E,'Adjusted IS'!$E12) | EV12: =SUMIFS('QofE DD adjustments'!H:H,'QofE DD adjustments'!$E:$E,'Adjusted IS'!$E12) | EW12: =SUMIFS('QofE DD adjustments'!I:I,'QofE DD adjustments'!$E:$E,'Adjusted IS'!$E12) | EX12: =SUMIFS('QofE DD adjustments'!J:J,'QofE DD adjustments'!$E:$E,'Adjusted IS'!$E12) | EY12: =SUMIFS('QofE DD adjustments'!K:K,'QofE DD adjustments'!$E:$E,'Adjusted IS'!$E12) | EZ12: =SUMIFS('QofE DD adjustments'!L:L,'QofE DD adjustments'!$E:$E,'Adjusted IS'!$E12) | FA12: =SUMIFS('QofE DD adjustments'!M:M,'QofE DD adjustments'!$E:$E,'Adjusted IS'!$E12) | FB12: =SUMIFS('QofE DD adjustments'!N:N,'QofE DD adjustments'!$E:$E,'Adjusted IS'!$E12) | FC12: =SUMIFS('QofE DD adjustments'!O:O,'QofE DD adjustments'!$E:$E,'Adjusted IS'!$E12) | FD12: =SUMIFS('QofE DD adjustments'!P:P,'QofE DD adjustments'!$E:$E,'Adjusted IS'!$E12) | FE12: =SUMIFS('QofE DD adjustments'!Q:Q,'QofE DD adjustments'!$E:$E,'Adjusted IS'!$E12) | FF12: =SUMIFS('QofE DD adjustments'!R:R,'QofE DD adjustments'!$E:$E,'Adjusted IS'!$E12) | FG12: =SUMIFS('QofE DD adjustments'!S:S,'QofE DD adjustments'!$E:$E,'Adjusted IS'!$E12) | FH12: =SUMIFS('QofE DD adjustments'!T:T,'QofE DD adjustments'!$E:$E,'Adjusted IS'!$E12) | FI12: =SUMIFS('QofE DD adjustments'!U:U,'QofE DD adjustments'!$E:$E,'Adjusted IS'!$E12) | FJ12: =SUMIFS('QofE DD adjustments'!V:V,'QofE DD adjustments'!$E:$E,'Adjusted IS'!$E12) | FK12: =SUMIFS('QofE DD adjustments'!W:W,'QofE DD adjustments'!$E:$E,'Adjusted IS'!$E12) | FL12: =SUMIFS('QofE DD adjustments'!X:X,'QofE DD adjustments'!$E:$E,'Adjusted IS'!$E12) | FM12: =SUMIFS('QofE DD adjustments'!Y:Y,'QofE DD adjustments'!$E:$E,'Adjusted IS'!$E12) | FN12: =SUMIFS('QofE DD adjustments'!Z:Z,'QofE DD adjustments'!$E:$E,'Adjusted IS'!$E12) | FO12: =SUMIFS('QofE DD adjustments'!AA:AA,'QofE DD adjustments'!$E:$E,'Adjusted IS'!$E12) | FP12: =SUMIFS('QofE DD adjustments'!AB:AB,'QofE DD adjustments'!$E:$E,'Adjusted IS'!$E12) | FQ12: =SUMIFS('QofE DD adjustments'!AC:AC,'QofE DD adjustments'!$E:$E,'Adjusted IS'!$E12) | FR12: =SUMIFS('QofE DD adjustments'!AD:AD,'QofE DD adjustments'!$E:$E,'Adjusted IS'!$E12) | FS12: =SUMIFS('QofE DD adjustments'!AE:AE,'QofE DD adjustments'!$E:$E,'Adjusted IS'!$E12) | FT12: =SUMIFS('QofE DD adjustments'!AF:AF,'QofE DD adjustments'!$E:$E,'Adjusted IS'!$E12) | FU12: =SUMIFS('QofE DD adjustments'!AG:AG,'QofE DD adjustments'!$E:$E,'Adjusted IS'!$E12) | FV12: =SUMIFS('QofE DD adjustments'!AH:AH,'QofE DD adjustments'!$E:$E,'Adjusted IS'!$E12) | FW12: =SUMIFS('QofE DD adjustments'!AI:AI,'QofE DD adjustments'!$E:$E,'Adjusted IS'!$E12) | FX12: =SUMIFS('QofE DD adjustments'!AJ:AJ,'QofE DD adjustments'!$E:$E,'Adjusted IS'!$E12) | FY12: =SUMIFS('QofE DD adjustments'!AK:AK,'QofE DD adjustments'!$E:$E,'Adjusted IS'!$E12) | FZ12: =SUMIFS('QofE DD adjustments'!AL:AL,'QofE DD adjustments'!$E:$E,'Adjusted IS'!$E12) | GA12: =SUMIFS('QofE DD adjustments'!AM:AM,'QofE DD adjustments'!$E:$E,'Adjusted IS'!$E12) | GB12: =SUMIFS('QofE DD adjustments'!AN:AN,'QofE DD adjustments'!$E:$E,'Adjusted IS'!$E12) | GC12: =SUMIFS('QofE DD adjustments'!AO:AO,'QofE DD adjustments'!$E:$E,'Adjusted IS'!$E12) | GD12: =SUMIFS('QofE DD adjustments'!AP:AP,'QofE DD adjustments'!$E:$E,'Adjusted IS'!$E12) | GE12: =SUMIFS('QofE DD adjustments'!AQ:AQ,'QofE DD adjustments'!$E:$E,'Adjusted IS'!$E12) | GF12: =SUMIFS('QofE DD adjustments'!AR:AR,'QofE DD adjustments'!$E:$E,'Adjusted IS'!$E12) | GG12: =SUMIFS('QofE DD adjustments'!AS:AS,'QofE DD adjustments'!$E:$E,'Adjusted IS'!$E12) | GH12: =SUMIFS('QofE DD adjustments'!AT:AT,'QofE DD adjustments'!$E:$E,'Adjusted IS'!$E12) | GI12: =SUMIFS('QofE DD adjustments'!AU:AU,'QofE DD adjustments'!$E:$E,'Adjusted IS'!$E12) | GJ12: =SUM(ET12:FE12) | GK12: =SUM(FF12:FQ12) | GL12: =SUM(FR12:GC12) | GM12: =SUM(FV12:GG12) | GN12: =SUM(FX12:GI12) | GP12: =SUM(ET12,CX12) | GQ12: =SUM(EU12,CY12) | GR12: =SUM(EV12,CZ12) | GS12: =SUM(EW12,DA12) | GT12: =SUM(EX12,DB12) | GU12: =SUM(EY12,DC12) | GV12: =SUM(EZ12,DD12) | GW12: =SUM(FA12,DE12) | ... IE12: =SUM(GI12,EM12) | IF12: =SUM(GP12:HA12) | IG12: =SUM(HB12:HM12) | IH12: =SUM(HN12:HY12) | II12: =SUM(HR12:IC12) | IJ12: =SUM(HT12:IE12) | IL12: =SUMIFS('QofE PF adjustments'!F:F,'QofE PF adjustments'!$E:$E,'Adjusted IS'!$E12) | IM12: =SUMIFS('QofE PF adjustments'!G:G,'QofE PF adjustments'!$E:$E,'Adjusted IS'!$E12) | IN12: =SUMIFS('QofE PF adjustments'!H:H,'QofE PF adjustments'!$E:$E,'Adjusted IS'!$E12) | IO12: =SUMIFS('QofE PF adjustments'!I:I,'QofE PF adjustments'!$E:$E,'Adjusted IS'!$E12) | IP12: =SUMIFS('QofE PF adjustments'!J:J,'QofE PF adjustments'!$E:$E,'Adjusted IS'!$E12) | IQ12: =SUMIFS('QofE PF adjustments'!K:K,'QofE PF adjustments'!$E:$E,'Adjusted IS'!$E12) | IR12: =SUMIFS('QofE PF adjustments'!L:L,'QofE PF adjustments'!$E:$E,'Adjusted IS'!$E12) | IS12: =SUMIFS('QofE PF adjustments'!M:M,'QofE PF adjustments'!$E:$E,'Adjusted IS'!$E12) | IT12: =SUMIFS('QofE PF adjustments'!N:N,'QofE PF adjustments'!$E:$E,'Adjusted IS'!$E12) | IU12: =SUMIFS('QofE PF adjustments'!O:O,'QofE PF adjustments'!$E:$E,'Adjusted IS'!$E12) | IV12: =SUMIFS('QofE PF adjustments'!P:P,'QofE PF adjustments'!$E:$E,'Adjusted IS'!$E12) | IW12: =SUMIFS('QofE PF adjustments'!Q:Q,'QofE PF adjustments'!$E:$E,'Adjusted IS'!$E12) | IX12: =SUMIFS('QofE PF adjustments'!R:R,'QofE PF adjustments'!$E:$E,'Adjusted IS'!$E12) | IY12: =SUMIFS('QofE PF adjustments'!S:S,'QofE PF adjustments'!$E:$E,'Adjusted IS'!$E12) | IZ12: =SUMIFS('QofE PF adjustments'!T:T,'QofE PF adjustments'!$E:$E,'Adjusted IS'!$E12) | JA12: =SUMIFS('QofE PF adjustments'!U:U,'QofE PF adjustments'!$E:$E,'Adjusted IS'!$E12) | JB12: =SUMIFS('QofE PF adjustments'!V:V,'QofE PF adjustments'!$E:$E,'Adjusted IS'!$E12) | JC12: =SUMIFS('QofE PF adjustments'!W:W,'QofE PF adjustments'!$E:$E,'Adjusted IS'!$E12) | JD12: =SUMIFS('QofE PF adjustments'!X:X,'QofE PF adjustments'!$E:$E,'Adjusted IS'!$E12) | JE12: =SUMIFS('QofE PF adjustments'!Y:Y,'QofE PF adjustments'!$E:$E,'Adjusted IS'!$E12) | JF12: =SUMIFS('QofE PF adjustments'!Z:Z,'QofE PF adjustments'!$E:$E,'Adjusted IS'!$E12) | JG12: =SUMIFS('QofE PF adjustments'!AA:AA,'QofE PF adjustments'!$E:$E,'Adjusted IS'!$E12) | JH12: =SUMIFS('QofE PF adjustments'!AB:AB,'QofE PF adjustments'!$E:$E,'Adjusted IS'!$E12) | JI12: =SUMIFS('QofE PF adjustments'!AC:AC,'QofE PF adjustments'!$E:$E,'Adjusted IS'!$E12) | JJ12: =SUMIFS('QofE PF adjustments'!AD:AD,'QofE PF adjustments'!$E:$E,'Adjusted IS'!$E12) | JK12: =SUMIFS('QofE PF adjustments'!AE:AE,'QofE PF adjustments'!$E:$E,'Adjusted IS'!$E12) | JL12: =SUMIFS('QofE PF adjustments'!AF:AF,'QofE PF adjustments'!$E:$E,'Adjusted IS'!$E12) | JM12: =SUMIFS('QofE PF adjustments'!AG:AG,'QofE PF adjustments'!$E:$E,'Adjusted IS'!$E12) | JN12: =SUMIFS('QofE PF adjustments'!AH:AH,'QofE PF adjustments'!$E:$E,'Adjusted IS'!$E12) | JO12: =SUMIFS('QofE PF adjustments'!AI:AI,'QofE PF adjustments'!$E:$E,'Adjusted IS'!$E12) | JP12: =SUMIFS('QofE PF adjustments'!AJ:AJ,'QofE PF adjustments'!$E:$E,'Adjusted IS'!$E12) | JQ12: =SUMIFS('QofE PF adjustments'!AK:AK,'QofE PF adjustments'!$E:$E,'Adjusted IS'!$E12) | JR12: =SUMIFS('QofE PF adjustments'!AL:AL,'QofE PF adjustments'!$E:$E,'Adjusted IS'!$E12) | JS12: =SUMIFS('QofE PF adjustments'!AM:AM,'QofE PF adjustments'!$E:$E,'Adjusted IS'!$E12) | JT12: =SUMIFS('QofE PF adjustments'!AN:AN,'QofE PF adjustments'!$E:$E,'Adjusted IS'!$E12) | JU12: =SUMIFS('QofE PF adjustments'!AO:AO,'QofE PF adjustments'!$E:$E,'Adjusted IS'!$E12) | JV12: =SUMIFS('QofE PF adjustments'!AP:AP,'QofE PF adjustments'!$E:$E,'Adjusted IS'!$E12) | JW12: =SUMIFS('QofE PF adjustments'!AQ:AQ,'QofE PF adjustments'!$E:$E,'Adjusted IS'!$E12) | JX12: =SUMIFS('QofE PF adjustments'!AR:AR,'QofE PF adjustments'!$E:$E,'Adjusted IS'!$E12) | JY12: =SUMIFS('QofE PF adjustments'!AS:AS,'QofE PF adjustments'!$E:$E,'Adjusted IS'!$E12) | JZ12: =SUMIFS('QofE PF adjustments'!AT:AT,'QofE PF adjustments'!$E:$E,'Adjusted IS'!$E12) | KA12: =SUMIFS('QofE PF adjustments'!AU:AU,'QofE PF adjustments'!$E:$E,'Adjusted IS'!$E12) | KB12: =SUM(IL12:IW12) | KC12: =SUM(IX12:JI12) | KD12: =SUM(JJ12:JU12) | KE12: =SUM(JN12:JY12) | KF12: =SUM(JP12:KA12) | KH12: =SUM(IL12,GP12) | KI12: =SUM(IM12,GQ12) | KJ12: =SUM(IN12,GR12) | KK12: =SUM(IO12,GS12) | KL12: =SUM(IP12,GT12) | KM12: =SUM(IQ12,GU12) | KN12: =SUM(IR12,GV12) | KO12: =SUM(IS12,GW12) | ... LW12: =SUM(KA12,IE12) | LX12: =SUM(KH12:KS12) | LY12: =SUM(KT12:LE12) | LZ12: =SUM(LF12:LQ12) | MA12: =SUM(LJ12:LU12) | MB12: =SUM(LL12:LW12) | MD12: =IFERROR(KH12/KH$117,0) | ME12: =IFERROR(KI12/KI$117,0) | MF12: =IFERROR(KJ12/KJ$117,0) | MG12: =IFERROR(KK12/KK$117,0) | MH12: =IFERROR(KL12/KL$117,0) | MI12: =IFERROR(KM12/KM$117,0) | MJ12: =IFERROR(KN12/KN$117,0) | MK12: =IFERROR(KO12/KO$117,0) | ... NX12: =IFERROR(MB12/MB$117,0) | NZ12: =LY12-LX12 | OA12: =LZ12-LY12 | OB12: =MA12-LZ12 | OC12: =MB12-LZ12 | OE12: Processing services revenue | OF12: Processing services revenue | OG12: Processing services revenue
C13: Ifrs 15 adj to processing | D13: 411119 | E13: =CONCATENATE(D13," - ",C13) | F13: ='Income statement'!F13 | G13: ='Income statement'!G13 | H13: ='Income statement'!H13 | I13: ='Income statement'!I13 | J13: ='Income statement'!J13 | K13: ='Income statement'!K13 | L13: ='Income statement'!L13 | M13: ='Income statement'!M13 | ... AU13: ='Income statement'!AU13 | AV13: =SUM(F13:Q13) | AW13: =SUM(R13:AC13) | AX13: =SUM(AD13:AO13) | AY13: =SUM(AH13:AS13) | AZ13: =SUM(AJ13:AU13) | BB13: =SUMIFS('QofE Def adjustments'!F:F,'QofE Def adjustments'!$E:$E,'Adjusted IS'!$E13) | BC13: =SUMIFS('QofE Def adjustments'!G:G,'QofE Def adjustments'!$E:$E,'Adjusted IS'!$E13) | BD13: =SUMIFS('QofE Def adjustments'!H:H,'QofE Def adjustments'!$E:$E,'Adjusted IS'!$E13) | BE13: =SUMIFS('QofE Def adjustments'!I:I,'QofE Def adjustments'!$E:$E,'Adjusted IS'!$E13) | BF13: =SUMIFS('QofE Def adjustments'!J:J,'QofE Def adjustments'!$E:$E,'Adjusted IS'!$E13) | BG13: =SUMIFS('QofE Def adjustments'!K:K,'QofE Def adjustments'!$E:$E,'Adjusted IS'!$E13) | BH13: =SUMIFS('QofE Def adjustments'!L:L,'QofE Def adjustments'!$E:$E,'Adjusted IS'!$E13) | BI13: =SUMIFS('QofE Def adjustments'!M:M,'QofE Def adjustments'!$E:$E,'Adjusted IS'!$E13) | BJ13: =SUMIFS('QofE Def adjustments'!N:N,'QofE Def adjustments'!$E:$E,'Adjusted IS'!$E13) | BK13: =SUMIFS('QofE Def adjustments'!O:O,'QofE Def adjustments'!$E:$E,'Adjusted IS'!$E13) | BL13: =SUMIFS('QofE Def adjustments'!P:P,'QofE Def adjustments'!$E:$E,'Adjusted IS'!$E13) | BM13: =SUMIFS('QofE Def adjustments'!Q:Q,'QofE Def adjustments'!$E:$E,'Adjusted IS'!$E13) | BN13: =SUMIFS('QofE Def adjustments'!R:R,'QofE Def adjustments'!$E:$E,'Adjusted IS'!$E13) | BO13: =SUMIFS('QofE Def adjustments'!S:S,'QofE Def adjustments'!$E:$E,'Adjusted IS'!$E13) | BP13: =SUMIFS('QofE Def adjustments'!T:T,'QofE Def adjustments'!$E:$E,'Adjusted IS'!$E13) | BQ13: =SUMIFS('QofE Def adjustments'!U:U,'QofE Def adjustments'!$E:$E,'Adjusted IS'!$E13) | BR13: =SUMIFS('QofE Def adjustments'!V:V,'QofE Def adjustments'!$E:$E,'Adjusted IS'!$E13) | BS13: =SUMIFS('QofE Def adjustments'!W:W,'QofE Def adjustments'!$E:$E,'Adjusted IS'!$E13) | BT13: =SUMIFS('QofE Def adjustments'!X:X,'QofE Def adjustments'!$E:$E,'Adjusted IS'!$E13) | BU13: =SUMIFS('QofE Def adjustments'!Y:Y,'QofE Def adjustments'!$E:$E,'Adjusted IS'!$E13) | BV13: =SUMIFS('QofE Def adjustments'!Z:Z,'QofE Def adjustments'!$E:$E,'Adjusted IS'!$E13) | BW13: =SUMIFS('QofE Def adjustments'!AA:AA,'QofE Def adjustments'!$E:$E,'Adjusted IS'!$E13) | BX13: =SUMIFS('QofE Def adjustments'!AB:AB,'QofE Def adjustments'!$E:$E,'Adjusted IS'!$E13) | BY13: =SUMIFS('QofE Def adjustments'!AC:AC,'QofE Def adjustments'!$E:$E,'Adjusted IS'!$E13) | BZ13: =SUMIFS('QofE Def adjustments'!AD:AD,'QofE Def adjustments'!$E:$E,'Adjusted IS'!$E13) | CA13: =SUMIFS('QofE Def adjustments'!AE:AE,'QofE Def adjustments'!$E:$E,'Adjusted IS'!$E13) | CB13: =SUMIFS('QofE Def adjustments'!AF:AF,'QofE Def adjustments'!$E:$E,'Adjusted IS'!$E13) | CC13: =SUMIFS('QofE Def adjustments'!AG:AG,'QofE Def adjustments'!$E:$E,'Adjusted IS'!$E13) | CD13: =SUMIFS('QofE Def adjustments'!AH:AH,'QofE Def adjustments'!$E:$E,'Adjusted IS'!$E13) | CE13: =SUMIFS('QofE Def adjustments'!AI:AI,'QofE Def adjustments'!$E:$E,'Adjusted IS'!$E13) | CF13: =SUMIFS('QofE Def adjustments'!AJ:AJ,'QofE Def adjustments'!$E:$E,'Adjusted IS'!$E13) | CG13: =SUMIFS('QofE Def adjustments'!AK:AK,'QofE Def adjustments'!$E:$E,'Adjusted IS'!$E13) | CH13: =SUMIFS('QofE Def adjustments'!AL:AL,'QofE Def adjustments'!$E:$E,'Adjusted IS'!$E13) | CI13: =SUMIFS('QofE Def adjustments'!AM:AM,'QofE Def adjustments'!$E:$E,'Adjusted IS'!$E13) | CJ13: =SUMIFS('QofE Def adjustments'!AN:AN,'QofE Def adjustments'!$E:$E,'Adjusted IS'!$E13) | CK13: =SUMIFS('QofE Def adjustments'!AO:AO,'QofE Def adjustments'!$E:$E,'Adjusted IS'!$E13) | CL13: =SUMIFS('QofE Def adjustments'!AP:AP,'QofE Def adjustments'!$E:$E,'Adjusted IS'!$E13) | CM13: =SUMIFS('QofE Def adjustments'!AQ:AQ,'QofE Def adjustments'!$E:$E,'Adjusted IS'!$E13) | CN13: =SUMIFS('QofE Def adjustments'!AR:AR,'QofE Def adjustments'!$E:$E,'Adjusted IS'!$E13) | CO13: =SUMIFS('QofE Def adjustments'!AS:AS,'QofE Def adjustments'!$E:$E,'Adjusted IS'!$E13) | CP13: =SUMIFS('QofE Def adjustments'!AT:AT,'QofE Def adjustments'!$E:$E,'Adjusted IS'!$E13) | CQ13: =SUMIFS('QofE Def adjustments'!AU:AU,'QofE Def adjustments'!$E:$E,'Adjusted IS'!$E13) | CR13: =SUM(BB13:BM13) | CS13: =SUM(BN13:BY13) | CT13: =SUM(BZ13:CK13) | CU13: =SUM(CD13:CO13) | CV13: =SUM(CF13:CQ13) | CX13: =SUM(BB13,F13) | CY13: =SUM(BC13,G13) | CZ13: =SUM(BD13,H13) | DA13: =SUM(BE13,I13) | DB13: =SUM(BF13,J13) | DC13: =SUM(BG13,K13) | DD13: =SUM(BH13,L13) | DE13: =SUM(BI13,M13) | ... EM13: =SUM(CQ13,AU13) | EN13: =SUM(CX13:DI13) | EO13: =SUM(DJ13:DU13) | EP13: =SUM(DV13:EG13) | EQ13: =SUM(DZ13:EK13) | ER13: =SUM(EB13:EM13) | ET13: =SUMIFS('QofE DD adjustments'!F:F,'QofE DD adjustments'!$E:$E,'Adjusted IS'!$E13) | EU13: =SUMIFS('QofE DD adjustments'!G:G,'QofE DD adjustments'!$E:$E,'Adjusted IS'!$E13) | EV13: =SUMIFS('QofE DD adjustments'!H:H,'QofE DD adjustments'!$E:$E,'Adjusted IS'!$E13) | EW13: =SUMIFS('QofE DD adjustments'!I:I,'QofE DD adjustments'!$E:$E,'Adjusted IS'!$E13) | EX13: =SUMIFS('QofE DD adjustments'!J:J,'QofE DD adjustments'!$E:$E,'Adjusted IS'!$E13) | EY13: =SUMIFS('QofE DD adjustments'!K:K,'QofE DD adjustments'!$E:$E,'Adjusted IS'!$E13) | EZ13: =SUMIFS('QofE DD adjustments'!L:L,'QofE DD adjustments'!$E:$E,'Adjusted IS'!$E13) | FA13: =SUMIFS('QofE DD adjustments'!M:M,'QofE DD adjustments'!$E:$E,'Adjusted IS'!$E13) | FB13: =SUMIFS('QofE DD adjustments'!N:N,'QofE DD adjustments'!$E:$E,'Adjusted IS'!$E13) | FC13: =SUMIFS('QofE DD adjustments'!O:O,'QofE DD adjustments'!$E:$E,'Adjusted IS'!$E13) | FD13: =SUMIFS('QofE DD adjustments'!P:P,'QofE DD adjustments'!$E:$E,'Adjusted IS'!$E13) | FE13: =SUMIFS('QofE DD adjustments'!Q:Q,'QofE DD adjustments'!$E:$E,'Adjusted IS'!$E13) | FF13: =SUMIFS('QofE DD adjustments'!R:R,'QofE DD adjustments'!$E:$E,'Adjusted IS'!$E13) | FG13: =SUMIFS('QofE DD adjustments'!S:S,'QofE DD adjustments'!$E:$E,'Adjusted IS'!$E13) | FH13: =SUMIFS('QofE DD adjustments'!T:T,'QofE DD adjustments'!$E:$E,'Adjusted IS'!$E13) | FI13: =SUMIFS('QofE DD adjustments'!U:U,'QofE DD adjustments'!$E:$E,'Adjusted IS'!$E13) | FJ13: =SUMIFS('QofE DD adjustments'!V:V,'QofE DD adjustments'!$E:$E,'Adjusted IS'!$E13) | FK13: =SUMIFS('QofE DD adjustments'!W:W,'QofE DD adjustments'!$E:$E,'Adjusted IS'!$E13) | FL13: =SUMIFS('QofE DD adjustments'!X:X,'QofE DD adjustments'!$E:$E,'Adjusted IS'!$E13) | FM13: =SUMIFS('QofE DD adjustments'!Y:Y,'QofE DD adjustments'!$E:$E,'Adjusted IS'!$E13) | FN13: =SUMIFS('QofE DD adjustments'!Z:Z,'QofE DD adjustments'!$E:$E,'Adjusted IS'!$E13) | FO13: =SUMIFS('QofE DD adjustments'!AA:AA,'QofE DD adjustments'!$E:$E,'Adjusted IS'!$E13) | FP13: =SUMIFS('QofE DD adjustments'!AB:AB,'QofE DD adjustments'!$E:$E,'Adjusted IS'!$E13) | FQ13: =SUMIFS('QofE DD adjustments'!AC:AC,'QofE DD adjustments'!$E:$E,'Adjusted IS'!$E13) | FR13: =SUMIFS('QofE DD adjustments'!AD:AD,'QofE DD adjustments'!$E:$E,'Adjusted IS'!$E13) | FS13: =SUMIFS('QofE DD adjustments'!AE:AE,'QofE DD adjustments'!$E:$E,'Adjusted IS'!$E13) | FT13: =SUMIFS('QofE DD adjustments'!AF:AF,'QofE DD adjustments'!$E:$E,'Adjusted IS'!$E13) | FU13: =SUMIFS('QofE DD adjustments'!AG:AG,'QofE DD adjustments'!$E:$E,'Adjusted IS'!$E13) | FV13: =SUMIFS('QofE DD adjustments'!AH:AH,'QofE DD adjustments'!$E:$E,'Adjusted IS'!$E13) | FW13: =SUMIFS('QofE DD adjustments'!AI:AI,'QofE DD adjustments'!$E:$E,'Adjusted IS'!$E13) | FX13: =SUMIFS('QofE DD adjustments'!AJ:AJ,'QofE DD adjustments'!$E:$E,'Adjusted IS'!$E13) | FY13: =SUMIFS('QofE DD adjustments'!AK:AK,'QofE DD adjustments'!$E:$E,'Adjusted IS'!$E13) | FZ13: =SUMIFS('QofE DD adjustments'!AL:AL,'QofE DD adjustments'!$E:$E,'Adjusted IS'!$E13) | GA13: =SUMIFS('QofE DD adjustments'!AM:AM,'QofE DD adjustments'!$E:$E,'Adjusted IS'!$E13) | GB13: =SUMIFS('QofE DD adjustments'!AN:AN,'QofE DD adjustments'!$E:$E,'Adjusted IS'!$E13) | GC13: =SUMIFS('QofE DD adjustments'!AO:AO,'QofE DD adjustments'!$E:$E,'Adjusted IS'!$E13) | GD13: =SUMIFS('QofE DD adjustments'!AP:AP,'QofE DD adjustments'!$E:$E,'Adjusted IS'!$E13) | GE13: =SUMIFS('QofE DD adjustments'!AQ:AQ,'QofE DD adjustments'!$E:$E,'Adjusted IS'!$E13) | GF13: =SUMIFS('QofE DD adjustments'!AR:AR,'QofE DD adjustments'!$E:$E,'Adjusted IS'!$E13) | GG13: =SUMIFS('QofE DD adjustments'!AS:AS,'QofE DD adjustments'!$E:$E,'Adjusted IS'!$E13) | GH13: =SUMIFS('QofE DD adjustments'!AT:AT,'QofE DD adjustments'!$E:$E,'Adjusted IS'!$E13) | GI13: =SUMIFS('QofE DD adjustments'!AU:AU,'QofE DD adjustments'!$E:$E,'Adjusted IS'!$E13) | GJ13: =SUM(ET13:FE13) | GK13: =SUM(FF13:FQ13) | GL13: =SUM(FR13:GC13) | GM13: =SUM(FV13:GG13) | GN13: =SUM(FX13:GI13) | GP13: =SUM(ET13,CX13) | GQ13: =SUM(EU13,CY13) | GR13: =SUM(EV13,CZ13) | GS13: =SUM(EW13,DA13) | GT13: =SUM(EX13,DB13) | GU13: =SUM(EY13,DC13) | GV13: =SUM(EZ13,DD13) | GW13: =SUM(FA13,DE13) | ... IE13: =SUM(GI13,EM13) | IF13: =SUM(GP13:HA13) | IG13: =SUM(HB13:HM13) | IH13: =SUM(HN13:HY13) | II13: =SUM(HR13:IC13) | IJ13: =SUM(HT13:IE13) | IL13: =SUMIFS('QofE PF adjustments'!F:F,'QofE PF adjustments'!$E:$E,'Adjusted IS'!$E13) | IM13: =SUMIFS('QofE PF adjustments'!G:G,'QofE PF adjustments'!$E:$E,'Adjusted IS'!$E13) | IN13: =SUMIFS('QofE PF adjustments'!H:H,'QofE PF adjustments'!$E:$E,'Adjusted IS'!$E13) | IO13: =SUMIFS('QofE PF adjustments'!I:I,'QofE PF adjustments'!$E:$E,'Adjusted IS'!$E13) | IP13: =SUMIFS('QofE PF adjustments'!J:J,'QofE PF adjustments'!$E:$E,'Adjusted IS'!$E13) | IQ13: =SUMIFS('QofE PF adjustments'!K:K,'QofE PF adjustments'!$E:$E,'Adjusted IS'!$E13) | IR13: =SUMIFS('QofE PF adjustments'!L:L,'QofE PF adjustments'!$E:$E,'Adjusted IS'!$E13) | IS13: =SUMIFS('QofE PF adjustments'!M:M,'QofE PF adjustments'!$E:$E,'Adjusted IS'!$E13) | IT13: =SUMIFS('QofE PF adjustments'!N:N,'QofE PF adjustments'!$E:$E,'Adjusted IS'!$E13) | IU13: =SUMIFS('QofE PF adjustments'!O:O,'QofE PF adjustments'!$E:$E,'Adjusted IS'!$E13) | IV13: =SUMIFS('QofE PF adjustments'!P:P,'QofE PF adjustments'!$E:$E,'Adjusted IS'!$E13) | IW13: =SUMIFS('QofE PF adjustments'!Q:Q,'QofE PF adjustments'!$E:$E,'Adjusted IS'!$E13) | IX13: =SUMIFS('QofE PF adjustments'!R:R,'QofE PF adjustments'!$E:$E,'Adjusted IS'!$E13) | IY13: =SUMIFS('QofE PF adjustments'!S:S,'QofE PF adjustments'!$E:$E,'Adjusted IS'!$E13) | IZ13: =SUMIFS('QofE PF adjustments'!T:T,'QofE PF adjustments'!$E:$E,'Adjusted IS'!$E13) | JA13: =SUMIFS('QofE PF adjustments'!U:U,'QofE PF adjustments'!$E:$E,'Adjusted IS'!$E13) | JB13: =SUMIFS('QofE PF adjustments'!V:V,'QofE PF adjustments'!$E:$E,'Adjusted IS'!$E13) | JC13: =SUMIFS('QofE PF adjustments'!W:W,'QofE PF adjustments'!$E:$E,'Adjusted IS'!$E13) | JD13: =SUMIFS('QofE PF adjustments'!X:X,'QofE PF adjustments'!$E:$E,'Adjusted IS'!$E13) | JE13: =SUMIFS('QofE PF adjustments'!Y:Y,'QofE PF adjustments'!$E:$E,'Adjusted IS'!$E13) | JF13: =SUMIFS('QofE PF adjustments'!Z:Z,'QofE PF adjustments'!$E:$E,'Adjusted IS'!$E13) | JG13: =SUMIFS('QofE PF adjustments'!AA:AA,'QofE PF adjustments'!$E:$E,'Adjusted IS'!$E13) | JH13: =SUMIFS('QofE PF adjustments'!AB:AB,'QofE PF adjustments'!$E:$E,'Adjusted IS'!$E13) | JI13: =SUMIFS('QofE PF adjustments'!AC:AC,'QofE PF adjustments'!$E:$E,'Adjusted IS'!$E13) | JJ13: =SUMIFS('QofE PF adjustments'!AD:AD,'QofE PF adjustments'!$E:$E,'Adjusted IS'!$E13) | JK13: =SUMIFS('QofE PF adjustments'!AE:AE,'QofE PF adjustments'!$E:$E,'Adjusted IS'!$E13) | JL13: =SUMIFS('QofE PF adjustments'!AF:AF,'QofE PF adjustments'!$E:$E,'Adjusted IS'!$E13) | JM13: =SUMIFS('QofE PF adjustments'!AG:AG,'QofE PF adjustments'!$E:$E,'Adjusted IS'!$E13) | JN13: =SUMIFS('QofE PF adjustments'!AH:AH,'QofE PF adjustments'!$E:$E,'Adjusted IS'!$E13) | JO13: =SUMIFS('QofE PF adjustments'!AI:AI,'QofE PF adjustments'!$E:$E,'Adjusted IS'!$E13) | JP13: =SUMIFS('QofE PF adjustments'!AJ:AJ,'QofE PF adjustments'!$E:$E,'Adjusted IS'!$E13) | JQ13: =SUMIFS('QofE PF adjustments'!AK:AK,'QofE PF adjustments'!$E:$E,'Adjusted IS'!$E13) | JR13: =SUMIFS('QofE PF adjustments'!AL:AL,'QofE PF adjustments'!$E:$E,'Adjusted IS'!$E13) | JS13: =SUMIFS('QofE PF adjustments'!AM:AM,'QofE PF adjustments'!$E:$E,'Adjusted IS'!$E13) | JT13: =SUMIFS('QofE PF adjustments'!AN:AN,'QofE PF adjustments'!$E:$E,'Adjusted IS'!$E13) | JU13: =SUMIFS('QofE PF adjustments'!AO:AO,'QofE PF adjustments'!$E:$E,'Adjusted IS'!$E13) | JV13: =SUMIFS('QofE PF adjustments'!AP:AP,'QofE PF adjustments'!$E:$E,'Adjusted IS'!$E13) | JW13: =SUMIFS('QofE PF adjustments'!AQ:AQ,'QofE PF adjustments'!$E:$E,'Adjusted IS'!$E13) | JX13: =SUMIFS('QofE PF adjustments'!AR:AR,'QofE PF adjustments'!$E:$E,'Adjusted IS'!$E13) | JY13: =SUMIFS('QofE PF adjustments'!AS:AS,'QofE PF adjustments'!$E:$E,'Adjusted IS'!$E13) | JZ13: =SUMIFS('QofE PF adjustments'!AT:AT,'QofE PF adjustments'!$E:$E,'Adjusted IS'!$E13) | KA13: =SUMIFS('QofE PF adjustments'!AU:AU,'QofE PF adjustments'!$E:$E,'Adjusted IS'!$E13) | KB13: =SUM(IL13:IW13) | KC13: =SUM(IX13:JI13) | KD13: =SUM(JJ13:JU13) | KE13: =SUM(JN13:JY13) | KF13: =SUM(JP13:KA13) | KH13: =SUM(IL13,GP13) | KI13: =SUM(IM13,GQ13) | KJ13: =SUM(IN13,GR13) | KK13: =SUM(IO13,GS13) | KL13: =SUM(IP13,GT13) | KM13: =SUM(IQ13,GU13) | KN13: =SUM(IR13,GV13) | KO13: =SUM(IS13,GW13) | ... LW13: =SUM(KA13,IE13) | LX13: =SUM(KH13:KS13) | LY13: =SUM(KT13:LE13) | LZ13: =SUM(LF13:LQ13) | MA13: =SUM(LJ13:LU13) | MB13: =SUM(LL13:LW13) | MD13: =IFERROR(KH13/KH$117,0) | ME13: =IFERROR(KI13/KI$117,0) | MF13: =IFERROR(KJ13/KJ$117,0) | MG13: =IFERROR(KK13/KK$117,0) | MH13: =IFERROR(KL13/KL$117,0) | MI13: =IFERROR(KM13/KM$117,0) | MJ13: =IFERROR(KN13/KN$117,0) | MK13: =IFERROR(KO13/KO$117,0) | ... NX13: =IFERROR(MB13/MB$117,0) | NZ13: =LY13-LX13 | OA13: =LZ13-LY13 | OB13: =MA13-LZ13 | OC13: =MB13-LZ13 | OE13: Processing services revenue | OF13: Processing services revenue | OG13: Processing services revenue
C14: Mobile provisioning & lcm-transaction fees | D14: 411116 | E14: =CONCATENATE(D14," - ",C14) | F14: ='Income statement'!F14 | G14: ='Income statement'!G14 | H14: ='Income statement'!H14 | I14: ='Income statement'!I14 | J14: ='Income statement'!J14 | K14: ='Income statement'!K14 | L14: ='Income statement'!L14 | M14: ='Income statement'!M14 | ... AU14: ='Income statement'!AU14 | AV14: =SUM(F14:Q14) | AW14: =SUM(R14:AC14) | AX14: =SUM(AD14:AO14) | AY14: =SUM(AH14:AS14) | AZ14: =SUM(AJ14:AU14) | BB14: =SUMIFS('QofE Def adjustments'!F:F,'QofE Def adjustments'!$E:$E,'Adjusted IS'!$E14) | BC14: =SUMIFS('QofE Def adjustments'!G:G,'QofE Def adjustments'!$E:$E,'Adjusted IS'!$E14) | BD14: =SUMIFS('QofE Def adjustments'!H:H,'QofE Def adjustments'!$E:$E,'Adjusted IS'!$E14) | BE14: =SUMIFS('QofE Def adjustments'!I:I,'QofE Def adjustments'!$E:$E,'Adjusted IS'!$E14) | BF14: =SUMIFS('QofE Def adjustments'!J:J,'QofE Def adjustments'!$E:$E,'Adjusted IS'!$E14) | BG14: =SUMIFS('QofE Def adjustments'!K:K,'QofE Def adjustments'!$E:$E,'Adjusted IS'!$E14) | BH14: =SUMIFS('QofE Def adjustments'!L:L,'QofE Def adjustments'!$E:$E,'Adjusted IS'!$E14) | BI14: =SUMIFS('QofE Def adjustments'!M:M,'QofE Def adjustments'!$E:$E,'Adjusted IS'!$E14) | BJ14: =SUMIFS('QofE Def adjustments'!N:N,'QofE Def adjustments'!$E:$E,'Adjusted IS'!$E14) | BK14: =SUMIFS('QofE Def adjustments'!O:O,'QofE Def adjustments'!$E:$E,'Adjusted IS'!$E14) | BL14: =SUMIFS('QofE Def adjustments'!P:P,'QofE Def adjustments'!$E:$E,'Adjusted IS'!$E14) | BM14: =SUMIFS('QofE Def adjustments'!Q:Q,'QofE Def adjustments'!$E:$E,'Adjusted IS'!$E14) | BN14: =SUMIFS('QofE Def adjustments'!R:R,'QofE Def adjustments'!$E:$E,'Adjusted IS'!$E14) | BO14: =SUMIFS('QofE Def adjustments'!S:S,'QofE Def adjustments'!$E:$E,'Adjusted IS'!$E14) | BP14: =SUMIFS('QofE Def adjustments'!T:T,'QofE Def adjustments'!$E:$E,'Adjusted IS'!$E14) | BQ14: =SUMIFS('QofE Def adjustments'!U:U,'QofE Def adjustments'!$E:$E,'Adjusted IS'!$E14) | BR14: =SUMIFS('QofE Def adjustments'!V:V,'QofE Def adjustments'!$E:$E,'Adjusted IS'!$E14) | BS14: =SUMIFS('QofE Def adjustments'!W:W,'QofE Def adjustments'!$E:$E,'Adjusted IS'!$E14) | BT14: =SUMIFS('QofE Def adjustments'!X:X,'QofE Def adjustments'!$E:$E,'Adjusted IS'!$E14) | BU14: =SUMIFS('QofE Def adjustments'!Y:Y,'QofE Def adjustments'!$E:$E,'Adjusted IS'!$E14) | BV14: =SUMIFS('QofE Def adjustments'!Z:Z,'QofE Def adjustments'!$E:$E,'Adjusted IS'!$E14) | BW14: =SUMIFS('QofE Def adjustments'!AA:AA,'QofE Def adjustments'!$E:$E,'Adjusted IS'!$E14) | BX14: =SUMIFS('QofE Def adjustments'!AB:AB,'QofE Def adjustments'!$E:$E,'Adjusted IS'!$E14) | BY14: =SUMIFS('QofE Def adjustments'!AC:AC,'QofE Def adjustments'!$E:$E,'Adjusted IS'!$E14) | BZ14: =SUMIFS('QofE Def adjustments'!AD:AD,'QofE Def adjustments'!$E:$E,'Adjusted IS'!$E14) | CA14: =SUMIFS('QofE Def adjustments'!AE:AE,'QofE Def adjustments'!$E:$E,'Adjusted IS'!$E14) | CB14: =SUMIFS('QofE Def adjustments'!AF:AF,'QofE Def adjustments'!$E:$E,'Adjusted IS'!$E14) | CC14: =SUMIFS('QofE Def adjustments'!AG:AG,'QofE Def adjustments'!$E:$E,'Adjusted IS'!$E14) | CD14: =SUMIFS('QofE Def adjustments'!AH:AH,'QofE Def adjustments'!$E:$E,'Adjusted IS'!$E14) | CE14: =SUMIFS('QofE Def adjustments'!AI:AI,'QofE Def adjustments'!$E:$E,'Adjusted IS'!$E14) | CF14: =SUMIFS('QofE Def adjustments'!AJ:AJ,'QofE Def adjustments'!$E:$E,'Adjusted IS'!$E14) | CG14: =SUMIFS('QofE Def adjustments'!AK:AK,'QofE Def adjustments'!$E:$E,'Adjusted IS'!$E14) | CH14: =SUMIFS('QofE Def adjustments'!AL:AL,'QofE Def adjustments'!$E:$E,'Adjusted IS'!$E14) | CI14: =SUMIFS('QofE Def adjustments'!AM:AM,'QofE Def adjustments'!$E:$E,'Adjusted IS'!$E14) | CJ14: =SUMIFS('QofE Def adjustments'!AN:AN,'QofE Def adjustments'!$E:$E,'Adjusted IS'!$E14) | CK14: =SUMIFS('QofE Def adjustments'!AO:AO,'QofE Def adjustments'!$E:$E,'Adjusted IS'!$E14) | CL14: =SUMIFS('QofE Def adjustments'!AP:AP,'QofE Def adjustments'!$E:$E,'Adjusted IS'!$E14) | CM14: =SUMIFS('QofE Def adjustments'!AQ:AQ,'QofE Def adjustments'!$E:$E,'Adjusted IS'!$E14) | CN14: =SUMIFS('QofE Def adjustments'!AR:AR,'QofE Def adjustments'!$E:$E,'Adjusted IS'!$E14) | CO14: =SUMIFS('QofE Def adjustments'!AS:AS,'QofE Def adjustments'!$E:$E,'Adjusted IS'!$E14) | CP14: =SUMIFS('QofE Def adjustments'!AT:AT,'QofE Def adjustments'!$E:$E,'Adjusted IS'!$E14) | CQ14: =SUMIFS('QofE Def adjustments'!AU:AU,'QofE Def adjustments'!$E:$E,'Adjusted IS'!$E14) | CR14: =SUM(BB14:BM14) | CS14: =SUM(BN14:BY14) | CT14: =SUM(BZ14:CK14) | CU14: =SUM(CD14:CO14) | CV14: =SUM(CF14:CQ14) | CX14: =SUM(BB14,F14) | CY14: =SUM(BC14,G14) | CZ14: =SUM(BD14,H14) | DA14: =SUM(BE14,I14) | DB14: =SUM(BF14,J14) | DC14: =SUM(BG14,K14) | DD14: =SUM(BH14,L14) | DE14: =SUM(BI14,M14) | ... EM14: =SUM(CQ14,AU14) | EN14: =SUM(CX14:DI14) | EO14: =SUM(DJ14:DU14) | EP14: =SUM(DV14:EG14) | EQ14: =SUM(DZ14:EK14) | ER14: =SUM(EB14:EM14) | ET14: =SUMIFS('QofE DD adjustments'!F:F,'QofE DD adjustments'!$E:$E,'Adjusted IS'!$E14) | EU14: =SUMIFS('QofE DD adjustments'!G:G,'QofE DD adjustments'!$E:$E,'Adjusted IS'!$E14) | EV14: =SUMIFS('QofE DD adjustments'!H:H,'QofE DD adjustments'!$E:$E,'Adjusted IS'!$E14) | EW14: =SUMIFS('QofE DD adjustments'!I:I,'QofE DD adjustments'!$E:$E,'Adjusted IS'!$E14) | EX14: =SUMIFS('QofE DD adjustments'!J:J,'QofE DD adjustments'!$E:$E,'Adjusted IS'!$E14) | EY14: =SUMIFS('QofE DD adjustments'!K:K,'QofE DD adjustments'!$E:$E,'Adjusted IS'!$E14) | EZ14: =SUMIFS('QofE DD adjustments'!L:L,'QofE DD adjustments'!$E:$E,'Adjusted IS'!$E14) | FA14: =SUMIFS('QofE DD adjustments'!M:M,'QofE DD adjustments'!$E:$E,'Adjusted IS'!$E14) | FB14: =SUMIFS('QofE DD adjustments'!N:N,'QofE DD adjustments'!$E:$E,'Adjusted IS'!$E14) | FC14: =SUMIFS('QofE DD adjustments'!O:O,'QofE DD adjustments'!$E:$E,'Adjusted IS'!$E14) | FD14: =SUMIFS('QofE DD adjustments'!P:P,'QofE DD adjustments'!$E:$E,'Adjusted IS'!$E14) | FE14: =SUMIFS('QofE DD adjustments'!Q:Q,'QofE DD adjustments'!$E:$E,'Adjusted IS'!$E14) | FF14: =SUMIFS('QofE DD adjustments'!R:R,'QofE DD adjustments'!$E:$E,'Adjusted IS'!$E14) | FG14: =SUMIFS('QofE DD adjustments'!S:S,'QofE DD adjustments'!$E:$E,'Adjusted IS'!$E14) | FH14: =SUMIFS('QofE DD adjustments'!T:T,'QofE DD adjustments'!$E:$E,'Adjusted IS'!$E14) | FI14: =SUMIFS('QofE DD adjustments'!U:U,'QofE DD adjustments'!$E:$E,'Adjusted IS'!$E14) | FJ14: =SUMIFS('QofE DD adjustments'!V:V,'QofE DD adjustments'!$E:$E,'Adjusted IS'!$E14) | FK14: =SUMIFS('QofE DD adjustments'!W:W,'QofE DD adjustments'!$E:$E,'Adjusted IS'!$E14) | FL14: =SUMIFS('QofE DD adjustments'!X:X,'QofE DD adjustments'!$E:$E,'Adjusted IS'!$E14) | FM14: =SUMIFS('QofE DD adjustments'!Y:Y,'QofE DD adjustments'!$E:$E,'Adjusted IS'!$E14) | FN14: =SUMIFS('QofE DD adjustments'!Z:Z,'QofE DD adjustments'!$E:$E,'Adjusted IS'!$E14) | FO14: =SUMIFS('QofE DD adjustments'!AA:AA,'QofE DD adjustments'!$E:$E,'Adjusted IS'!$E14) | FP14: =SUMIFS('QofE DD adjustments'!AB:AB,'QofE DD adjustments'!$E:$E,'Adjusted IS'!$E14) | FQ14: =SUMIFS('QofE DD adjustments'!AC:AC,'QofE DD adjustments'!$E:$E,'Adjusted IS'!$E14) | FR14: =SUMIFS('QofE DD adjustments'!AD:AD,'QofE DD adjustments'!$E:$E,'Adjusted IS'!$E14) | FS14: =SUMIFS('QofE DD adjustments'!AE:AE,'QofE DD adjustments'!$E:$E,'Adjusted IS'!$E14) | FT14: =SUMIFS('QofE DD adjustments'!AF:AF,'QofE DD adjustments'!$E:$E,'Adjusted IS'!$E14) | FU14: =SUMIFS('QofE DD adjustments'!AG:AG,'QofE DD adjustments'!$E:$E,'Adjusted IS'!$E14) | FV14: =SUMIFS('QofE DD adjustments'!AH:AH,'QofE DD adjustments'!$E:$E,'Adjusted IS'!$E14) | FW14: =SUMIFS('QofE DD adjustments'!AI:AI,'QofE DD adjustments'!$E:$E,'Adjusted IS'!$E14) | FX14: =SUMIFS('QofE DD adjustments'!AJ:AJ,'QofE DD adjustments'!$E:$E,'Adjusted IS'!$E14) | FY14: =SUMIFS('QofE DD adjustments'!AK:AK,'QofE DD adjustments'!$E:$E,'Adjusted IS'!$E14) | FZ14: =SUMIFS('QofE DD adjustments'!AL:AL,'QofE DD adjustments'!$E:$E,'Adjusted IS'!$E14) | GA14: =SUMIFS('QofE DD adjustments'!AM:AM,'QofE DD adjustments'!$E:$E,'Adjusted IS'!$E14) | GB14: =SUMIFS('QofE DD adjustments'!AN:AN,'QofE DD adjustments'!$E:$E,'Adjusted IS'!$E14) | GC14: =SUMIFS('QofE DD adjustments'!AO:AO,'QofE DD adjustments'!$E:$E,'Adjusted IS'!$E14) | GD14: =SUMIFS('QofE DD adjustments'!AP:AP,'QofE DD adjustments'!$E:$E,'Adjusted IS'!$E14) | GE14: =SUMIFS('QofE DD adjustments'!AQ:AQ,'QofE DD adjustments'!$E:$E,'Adjusted IS'!$E14) | GF14: =SUMIFS('QofE DD adjustments'!AR:AR,'QofE DD adjustments'!$E:$E,'Adjusted IS'!$E14) | GG14: =SUMIFS('QofE DD adjustments'!AS:AS,'QofE DD adjustments'!$E:$E,'Adjusted IS'!$E14) | GH14: =SUMIFS('QofE DD adjustments'!AT:AT,'QofE DD adjustments'!$E:$E,'Adjusted IS'!$E14) | GI14: =SUMIFS('QofE DD adjustments'!AU:AU,'QofE DD adjustments'!$E:$E,'Adjusted IS'!$E14) | GJ14: =SUM(ET14:FE14) | GK14: =SUM(FF14:FQ14) | GL14: =SUM(FR14:GC14) | GM14: =SUM(FV14:GG14) | GN14: =SUM(FX14:GI14) | GP14: =SUM(ET14,CX14) | GQ14: =SUM(EU14,CY14) | GR14: =SUM(EV14,CZ14) | GS14: =SUM(EW14,DA14) | GT14: =SUM(EX14,DB14) | GU14: =SUM(EY14,DC14) | GV14: =SUM(EZ14,DD14) | GW14: =SUM(FA14,DE14) | ... IE14: =SUM(GI14,EM14) | IF14: =SUM(GP14:HA14) | IG14: =SUM(HB14:HM14) | IH14: =SUM(HN14:HY14) | II14: =SUM(HR14:IC14) | IJ14: =SUM(HT14:IE14) | IL14: =SUMIFS('QofE PF adjustments'!F:F,'QofE PF adjustments'!$E:$E,'Adjusted IS'!$E14) | IM14: =SUMIFS('QofE PF adjustments'!G:G,'QofE PF adjustments'!$E:$E,'Adjusted IS'!$E14) | IN14: =SUMIFS('QofE PF adjustments'!H:H,'QofE PF adjustments'!$E:$E,'Adjusted IS'!$E14) | IO14: =SUMIFS('QofE PF adjustments'!I:I,'QofE PF adjustments'!$E:$E,'Adjusted IS'!$E14) | IP14: =SUMIFS('QofE PF adjustments'!J:J,'QofE PF adjustments'!$E:$E,'Adjusted IS'!$E14) | IQ14: =SUMIFS('QofE PF adjustments'!K:K,'QofE PF adjustments'!$E:$E,'Adjusted IS'!$E14) | IR14: =SUMIFS('QofE PF adjustments'!L:L,'QofE PF adjustments'!$E:$E,'Adjusted IS'!$E14) | IS14: =SUMIFS('QofE PF adjustments'!M:M,'QofE PF adjustments'!$E:$E,'Adjusted IS'!$E14) | IT14: =SUMIFS('QofE PF adjustments'!N:N,'QofE PF adjustments'!$E:$E,'Adjusted IS'!$E14) | IU14: =SUMIFS('QofE PF adjustments'!O:O,'QofE PF adjustments'!$E:$E,'Adjusted IS'!$E14) | IV14: =SUMIFS('QofE PF adjustments'!P:P,'QofE PF adjustments'!$E:$E,'Adjusted IS'!$E14) | IW14: =SUMIFS('QofE PF adjustments'!Q:Q,'QofE PF adjustments'!$E:$E,'Adjusted IS'!$E14) | IX14: =SUMIFS('QofE PF adjustments'!R:R,'QofE PF adjustments'!$E:$E,'Adjusted IS'!$E14) | IY14: =SUMIFS('QofE PF adjustments'!S:S,'QofE PF adjustments'!$E:$E,'Adjusted IS'!$E14) | IZ14: =SUMIFS('QofE PF adjustments'!T:T,'QofE PF adjustments'!$E:$E,'Adjusted IS'!$E14) | JA14: =SUMIFS('QofE PF adjustments'!U:U,'QofE PF adjustments'!$E:$E,'Adjusted IS'!$E14) | JB14: =SUMIFS('QofE PF adjustments'!V:V,'QofE PF adjustments'!$E:$E,'Adjusted IS'!$E14) | JC14: =SUMIFS('QofE PF adjustments'!W:W,'QofE PF adjustments'!$E:$E,'Adjusted IS'!$E14) | JD14: =SUMIFS('QofE PF adjustments'!X:X,'QofE PF adjustments'!$E:$E,'Adjusted IS'!$E14) | JE14: =SUMIFS('QofE PF adjustments'!Y:Y,'QofE PF adjustments'!$E:$E,'Adjusted IS'!$E14) | JF14: =SUMIFS('QofE PF adjustments'!Z:Z,'QofE PF adjustments'!$E:$E,'Adjusted IS'!$E14) | JG14: =SUMIFS('QofE PF adjustments'!AA:AA,'QofE PF adjustments'!$E:$E,'Adjusted IS'!$E14) | JH14: =SUMIFS('QofE PF adjustments'!AB:AB,'QofE PF adjustments'!$E:$E,'Adjusted IS'!$E14) | JI14: =SUMIFS('QofE PF adjustments'!AC:AC,'QofE PF adjustments'!$E:$E,'Adjusted IS'!$E14) | JJ14: =SUMIFS('QofE PF adjustments'!AD:AD,'QofE PF adjustments'!$E:$E,'Adjusted IS'!$E14) | JK14: =SUMIFS('QofE PF adjustments'!AE:AE,'QofE PF adjustments'!$E:$E,'Adjusted IS'!$E14) | JL14: =SUMIFS('QofE PF adjustments'!AF:AF,'QofE PF adjustments'!$E:$E,'Adjusted IS'!$E14) | JM14: =SUMIFS('QofE PF adjustments'!AG:AG,'QofE PF adjustments'!$E:$E,'Adjusted IS'!$E14) | JN14: =SUMIFS('QofE PF adjustments'!AH:AH,'QofE PF adjustments'!$E:$E,'Adjusted IS'!$E14) | JO14: =SUMIFS('QofE PF adjustments'!AI:AI,'QofE PF adjustments'!$E:$E,'Adjusted IS'!$E14) | JP14: =SUMIFS('QofE PF adjustments'!AJ:AJ,'QofE PF adjustments'!$E:$E,'Adjusted IS'!$E14) | JQ14: =SUMIFS('QofE PF adjustments'!AK:AK,'QofE PF adjustments'!$E:$E,'Adjusted IS'!$E14) | JR14: =SUMIFS('QofE PF adjustments'!AL:AL,'QofE PF adjustments'!$E:$E,'Adjusted IS'!$E14) | JS14: =SUMIFS('QofE PF adjustments'!AM:AM,'QofE PF adjustments'!$E:$E,'Adjusted IS'!$E14) | JT14: =SUMIFS('QofE PF adjustments'!AN:AN,'QofE PF adjustments'!$E:$E,'Adjusted IS'!$E14) | JU14: =SUMIFS('QofE PF adjustments'!AO:AO,'QofE PF adjustments'!$E:$E,'Adjusted IS'!$E14) | JV14: =SUMIFS('QofE PF adjustments'!AP:AP,'QofE PF adjustments'!$E:$E,'Adjusted IS'!$E14) | JW14: =SUMIFS('QofE PF adjustments'!AQ:AQ,'QofE PF adjustments'!$E:$E,'Adjusted IS'!$E14) | JX14: =SUMIFS('QofE PF adjustments'!AR:AR,'QofE PF adjustments'!$E:$E,'Adjusted IS'!$E14) | JY14: =SUMIFS('QofE PF adjustments'!AS:AS,'QofE PF adjustments'!$E:$E,'Adjusted IS'!$E14) | JZ14: =SUMIFS('QofE PF adjustments'!AT:AT,'QofE PF adjustments'!$E:$E,'Adjusted IS'!$E14) | KA14: =SUMIFS('QofE PF adjustments'!AU:AU,'QofE PF adjustments'!$E:$E,'Adjusted IS'!$E14) | KB14: =SUM(IL14:IW14) | KC14: =SUM(IX14:JI14) | KD14: =SUM(JJ14:JU14) | KE14: =SUM(JN14:JY14) | KF14: =SUM(JP14:KA14) | KH14: =SUM(IL14,GP14) | KI14: =SUM(IM14,GQ14) | KJ14: =SUM(IN14,GR14) | KK14: =SUM(IO14,GS14) | KL14: =SUM(IP14,GT14) | KM14: =SUM(IQ14,GU14) | KN14: =SUM(IR14,GV14) | KO14: =SUM(IS14,GW14) | ... LW14: =SUM(KA14,IE14) | LX14: =SUM(KH14:KS14) | LY14: =SUM(KT14:LE14) | LZ14: =SUM(LF14:LQ14) | MA14: =SUM(LJ14:LU14) | MB14: =SUM(LL14:LW14) | MD14: =IFERROR(KH14/KH$117,0) | ME14: =IFERROR(KI14/KI$117,0) | MF14: =IFERROR(KJ14/KJ$117,0) | MG14: =IFERROR(KK14/KK$117,0) | MH14: =IFERROR(KL14/KL$117,0) | MI14: =IFERROR(KM14/KM$117,0) | MJ14: =IFERROR(KN14/KN$117,0) | MK14: =IFERROR(KO14/KO$117,0) | ... NX14: =IFERROR(MB14/MB$117,0) | NZ14: =LY14-LX14 | OA14: =LZ14-LY14 | OB14: =MA14-LZ14 | OC14: =MB14-LZ14 | OE14: Processing services revenue | OF14: Processing services revenue | OG14: Processing services revenue
C15: Interest income-other | D15: ADJ | E15: =CONCATENATE(D15," - ",C15) | F15: ='Income statement'!F15 | G15: ='Income statement'!G15 | H15: ='Income statement'!H15 | I15: ='Income statement'!I15 | J15: ='Income statement'!J15 | K15: ='Income statement'!K15 | L15: ='Income statement'!L15 | M15: ='Income statement'!M15 | ... AU15: ='Income statement'!AU15 | AV15: =SUM(F15:Q15) | AW15: =SUM(R15:AC15) | AX15: =SUM(AD15:AO15) | AY15: =SUM(AH15:AS15) | AZ15: =SUM(AJ15:AU15) | BB15: =SUMIFS('QofE Def adjustments'!F:F,'QofE Def adjustments'!$E:$E,'Adjusted IS'!$E15) | BC15: =SUMIFS('QofE Def adjustments'!G:G,'QofE Def adjustments'!$E:$E,'Adjusted IS'!$E15) | BD15: =SUMIFS('QofE Def adjustments'!H:H,'QofE Def adjustments'!$E:$E,'Adjusted IS'!$E15) | BE15: =SUMIFS('QofE Def adjustments'!I:I,'QofE Def adjustments'!$E:$E,'Adjusted IS'!$E15) | BF15: =SUMIFS('QofE Def adjustments'!J:J,'QofE Def adjustments'!$E:$E,'Adjusted IS'!$E15) | BG15: =SUMIFS('QofE Def adjustments'!K:K,'QofE Def adjustments'!$E:$E,'Adjusted IS'!$E15) | BH15: =SUMIFS('QofE Def adjustments'!L:L,'QofE Def adjustments'!$E:$E,'Adjusted IS'!$E15) | BI15: =SUMIFS('QofE Def adjustments'!M:M,'QofE Def adjustments'!$E:$E,'Adjusted IS'!$E15) | BJ15: =SUMIFS('QofE Def adjustments'!N:N,'QofE Def adjustments'!$E:$E,'Adjusted IS'!$E15) | BK15: =SUMIFS('QofE Def adjustments'!O:O,'QofE Def adjustments'!$E:$E,'Adjusted IS'!$E15) | BL15: =SUMIFS('QofE Def adjustments'!P:P,'QofE Def adjustments'!$E:$E,'Adjusted IS'!$E15) | BM15: =SUMIFS('QofE Def adjustments'!Q:Q,'QofE Def adjustments'!$E:$E,'Adjusted IS'!$E15) | BN15: =SUMIFS('QofE Def adjustments'!R:R,'QofE Def adjustments'!$E:$E,'Adjusted IS'!$E15) | BO15: =SUMIFS('QofE Def adjustments'!S:S,'QofE Def adjustments'!$E:$E,'Adjusted IS'!$E15) | BP15: =SUMIFS('QofE Def adjustments'!T:T,'QofE Def adjustments'!$E:$E,'Adjusted IS'!$E15) | BQ15: =SUMIFS('QofE Def adjustments'!U:U,'QofE Def adjustments'!$E:$E,'Adjusted IS'!$E15) | BR15: =SUMIFS('QofE Def adjustments'!V:V,'QofE Def adjustments'!$E:$E,'Adjusted IS'!$E15) | BS15: =SUMIFS('QofE Def adjustments'!W:W,'QofE Def adjustments'!$E:$E,'Adjusted IS'!$E15) | BT15: =SUMIFS('QofE Def adjustments'!X:X,'QofE Def adjustments'!$E:$E,'Adjusted IS'!$E15) | BU15: =SUMIFS('QofE Def adjustments'!Y:Y,'QofE Def adjustments'!$E:$E,'Adjusted IS'!$E15) | BV15: =SUMIFS('QofE Def adjustments'!Z:Z,'QofE Def adjustments'!$E:$E,'Adjusted IS'!$E15) | BW15: =SUMIFS('QofE Def adjustments'!AA:AA,'QofE Def adjustments'!$E:$E,'Adjusted IS'!$E15) | BX15: =SUMIFS('QofE Def adjustments'!AB:AB,'QofE Def adjustments'!$E:$E,'Adjusted IS'!$E15) | BY15: =SUMIFS('QofE Def adjustments'!AC:AC,'QofE Def adjustments'!$E:$E,'Adjusted IS'!$E15) | BZ15: =SUMIFS('QofE Def adjustments'!AD:AD,'QofE Def adjustments'!$E:$E,'Adjusted IS'!$E15) | CA15: =SUMIFS('QofE Def adjustments'!AE:AE,'QofE Def adjustments'!$E:$E,'Adjusted IS'!$E15) | CB15: =SUMIFS('QofE Def adjustments'!AF:AF,'QofE Def adjustments'!$E:$E,'Adjusted IS'!$E15) | CC15: =SUMIFS('QofE Def adjustments'!AG:AG,'QofE Def adjustments'!$E:$E,'Adjusted IS'!$E15) | CD15: =SUMIFS('QofE Def adjustments'!AH:AH,'QofE Def adjustments'!$E:$E,'Adjusted IS'!$E15) | CE15: =SUMIFS('QofE Def adjustments'!AI:AI,'QofE Def adjustments'!$E:$E,'Adjusted IS'!$E15) | CF15: =SUMIFS('QofE Def adjustments'!AJ:AJ,'QofE Def adjustments'!$E:$E,'Adjusted IS'!$E15) | CG15: =SUMIFS('QofE Def adjustments'!AK:AK,'QofE Def adjustments'!$E:$E,'Adjusted IS'!$E15) | CH15: =SUMIFS('QofE Def adjustments'!AL:AL,'QofE Def adjustments'!$E:$E,'Adjusted IS'!$E15) | CI15: =SUMIFS('QofE Def adjustments'!AM:AM,'QofE Def adjustments'!$E:$E,'Adjusted IS'!$E15) | CJ15: =SUMIFS('QofE Def adjustments'!AN:AN,'QofE Def adjustments'!$E:$E,'Adjusted IS'!$E15) | CK15: =SUMIFS('QofE Def adjustments'!AO:AO,'QofE Def adjustments'!$E:$E,'Adjusted IS'!$E15) | CL15: =SUMIFS('QofE Def adjustments'!AP:AP,'QofE Def adjustments'!$E:$E,'Adjusted IS'!$E15) | CM15: =SUMIFS('QofE Def adjustments'!AQ:AQ,'QofE Def adjustments'!$E:$E,'Adjusted IS'!$E15) | CN15: =SUMIFS('QofE Def adjustments'!AR:AR,'QofE Def adjustments'!$E:$E,'Adjusted IS'!$E15) | CO15: =SUMIFS('QofE Def adjustments'!AS:AS,'QofE Def adjustments'!$E:$E,'Adjusted IS'!$E15) | CP15: =SUMIFS('QofE Def adjustments'!AT:AT,'QofE Def adjustments'!$E:$E,'Adjusted IS'!$E15) | CQ15: =SUMIFS('QofE Def adjustments'!AU:AU,'QofE Def adjustments'!$E:$E,'Adjusted IS'!$E15) | CR15: =SUM(BB15:BM15) | CS15: =SUM(BN15:BY15) | CT15: =SUM(BZ15:CK15) | CU15: =SUM(CD15:CO15) | CV15: =SUM(CF15:CQ15) | CX15: =SUM(BB15,F15) | CY15: =SUM(BC15,G15) | CZ15: =SUM(BD15,H15) | DA15: =SUM(BE15,I15) | DB15: =SUM(BF15,J15) | DC15: =SUM(BG15,K15) | DD15: =SUM(BH15,L15) | DE15: =SUM(BI15,M15) | ... EM15: =SUM(CQ15,AU15) | EN15: =SUM(CX15:DI15) | EO15: =SUM(DJ15:DU15) | EP15: =SUM(DV15:EG15) | EQ15: =SUM(DZ15:EK15) | ER15: =SUM(EB15:EM15) | ET15: =SUMIFS('QofE DD adjustments'!F:F,'QofE DD adjustments'!$E:$E,'Adjusted IS'!$E15) | EU15: =SUMIFS('QofE DD adjustments'!G:G,'QofE DD adjustments'!$E:$E,'Adjusted IS'!$E15) | EV15: =SUMIFS('QofE DD adjustments'!H:H,'QofE DD adjustments'!$E:$E,'Adjusted IS'!$E15) | EW15: =SUMIFS('QofE DD adjustments'!I:I,'QofE DD adjustments'!$E:$E,'Adjusted IS'!$E15) | EX15: =SUMIFS('QofE DD adjustments'!J:J,'QofE DD adjustments'!$E:$E,'Adjusted IS'!$E15) | EY15: =SUMIFS('QofE DD adjustments'!K:K,'QofE DD adjustments'!$E:$E,'Adjusted IS'!$E15) | EZ15: =SUMIFS('QofE DD adjustments'!L:L,'QofE DD adjustments'!$E:$E,'Adjusted IS'!$E15) | FA15: =SUMIFS('QofE DD adjustments'!M:M,'QofE DD adjustments'!$E:$E,'Adjusted IS'!$E15) | FB15: =SUMIFS('QofE DD adjustments'!N:N,'QofE DD adjustments'!$E:$E,'Adjusted IS'!$E15) | FC15: =SUMIFS('QofE DD adjustments'!O:O,'QofE DD adjustments'!$E:$E,'Adjusted IS'!$E15) | FD15: =SUMIFS('QofE DD adjustments'!P:P,'QofE DD adjustments'!$E:$E,'Adjusted IS'!$E15) | FE15: =SUMIFS('QofE DD adjustments'!Q:Q,'QofE DD adjustments'!$E:$E,'Adjusted IS'!$E15) | FF15: =SUMIFS('QofE DD adjustments'!R:R,'QofE DD adjustments'!$E:$E,'Adjusted IS'!$E15) | FG15: =SUMIFS('QofE DD adjustments'!S:S,'QofE DD adjustments'!$E:$E,'Adjusted IS'!$E15) | FH15: =SUMIFS('QofE DD adjustments'!T:T,'QofE DD adjustments'!$E:$E,'Adjusted IS'!$E15) | FI15: =SUMIFS('QofE DD adjustments'!U:U,'QofE DD adjustments'!$E:$E,'Adjusted IS'!$E15) | FJ15: =SUMIFS('QofE DD adjustments'!V:V,'QofE DD adjustments'!$E:$E,'Adjusted IS'!$E15) | FK15: =SUMIFS('QofE DD adjustments'!W:W,'QofE DD adjustments'!$E:$E,'Adjusted IS'!$E15) | FL15: =SUMIFS('QofE DD adjustments'!X:X,'QofE DD adjustments'!$E:$E,'Adjusted IS'!$E15) | FM15: =SUMIFS('QofE DD adjustments'!Y:Y,'QofE DD adjustments'!$E:$E,'Adjusted IS'!$E15) | FN15: =SUMIFS('QofE DD adjustments'!Z:Z,'QofE DD adjustments'!$E:$E,'Adjusted IS'!$E15) | FO15: =SUMIFS('QofE DD adjustments'!AA:AA,'QofE DD adjustments'!$E:$E,'Adjusted IS'!$E15) | FP15: =SUMIFS('QofE DD adjustments'!AB:AB,'QofE DD adjustments'!$E:$E,'Adjusted IS'!$E15) | FQ15: =SUMIFS('QofE DD adjustments'!AC:AC,'QofE DD adjustments'!$E:$E,'Adjusted IS'!$E15) | FR15: =SUMIFS('QofE DD adjustments'!AD:AD,'QofE DD adjustments'!$E:$E,'Adjusted IS'!$E15) | FS15: =SUMIFS('QofE DD adjustments'!AE:AE,'QofE DD adjustments'!$E:$E,'Adjusted IS'!$E15) | FT15: =SUMIFS('QofE DD adjustments'!AF:AF,'QofE DD adjustments'!$E:$E,'Adjusted IS'!$E15) | FU15: =SUMIFS('QofE DD adjustments'!AG:AG,'QofE DD adjustments'!$E:$E,'Adjusted IS'!$E15) | FV15: =SUMIFS('QofE DD adjustments'!AH:AH,'QofE DD adjustments'!$E:$E,'Adjusted IS'!$E15) | FW15: =SUMIFS('QofE DD adjustments'!AI:AI,'QofE DD adjustments'!$E:$E,'Adjusted IS'!$E15) | FX15: =SUMIFS('QofE DD adjustments'!AJ:AJ,'QofE DD adjustments'!$E:$E,'Adjusted IS'!$E15) | FY15: =SUMIFS('QofE DD adjustments'!AK:AK,'QofE DD adjustments'!$E:$E,'Adjusted IS'!$E15) | FZ15: =SUMIFS('QofE DD adjustments'!AL:AL,'QofE DD adjustments'!$E:$E,'Adjusted IS'!$E15) | GA15: =SUMIFS('QofE DD adjustments'!AM:AM,'QofE DD adjustments'!$E:$E,'Adjusted IS'!$E15) | GB15: =SUMIFS('QofE DD adjustments'!AN:AN,'QofE DD adjustments'!$E:$E,'Adjusted IS'!$E15) | GC15: =SUMIFS('QofE DD adjustments'!AO:AO,'QofE DD adjustments'!$E:$E,'Adjusted IS'!$E15) | GD15: =SUMIFS('QofE DD adjustments'!AP:AP,'QofE DD adjustments'!$E:$E,'Adjusted IS'!$E15) | GE15: =SUMIFS('QofE DD adjustments'!AQ:AQ,'QofE DD adjustments'!$E:$E,'Adjusted IS'!$E15) | GF15: =SUMIFS('QofE DD adjustments'!AR:AR,'QofE DD adjustments'!$E:$E,'Adjusted IS'!$E15) | GG15: =SUMIFS('QofE DD adjustments'!AS:AS,'QofE DD adjustments'!$E:$E,'Adjusted IS'!$E15) | GH15: =SUMIFS('QofE DD adjustments'!AT:AT,'QofE DD adjustments'!$E:$E,'Adjusted IS'!$E15) | GI15: =SUMIFS('QofE DD adjustments'!AU:AU,'QofE DD adjustments'!$E:$E,'Adjusted IS'!$E15) | GJ15: =SUM(ET15:FE15) | GK15: =SUM(FF15:FQ15) | GL15: =SUM(FR15:GC15) | GM15: =SUM(FV15:GG15) | GN15: =SUM(FX15:GI15) | GP15: =SUM(ET15,CX15) | GQ15: =SUM(EU15,CY15) | GR15: =SUM(EV15,CZ15) | GS15: =SUM(EW15,DA15) | GT15: =SUM(EX15,DB15) | GU15: =SUM(EY15,DC15) | GV15: =SUM(EZ15,DD15) | GW15: =SUM(FA15,DE15) | ... IE15: =SUM(GI15,EM15) | IF15: =SUM(GP15:HA15) | IG15: =SUM(HB15:HM15) | IH15: =SUM(HN15:HY15) | II15: =SUM(HR15:IC15) | IJ15: =SUM(HT15:IE15) | IL15: =SUMIFS('QofE PF adjustments'!F:F,'QofE PF adjustments'!$E:$E,'Adjusted IS'!$E15) | IM15: =SUMIFS('QofE PF adjustments'!G:G,'QofE PF adjustments'!$E:$E,'Adjusted IS'!$E15) | IN15: =SUMIFS('QofE PF adjustments'!H:H,'QofE PF adjustments'!$E:$E,'Adjusted IS'!$E15) | IO15: =SUMIFS('QofE PF adjustments'!I:I,'QofE PF adjustments'!$E:$E,'Adjusted IS'!$E15) | IP15: =SUMIFS('QofE PF adjustments'!J:J,'QofE PF adjustments'!$E:$E,'Adjusted IS'!$E15) | IQ15: =SUMIFS('QofE PF adjustments'!K:K,'QofE PF adjustments'!$E:$E,'Adjusted IS'!$E15) | IR15: =SUMIFS('QofE PF adjustments'!L:L,'QofE PF adjustments'!$E:$E,'Adjusted IS'!$E15) | IS15: =SUMIFS('QofE PF adjustments'!M:M,'QofE PF adjustments'!$E:$E,'Adjusted IS'!$E15) | IT15: =SUMIFS('QofE PF adjustments'!N:N,'QofE PF adjustments'!$E:$E,'Adjusted IS'!$E15) | IU15: =SUMIFS('QofE PF adjustments'!O:O,'QofE PF adjustments'!$E:$E,'Adjusted IS'!$E15) | IV15: =SUMIFS('QofE PF adjustments'!P:P,'QofE PF adjustments'!$E:$E,'Adjusted IS'!$E15) | IW15: =SUMIFS('QofE PF adjustments'!Q:Q,'QofE PF adjustments'!$E:$E,'Adjusted IS'!$E15) | IX15: =SUMIFS('QofE PF adjustments'!R:R,'QofE PF adjustments'!$E:$E,'Adjusted IS'!$E15) | IY15: =SUMIFS('QofE PF adjustments'!S:S,'QofE PF adjustments'!$E:$E,'Adjusted IS'!$E15) | IZ15: =SUMIFS('QofE PF adjustments'!T:T,'QofE PF adjustments'!$E:$E,'Adjusted IS'!$E15) | JA15: =SUMIFS('QofE PF adjustments'!U:U,'QofE PF adjustments'!$E:$E,'Adjusted IS'!$E15) | JB15: =SUMIFS('QofE PF adjustments'!V:V,'QofE PF adjustments'!$E:$E,'Adjusted IS'!$E15) | JC15: =SUMIFS('QofE PF adjustments'!W:W,'QofE PF adjustments'!$E:$E,'Adjusted IS'!$E15) | JD15: =SUMIFS('QofE PF adjustments'!X:X,'QofE PF adjustments'!$E:$E,'Adjusted IS'!$E15) | JE15: =SUMIFS('QofE PF adjustments'!Y:Y,'QofE PF adjustments'!$E:$E,'Adjusted IS'!$E15) | JF15: =SUMIFS('QofE PF adjustments'!Z:Z,'QofE PF adjustments'!$E:$E,'Adjusted IS'!$E15) | JG15: =SUMIFS('QofE PF adjustments'!AA:AA,'QofE PF adjustments'!$E:$E,'Adjusted IS'!$E15) | JH15: =SUMIFS('QofE PF adjustments'!AB:AB,'QofE PF adjustments'!$E:$E,'Adjusted IS'!$E15) | JI15: =SUMIFS('QofE PF adjustments'!AC:AC,'QofE PF adjustments'!$E:$E,'Adjusted IS'!$E15) | JJ15: =SUMIFS('QofE PF adjustments'!AD:AD,'QofE PF adjustments'!$E:$E,'Adjusted IS'!$E15) | JK15: =SUMIFS('QofE PF adjustments'!AE:AE,'QofE PF adjustments'!$E:$E,'Adjusted IS'!$E15) | JL15: =SUMIFS('QofE PF adjustments'!AF:AF,'QofE PF adjustments'!$E:$E,'Adjusted IS'!$E15) | JM15: =SUMIFS('QofE PF adjustments'!AG:AG,'QofE PF adjustments'!$E:$E,'Adjusted IS'!$E15) | JN15: =SUMIFS('QofE PF adjustments'!AH:AH,'QofE PF adjustments'!$E:$E,'Adjusted IS'!$E15) | JO15: =SUMIFS('QofE PF adjustments'!AI:AI,'QofE PF adjustments'!$E:$E,'Adjusted IS'!$E15) | JP15: =SUMIFS('QofE PF adjustments'!AJ:AJ,'QofE PF adjustments'!$E:$E,'Adjusted IS'!$E15) | JQ15: =SUMIFS('QofE PF adjustments'!AK:AK,'QofE PF adjustments'!$E:$E,'Adjusted IS'!$E15) | JR15: =SUMIFS('QofE PF adjustments'!AL:AL,'QofE PF adjustments'!$E:$E,'Adjusted IS'!$E15) | JS15: =SUMIFS('QofE PF adjustments'!AM:AM,'QofE PF adjustments'!$E:$E,'Adjusted IS'!$E15) | JT15: =SUMIFS('QofE PF adjustments'!AN:AN,'QofE PF adjustments'!$E:$E,'Adjusted IS'!$E15) | JU15: =SUMIFS('QofE PF adjustments'!AO:AO,'QofE PF adjustments'!$E:$E,'Adjusted IS'!$E15) | JV15: =SUMIFS('QofE PF adjustments'!AP:AP,'QofE PF adjustments'!$E:$E,'Adjusted IS'!$E15) | JW15: =SUMIFS('QofE PF adjustments'!AQ:AQ,'QofE PF adjustments'!$E:$E,'Adjusted IS'!$E15) | JX15: =SUMIFS('QofE PF adjustments'!AR:AR,'QofE PF adjustments'!$E:$E,'Adjusted IS'!$E15) | JY15: =SUMIFS('QofE PF adjustments'!AS:AS,'QofE PF adjustments'!$E:$E,'Adjusted IS'!$E15) | JZ15: =SUMIFS('QofE PF adjustments'!AT:AT,'QofE PF adjustments'!$E:$E,'Adjusted IS'!$E15) | KA15: =SUMIFS('QofE PF adjustments'!AU:AU,'QofE PF adjustments'!$E:$E,'Adjusted IS'!$E15) | KB15: =SUM(IL15:IW15) | KC15: =SUM(IX15:JI15) | KD15: =SUM(JJ15:JU15) | KE15: =SUM(JN15:JY15) | KF15: =SUM(JP15:KA15) | KH15: =SUM(IL15,GP15) | KI15: =SUM(IM15,GQ15) | KJ15: =SUM(IN15,GR15) | KK15: =SUM(IO15,GS15) | KL15: =SUM(IP15,GT15) | KM15: =SUM(IQ15,GU15) | KN15: =SUM(IR15,GV15) | KO15: =SUM(IS15,GW15) | ... LW15: =SUM(KA15,IE15) | LX15: =SUM(KH15:KS15) | LY15: =SUM(KT15:LE15) | LZ15: =SUM(LF15:LQ15) | MA15: =SUM(LJ15:LU15) | MB15: =SUM(LL15:LW15) | MD15: =IFERROR(KH15/KH$117,0) | ME15: =IFERROR(KI15/KI$117,0) | MF15: =IFERROR(KJ15/KJ$117,0) | MG15: =IFERROR(KK15/KK$117,0) | MH15: =IFERROR(KL15/KL$117,0) | MI15: =IFERROR(KM15/KM$117,0) | MJ15: =IFERROR(KN15/KN$117,0) | MK15: =IFERROR(KO15/KO$117,0) | ... NX15: =IFERROR(MB15/MB$117,0) | NZ15: =LY15-LX15 | OA15: =LZ15-LY15 | OB15: =MA15-LZ15 | OC15: =MB15-LZ15 | OE15: Processing services revenue | OF15: Processing services revenue | OG15: Processing services revenue
C16: Png transactions revenue - scd | D16: 411102 | E16: =CONCATENATE(D16," - ",C16) | F16: ='Income statement'!F16 | G16: ='Income statement'!G16 | H16: ='Income statement'!H16 | I16: ='Income statement'!I16 | J16: ='Income statement'!J16 | K16: ='Income statement'!K16 | L16: ='Income statement'!L16 | M16: ='Income statement'!M16 | ... AU16: ='Income statement'!AU16 | AV16: =SUM(F16:Q16) | AW16: =SUM(R16:AC16) | AX16: =SUM(AD16:AO16) | AY16: =SUM(AH16:AS16) | AZ16: =SUM(AJ16:AU16) | BB16: =SUMIFS('QofE Def adjustments'!F:F,'QofE Def adjustments'!$E:$E,'Adjusted IS'!$E16) | BC16: =SUMIFS('QofE Def adjustments'!G:G,'QofE Def adjustments'!$E:$E,'Adjusted IS'!$E16) | BD16: =SUMIFS('QofE Def adjustments'!H:H,'QofE Def adjustments'!$E:$E,'Adjusted IS'!$E16) | BE16: =SUMIFS('QofE Def adjustments'!I:I,'QofE Def adjustments'!$E:$E,'Adjusted IS'!$E16) | BF16: =SUMIFS('QofE Def adjustments'!J:J,'QofE Def adjustments'!$E:$E,'Adjusted IS'!$E16) | BG16: =SUMIFS('QofE Def adjustments'!K:K,'QofE Def adjustments'!$E:$E,'Adjusted IS'!$E16) | BH16: =SUMIFS('QofE Def adjustments'!L:L,'QofE Def adjustments'!$E:$E,'Adjusted IS'!$E16) | BI16: =SUMIFS('QofE Def adjustments'!M:M,'QofE Def adjustments'!$E:$E,'Adjusted IS'!$E16) | BJ16: =SUMIFS('QofE Def adjustments'!N:N,'QofE Def adjustments'!$E:$E,'Adjusted IS'!$E16) | BK16: =SUMIFS('QofE Def adjustments'!O:O,'QofE Def adjustments'!$E:$E,'Adjusted IS'!$E16) | BL16: =SUMIFS('QofE Def adjustments'!P:P,'QofE Def adjustments'!$E:$E,'Adjusted IS'!$E16) | BM16: =SUMIFS('QofE Def adjustments'!Q:Q,'QofE Def adjustments'!$E:$E,'Adjusted IS'!$E16) | BN16: =SUMIFS('QofE Def adjustments'!R:R,'QofE Def adjustments'!$E:$E,'Adjusted IS'!$E16) | BO16: =SUMIFS('QofE Def adjustments'!S:S,'QofE Def adjustments'!$E:$E,'Adjusted IS'!$E16) | BP16: =SUMIFS('QofE Def adjustments'!T:T,'QofE Def adjustments'!$E:$E,'Adjusted IS'!$E16) | BQ16: =SUMIFS('QofE Def adjustments'!U:U,'QofE Def adjustments'!$E:$E,'Adjusted IS'!$E16) | BR16: =SUMIFS('QofE Def adjustments'!V:V,'QofE Def adjustments'!$E:$E,'Adjusted IS'!$E16) | BS16: =SUMIFS('QofE Def adjustments'!W:W,'QofE Def adjustments'!$E:$E,'Adjusted IS'!$E16) | BT16: =SUMIFS('QofE Def adjustments'!X:X,'QofE Def adjustments'!$E:$E,'Adjusted IS'!$E16) | BU16: =SUMIFS('QofE Def adjustments'!Y:Y,'QofE Def adjustments'!$E:$E,'Adjusted IS'!$E16) | BV16: =SUMIFS('QofE Def adjustments'!Z:Z,'QofE Def adjustments'!$E:$E,'Adjusted IS'!$E16) | BW16: =SUMIFS('QofE Def adjustments'!AA:AA,'QofE Def adjustments'!$E:$E,'Adjusted IS'!$E16) | BX16: =SUMIFS('QofE Def adjustments'!AB:AB,'QofE Def adjustments'!$E:$E,'Adjusted IS'!$E16) | BY16: =SUMIFS('QofE Def adjustments'!AC:AC,'QofE Def adjustments'!$E:$E,'Adjusted IS'!$E16) | BZ16: =SUMIFS('QofE Def adjustments'!AD:AD,'QofE Def adjustments'!$E:$E,'Adjusted IS'!$E16) | CA16: =SUMIFS('QofE Def adjustments'!AE:AE,'QofE Def adjustments'!$E:$E,'Adjusted IS'!$E16) | CB16: =SUMIFS('QofE Def adjustments'!AF:AF,'QofE Def adjustments'!$E:$E,'Adjusted IS'!$E16) | CC16: =SUMIFS('QofE Def adjustments'!AG:AG,'QofE Def adjustments'!$E:$E,'Adjusted IS'!$E16) | CD16: =SUMIFS('QofE Def adjustments'!AH:AH,'QofE Def adjustments'!$E:$E,'Adjusted IS'!$E16) | CE16: =SUMIFS('QofE Def adjustments'!AI:AI,'QofE Def adjustments'!$E:$E,'Adjusted IS'!$E16) | CF16: =SUMIFS('QofE Def adjustments'!AJ:AJ,'QofE Def adjustments'!$E:$E,'Adjusted IS'!$E16) | CG16: =SUMIFS('QofE Def adjustments'!AK:AK,'QofE Def adjustments'!$E:$E,'Adjusted IS'!$E16) | CH16: =SUMIFS('QofE Def adjustments'!AL:AL,'QofE Def adjustments'!$E:$E,'Adjusted IS'!$E16) | CI16: =SUMIFS('QofE Def adjustments'!AM:AM,'QofE Def adjustments'!$E:$E,'Adjusted IS'!$E16) | CJ16: =SUMIFS('QofE Def adjustments'!AN:AN,'QofE Def adjustments'!$E:$E,'Adjusted IS'!$E16) | CK16: =SUMIFS('QofE Def adjustments'!AO:AO,'QofE Def adjustments'!$E:$E,'Adjusted IS'!$E16) | CL16: =SUMIFS('QofE Def adjustments'!AP:AP,'QofE Def adjustments'!$E:$E,'Adjusted IS'!$E16) | CM16: =SUMIFS('QofE Def adjustments'!AQ:AQ,'QofE Def adjustments'!$E:$E,'Adjusted IS'!$E16) | CN16: =SUMIFS('QofE Def adjustments'!AR:AR,'QofE Def adjustments'!$E:$E,'Adjusted IS'!$E16) | CO16: =SUMIFS('QofE Def adjustments'!AS:AS,'QofE Def adjustments'!$E:$E,'Adjusted IS'!$E16) | CP16: =SUMIFS('QofE Def adjustments'!AT:AT,'QofE Def adjustments'!$E:$E,'Adjusted IS'!$E16) | CQ16: =SUMIFS('QofE Def adjustments'!AU:AU,'QofE Def adjustments'!$E:$E,'Adjusted IS'!$E16) | CR16: =SUM(BB16:BM16) | CS16: =SUM(BN16:BY16) | CT16: =SUM(BZ16:CK16) | CU16: =SUM(CD16:CO16) | CV16: =SUM(CF16:CQ16) | CX16: =SUM(BB16,F16) | CY16: =SUM(BC16,G16) | CZ16: =SUM(BD16,H16) | DA16: =SUM(BE16,I16) | DB16: =SUM(BF16,J16) | DC16: =SUM(BG16,K16) | DD16: =SUM(BH16,L16) | DE16: =SUM(BI16,M16) | ... EM16: =SUM(CQ16,AU16) | EN16: =SUM(CX16:DI16) | EO16: =SUM(DJ16:DU16) | EP16: =SUM(DV16:EG16) | EQ16: =SUM(DZ16:EK16) | ER16: =SUM(EB16:EM16) | ET16: =SUMIFS('QofE DD adjustments'!F:F,'QofE DD adjustments'!$E:$E,'Adjusted IS'!$E16) | EU16: =SUMIFS('QofE DD adjustments'!G:G,'QofE DD adjustments'!$E:$E,'Adjusted IS'!$E16) | EV16: =SUMIFS('QofE DD adjustments'!H:H,'QofE DD adjustments'!$E:$E,'Adjusted IS'!$E16) | EW16: =SUMIFS('QofE DD adjustments'!I:I,'QofE DD adjustments'!$E:$E,'Adjusted IS'!$E16) | EX16: =SUMIFS('QofE DD adjustments'!J:J,'QofE DD adjustments'!$E:$E,'Adjusted IS'!$E16) | EY16: =SUMIFS('QofE DD adjustments'!K:K,'QofE DD adjustments'!$E:$E,'Adjusted IS'!$E16) | EZ16: =SUMIFS('QofE DD adjustments'!L:L,'QofE DD adjustments'!$E:$E,'Adjusted IS'!$E16) | FA16: =SUMIFS('QofE DD adjustments'!M:M,'QofE DD adjustments'!$E:$E,'Adjusted IS'!$E16) | FB16: =SUMIFS('QofE DD adjustments'!N:N,'QofE DD adjustments'!$E:$E,'Adjusted IS'!$E16) | FC16: =SUMIFS('QofE DD adjustments'!O:O,'QofE DD adjustments'!$E:$E,'Adjusted IS'!$E16) | FD16: =SUMIFS('QofE DD adjustments'!P:P,'QofE DD adjustments'!$E:$E,'Adjusted IS'!$E16) | FE16: =SUMIFS('QofE DD adjustments'!Q:Q,'QofE DD adjustments'!$E:$E,'Adjusted IS'!$E16) | FF16: =SUMIFS('QofE DD adjustments'!R:R,'QofE DD adjustments'!$E:$E,'Adjusted IS'!$E16) | FG16: =SUMIFS('QofE DD adjustments'!S:S,'QofE DD adjustments'!$E:$E,'Adjusted IS'!$E16) | FH16: =SUMIFS('QofE DD adjustments'!T:T,'QofE DD adjustments'!$E:$E,'Adjusted IS'!$E16) | FI16: =SUMIFS('QofE DD adjustments'!U:U,'QofE DD adjustments'!$E:$E,'Adjusted IS'!$E16) | FJ16: =SUMIFS('QofE DD adjustments'!V:V,'QofE DD adjustments'!$E:$E,'Adjusted IS'!$E16) | FK16: =SUMIFS('QofE DD adjustments'!W:W,'QofE DD adjustments'!$E:$E,'Adjusted IS'!$E16) | FL16: =SUMIFS('QofE DD adjustments'!X:X,'QofE DD adjustments'!$E:$E,'Adjusted IS'!$E16) | FM16: =SUMIFS('QofE DD adjustments'!Y:Y,'QofE DD adjustments'!$E:$E,'Adjusted IS'!$E16) | FN16: =SUMIFS('QofE DD adjustments'!Z:Z,'QofE DD adjustments'!$E:$E,'Adjusted IS'!$E16) | FO16: =SUMIFS('QofE DD adjustments'!AA:AA,'QofE DD adjustments'!$E:$E,'Adjusted IS'!$E16) | FP16: =SUMIFS('QofE DD adjustments'!AB:AB,'QofE DD adjustments'!$E:$E,'Adjusted IS'!$E16) | FQ16: =SUMIFS('QofE DD adjustments'!AC:AC,'QofE DD adjustments'!$E:$E,'Adjusted IS'!$E16) | FR16: =SUMIFS('QofE DD adjustments'!AD:AD,'QofE DD adjustments'!$E:$E,'Adjusted IS'!$E16) | FS16: =SUMIFS('QofE DD adjustments'!AE:AE,'QofE DD adjustments'!$E:$E,'Adjusted IS'!$E16) | FT16: =SUMIFS('QofE DD adjustments'!AF:AF,'QofE DD adjustments'!$E:$E,'Adjusted IS'!$E16) | FU16: =SUMIFS('QofE DD adjustments'!AG:AG,'QofE DD adjustments'!$E:$E,'Adjusted IS'!$E16) | FV16: =SUMIFS('QofE DD adjustments'!AH:AH,'QofE DD adjustments'!$E:$E,'Adjusted IS'!$E16) | FW16: =SUMIFS('QofE DD adjustments'!AI:AI,'QofE DD adjustments'!$E:$E,'Adjusted IS'!$E16) | FX16: =SUMIFS('QofE DD adjustments'!AJ:AJ,'QofE DD adjustments'!$E:$E,'Adjusted IS'!$E16) | FY16: =SUMIFS('QofE DD adjustments'!AK:AK,'QofE DD adjustments'!$E:$E,'Adjusted IS'!$E16) | FZ16: =SUMIFS('QofE DD adjustments'!AL:AL,'QofE DD adjustments'!$E:$E,'Adjusted IS'!$E16) | GA16: =SUMIFS('QofE DD adjustments'!AM:AM,'QofE DD adjustments'!$E:$E,'Adjusted IS'!$E16) | GB16: =SUMIFS('QofE DD adjustments'!AN:AN,'QofE DD adjustments'!$E:$E,'Adjusted IS'!$E16) | GC16: =SUMIFS('QofE DD adjustments'!AO:AO,'QofE DD adjustments'!$E:$E,'Adjusted IS'!$E16) | GD16: =SUMIFS('QofE DD adjustments'!AP:AP,'QofE DD adjustments'!$E:$E,'Adjusted IS'!$E16) | GE16: =SUMIFS('QofE DD adjustments'!AQ:AQ,'QofE DD adjustments'!$E:$E,'Adjusted IS'!$E16) | GF16: =SUMIFS('QofE DD adjustments'!AR:AR,'QofE DD adjustments'!$E:$E,'Adjusted IS'!$E16) | GG16: =SUMIFS('QofE DD adjustments'!AS:AS,'QofE DD adjustments'!$E:$E,'Adjusted IS'!$E16) | GH16: =SUMIFS('QofE DD adjustments'!AT:AT,'QofE DD adjustments'!$E:$E,'Adjusted IS'!$E16) | GI16: =SUMIFS('QofE DD adjustments'!AU:AU,'QofE DD adjustments'!$E:$E,'Adjusted IS'!$E16) | GJ16: =SUM(ET16:FE16) | GK16: =SUM(FF16:FQ16) | GL16: =SUM(FR16:GC16) | GM16: =SUM(FV16:GG16) | GN16: =SUM(FX16:GI16) | GP16: =SUM(ET16,CX16) | GQ16: =SUM(EU16,CY16) | GR16: =SUM(EV16,CZ16) | GS16: =SUM(EW16,DA16) | GT16: =SUM(EX16,DB16) | GU16: =SUM(EY16,DC16) | GV16: =SUM(EZ16,DD16) | GW16: =SUM(FA16,DE16) | ... IE16: =SUM(GI16,EM16) | IF16: =SUM(GP16:HA16) | IG16: =SUM(HB16:HM16) | IH16: =SUM(HN16:HY16) | II16: =SUM(HR16:IC16) | IJ16: =SUM(HT16:IE16) | IL16: =SUMIFS('QofE PF adjustments'!F:F,'QofE PF adjustments'!$E:$E,'Adjusted IS'!$E16) | IM16: =SUMIFS('QofE PF adjustments'!G:G,'QofE PF adjustments'!$E:$E,'Adjusted IS'!$E16) | IN16: =SUMIFS('QofE PF adjustments'!H:H,'QofE PF adjustments'!$E:$E,'Adjusted IS'!$E16) | IO16: =SUMIFS('QofE PF adjustments'!I:I,'QofE PF adjustments'!$E:$E,'Adjusted IS'!$E16) | IP16: =SUMIFS('QofE PF adjustments'!J:J,'QofE PF adjustments'!$E:$E,'Adjusted IS'!$E16) | IQ16: =SUMIFS('QofE PF adjustments'!K:K,'QofE PF adjustments'!$E:$E,'Adjusted IS'!$E16) | IR16: =SUMIFS('QofE PF adjustments'!L:L,'QofE PF adjustments'!$E:$E,'Adjusted IS'!$E16) | IS16: =SUMIFS('QofE PF adjustments'!M:M,'QofE PF adjustments'!$E:$E,'Adjusted IS'!$E16) | IT16: =SUMIFS('QofE PF adjustments'!N:N,'QofE PF adjustments'!$E:$E,'Adjusted IS'!$E16) | IU16: =SUMIFS('QofE PF adjustments'!O:O,'QofE PF adjustments'!$E:$E,'Adjusted IS'!$E16) | IV16: =SUMIFS('QofE PF adjustments'!P:P,'QofE PF adjustments'!$E:$E,'Adjusted IS'!$E16) | IW16: =SUMIFS('QofE PF adjustments'!Q:Q,'QofE PF adjustments'!$E:$E,'Adjusted IS'!$E16) | IX16: =SUMIFS('QofE PF adjustments'!R:R,'QofE PF adjustments'!$E:$E,'Adjusted IS'!$E16) | IY16: =SUMIFS('QofE PF adjustments'!S:S,'QofE PF adjustments'!$E:$E,'Adjusted IS'!$E16) | IZ16: =SUMIFS('QofE PF adjustments'!T:T,'QofE PF adjustments'!$E:$E,'Adjusted IS'!$E16) | JA16: =SUMIFS('QofE PF adjustments'!U:U,'QofE PF adjustments'!$E:$E,'Adjusted IS'!$E16) | JB16: =SUMIFS('QofE PF adjustments'!V:V,'QofE PF adjustments'!$E:$E,'Adjusted IS'!$E16) | JC16: =SUMIFS('QofE PF adjustments'!W:W,'QofE PF adjustments'!$E:$E,'Adjusted IS'!$E16) | JD16: =SUMIFS('QofE PF adjustments'!X:X,'QofE PF adjustments'!$E:$E,'Adjusted IS'!$E16) | JE16: =SUMIFS('QofE PF adjustments'!Y:Y,'QofE PF adjustments'!$E:$E,'Adjusted IS'!$E16) | JF16: =SUMIFS('QofE PF adjustments'!Z:Z,'QofE PF adjustments'!$E:$E,'Adjusted IS'!$E16) | JG16: =SUMIFS('QofE PF adjustments'!AA:AA,'QofE PF adjustments'!$E:$E,'Adjusted IS'!$E16) | JH16: =SUMIFS('QofE PF adjustments'!AB:AB,'QofE PF adjustments'!$E:$E,'Adjusted IS'!$E16) | JI16: =SUMIFS('QofE PF adjustments'!AC:AC,'QofE PF adjustments'!$E:$E,'Adjusted IS'!$E16) | JJ16: =SUMIFS('QofE PF adjustments'!AD:AD,'QofE PF adjustments'!$E:$E,'Adjusted IS'!$E16) | JK16: =SUMIFS('QofE PF adjustments'!AE:AE,'QofE PF adjustments'!$E:$E,'Adjusted IS'!$E16) | JL16: =SUMIFS('QofE PF adjustments'!AF:AF,'QofE PF adjustments'!$E:$E,'Adjusted IS'!$E16) | JM16: =SUMIFS('QofE PF adjustments'!AG:AG,'QofE PF adjustments'!$E:$E,'Adjusted IS'!$E16) | JN16: =SUMIFS('QofE PF adjustments'!AH:AH,'QofE PF adjustments'!$E:$E,'Adjusted IS'!$E16) | JO16: =SUMIFS('QofE PF adjustments'!AI:AI,'QofE PF adjustments'!$E:$E,'Adjusted IS'!$E16) | JP16: =SUMIFS('QofE PF adjustments'!AJ:AJ,'QofE PF adjustments'!$E:$E,'Adjusted IS'!$E16) | JQ16: =SUMIFS('QofE PF adjustments'!AK:AK,'QofE PF adjustments'!$E:$E,'Adjusted IS'!$E16) | JR16: =SUMIFS('QofE PF adjustments'!AL:AL,'QofE PF adjustments'!$E:$E,'Adjusted IS'!$E16) | JS16: =SUMIFS('QofE PF adjustments'!AM:AM,'QofE PF adjustments'!$E:$E,'Adjusted IS'!$E16) | JT16: =SUMIFS('QofE PF adjustments'!AN:AN,'QofE PF adjustments'!$E:$E,'Adjusted IS'!$E16) | JU16: =SUMIFS('QofE PF adjustments'!AO:AO,'QofE PF adjustments'!$E:$E,'Adjusted IS'!$E16) | JV16: =SUMIFS('QofE PF adjustments'!AP:AP,'QofE PF adjustments'!$E:$E,'Adjusted IS'!$E16) | JW16: =SUMIFS('QofE PF adjustments'!AQ:AQ,'QofE PF adjustments'!$E:$E,'Adjusted IS'!$E16) | JX16: =SUMIFS('QofE PF adjustments'!AR:AR,'QofE PF adjustments'!$E:$E,'Adjusted IS'!$E16) | JY16: =SUMIFS('QofE PF adjustments'!AS:AS,'QofE PF adjustments'!$E:$E,'Adjusted IS'!$E16) | JZ16: =SUMIFS('QofE PF adjustments'!AT:AT,'QofE PF adjustments'!$E:$E,'Adjusted IS'!$E16) | KA16: =SUMIFS('QofE PF adjustments'!AU:AU,'QofE PF adjustments'!$E:$E,'Adjusted IS'!$E16) | KB16: =SUM(IL16:IW16) | KC16: =SUM(IX16:JI16) | KD16: =SUM(JJ16:JU16) | KE16: =SUM(JN16:JY16) | KF16: =SUM(JP16:KA16) | KH16: =SUM(IL16,GP16) | KI16: =SUM(IM16,GQ16) | KJ16: =SUM(IN16,GR16) | KK16: =SUM(IO16,GS16) | KL16: =SUM(IP16,GT16) | KM16: =SUM(IQ16,GU16) | KN16: =SUM(IR16,GV16) | KO16: =SUM(IS16,GW16) | ... LW16: =SUM(KA16,IE16) | LX16: =SUM(KH16:KS16) | LY16: =SUM(KT16:LE16) | LZ16: =SUM(LF16:LQ16) | MA16: =SUM(LJ16:LU16) | MB16: =SUM(LL16:LW16) | MD16: =IFERROR(KH16/KH$117,0) | ME16: =IFERROR(KI16/KI$117,0) | MF16: =IFERROR(KJ16/KJ$117,0) | MG16: =IFERROR(KK16/KK$117,0) | MH16: =IFERROR(KL16/KL$117,0) | MI16: =IFERROR(KM16/KM$117,0) | MJ16: =IFERROR(KN16/KN$117,0) | MK16: =IFERROR(KO16/KO$117,0) | ... NX16: =IFERROR(MB16/MB$117,0) | NZ16: =LY16-LX16 | OA16: =LZ16-LY16 | OB16: =MA16-LZ16 | OC16: =MB16-LZ16 | OE16: Processing services revenue | OF16: Processing services revenue | OG16: Processing services revenue
C17: Caf revenue | D17: 411106 | E17: =CONCATENATE(D17," - ",C17) | F17: ='Income statement'!F17 | G17: ='Income statement'!G17 | H17: ='Income statement'!H17 | I17: ='Income statement'!I17 | J17: ='Income statement'!J17 | K17: ='Income statement'!K17 | L17: ='Income statement'!L17 | M17: ='Income statement'!M17 | ... AU17: ='Income statement'!AU17 | AV17: =SUM(F17:Q17) | AW17: =SUM(R17:AC17) | AX17: =SUM(AD17:AO17) | AY17: =SUM(AH17:AS17) | AZ17: =SUM(AJ17:AU17) | BB17: =SUMIFS('QofE Def adjustments'!F:F,'QofE Def adjustments'!$E:$E,'Adjusted IS'!$E17) | BC17: =SUMIFS('QofE Def adjustments'!G:G,'QofE Def adjustments'!$E:$E,'Adjusted IS'!$E17) | BD17: =SUMIFS('QofE Def adjustments'!H:H,'QofE Def adjustments'!$E:$E,'Adjusted IS'!$E17) | BE17: =SUMIFS('QofE Def adjustments'!I:I,'QofE Def adjustments'!$E:$E,'Adjusted IS'!$E17) | BF17: =SUMIFS('QofE Def adjustments'!J:J,'QofE Def adjustments'!$E:$E,'Adjusted IS'!$E17) | BG17: =SUMIFS('QofE Def adjustments'!K:K,'QofE Def adjustments'!$E:$E,'Adjusted IS'!$E17) | BH17: =SUMIFS('QofE Def adjustments'!L:L,'QofE Def adjustments'!$E:$E,'Adjusted IS'!$E17) | BI17: =SUMIFS('QofE Def adjustments'!M:M,'QofE Def adjustments'!$E:$E,'Adjusted IS'!$E17) | BJ17: =SUMIFS('QofE Def adjustments'!N:N,'QofE Def adjustments'!$E:$E,'Adjusted IS'!$E17) | BK17: =SUMIFS('QofE Def adjustments'!O:O,'QofE Def adjustments'!$E:$E,'Adjusted IS'!$E17) | BL17: =SUMIFS('QofE Def adjustments'!P:P,'QofE Def adjustments'!$E:$E,'Adjusted IS'!$E17) | BM17: =SUMIFS('QofE Def adjustments'!Q:Q,'QofE Def adjustments'!$E:$E,'Adjusted IS'!$E17) | BN17: =SUMIFS('QofE Def adjustments'!R:R,'QofE Def adjustments'!$E:$E,'Adjusted IS'!$E17) | BO17: =SUMIFS('QofE Def adjustments'!S:S,'QofE Def adjustments'!$E:$E,'Adjusted IS'!$E17) | BP17: =SUMIFS('QofE Def adjustments'!T:T,'QofE Def adjustments'!$E:$E,'Adjusted IS'!$E17) | BQ17: =SUMIFS('QofE Def adjustments'!U:U,'QofE Def adjustments'!$E:$E,'Adjusted IS'!$E17) | BR17: =SUMIFS('QofE Def adjustments'!V:V,'QofE Def adjustments'!$E:$E,'Adjusted IS'!$E17) | BS17: =SUMIFS('QofE Def adjustments'!W:W,'QofE Def adjustments'!$E:$E,'Adjusted IS'!$E17) | BT17: =SUMIFS('QofE Def adjustments'!X:X,'QofE Def adjustments'!$E:$E,'Adjusted IS'!$E17) | BU17: =SUMIFS('QofE Def adjustments'!Y:Y,'QofE Def adjustments'!$E:$E,'Adjusted IS'!$E17) | BV17: =SUMIFS('QofE Def adjustments'!Z:Z,'QofE Def adjustments'!$E:$E,'Adjusted IS'!$E17) | BW17: =SUMIFS('QofE Def adjustments'!AA:AA,'QofE Def adjustments'!$E:$E,'Adjusted IS'!$E17) | BX17: =SUMIFS('QofE Def adjustments'!AB:AB,'QofE Def adjustments'!$E:$E,'Adjusted IS'!$E17) | BY17: =SUMIFS('QofE Def adjustments'!AC:AC,'QofE Def adjustments'!$E:$E,'Adjusted IS'!$E17) | BZ17: =SUMIFS('QofE Def adjustments'!AD:AD,'QofE Def adjustments'!$E:$E,'Adjusted IS'!$E17) | CA17: =SUMIFS('QofE Def adjustments'!AE:AE,'QofE Def adjustments'!$E:$E,'Adjusted IS'!$E17) | CB17: =SUMIFS('QofE Def adjustments'!AF:AF,'QofE Def adjustments'!$E:$E,'Adjusted IS'!$E17) | CC17: =SUMIFS('QofE Def adjustments'!AG:AG,'QofE Def adjustments'!$E:$E,'Adjusted IS'!$E17) | CD17: =SUMIFS('QofE Def adjustments'!AH:AH,'QofE Def adjustments'!$E:$E,'Adjusted IS'!$E17) | CE17: =SUMIFS('QofE Def adjustments'!AI:AI,'QofE Def adjustments'!$E:$E,'Adjusted IS'!$E17) | CF17: =SUMIFS('QofE Def adjustments'!AJ:AJ,'QofE Def adjustments'!$E:$E,'Adjusted IS'!$E17) | CG17: =SUMIFS('QofE Def adjustments'!AK:AK,'QofE Def adjustments'!$E:$E,'Adjusted IS'!$E17) | CH17: =SUMIFS('QofE Def adjustments'!AL:AL,'QofE Def adjustments'!$E:$E,'Adjusted IS'!$E17) | CI17: =SUMIFS('QofE Def adjustments'!AM:AM,'QofE Def adjustments'!$E:$E,'Adjusted IS'!$E17) | CJ17: =SUMIFS('QofE Def adjustments'!AN:AN,'QofE Def adjustments'!$E:$E,'Adjusted IS'!$E17) | CK17: =SUMIFS('QofE Def adjustments'!AO:AO,'QofE Def adjustments'!$E:$E,'Adjusted IS'!$E17) | CL17: =SUMIFS('QofE Def adjustments'!AP:AP,'QofE Def adjustments'!$E:$E,'Adjusted IS'!$E17) | CM17: =SUMIFS('QofE Def adjustments'!AQ:AQ,'QofE Def adjustments'!$E:$E,'Adjusted IS'!$E17) | CN17: =SUMIFS('QofE Def adjustments'!AR:AR,'QofE Def adjustments'!$E:$E,'Adjusted IS'!$E17) | CO17: =SUMIFS('QofE Def adjustments'!AS:AS,'QofE Def adjustments'!$E:$E,'Adjusted IS'!$E17) | CP17: =SUMIFS('QofE Def adjustments'!AT:AT,'QofE Def adjustments'!$E:$E,'Adjusted IS'!$E17) | CQ17: =SUMIFS('QofE Def adjustments'!AU:AU,'QofE Def adjustments'!$E:$E,'Adjusted IS'!$E17) | CR17: =SUM(BB17:BM17) | CS17: =SUM(BN17:BY17) | CT17: =SUM(BZ17:CK17) | CU17: =SUM(CD17:CO17) | CV17: =SUM(CF17:CQ17) | CX17: =SUM(BB17,F17) | CY17: =SUM(BC17,G17) | CZ17: =SUM(BD17,H17) | DA17: =SUM(BE17,I17) | DB17: =SUM(BF17,J17) | DC17: =SUM(BG17,K17) | DD17: =SUM(BH17,L17) | DE17: =SUM(BI17,M17) | ... EM17: =SUM(CQ17,AU17) | EN17: =SUM(CX17:DI17) | EO17: =SUM(DJ17:DU17) | EP17: =SUM(DV17:EG17) | EQ17: =SUM(DZ17:EK17) | ER17: =SUM(EB17:EM17) | ET17: =SUMIFS('QofE DD adjustments'!F:F,'QofE DD adjustments'!$E:$E,'Adjusted IS'!$E17) | EU17: =SUMIFS('QofE DD adjustments'!G:G,'QofE DD adjustments'!$E:$E,'Adjusted IS'!$E17) | EV17: =SUMIFS('QofE DD adjustments'!H:H,'QofE DD adjustments'!$E:$E,'Adjusted IS'!$E17) | EW17: =SUMIFS('QofE DD adjustments'!I:I,'QofE DD adjustments'!$E:$E,'Adjusted IS'!$E17) | EX17: =SUMIFS('QofE DD adjustments'!J:J,'QofE DD adjustments'!$E:$E,'Adjusted IS'!$E17) | EY17: =SUMIFS('QofE DD adjustments'!K:K,'QofE DD adjustments'!$E:$E,'Adjusted IS'!$E17) | EZ17: =SUMIFS('QofE DD adjustments'!L:L,'QofE DD adjustments'!$E:$E,'Adjusted IS'!$E17) | FA17: =SUMIFS('QofE DD adjustments'!M:M,'QofE DD adjustments'!$E:$E,'Adjusted IS'!$E17) | FB17: =SUMIFS('QofE DD adjustments'!N:N,'QofE DD adjustments'!$E:$E,'Adjusted IS'!$E17) | FC17: =SUMIFS('QofE DD adjustments'!O:O,'QofE DD adjustments'!$E:$E,'Adjusted IS'!$E17) | FD17: =SUMIFS('QofE DD adjustments'!P:P,'QofE DD adjustments'!$E:$E,'Adjusted IS'!$E17) | FE17: =SUMIFS('QofE DD adjustments'!Q:Q,'QofE DD adjustments'!$E:$E,'Adjusted IS'!$E17) | FF17: =SUMIFS('QofE DD adjustments'!R:R,'QofE DD adjustments'!$E:$E,'Adjusted IS'!$E17) | FG17: =SUMIFS('QofE DD adjustments'!S:S,'QofE DD adjustments'!$E:$E,'Adjusted IS'!$E17) | FH17: =SUMIFS('QofE DD adjustments'!T:T,'QofE DD adjustments'!$E:$E,'Adjusted IS'!$E17) | FI17: =SUMIFS('QofE DD adjustments'!U:U,'QofE DD adjustments'!$E:$E,'Adjusted IS'!$E17) | FJ17: =SUMIFS('QofE DD adjustments'!V:V,'QofE DD adjustments'!$E:$E,'Adjusted IS'!$E17) | FK17: =SUMIFS('QofE DD adjustments'!W:W,'QofE DD adjustments'!$E:$E,'Adjusted IS'!$E17) | FL17: =SUMIFS('QofE DD adjustments'!X:X,'QofE DD adjustments'!$E:$E,'Adjusted IS'!$E17) | FM17: =SUMIFS('QofE DD adjustments'!Y:Y,'QofE DD adjustments'!$E:$E,'Adjusted IS'!$E17) | FN17: =SUMIFS('QofE DD adjustments'!Z:Z,'QofE DD adjustments'!$E:$E,'Adjusted IS'!$E17) | FO17: =SUMIFS('QofE DD adjustments'!AA:AA,'QofE DD adjustments'!$E:$E,'Adjusted IS'!$E17) | FP17: =SUMIFS('QofE DD adjustments'!AB:AB,'QofE DD adjustments'!$E:$E,'Adjusted IS'!$E17) | FQ17: =SUMIFS('QofE DD adjustments'!AC:AC,'QofE DD adjustments'!$E:$E,'Adjusted IS'!$E17) | FR17: =SUMIFS('QofE DD adjustments'!AD:AD,'QofE DD adjustments'!$E:$E,'Adjusted IS'!$E17) | FS17: =SUMIFS('QofE DD adjustments'!AE:AE,'QofE DD adjustments'!$E:$E,'Adjusted IS'!$E17) | FT17: =SUMIFS('QofE DD adjustments'!AF:AF,'QofE DD adjustments'!$E:$E,'Adjusted IS'!$E17) | FU17: =SUMIFS('QofE DD adjustments'!AG:AG,'QofE DD adjustments'!$E:$E,'Adjusted IS'!$E17) | FV17: =SUMIFS('QofE DD adjustments'!AH:AH,'QofE DD adjustments'!$E:$E,'Adjusted IS'!$E17) | FW17: =SUMIFS('QofE DD adjustments'!AI:AI,'QofE DD adjustments'!$E:$E,'Adjusted IS'!$E17) | FX17: =SUMIFS('QofE DD adjustments'!AJ:AJ,'QofE DD adjustments'!$E:$E,'Adjusted IS'!$E17) | FY17: =SUMIFS('QofE DD adjustments'!AK:AK,'QofE DD adjustments'!$E:$E,'Adjusted IS'!$E17) | FZ17: =SUMIFS('QofE DD adjustments'!AL:AL,'QofE DD adjustments'!$E:$E,'Adjusted IS'!$E17) | GA17: =SUMIFS('QofE DD adjustments'!AM:AM,'QofE DD adjustments'!$E:$E,'Adjusted IS'!$E17) | GB17: =SUMIFS('QofE DD adjustments'!AN:AN,'QofE DD adjustments'!$E:$E,'Adjusted IS'!$E17) | GC17: =SUMIFS('QofE DD adjustments'!AO:AO,'QofE DD adjustments'!$E:$E,'Adjusted IS'!$E17) | GD17: =SUMIFS('QofE DD adjustments'!AP:AP,'QofE DD adjustments'!$E:$E,'Adjusted IS'!$E17) | GE17: =SUMIFS('QofE DD adjustments'!AQ:AQ,'QofE DD adjustments'!$E:$E,'Adjusted IS'!$E17) | GF17: =SUMIFS('QofE DD adjustments'!AR:AR,'QofE DD adjustments'!$E:$E,'Adjusted IS'!$E17) | GG17: =SUMIFS('QofE DD adjustments'!AS:AS,'QofE DD adjustments'!$E:$E,'Adjusted IS'!$E17) | GH17: =SUMIFS('QofE DD adjustments'!AT:AT,'QofE DD adjustments'!$E:$E,'Adjusted IS'!$E17) | GI17: =SUMIFS('QofE DD adjustments'!AU:AU,'QofE DD adjustments'!$E:$E,'Adjusted IS'!$E17) | GJ17: =SUM(ET17:FE17) | GK17: =SUM(FF17:FQ17) | GL17: =SUM(FR17:GC17) | GM17: =SUM(FV17:GG17) | GN17: =SUM(FX17:GI17) | GP17: =SUM(ET17,CX17) | GQ17: =SUM(EU17,CY17) | GR17: =SUM(EV17,CZ17) | GS17: =SUM(EW17,DA17) | GT17: =SUM(EX17,DB17) | GU17: =SUM(EY17,DC17) | GV17: =SUM(EZ17,DD17) | GW17: =SUM(FA17,DE17) | ... IE17: =SUM(GI17,EM17) | IF17: =SUM(GP17:HA17) | IG17: =SUM(HB17:HM17) | IH17: =SUM(HN17:HY17) | II17: =SUM(HR17:IC17) | IJ17: =SUM(HT17:IE17) | IL17: =SUMIFS('QofE PF adjustments'!F:F,'QofE PF adjustments'!$E:$E,'Adjusted IS'!$E17) | IM17: =SUMIFS('QofE PF adjustments'!G:G,'QofE PF adjustments'!$E:$E,'Adjusted IS'!$E17) | IN17: =SUMIFS('QofE PF adjustments'!H:H,'QofE PF adjustments'!$E:$E,'Adjusted IS'!$E17) | IO17: =SUMIFS('QofE PF adjustments'!I:I,'QofE PF adjustments'!$E:$E,'Adjusted IS'!$E17) | IP17: =SUMIFS('QofE PF adjustments'!J:J,'QofE PF adjustments'!$E:$E,'Adjusted IS'!$E17) | IQ17: =SUMIFS('QofE PF adjustments'!K:K,'QofE PF adjustments'!$E:$E,'Adjusted IS'!$E17) | IR17: =SUMIFS('QofE PF adjustments'!L:L,'QofE PF adjustments'!$E:$E,'Adjusted IS'!$E17) | IS17: =SUMIFS('QofE PF adjustments'!M:M,'QofE PF adjustments'!$E:$E,'Adjusted IS'!$E17) | IT17: =SUMIFS('QofE PF adjustments'!N:N,'QofE PF adjustments'!$E:$E,'Adjusted IS'!$E17) | IU17: =SUMIFS('QofE PF adjustments'!O:O,'QofE PF adjustments'!$E:$E,'Adjusted IS'!$E17) | IV17: =SUMIFS('QofE PF adjustments'!P:P,'QofE PF adjustments'!$E:$E,'Adjusted IS'!$E17) | IW17: =SUMIFS('QofE PF adjustments'!Q:Q,'QofE PF adjustments'!$E:$E,'Adjusted IS'!$E17) | IX17: =SUMIFS('QofE PF adjustments'!R:R,'QofE PF adjustments'!$E:$E,'Adjusted IS'!$E17) | IY17: =SUMIFS('QofE PF adjustments'!S:S,'QofE PF adjustments'!$E:$E,'Adjusted IS'!$E17) | IZ17: =SUMIFS('QofE PF adjustments'!T:T,'QofE PF adjustments'!$E:$E,'Adjusted IS'!$E17) | JA17: =SUMIFS('QofE PF adjustments'!U:U,'QofE PF adjustments'!$E:$E,'Adjusted IS'!$E17) | JB17: =SUMIFS('QofE PF adjustments'!V:V,'QofE PF adjustments'!$E:$E,'Adjusted IS'!$E17) | JC17: =SUMIFS('QofE PF adjustments'!W:W,'QofE PF adjustments'!$E:$E,'Adjusted IS'!$E17) | JD17: =SUMIFS('QofE PF adjustments'!X:X,'QofE PF adjustments'!$E:$E,'Adjusted IS'!$E17) | JE17: =SUMIFS('QofE PF adjustments'!Y:Y,'QofE PF adjustments'!$E:$E,'Adjusted IS'!$E17) | JF17: =SUMIFS('QofE PF adjustments'!Z:Z,'QofE PF adjustments'!$E:$E,'Adjusted IS'!$E17) | JG17: =SUMIFS('QofE PF adjustments'!AA:AA,'QofE PF adjustments'!$E:$E,'Adjusted IS'!$E17) | JH17: =SUMIFS('QofE PF adjustments'!AB:AB,'QofE PF adjustments'!$E:$E,'Adjusted IS'!$E17) | JI17: =SUMIFS('QofE PF adjustments'!AC:AC,'QofE PF adjustments'!$E:$E,'Adjusted IS'!$E17) | JJ17: =SUMIFS('QofE PF adjustments'!AD:AD,'QofE PF adjustments'!$E:$E,'Adjusted IS'!$E17) | JK17: =SUMIFS('QofE PF adjustments'!AE:AE,'QofE PF adjustments'!$E:$E,'Adjusted IS'!$E17) | JL17: =SUMIFS('QofE PF adjustments'!AF:AF,'QofE PF adjustments'!$E:$E,'Adjusted IS'!$E17) | JM17: =SUMIFS('QofE PF adjustments'!AG:AG,'QofE PF adjustments'!$E:$E,'Adjusted IS'!$E17) | JN17: =SUMIFS('QofE PF adjustments'!AH:AH,'QofE PF adjustments'!$E:$E,'Adjusted IS'!$E17) | JO17: =SUMIFS('QofE PF adjustments'!AI:AI,'QofE PF adjustments'!$E:$E,'Adjusted IS'!$E17) | JP17: =SUMIFS('QofE PF adjustments'!AJ:AJ,'QofE PF adjustments'!$E:$E,'Adjusted IS'!$E17) | JQ17: =SUMIFS('QofE PF adjustments'!AK:AK,'QofE PF adjustments'!$E:$E,'Adjusted IS'!$E17) | JR17: =SUMIFS('QofE PF adjustments'!AL:AL,'QofE PF adjustments'!$E:$E,'Adjusted IS'!$E17) | JS17: =SUMIFS('QofE PF adjustments'!AM:AM,'QofE PF adjustments'!$E:$E,'Adjusted IS'!$E17) | JT17: =SUMIFS('QofE PF adjustments'!AN:AN,'QofE PF adjustments'!$E:$E,'Adjusted IS'!$E17) | JU17: =SUMIFS('QofE PF adjustments'!AO:AO,'QofE PF adjustments'!$E:$E,'Adjusted IS'!$E17) | JV17: =SUMIFS('QofE PF adjustments'!AP:AP,'QofE PF adjustments'!$E:$E,'Adjusted IS'!$E17) | JW17: =SUMIFS('QofE PF adjustments'!AQ:AQ,'QofE PF adjustments'!$E:$E,'Adjusted IS'!$E17) | JX17: =SUMIFS('QofE PF adjustments'!AR:AR,'QofE PF adjustments'!$E:$E,'Adjusted IS'!$E17) | JY17: =SUMIFS('QofE PF adjustments'!AS:AS,'QofE PF adjustments'!$E:$E,'Adjusted IS'!$E17) | JZ17: =SUMIFS('QofE PF adjustments'!AT:AT,'QofE PF adjustments'!$E:$E,'Adjusted IS'!$E17) | KA17: =SUMIFS('QofE PF adjustments'!AU:AU,'QofE PF adjustments'!$E:$E,'Adjusted IS'!$E17) | KB17: =SUM(IL17:IW17) | KC17: =SUM(IX17:JI17) | KD17: =SUM(JJ17:JU17) | KE17: =SUM(JN17:JY17) | KF17: =SUM(JP17:KA17) | KH17: =SUM(IL17,GP17) | KI17: =SUM(IM17,GQ17) | KJ17: =SUM(IN17,GR17) | KK17: =SUM(IO17,GS17) | KL17: =SUM(IP17,GT17) | KM17: =SUM(IQ17,GU17) | KN17: =SUM(IR17,GV17) | KO17: =SUM(IS17,GW17) | ... LW17: =SUM(KA17,IE17) | LX17: =SUM(KH17:KS17) | LY17: =SUM(KT17:LE17) | LZ17: =SUM(LF17:LQ17) | MA17: =SUM(LJ17:LU17) | MB17: =SUM(LL17:LW17) | MD17: =IFERROR(KH17/KH$117,0) | ME17: =IFERROR(KI17/KI$117,0) | MF17: =IFERROR(KJ17/KJ$117,0) | MG17: =IFERROR(KK17/KK$117,0) | MH17: =IFERROR(KL17/KL$117,0) | MI17: =IFERROR(KM17/KM$117,0) | MJ17: =IFERROR(KN17/KN$117,0) | MK17: =IFERROR(KO17/KO$117,0) | ... NX17: =IFERROR(MB17/MB$117,0) | NZ17: =LY17-LX17 | OA17: =LZ17-LY17 | OB17: =MA17-LZ17 | OC17: =MB17-LZ17 | OE17: Processing services revenue | OF17: Processing services revenue | OG17: Processing services revenue
C18: Reporting & other fees | D18: 411107 | E18: =CONCATENATE(D18," - ",C18) | F18: ='Income statement'!F18 | G18: ='Income statement'!G18 | H18: ='Income statement'!H18 | I18: ='Income statement'!I18 | J18: ='Income statement'!J18 | K18: ='Income statement'!K18 | L18: ='Income statement'!L18 | M18: ='Income statement'!M18 | ... AU18: ='Income statement'!AU18 | AV18: =SUM(F18:Q18) | AW18: =SUM(R18:AC18) | AX18: =SUM(AD18:AO18) | AY18: =SUM(AH18:AS18) | AZ18: =SUM(AJ18:AU18) | BB18: =SUMIFS('QofE Def adjustments'!F:F,'QofE Def adjustments'!$E:$E,'Adjusted IS'!$E18) | BC18: =SUMIFS('QofE Def adjustments'!G:G,'QofE Def adjustments'!$E:$E,'Adjusted IS'!$E18) | BD18: =SUMIFS('QofE Def adjustments'!H:H,'QofE Def adjustments'!$E:$E,'Adjusted IS'!$E18) | BE18: =SUMIFS('QofE Def adjustments'!I:I,'QofE Def adjustments'!$E:$E,'Adjusted IS'!$E18) | BF18: =SUMIFS('QofE Def adjustments'!J:J,'QofE Def adjustments'!$E:$E,'Adjusted IS'!$E18) | BG18: =SUMIFS('QofE Def adjustments'!K:K,'QofE Def adjustments'!$E:$E,'Adjusted IS'!$E18) | BH18: =SUMIFS('QofE Def adjustments'!L:L,'QofE Def adjustments'!$E:$E,'Adjusted IS'!$E18) | BI18: =SUMIFS('QofE Def adjustments'!M:M,'QofE Def adjustments'!$E:$E,'Adjusted IS'!$E18) | BJ18: =SUMIFS('QofE Def adjustments'!N:N,'QofE Def adjustments'!$E:$E,'Adjusted IS'!$E18) | BK18: =SUMIFS('QofE Def adjustments'!O:O,'QofE Def adjustments'!$E:$E,'Adjusted IS'!$E18) | BL18: =SUMIFS('QofE Def adjustments'!P:P,'QofE Def adjustments'!$E:$E,'Adjusted IS'!$E18) | BM18: =SUMIFS('QofE Def adjustments'!Q:Q,'QofE Def adjustments'!$E:$E,'Adjusted IS'!$E18) | BN18: =SUMIFS('QofE Def adjustments'!R:R,'QofE Def adjustments'!$E:$E,'Adjusted IS'!$E18) | BO18: =SUMIFS('QofE Def adjustments'!S:S,'QofE Def adjustments'!$E:$E,'Adjusted IS'!$E18) | BP18: =SUMIFS('QofE Def adjustments'!T:T,'QofE Def adjustments'!$E:$E,'Adjusted IS'!$E18) | BQ18: =SUMIFS('QofE Def adjustments'!U:U,'QofE Def adjustments'!$E:$E,'Adjusted IS'!$E18) | BR18: =SUMIFS('QofE Def adjustments'!V:V,'QofE Def adjustments'!$E:$E,'Adjusted IS'!$E18) | BS18: =SUMIFS('QofE Def adjustments'!W:W,'QofE Def adjustments'!$E:$E,'Adjusted IS'!$E18) | BT18: =SUMIFS('QofE Def adjustments'!X:X,'QofE Def adjustments'!$E:$E,'Adjusted IS'!$E18) | BU18: =SUMIFS('QofE Def adjustments'!Y:Y,'QofE Def adjustments'!$E:$E,'Adjusted IS'!$E18) | BV18: =SUMIFS('QofE Def adjustments'!Z:Z,'QofE Def adjustments'!$E:$E,'Adjusted IS'!$E18) | BW18: =SUMIFS('QofE Def adjustments'!AA:AA,'QofE Def adjustments'!$E:$E,'Adjusted IS'!$E18) | BX18: =SUMIFS('QofE Def adjustments'!AB:AB,'QofE Def adjustments'!$E:$E,'Adjusted IS'!$E18) | BY18: =SUMIFS('QofE Def adjustments'!AC:AC,'QofE Def adjustments'!$E:$E,'Adjusted IS'!$E18) | BZ18: =SUMIFS('QofE Def adjustments'!AD:AD,'QofE Def adjustments'!$E:$E,'Adjusted IS'!$E18) | CA18: =SUMIFS('QofE Def adjustments'!AE:AE,'QofE Def adjustments'!$E:$E,'Adjusted IS'!$E18) | CB18: =SUMIFS('QofE Def adjustments'!AF:AF,'QofE Def adjustments'!$E:$E,'Adjusted IS'!$E18) | CC18: =SUMIFS('QofE Def adjustments'!AG:AG,'QofE Def adjustments'!$E:$E,'Adjusted IS'!$E18) | CD18: =SUMIFS('QofE Def adjustments'!AH:AH,'QofE Def adjustments'!$E:$E,'Adjusted IS'!$E18) | CE18: =SUMIFS('QofE Def adjustments'!AI:AI,'QofE Def adjustments'!$E:$E,'Adjusted IS'!$E18) | CF18: =SUMIFS('QofE Def adjustments'!AJ:AJ,'QofE Def adjustments'!$E:$E,'Adjusted IS'!$E18) | CG18: =SUMIFS('QofE Def adjustments'!AK:AK,'QofE Def adjustments'!$E:$E,'Adjusted IS'!$E18) | CH18: =SUMIFS('QofE Def adjustments'!AL:AL,'QofE Def adjustments'!$E:$E,'Adjusted IS'!$E18) | CI18: =SUMIFS('QofE Def adjustments'!AM:AM,'QofE Def adjustments'!$E:$E,'Adjusted IS'!$E18) | CJ18: =SUMIFS('QofE Def adjustments'!AN:AN,'QofE Def adjustments'!$E:$E,'Adjusted IS'!$E18) | CK18: =SUMIFS('QofE Def adjustments'!AO:AO,'QofE Def adjustments'!$E:$E,'Adjusted IS'!$E18) | CL18: =SUMIFS('QofE Def adjustments'!AP:AP,'QofE Def adjustments'!$E:$E,'Adjusted IS'!$E18) | CM18: =SUMIFS('QofE Def adjustments'!AQ:AQ,'QofE Def adjustments'!$E:$E,'Adjusted IS'!$E18) | CN18: =SUMIFS('QofE Def adjustments'!AR:AR,'QofE Def adjustments'!$E:$E,'Adjusted IS'!$E18) | CO18: =SUMIFS('QofE Def adjustments'!AS:AS,'QofE Def adjustments'!$E:$E,'Adjusted IS'!$E18) | CP18: =SUMIFS('QofE Def adjustments'!AT:AT,'QofE Def adjustments'!$E:$E,'Adjusted IS'!$E18) | CQ18: =SUMIFS('QofE Def adjustments'!AU:AU,'QofE Def adjustments'!$E:$E,'Adjusted IS'!$E18) | CR18: =SUM(BB18:BM18) | CS18: =SUM(BN18:BY18) | CT18: =SUM(BZ18:CK18) | CU18: =SUM(CD18:CO18) | CV18: =SUM(CF18:CQ18) | CX18: =SUM(BB18,F18) | CY18: =SUM(BC18,G18) | CZ18: =SUM(BD18,H18) | DA18: =SUM(BE18,I18) | DB18: =SUM(BF18,J18) | DC18: =SUM(BG18,K18) | DD18: =SUM(BH18,L18) | DE18: =SUM(BI18,M18) | ... EM18: =SUM(CQ18,AU18) | EN18: =SUM(CX18:DI18) | EO18: =SUM(DJ18:DU18) | EP18: =SUM(DV18:EG18) | EQ18: =SUM(DZ18:EK18) | ER18: =SUM(EB18:EM18) | ET18: =SUMIFS('QofE DD adjustments'!F:F,'QofE DD adjustments'!$E:$E,'Adjusted IS'!$E18) | EU18: =SUMIFS('QofE DD adjustments'!G:G,'QofE DD adjustments'!$E:$E,'Adjusted IS'!$E18) | EV18: =SUMIFS('QofE DD adjustments'!H:H,'QofE DD adjustments'!$E:$E,'Adjusted IS'!$E18) | EW18: =SUMIFS('QofE DD adjustments'!I:I,'QofE DD adjustments'!$E:$E,'Adjusted IS'!$E18) | EX18: =SUMIFS('QofE DD adjustments'!J:J,'QofE DD adjustments'!$E:$E,'Adjusted IS'!$E18) | EY18: =SUMIFS('QofE DD adjustments'!K:K,'QofE DD adjustments'!$E:$E,'Adjusted IS'!$E18) | EZ18: =SUMIFS('QofE DD adjustments'!L:L,'QofE DD adjustments'!$E:$E,'Adjusted IS'!$E18) | FA18: =SUMIFS('QofE DD adjustments'!M:M,'QofE DD adjustments'!$E:$E,'Adjusted IS'!$E18) | FB18: =SUMIFS('QofE DD adjustments'!N:N,'QofE DD adjustments'!$E:$E,'Adjusted IS'!$E18) | FC18: =SUMIFS('QofE DD adjustments'!O:O,'QofE DD adjustments'!$E:$E,'Adjusted IS'!$E18) | FD18: =SUMIFS('QofE DD adjustments'!P:P,'QofE DD adjustments'!$E:$E,'Adjusted IS'!$E18) | FE18: =SUMIFS('QofE DD adjustments'!Q:Q,'QofE DD adjustments'!$E:$E,'Adjusted IS'!$E18) | FF18: =SUMIFS('QofE DD adjustments'!R:R,'QofE DD adjustments'!$E:$E,'Adjusted IS'!$E18) | FG18: =SUMIFS('QofE DD adjustments'!S:S,'QofE DD adjustments'!$E:$E,'Adjusted IS'!$E18) | FH18: =SUMIFS('QofE DD adjustments'!T:T,'QofE DD adjustments'!$E:$E,'Adjusted IS'!$E18) | FI18: =SUMIFS('QofE DD adjustments'!U:U,'QofE DD adjustments'!$E:$E,'Adjusted IS'!$E18) | FJ18: =SUMIFS('QofE DD adjustments'!V:V,'QofE DD adjustments'!$E:$E,'Adjusted IS'!$E18) | FK18: =SUMIFS('QofE DD adjustments'!W:W,'QofE DD adjustments'!$E:$E,'Adjusted IS'!$E18) | FL18: =SUMIFS('QofE DD adjustments'!X:X,'QofE DD adjustments'!$E:$E,'Adjusted IS'!$E18) | FM18: =SUMIFS('QofE DD adjustments'!Y:Y,'QofE DD adjustments'!$E:$E,'Adjusted IS'!$E18) | FN18: =SUMIFS('QofE DD adjustments'!Z:Z,'QofE DD adjustments'!$E:$E,'Adjusted IS'!$E18) | FO18: =SUMIFS('QofE DD adjustments'!AA:AA,'QofE DD adjustments'!$E:$E,'Adjusted IS'!$E18) | FP18: =SUMIFS('QofE DD adjustments'!AB:AB,'QofE DD adjustments'!$E:$E,'Adjusted IS'!$E18) | FQ18: =SUMIFS('QofE DD adjustments'!AC:AC,'QofE DD adjustments'!$E:$E,'Adjusted IS'!$E18) | FR18: =SUMIFS('QofE DD adjustments'!AD:AD,'QofE DD adjustments'!$E:$E,'Adjusted IS'!$E18) | FS18: =SUMIFS('QofE DD adjustments'!AE:AE,'QofE DD adjustments'!$E:$E,'Adjusted IS'!$E18) | FT18: =SUMIFS('QofE DD adjustments'!AF:AF,'QofE DD adjustments'!$E:$E,'Adjusted IS'!$E18) | FU18: =SUMIFS('QofE DD adjustments'!AG:AG,'QofE DD adjustments'!$E:$E,'Adjusted IS'!$E18) | FV18: =SUMIFS('QofE DD adjustments'!AH:AH,'QofE DD adjustments'!$E:$E,'Adjusted IS'!$E18) | FW18: =SUMIFS('QofE DD adjustments'!AI:AI,'QofE DD adjustments'!$E:$E,'Adjusted IS'!$E18) | FX18: =SUMIFS('QofE DD adjustments'!AJ:AJ,'QofE DD adjustments'!$E:$E,'Adjusted IS'!$E18) | FY18: =SUMIFS('QofE DD adjustments'!AK:AK,'QofE DD adjustments'!$E:$E,'Adjusted IS'!$E18) | FZ18: =SUMIFS('QofE DD adjustments'!AL:AL,'QofE DD adjustments'!$E:$E,'Adjusted IS'!$E18) | GA18: =SUMIFS('QofE DD adjustments'!AM:AM,'QofE DD adjustments'!$E:$E,'Adjusted IS'!$E18) | GB18: =SUMIFS('QofE DD adjustments'!AN:AN,'QofE DD adjustments'!$E:$E,'Adjusted IS'!$E18) | GC18: =SUMIFS('QofE DD adjustments'!AO:AO,'QofE DD adjustments'!$E:$E,'Adjusted IS'!$E18) | GD18: =SUMIFS('QofE DD adjustments'!AP:AP,'QofE DD adjustments'!$E:$E,'Adjusted IS'!$E18) | GE18: =SUMIFS('QofE DD adjustments'!AQ:AQ,'QofE DD adjustments'!$E:$E,'Adjusted IS'!$E18) | GF18: =SUMIFS('QofE DD adjustments'!AR:AR,'QofE DD adjustments'!$E:$E,'Adjusted IS'!$E18) | GG18: =SUMIFS('QofE DD adjustments'!AS:AS,'QofE DD adjustments'!$E:$E,'Adjusted IS'!$E18) | GH18: =SUMIFS('QofE DD adjustments'!AT:AT,'QofE DD adjustments'!$E:$E,'Adjusted IS'!$E18) | GI18: =SUMIFS('QofE DD adjustments'!AU:AU,'QofE DD adjustments'!$E:$E,'Adjusted IS'!$E18) | GJ18: =SUM(ET18:FE18) | GK18: =SUM(FF18:FQ18) | GL18: =SUM(FR18:GC18) | GM18: =SUM(FV18:GG18) | GN18: =SUM(FX18:GI18) | GP18: =SUM(ET18,CX18) | GQ18: =SUM(EU18,CY18) | GR18: =SUM(EV18,CZ18) | GS18: =SUM(EW18,DA18) | GT18: =SUM(EX18,DB18) | GU18: =SUM(EY18,DC18) | GV18: =SUM(EZ18,DD18) | GW18: =SUM(FA18,DE18) | ... IE18: =SUM(GI18,EM18) | IF18: =SUM(GP18:HA18) | IG18: =SUM(HB18:HM18) | IH18: =SUM(HN18:HY18) | II18: =SUM(HR18:IC18) | IJ18: =SUM(HT18:IE18) | IL18: =SUMIFS('QofE PF adjustments'!F:F,'QofE PF adjustments'!$E:$E,'Adjusted IS'!$E18) | IM18: =SUMIFS('QofE PF adjustments'!G:G,'QofE PF adjustments'!$E:$E,'Adjusted IS'!$E18) | IN18: =SUMIFS('QofE PF adjustments'!H:H,'QofE PF adjustments'!$E:$E,'Adjusted IS'!$E18) | IO18: =SUMIFS('QofE PF adjustments'!I:I,'QofE PF adjustments'!$E:$E,'Adjusted IS'!$E18) | IP18: =SUMIFS('QofE PF adjustments'!J:J,'QofE PF adjustments'!$E:$E,'Adjusted IS'!$E18) | IQ18: =SUMIFS('QofE PF adjustments'!K:K,'QofE PF adjustments'!$E:$E,'Adjusted IS'!$E18) | IR18: =SUMIFS('QofE PF adjustments'!L:L,'QofE PF adjustments'!$E:$E,'Adjusted IS'!$E18) | IS18: =SUMIFS('QofE PF adjustments'!M:M,'QofE PF adjustments'!$E:$E,'Adjusted IS'!$E18) | IT18: =SUMIFS('QofE PF adjustments'!N:N,'QofE PF adjustments'!$E:$E,'Adjusted IS'!$E18) | IU18: =SUMIFS('QofE PF adjustments'!O:O,'QofE PF adjustments'!$E:$E,'Adjusted IS'!$E18) | IV18: =SUMIFS('QofE PF adjustments'!P:P,'QofE PF adjustments'!$E:$E,'Adjusted IS'!$E18) | IW18: =SUMIFS('QofE PF adjustments'!Q:Q,'QofE PF adjustments'!$E:$E,'Adjusted IS'!$E18) | IX18: =SUMIFS('QofE PF adjustments'!R:R,'QofE PF adjustments'!$E:$E,'Adjusted IS'!$E18) | IY18: =SUMIFS('QofE PF adjustments'!S:S,'QofE PF adjustments'!$E:$E,'Adjusted IS'!$E18) | IZ18: =SUMIFS('QofE PF adjustments'!T:T,'QofE PF adjustments'!$E:$E,'Adjusted IS'!$E18) | JA18: =SUMIFS('QofE PF adjustments'!U:U,'QofE PF adjustments'!$E:$E,'Adjusted IS'!$E18) | JB18: =SUMIFS('QofE PF adjustments'!V:V,'QofE PF adjustments'!$E:$E,'Adjusted IS'!$E18) | JC18: =SUMIFS('QofE PF adjustments'!W:W,'QofE PF adjustments'!$E:$E,'Adjusted IS'!$E18) | JD18: =SUMIFS('QofE PF adjustments'!X:X,'QofE PF adjustments'!$E:$E,'Adjusted IS'!$E18) | JE18: =SUMIFS('QofE PF adjustments'!Y:Y,'QofE PF adjustments'!$E:$E,'Adjusted IS'!$E18) | JF18: =SUMIFS('QofE PF adjustments'!Z:Z,'QofE PF adjustments'!$E:$E,'Adjusted IS'!$E18) | JG18: =SUMIFS('QofE PF adjustments'!AA:AA,'QofE PF adjustments'!$E:$E,'Adjusted IS'!$E18) | JH18: =SUMIFS('QofE PF adjustments'!AB:AB,'QofE PF adjustments'!$E:$E,'Adjusted IS'!$E18) | JI18: =SUMIFS('QofE PF adjustments'!AC:AC,'QofE PF adjustments'!$E:$E,'Adjusted IS'!$E18) | JJ18: =SUMIFS('QofE PF adjustments'!AD:AD,'QofE PF adjustments'!$E:$E,'Adjusted IS'!$E18) | JK18: =SUMIFS('QofE PF adjustments'!AE:AE,'QofE PF adjustments'!$E:$E,'Adjusted IS'!$E18) | JL18: =SUMIFS('QofE PF adjustments'!AF:AF,'QofE PF adjustments'!$E:$E,'Adjusted IS'!$E18) | JM18: =SUMIFS('QofE PF adjustments'!AG:AG,'QofE PF adjustments'!$E:$E,'Adjusted IS'!$E18) | JN18: =SUMIFS('QofE PF adjustments'!AH:AH,'QofE PF adjustments'!$E:$E,'Adjusted IS'!$E18) | JO18: =SUMIFS('QofE PF adjustments'!AI:AI,'QofE PF adjustments'!$E:$E,'Adjusted IS'!$E18) | JP18: =SUMIFS('QofE PF adjustments'!AJ:AJ,'QofE PF adjustments'!$E:$E,'Adjusted IS'!$E18) | JQ18: =SUMIFS('QofE PF adjustments'!AK:AK,'QofE PF adjustments'!$E:$E,'Adjusted IS'!$E18) | JR18: =SUMIFS('QofE PF adjustments'!AL:AL,'QofE PF adjustments'!$E:$E,'Adjusted IS'!$E18) | JS18: =SUMIFS('QofE PF adjustments'!AM:AM,'QofE PF adjustments'!$E:$E,'Adjusted IS'!$E18) | JT18: =SUMIFS('QofE PF adjustments'!AN:AN,'QofE PF adjustments'!$E:$E,'Adjusted IS'!$E18) | JU18: =SUMIFS('QofE PF adjustments'!AO:AO,'QofE PF adjustments'!$E:$E,'Adjusted IS'!$E18) | JV18: =SUMIFS('QofE PF adjustments'!AP:AP,'QofE PF adjustments'!$E:$E,'Adjusted IS'!$E18) | JW18: =SUMIFS('QofE PF adjustments'!AQ:AQ,'QofE PF adjustments'!$E:$E,'Adjusted IS'!$E18) | JX18: =SUMIFS('QofE PF adjustments'!AR:AR,'QofE PF adjustments'!$E:$E,'Adjusted IS'!$E18) | JY18: =SUMIFS('QofE PF adjustments'!AS:AS,'QofE PF adjustments'!$E:$E,'Adjusted IS'!$E18) | JZ18: =SUMIFS('QofE PF adjustments'!AT:AT,'QofE PF adjustments'!$E:$E,'Adjusted IS'!$E18) | KA18: =SUMIFS('QofE PF adjustments'!AU:AU,'QofE PF adjustments'!$E:$E,'Adjusted IS'!$E18) | KB18: =SUM(IL18:IW18) | KC18: =SUM(IX18:JI18) | KD18: =SUM(JJ18:JU18) | KE18: =SUM(JN18:JY18) | KF18: =SUM(JP18:KA18) | KH18: =SUM(IL18,GP18) | KI18: =SUM(IM18,GQ18) | KJ18: =SUM(IN18,GR18) | KK18: =SUM(IO18,GS18) | KL18: =SUM(IP18,GT18) | KM18: =SUM(IQ18,GU18) | KN18: =SUM(IR18,GV18) | KO18: =SUM(IS18,GW18) | ... LW18: =SUM(KA18,IE18) | LX18: =SUM(KH18:KS18) | LY18: =SUM(KT18:LE18) | LZ18: =SUM(LF18:LQ18) | MA18: =SUM(LJ18:LU18) | MB18: =SUM(LL18:LW18) | MD18: =IFERROR(KH18/KH$117,0) | ME18: =IFERROR(KI18/KI$117,0) | MF18: =IFERROR(KJ18/KJ$117,0) | MG18: =IFERROR(KK18/KK$117,0) | MH18: =IFERROR(KL18/KL$117,0) | MI18: =IFERROR(KM18/KM$117,0) | MJ18: =IFERROR(KN18/KN$117,0) | MK18: =IFERROR(KO18/KO$117,0) | ... NX18: =IFERROR(MB18/MB$117,0) | NZ18: =LY18-LX18 | OA18: =LZ18-LY18 | OB18: =MA18-LZ18 | OC18: =MB18-LZ18 | OE18: Processing services revenue | OF18: Processing services revenue | OG18: Processing services revenue
C19: Host connection revenue | D19: 411114 | E19: =CONCATENATE(D19," - ",C19) | F19: ='Income statement'!F19 | G19: ='Income statement'!G19 | H19: ='Income statement'!H19 | I19: ='Income statement'!I19 | J19: ='Income statement'!J19 | K19: ='Income statement'!K19 | L19: ='Income statement'!L19 | M19: ='Income statement'!M19 | ... AU19: ='Income statement'!AU19 | AV19: =SUM(F19:Q19) | AW19: =SUM(R19:AC19) | AX19: =SUM(AD19:AO19) | AY19: =SUM(AH19:AS19) | AZ19: =SUM(AJ19:AU19) | BB19: =SUMIFS('QofE Def adjustments'!F:F,'QofE Def adjustments'!$E:$E,'Adjusted IS'!$E19) | BC19: =SUMIFS('QofE Def adjustments'!G:G,'QofE Def adjustments'!$E:$E,'Adjusted IS'!$E19) | BD19: =SUMIFS('QofE Def adjustments'!H:H,'QofE Def adjustments'!$E:$E,'Adjusted IS'!$E19) | BE19: =SUMIFS('QofE Def adjustments'!I:I,'QofE Def adjustments'!$E:$E,'Adjusted IS'!$E19) | BF19: =SUMIFS('QofE Def adjustments'!J:J,'QofE Def adjustments'!$E:$E,'Adjusted IS'!$E19) | BG19: =SUMIFS('QofE Def adjustments'!K:K,'QofE Def adjustments'!$E:$E,'Adjusted IS'!$E19) | BH19: =SUMIFS('QofE Def adjustments'!L:L,'QofE Def adjustments'!$E:$E,'Adjusted IS'!$E19) | BI19: =SUMIFS('QofE Def adjustments'!M:M,'QofE Def adjustments'!$E:$E,'Adjusted IS'!$E19) | BJ19: =SUMIFS('QofE Def adjustments'!N:N,'QofE Def adjustments'!$E:$E,'Adjusted IS'!$E19) | BK19: =SUMIFS('QofE Def adjustments'!O:O,'QofE Def adjustments'!$E:$E,'Adjusted IS'!$E19) | BL19: =SUMIFS('QofE Def adjustments'!P:P,'QofE Def adjustments'!$E:$E,'Adjusted IS'!$E19) | BM19: =SUMIFS('QofE Def adjustments'!Q:Q,'QofE Def adjustments'!$E:$E,'Adjusted IS'!$E19) | BN19: =SUMIFS('QofE Def adjustments'!R:R,'QofE Def adjustments'!$E:$E,'Adjusted IS'!$E19) | BO19: =SUMIFS('QofE Def adjustments'!S:S,'QofE Def adjustments'!$E:$E,'Adjusted IS'!$E19) | BP19: =SUMIFS('QofE Def adjustments'!T:T,'QofE Def adjustments'!$E:$E,'Adjusted IS'!$E19) | BQ19: =SUMIFS('QofE Def adjustments'!U:U,'QofE Def adjustments'!$E:$E,'Adjusted IS'!$E19) | BR19: =SUMIFS('QofE Def adjustments'!V:V,'QofE Def adjustments'!$E:$E,'Adjusted IS'!$E19) | BS19: =SUMIFS('QofE Def adjustments'!W:W,'QofE Def adjustments'!$E:$E,'Adjusted IS'!$E19) | BT19: =SUMIFS('QofE Def adjustments'!X:X,'QofE Def adjustments'!$E:$E,'Adjusted IS'!$E19) | BU19: =SUMIFS('QofE Def adjustments'!Y:Y,'QofE Def adjustments'!$E:$E,'Adjusted IS'!$E19) | BV19: =SUMIFS('QofE Def adjustments'!Z:Z,'QofE Def adjustments'!$E:$E,'Adjusted IS'!$E19) | BW19: =SUMIFS('QofE Def adjustments'!AA:AA,'QofE Def adjustments'!$E:$E,'Adjusted IS'!$E19) | BX19: =SUMIFS('QofE Def adjustments'!AB:AB,'QofE Def adjustments'!$E:$E,'Adjusted IS'!$E19) | BY19: =SUMIFS('QofE Def adjustments'!AC:AC,'QofE Def adjustments'!$E:$E,'Adjusted IS'!$E19) | BZ19: =SUMIFS('QofE Def adjustments'!AD:AD,'QofE Def adjustments'!$E:$E,'Adjusted IS'!$E19) | CA19: =SUMIFS('QofE Def adjustments'!AE:AE,'QofE Def adjustments'!$E:$E,'Adjusted IS'!$E19) | CB19: =SUMIFS('QofE Def adjustments'!AF:AF,'QofE Def adjustments'!$E:$E,'Adjusted IS'!$E19) | CC19: =SUMIFS('QofE Def adjustments'!AG:AG,'QofE Def adjustments'!$E:$E,'Adjusted IS'!$E19) | CD19: =SUMIFS('QofE Def adjustments'!AH:AH,'QofE Def adjustments'!$E:$E,'Adjusted IS'!$E19) | CE19: =SUMIFS('QofE Def adjustments'!AI:AI,'QofE Def adjustments'!$E:$E,'Adjusted IS'!$E19) | CF19: =SUMIFS('QofE Def adjustments'!AJ:AJ,'QofE Def adjustments'!$E:$E,'Adjusted IS'!$E19) | CG19: =SUMIFS('QofE Def adjustments'!AK:AK,'QofE Def adjustments'!$E:$E,'Adjusted IS'!$E19) | CH19: =SUMIFS('QofE Def adjustments'!AL:AL,'QofE Def adjustments'!$E:$E,'Adjusted IS'!$E19) | CI19: =SUMIFS('QofE Def adjustments'!AM:AM,'QofE Def adjustments'!$E:$E,'Adjusted IS'!$E19) | CJ19: =SUMIFS('QofE Def adjustments'!AN:AN,'QofE Def adjustments'!$E:$E,'Adjusted IS'!$E19) | CK19: =SUMIFS('QofE Def adjustments'!AO:AO,'QofE Def adjustments'!$E:$E,'Adjusted IS'!$E19) | CL19: =SUMIFS('QofE Def adjustments'!AP:AP,'QofE Def adjustments'!$E:$E,'Adjusted IS'!$E19) | CM19: =SUMIFS('QofE Def adjustments'!AQ:AQ,'QofE Def adjustments'!$E:$E,'Adjusted IS'!$E19) | CN19: =SUMIFS('QofE Def adjustments'!AR:AR,'QofE Def adjustments'!$E:$E,'Adjusted IS'!$E19) | CO19: =SUMIFS('QofE Def adjustments'!AS:AS,'QofE Def adjustments'!$E:$E,'Adjusted IS'!$E19) | CP19: =SUMIFS('QofE Def adjustments'!AT:AT,'QofE Def adjustments'!$E:$E,'Adjusted IS'!$E19) | CQ19: =SUMIFS('QofE Def adjustments'!AU:AU,'QofE Def adjustments'!$E:$E,'Adjusted IS'!$E19) | CR19: =SUM(BB19:BM19) | CS19: =SUM(BN19:BY19) | CT19: =SUM(BZ19:CK19) | CU19: =SUM(CD19:CO19) | CV19: =SUM(CF19:CQ19) | CX19: =SUM(BB19,F19) | CY19: =SUM(BC19,G19) | CZ19: =SUM(BD19,H19) | DA19: =SUM(BE19,I19) | DB19: =SUM(BF19,J19) | DC19: =SUM(BG19,K19) | DD19: =SUM(BH19,L19) | DE19: =SUM(BI19,M19) | ... EM19: =SUM(CQ19,AU19) | EN19: =SUM(CX19:DI19) | EO19: =SUM(DJ19:DU19) | EP19: =SUM(DV19:EG19) | EQ19: =SUM(DZ19:EK19) | ER19: =SUM(EB19:EM19) | ET19: =SUMIFS('QofE DD adjustments'!F:F,'QofE DD adjustments'!$E:$E,'Adjusted IS'!$E19) | EU19: =SUMIFS('QofE DD adjustments'!G:G,'QofE DD adjustments'!$E:$E,'Adjusted IS'!$E19) | EV19: =SUMIFS('QofE DD adjustments'!H:H,'QofE DD adjustments'!$E:$E,'Adjusted IS'!$E19) | EW19: =SUMIFS('QofE DD adjustments'!I:I,'QofE DD adjustments'!$E:$E,'Adjusted IS'!$E19) | EX19: =SUMIFS('QofE DD adjustments'!J:J,'QofE DD adjustments'!$E:$E,'Adjusted IS'!$E19) | EY19: =SUMIFS('QofE DD adjustments'!K:K,'QofE DD adjustments'!$E:$E,'Adjusted IS'!$E19) | EZ19: =SUMIFS('QofE DD adjustments'!L:L,'QofE DD adjustments'!$E:$E,'Adjusted IS'!$E19) | FA19: =SUMIFS('QofE DD adjustments'!M:M,'QofE DD adjustments'!$E:$E,'Adjusted IS'!$E19) | FB19: =SUMIFS('QofE DD adjustments'!N:N,'QofE DD adjustments'!$E:$E,'Adjusted IS'!$E19) | FC19: =SUMIFS('QofE DD adjustments'!O:O,'QofE DD adjustments'!$E:$E,'Adjusted IS'!$E19) | FD19: =SUMIFS('QofE DD adjustments'!P:P,'QofE DD adjustments'!$E:$E,'Adjusted IS'!$E19) | FE19: =SUMIFS('QofE DD adjustments'!Q:Q,'QofE DD adjustments'!$E:$E,'Adjusted IS'!$E19) | FF19: =SUMIFS('QofE DD adjustments'!R:R,'QofE DD adjustments'!$E:$E,'Adjusted IS'!$E19) | FG19: =SUMIFS('QofE DD adjustments'!S:S,'QofE DD adjustments'!$E:$E,'Adjusted IS'!$E19) | FH19: =SUMIFS('QofE DD adjustments'!T:T,'QofE DD adjustments'!$E:$E,'Adjusted IS'!$E19) | FI19: =SUMIFS('QofE DD adjustments'!U:U,'QofE DD adjustments'!$E:$E,'Adjusted IS'!$E19) | FJ19: =SUMIFS('QofE DD adjustments'!V:V,'QofE DD adjustments'!$E:$E,'Adjusted IS'!$E19) | FK19: =SUMIFS('QofE DD adjustments'!W:W,'QofE DD adjustments'!$E:$E,'Adjusted IS'!$E19) | FL19: =SUMIFS('QofE DD adjustments'!X:X,'QofE DD adjustments'!$E:$E,'Adjusted IS'!$E19) | FM19: =SUMIFS('QofE DD adjustments'!Y:Y,'QofE DD adjustments'!$E:$E,'Adjusted IS'!$E19) | FN19: =SUMIFS('QofE DD adjustments'!Z:Z,'QofE DD adjustments'!$E:$E,'Adjusted IS'!$E19) | FO19: =SUMIFS('QofE DD adjustments'!AA:AA,'QofE DD adjustments'!$E:$E,'Adjusted IS'!$E19) | FP19: =SUMIFS('QofE DD adjustments'!AB:AB,'QofE DD adjustments'!$E:$E,'Adjusted IS'!$E19) | FQ19: =SUMIFS('QofE DD adjustments'!AC:AC,'QofE DD adjustments'!$E:$E,'Adjusted IS'!$E19) | FR19: =SUMIFS('QofE DD adjustments'!AD:AD,'QofE DD adjustments'!$E:$E,'Adjusted IS'!$E19) | FS19: =SUMIFS('QofE DD adjustments'!AE:AE,'QofE DD adjustments'!$E:$E,'Adjusted IS'!$E19) | FT19: =SUMIFS('QofE DD adjustments'!AF:AF,'QofE DD adjustments'!$E:$E,'Adjusted IS'!$E19) | FU19: =SUMIFS('QofE DD adjustments'!AG:AG,'QofE DD adjustments'!$E:$E,'Adjusted IS'!$E19) | FV19: =SUMIFS('QofE DD adjustments'!AH:AH,'QofE DD adjustments'!$E:$E,'Adjusted IS'!$E19) | FW19: =SUMIFS('QofE DD adjustments'!AI:AI,'QofE DD adjustments'!$E:$E,'Adjusted IS'!$E19) | FX19: =SUMIFS('QofE DD adjustments'!AJ:AJ,'QofE DD adjustments'!$E:$E,'Adjusted IS'!$E19) | FY19: =SUMIFS('QofE DD adjustments'!AK:AK,'QofE DD adjustments'!$E:$E,'Adjusted IS'!$E19) | FZ19: =SUMIFS('QofE DD adjustments'!AL:AL,'QofE DD adjustments'!$E:$E,'Adjusted IS'!$E19) | GA19: =SUMIFS('QofE DD adjustments'!AM:AM,'QofE DD adjustments'!$E:$E,'Adjusted IS'!$E19) | GB19: =SUMIFS('QofE DD adjustments'!AN:AN,'QofE DD adjustments'!$E:$E,'Adjusted IS'!$E19) | GC19: =SUMIFS('QofE DD adjustments'!AO:AO,'QofE DD adjustments'!$E:$E,'Adjusted IS'!$E19) | GD19: =SUMIFS('QofE DD adjustments'!AP:AP,'QofE DD adjustments'!$E:$E,'Adjusted IS'!$E19) | GE19: =SUMIFS('QofE DD adjustments'!AQ:AQ,'QofE DD adjustments'!$E:$E,'Adjusted IS'!$E19) | GF19: =SUMIFS('QofE DD adjustments'!AR:AR,'QofE DD adjustments'!$E:$E,'Adjusted IS'!$E19) | GG19: =SUMIFS('QofE DD adjustments'!AS:AS,'QofE DD adjustments'!$E:$E,'Adjusted IS'!$E19) | GH19: =SUMIFS('QofE DD adjustments'!AT:AT,'QofE DD adjustments'!$E:$E,'Adjusted IS'!$E19) | GI19: =SUMIFS('QofE DD adjustments'!AU:AU,'QofE DD adjustments'!$E:$E,'Adjusted IS'!$E19) | GJ19: =SUM(ET19:FE19) | GK19: =SUM(FF19:FQ19) | GL19: =SUM(FR19:GC19) | GM19: =SUM(FV19:GG19) | GN19: =SUM(FX19:GI19) | GP19: =SUM(ET19,CX19) | GQ19: =SUM(EU19,CY19) | GR19: =SUM(EV19,CZ19) | GS19: =SUM(EW19,DA19) | GT19: =SUM(EX19,DB19) | GU19: =SUM(EY19,DC19) | GV19: =SUM(EZ19,DD19) | GW19: =SUM(FA19,DE19) | ... IE19: =SUM(GI19,EM19) | IF19: =SUM(GP19:HA19) | IG19: =SUM(HB19:HM19) | IH19: =SUM(HN19:HY19) | II19: =SUM(HR19:IC19) | IJ19: =SUM(HT19:IE19) | IL19: =SUMIFS('QofE PF adjustments'!F:F,'QofE PF adjustments'!$E:$E,'Adjusted IS'!$E19) | IM19: =SUMIFS('QofE PF adjustments'!G:G,'QofE PF adjustments'!$E:$E,'Adjusted IS'!$E19) | IN19: =SUMIFS('QofE PF adjustments'!H:H,'QofE PF adjustments'!$E:$E,'Adjusted IS'!$E19) | IO19: =SUMIFS('QofE PF adjustments'!I:I,'QofE PF adjustments'!$E:$E,'Adjusted IS'!$E19) | IP19: =SUMIFS('QofE PF adjustments'!J:J,'QofE PF adjustments'!$E:$E,'Adjusted IS'!$E19) | IQ19: =SUMIFS('QofE PF adjustments'!K:K,'QofE PF adjustments'!$E:$E,'Adjusted IS'!$E19) | IR19: =SUMIFS('QofE PF adjustments'!L:L,'QofE PF adjustments'!$E:$E,'Adjusted IS'!$E19) | IS19: =SUMIFS('QofE PF adjustments'!M:M,'QofE PF adjustments'!$E:$E,'Adjusted IS'!$E19) | IT19: =SUMIFS('QofE PF adjustments'!N:N,'QofE PF adjustments'!$E:$E,'Adjusted IS'!$E19) | IU19: =SUMIFS('QofE PF adjustments'!O:O,'QofE PF adjustments'!$E:$E,'Adjusted IS'!$E19) | IV19: =SUMIFS('QofE PF adjustments'!P:P,'QofE PF adjustments'!$E:$E,'Adjusted IS'!$E19) | IW19: =SUMIFS('QofE PF adjustments'!Q:Q,'QofE PF adjustments'!$E:$E,'Adjusted IS'!$E19) | IX19: =SUMIFS('QofE PF adjustments'!R:R,'QofE PF adjustments'!$E:$E,'Adjusted IS'!$E19) | IY19: =SUMIFS('QofE PF adjustments'!S:S,'QofE PF adjustments'!$E:$E,'Adjusted IS'!$E19) | IZ19: =SUMIFS('QofE PF adjustments'!T:T,'QofE PF adjustments'!$E:$E,'Adjusted IS'!$E19) | JA19: =SUMIFS('QofE PF adjustments'!U:U,'QofE PF adjustments'!$E:$E,'Adjusted IS'!$E19) | JB19: =SUMIFS('QofE PF adjustments'!V:V,'QofE PF adjustments'!$E:$E,'Adjusted IS'!$E19) | JC19: =SUMIFS('QofE PF adjustments'!W:W,'QofE PF adjustments'!$E:$E,'Adjusted IS'!$E19) | JD19: =SUMIFS('QofE PF adjustments'!X:X,'QofE PF adjustments'!$E:$E,'Adjusted IS'!$E19) | JE19: =SUMIFS('QofE PF adjustments'!Y:Y,'QofE PF adjustments'!$E:$E,'Adjusted IS'!$E19) | JF19: =SUMIFS('QofE PF adjustments'!Z:Z,'QofE PF adjustments'!$E:$E,'Adjusted IS'!$E19) | JG19: =SUMIFS('QofE PF adjustments'!AA:AA,'QofE PF adjustments'!$E:$E,'Adjusted IS'!$E19) | JH19: =SUMIFS('QofE PF adjustments'!AB:AB,'QofE PF adjustments'!$E:$E,'Adjusted IS'!$E19) | JI19: =SUMIFS('QofE PF adjustments'!AC:AC,'QofE PF adjustments'!$E:$E,'Adjusted IS'!$E19) | JJ19: =SUMIFS('QofE PF adjustments'!AD:AD,'QofE PF adjustments'!$E:$E,'Adjusted IS'!$E19) | JK19: =SUMIFS('QofE PF adjustments'!AE:AE,'QofE PF adjustments'!$E:$E,'Adjusted IS'!$E19) | JL19: =SUMIFS('QofE PF adjustments'!AF:AF,'QofE PF adjustments'!$E:$E,'Adjusted IS'!$E19) | JM19: =SUMIFS('QofE PF adjustments'!AG:AG,'QofE PF adjustments'!$E:$E,'Adjusted IS'!$E19) | JN19: =SUMIFS('QofE PF adjustments'!AH:AH,'QofE PF adjustments'!$E:$E,'Adjusted IS'!$E19) | JO19: =SUMIFS('QofE PF adjustments'!AI:AI,'QofE PF adjustments'!$E:$E,'Adjusted IS'!$E19) | JP19: =SUMIFS('QofE PF adjustments'!AJ:AJ,'QofE PF adjustments'!$E:$E,'Adjusted IS'!$E19) | JQ19: =SUMIFS('QofE PF adjustments'!AK:AK,'QofE PF adjustments'!$E:$E,'Adjusted IS'!$E19) | JR19: =SUMIFS('QofE PF adjustments'!AL:AL,'QofE PF adjustments'!$E:$E,'Adjusted IS'!$E19) | JS19: =SUMIFS('QofE PF adjustments'!AM:AM,'QofE PF adjustments'!$E:$E,'Adjusted IS'!$E19) | JT19: =SUMIFS('QofE PF adjustments'!AN:AN,'QofE PF adjustments'!$E:$E,'Adjusted IS'!$E19) | JU19: =SUMIFS('QofE PF adjustments'!AO:AO,'QofE PF adjustments'!$E:$E,'Adjusted IS'!$E19) | JV19: =SUMIFS('QofE PF adjustments'!AP:AP,'QofE PF adjustments'!$E:$E,'Adjusted IS'!$E19) | JW19: =SUMIFS('QofE PF adjustments'!AQ:AQ,'QofE PF adjustments'!$E:$E,'Adjusted IS'!$E19) | JX19: =SUMIFS('QofE PF adjustments'!AR:AR,'QofE PF adjustments'!$E:$E,'Adjusted IS'!$E19) | JY19: =SUMIFS('QofE PF adjustments'!AS:AS,'QofE PF adjustments'!$E:$E,'Adjusted IS'!$E19) | JZ19: =SUMIFS('QofE PF adjustments'!AT:AT,'QofE PF adjustments'!$E:$E,'Adjusted IS'!$E19) | KA19: =SUMIFS('QofE PF adjustments'!AU:AU,'QofE PF adjustments'!$E:$E,'Adjusted IS'!$E19) | KB19: =SUM(IL19:IW19) | KC19: =SUM(IX19:JI19) | KD19: =SUM(JJ19:JU19) | KE19: =SUM(JN19:JY19) | KF19: =SUM(JP19:KA19) | KH19: =SUM(IL19,GP19) | KI19: =SUM(IM19,GQ19) | KJ19: =SUM(IN19,GR19) | KK19: =SUM(IO19,GS19) | KL19: =SUM(IP19,GT19) | KM19: =SUM(IQ19,GU19) | KN19: =SUM(IR19,GV19) | KO19: =SUM(IS19,GW19) | ... LW19: =SUM(KA19,IE19) | LX19: =SUM(KH19:KS19) | LY19: =SUM(KT19:LE19) | LZ19: =SUM(LF19:LQ19) | MA19: =SUM(LJ19:LU19) | MB19: =SUM(LL19:LW19) | MD19: =IFERROR(KH19/KH$117,0) | ME19: =IFERROR(KI19/KI$117,0) | MF19: =IFERROR(KJ19/KJ$117,0) | MG19: =IFERROR(KK19/KK$117,0) | MH19: =IFERROR(KL19/KL$117,0) | MI19: =IFERROR(KM19/KM$117,0) | MJ19: =IFERROR(KN19/KN$117,0) | MK19: =IFERROR(KO19/KO$117,0) | ... NX19: =IFERROR(MB19/MB$117,0) | NZ19: =LY19-LX19 | OA19: =LZ19-LY19 | OB19: =MA19-LZ19 | OC19: =MB19-LZ19 | OE19: Processing services revenue | OF19: Processing services revenue | OG19: Processing services revenue
C20: Merchant services credit transaction revenue | D20: 411104 | E20: =CONCATENATE(D20," - ",C20) | F20: ='Income statement'!F20 | G20: ='Income statement'!G20 | H20: ='Income statement'!H20 | I20: ='Income statement'!I20 | J20: ='Income statement'!J20 | K20: ='Income statement'!K20 | L20: ='Income statement'!L20 | M20: ='Income statement'!M20 | ... AU20: ='Income statement'!AU20 | AV20: =SUM(F20:Q20) | AW20: =SUM(R20:AC20) | AX20: =SUM(AD20:AO20) | AY20: =SUM(AH20:AS20) | AZ20: =SUM(AJ20:AU20) | BB20: =SUMIFS('QofE Def adjustments'!F:F,'QofE Def adjustments'!$E:$E,'Adjusted IS'!$E20) | BC20: =SUMIFS('QofE Def adjustments'!G:G,'QofE Def adjustments'!$E:$E,'Adjusted IS'!$E20) | BD20: =SUMIFS('QofE Def adjustments'!H:H,'QofE Def adjustments'!$E:$E,'Adjusted IS'!$E20) | BE20: =SUMIFS('QofE Def adjustments'!I:I,'QofE Def adjustments'!$E:$E,'Adjusted IS'!$E20) | BF20: =SUMIFS('QofE Def adjustments'!J:J,'QofE Def adjustments'!$E:$E,'Adjusted IS'!$E20) | BG20: =SUMIFS('QofE Def adjustments'!K:K,'QofE Def adjustments'!$E:$E,'Adjusted IS'!$E20) | BH20: =SUMIFS('QofE Def adjustments'!L:L,'QofE Def adjustments'!$E:$E,'Adjusted IS'!$E20) | BI20: =SUMIFS('QofE Def adjustments'!M:M,'QofE Def adjustments'!$E:$E,'Adjusted IS'!$E20) | BJ20: =SUMIFS('QofE Def adjustments'!N:N,'QofE Def adjustments'!$E:$E,'Adjusted IS'!$E20) | BK20: =SUMIFS('QofE Def adjustments'!O:O,'QofE Def adjustments'!$E:$E,'Adjusted IS'!$E20) | BL20: =SUMIFS('QofE Def adjustments'!P:P,'QofE Def adjustments'!$E:$E,'Adjusted IS'!$E20) | BM20: =SUMIFS('QofE Def adjustments'!Q:Q,'QofE Def adjustments'!$E:$E,'Adjusted IS'!$E20) | BN20: =SUMIFS('QofE Def adjustments'!R:R,'QofE Def adjustments'!$E:$E,'Adjusted IS'!$E20) | BO20: =SUMIFS('QofE Def adjustments'!S:S,'QofE Def adjustments'!$E:$E,'Adjusted IS'!$E20) | BP20: =SUMIFS('QofE Def adjustments'!T:T,'QofE Def adjustments'!$E:$E,'Adjusted IS'!$E20) | BQ20: =SUMIFS('QofE Def adjustments'!U:U,'QofE Def adjustments'!$E:$E,'Adjusted IS'!$E20) | BR20: =SUMIFS('QofE Def adjustments'!V:V,'QofE Def adjustments'!$E:$E,'Adjusted IS'!$E20) | BS20: =SUMIFS('QofE Def adjustments'!W:W,'QofE Def adjustments'!$E:$E,'Adjusted IS'!$E20) | BT20: =SUMIFS('QofE Def adjustments'!X:X,'QofE Def adjustments'!$E:$E,'Adjusted IS'!$E20) | BU20: =SUMIFS('QofE Def adjustments'!Y:Y,'QofE Def adjustments'!$E:$E,'Adjusted IS'!$E20) | BV20: =SUMIFS('QofE Def adjustments'!Z:Z,'QofE Def adjustments'!$E:$E,'Adjusted IS'!$E20) | BW20: =SUMIFS('QofE Def adjustments'!AA:AA,'QofE Def adjustments'!$E:$E,'Adjusted IS'!$E20) | BX20: =SUMIFS('QofE Def adjustments'!AB:AB,'QofE Def adjustments'!$E:$E,'Adjusted IS'!$E20) | BY20: =SUMIFS('QofE Def adjustments'!AC:AC,'QofE Def adjustments'!$E:$E,'Adjusted IS'!$E20) | BZ20: =SUMIFS('QofE Def adjustments'!AD:AD,'QofE Def adjustments'!$E:$E,'Adjusted IS'!$E20) | CA20: =SUMIFS('QofE Def adjustments'!AE:AE,'QofE Def adjustments'!$E:$E,'Adjusted IS'!$E20) | CB20: =SUMIFS('QofE Def adjustments'!AF:AF,'QofE Def adjustments'!$E:$E,'Adjusted IS'!$E20) | CC20: =SUMIFS('QofE Def adjustments'!AG:AG,'QofE Def adjustments'!$E:$E,'Adjusted IS'!$E20) | CD20: =SUMIFS('QofE Def adjustments'!AH:AH,'QofE Def adjustments'!$E:$E,'Adjusted IS'!$E20) | CE20: =SUMIFS('QofE Def adjustments'!AI:AI,'QofE Def adjustments'!$E:$E,'Adjusted IS'!$E20) | CF20: =SUMIFS('QofE Def adjustments'!AJ:AJ,'QofE Def adjustments'!$E:$E,'Adjusted IS'!$E20) | CG20: =SUMIFS('QofE Def adjustments'!AK:AK,'QofE Def adjustments'!$E:$E,'Adjusted IS'!$E20) | CH20: =SUMIFS('QofE Def adjustments'!AL:AL,'QofE Def adjustments'!$E:$E,'Adjusted IS'!$E20) | CI20: =SUMIFS('QofE Def adjustments'!AM:AM,'QofE Def adjustments'!$E:$E,'Adjusted IS'!$E20) | CJ20: =SUMIFS('QofE Def adjustments'!AN:AN,'QofE Def adjustments'!$E:$E,'Adjusted IS'!$E20) | CK20: =SUMIFS('QofE Def adjustments'!AO:AO,'QofE Def adjustments'!$E:$E,'Adjusted IS'!$E20) | CL20: =SUMIFS('QofE Def adjustments'!AP:AP,'QofE Def adjustments'!$E:$E,'Adjusted IS'!$E20) | CM20: =SUMIFS('QofE Def adjustments'!AQ:AQ,'QofE Def adjustments'!$E:$E,'Adjusted IS'!$E20) | CN20: =SUMIFS('QofE Def adjustments'!AR:AR,'QofE Def adjustments'!$E:$E,'Adjusted IS'!$E20) | CO20: =SUMIFS('QofE Def adjustments'!AS:AS,'QofE Def adjustments'!$E:$E,'Adjusted IS'!$E20) | CP20: =SUMIFS('QofE Def adjustments'!AT:AT,'QofE Def adjustments'!$E:$E,'Adjusted IS'!$E20) | CQ20: =SUMIFS('QofE Def adjustments'!AU:AU,'QofE Def adjustments'!$E:$E,'Adjusted IS'!$E20) | CR20: =SUM(BB20:BM20) | CS20: =SUM(BN20:BY20) | CT20: =SUM(BZ20:CK20) | CU20: =SUM(CD20:CO20) | CV20: =SUM(CF20:CQ20) | CX20: =SUM(BB20,F20) | CY20: =SUM(BC20,G20) | CZ20: =SUM(BD20,H20) | DA20: =SUM(BE20,I20) | DB20: =SUM(BF20,J20) | DC20: =SUM(BG20,K20) | DD20: =SUM(BH20,L20) | DE20: =SUM(BI20,M20) | ... EM20: =SUM(CQ20,AU20) | EN20: =SUM(CX20:DI20) | EO20: =SUM(DJ20:DU20) | EP20: =SUM(DV20:EG20) | EQ20: =SUM(DZ20:EK20) | ER20: =SUM(EB20:EM20) | ET20: =SUMIFS('QofE DD adjustments'!F:F,'QofE DD adjustments'!$E:$E,'Adjusted IS'!$E20) | EU20: =SUMIFS('QofE DD adjustments'!G:G,'QofE DD adjustments'!$E:$E,'Adjusted IS'!$E20) | EV20: =SUMIFS('QofE DD adjustments'!H:H,'QofE DD adjustments'!$E:$E,'Adjusted IS'!$E20) | EW20: =SUMIFS('QofE DD adjustments'!I:I,'QofE DD adjustments'!$E:$E,'Adjusted IS'!$E20) | EX20: =SUMIFS('QofE DD adjustments'!J:J,'QofE DD adjustments'!$E:$E,'Adjusted IS'!$E20) | EY20: =SUMIFS('QofE DD adjustments'!K:K,'QofE DD adjustments'!$E:$E,'Adjusted IS'!$E20) | EZ20: =SUMIFS('QofE DD adjustments'!L:L,'QofE DD adjustments'!$E:$E,'Adjusted IS'!$E20) | FA20: =SUMIFS('QofE DD adjustments'!M:M,'QofE DD adjustments'!$E:$E,'Adjusted IS'!$E20) | FB20: =SUMIFS('QofE DD adjustments'!N:N,'QofE DD adjustments'!$E:$E,'Adjusted IS'!$E20) | FC20: =SUMIFS('QofE DD adjustments'!O:O,'QofE DD adjustments'!$E:$E,'Adjusted IS'!$E20) | FD20: =SUMIFS('QofE DD adjustments'!P:P,'QofE DD adjustments'!$E:$E,'Adjusted IS'!$E20) | FE20: =SUMIFS('QofE DD adjustments'!Q:Q,'QofE DD adjustments'!$E:$E,'Adjusted IS'!$E20) | FF20: =SUMIFS('QofE DD adjustments'!R:R,'QofE DD adjustments'!$E:$E,'Adjusted IS'!$E20) | FG20: =SUMIFS('QofE DD adjustments'!S:S,'QofE DD adjustments'!$E:$E,'Adjusted IS'!$E20) | FH20: =SUMIFS('QofE DD adjustments'!T:T,'QofE DD adjustments'!$E:$E,'Adjusted IS'!$E20) | FI20: =SUMIFS('QofE DD adjustments'!U:U,'QofE DD adjustments'!$E:$E,'Adjusted IS'!$E20) | FJ20: =SUMIFS('QofE DD adjustments'!V:V,'QofE DD adjustments'!$E:$E,'Adjusted IS'!$E20) | FK20: =SUMIFS('QofE DD adjustments'!W:W,'QofE DD adjustments'!$E:$E,'Adjusted IS'!$E20) | FL20: =SUMIFS('QofE DD adjustments'!X:X,'QofE DD adjustments'!$E:$E,'Adjusted IS'!$E20) | FM20: =SUMIFS('QofE DD adjustments'!Y:Y,'QofE DD adjustments'!$E:$E,'Adjusted IS'!$E20) | FN20: =SUMIFS('QofE DD adjustments'!Z:Z,'QofE DD adjustments'!$E:$E,'Adjusted IS'!$E20) | FO20: =SUMIFS('QofE DD adjustments'!AA:AA,'QofE DD adjustments'!$E:$E,'Adjusted IS'!$E20) | FP20: =SUMIFS('QofE DD adjustments'!AB:AB,'QofE DD adjustments'!$E:$E,'Adjusted IS'!$E20) | FQ20: =SUMIFS('QofE DD adjustments'!AC:AC,'QofE DD adjustments'!$E:$E,'Adjusted IS'!$E20) | FR20: =SUMIFS('QofE DD adjustments'!AD:AD,'QofE DD adjustments'!$E:$E,'Adjusted IS'!$E20) | FS20: =SUMIFS('QofE DD adjustments'!AE:AE,'QofE DD adjustments'!$E:$E,'Adjusted IS'!$E20) | FT20: =SUMIFS('QofE DD adjustments'!AF:AF,'QofE DD adjustments'!$E:$E,'Adjusted IS'!$E20) | FU20: =SUMIFS('QofE DD adjustments'!AG:AG,'QofE DD adjustments'!$E:$E,'Adjusted IS'!$E20) | FV20: =SUMIFS('QofE DD adjustments'!AH:AH,'QofE DD adjustments'!$E:$E,'Adjusted IS'!$E20) | FW20: =SUMIFS('QofE DD adjustments'!AI:AI,'QofE DD adjustments'!$E:$E,'Adjusted IS'!$E20) | FX20: =SUMIFS('QofE DD adjustments'!AJ:AJ,'QofE DD adjustments'!$E:$E,'Adjusted IS'!$E20) | FY20: =SUMIFS('QofE DD adjustments'!AK:AK,'QofE DD adjustments'!$E:$E,'Adjusted IS'!$E20) | FZ20: =SUMIFS('QofE DD adjustments'!AL:AL,'QofE DD adjustments'!$E:$E,'Adjusted IS'!$E20) | GA20: =SUMIFS('QofE DD adjustments'!AM:AM,'QofE DD adjustments'!$E:$E,'Adjusted IS'!$E20) | GB20: =SUMIFS('QofE DD adjustments'!AN:AN,'QofE DD adjustments'!$E:$E,'Adjusted IS'!$E20) | GC20: =SUMIFS('QofE DD adjustments'!AO:AO,'QofE DD adjustments'!$E:$E,'Adjusted IS'!$E20) | GD20: =SUMIFS('QofE DD adjustments'!AP:AP,'QofE DD adjustments'!$E:$E,'Adjusted IS'!$E20) | GE20: =SUMIFS('QofE DD adjustments'!AQ:AQ,'QofE DD adjustments'!$E:$E,'Adjusted IS'!$E20) | GF20: =SUMIFS('QofE DD adjustments'!AR:AR,'QofE DD adjustments'!$E:$E,'Adjusted IS'!$E20) | GG20: =SUMIFS('QofE DD adjustments'!AS:AS,'QofE DD adjustments'!$E:$E,'Adjusted IS'!$E20) | GH20: =SUMIFS('QofE DD adjustments'!AT:AT,'QofE DD adjustments'!$E:$E,'Adjusted IS'!$E20) | GI20: =SUMIFS('QofE DD adjustments'!AU:AU,'QofE DD adjustments'!$E:$E,'Adjusted IS'!$E20) | GJ20: =SUM(ET20:FE20) | GK20: =SUM(FF20:FQ20) | GL20: =SUM(FR20:GC20) | GM20: =SUM(FV20:GG20) | GN20: =SUM(FX20:GI20) | GP20: =SUM(ET20,CX20) | GQ20: =SUM(EU20,CY20) | GR20: =SUM(EV20,CZ20) | GS20: =SUM(EW20,DA20) | GT20: =SUM(EX20,DB20) | GU20: =SUM(EY20,DC20) | GV20: =SUM(EZ20,DD20) | GW20: =SUM(FA20,DE20) | ... IE20: =SUM(GI20,EM20) | IF20: =SUM(GP20:HA20) | IG20: =SUM(HB20:HM20) | IH20: =SUM(HN20:HY20) | II20: =SUM(HR20:IC20) | IJ20: =SUM(HT20:IE20) | IL20: =SUMIFS('QofE PF adjustments'!F:F,'QofE PF adjustments'!$E:$E,'Adjusted IS'!$E20) | IM20: =SUMIFS('QofE PF adjustments'!G:G,'QofE PF adjustments'!$E:$E,'Adjusted IS'!$E20) | IN20: =SUMIFS('QofE PF adjustments'!H:H,'QofE PF adjustments'!$E:$E,'Adjusted IS'!$E20) | IO20: =SUMIFS('QofE PF adjustments'!I:I,'QofE PF adjustments'!$E:$E,'Adjusted IS'!$E20) | IP20: =SUMIFS('QofE PF adjustments'!J:J,'QofE PF adjustments'!$E:$E,'Adjusted IS'!$E20) | IQ20: =SUMIFS('QofE PF adjustments'!K:K,'QofE PF adjustments'!$E:$E,'Adjusted IS'!$E20) | IR20: =SUMIFS('QofE PF adjustments'!L:L,'QofE PF adjustments'!$E:$E,'Adjusted IS'!$E20) | IS20: =SUMIFS('QofE PF adjustments'!M:M,'QofE PF adjustments'!$E:$E,'Adjusted IS'!$E20) | IT20: =SUMIFS('QofE PF adjustments'!N:N,'QofE PF adjustments'!$E:$E,'Adjusted IS'!$E20) | IU20: =SUMIFS('QofE PF adjustments'!O:O,'QofE PF adjustments'!$E:$E,'Adjusted IS'!$E20) | IV20: =SUMIFS('QofE PF adjustments'!P:P,'QofE PF adjustments'!$E:$E,'Adjusted IS'!$E20) | IW20: =SUMIFS('QofE PF adjustments'!Q:Q,'QofE PF adjustments'!$E:$E,'Adjusted IS'!$E20) | IX20: =SUMIFS('QofE PF adjustments'!R:R,'QofE PF adjustments'!$E:$E,'Adjusted IS'!$E20) | IY20: =SUMIFS('QofE PF adjustments'!S:S,'QofE PF adjustments'!$E:$E,'Adjusted IS'!$E20) | IZ20: =SUMIFS('QofE PF adjustments'!T:T,'QofE PF adjustments'!$E:$E,'Adjusted IS'!$E20) | JA20: =SUMIFS('QofE PF adjustments'!U:U,'QofE PF adjustments'!$E:$E,'Adjusted IS'!$E20) | JB20: =SUMIFS('QofE PF adjustments'!V:V,'QofE PF adjustments'!$E:$E,'Adjusted IS'!$E20) | JC20: =SUMIFS('QofE PF adjustments'!W:W,'QofE PF adjustments'!$E:$E,'Adjusted IS'!$E20) | JD20: =SUMIFS('QofE PF adjustments'!X:X,'QofE PF adjustments'!$E:$E,'Adjusted IS'!$E20) | JE20: =SUMIFS('QofE PF adjustments'!Y:Y,'QofE PF adjustments'!$E:$E,'Adjusted IS'!$E20) | JF20: =SUMIFS('QofE PF adjustments'!Z:Z,'QofE PF adjustments'!$E:$E,'Adjusted IS'!$E20) | JG20: =SUMIFS('QofE PF adjustments'!AA:AA,'QofE PF adjustments'!$E:$E,'Adjusted IS'!$E20) | JH20: =SUMIFS('QofE PF adjustments'!AB:AB,'QofE PF adjustments'!$E:$E,'Adjusted IS'!$E20) | JI20: =SUMIFS('QofE PF adjustments'!AC:AC,'QofE PF adjustments'!$E:$E,'Adjusted IS'!$E20) | JJ20: =SUMIFS('QofE PF adjustments'!AD:AD,'QofE PF adjustments'!$E:$E,'Adjusted IS'!$E20) | JK20: =SUMIFS('QofE PF adjustments'!AE:AE,'QofE PF adjustments'!$E:$E,'Adjusted IS'!$E20) | JL20: =SUMIFS('QofE PF adjustments'!AF:AF,'QofE PF adjustments'!$E:$E,'Adjusted IS'!$E20) | JM20: =SUMIFS('QofE PF adjustments'!AG:AG,'QofE PF adjustments'!$E:$E,'Adjusted IS'!$E20) | JN20: =SUMIFS('QofE PF adjustments'!AH:AH,'QofE PF adjustments'!$E:$E,'Adjusted IS'!$E20) | JO20: =SUMIFS('QofE PF adjustments'!AI:AI,'QofE PF adjustments'!$E:$E,'Adjusted IS'!$E20) | JP20: =SUMIFS('QofE PF adjustments'!AJ:AJ,'QofE PF adjustments'!$E:$E,'Adjusted IS'!$E20) | JQ20: =SUMIFS('QofE PF adjustments'!AK:AK,'QofE PF adjustments'!$E:$E,'Adjusted IS'!$E20) | JR20: =SUMIFS('QofE PF adjustments'!AL:AL,'QofE PF adjustments'!$E:$E,'Adjusted IS'!$E20) | JS20: =SUMIFS('QofE PF adjustments'!AM:AM,'QofE PF adjustments'!$E:$E,'Adjusted IS'!$E20) | JT20: =SUMIFS('QofE PF adjustments'!AN:AN,'QofE PF adjustments'!$E:$E,'Adjusted IS'!$E20) | JU20: =SUMIFS('QofE PF adjustments'!AO:AO,'QofE PF adjustments'!$E:$E,'Adjusted IS'!$E20) | JV20: =SUMIFS('QofE PF adjustments'!AP:AP,'QofE PF adjustments'!$E:$E,'Adjusted IS'!$E20) | JW20: =SUMIFS('QofE PF adjustments'!AQ:AQ,'QofE PF adjustments'!$E:$E,'Adjusted IS'!$E20) | JX20: =SUMIFS('QofE PF adjustments'!AR:AR,'QofE PF adjustments'!$E:$E,'Adjusted IS'!$E20) | JY20: =SUMIFS('QofE PF adjustments'!AS:AS,'QofE PF adjustments'!$E:$E,'Adjusted IS'!$E20) | JZ20: =SUMIFS('QofE PF adjustments'!AT:AT,'QofE PF adjustments'!$E:$E,'Adjusted IS'!$E20) | KA20: =SUMIFS('QofE PF adjustments'!AU:AU,'QofE PF adjustments'!$E:$E,'Adjusted IS'!$E20) | KB20: =SUM(IL20:IW20) | KC20: =SUM(IX20:JI20) | KD20: =SUM(JJ20:JU20) | KE20: =SUM(JN20:JY20) | KF20: =SUM(JP20:KA20) | KH20: =SUM(IL20,GP20) | KI20: =SUM(IM20,GQ20) | KJ20: =SUM(IN20,GR20) | KK20: =SUM(IO20,GS20) | KL20: =SUM(IP20,GT20) | KM20: =SUM(IQ20,GU20) | KN20: =SUM(IR20,GV20) | KO20: =SUM(IS20,GW20) | ... LW20: =SUM(KA20,IE20) | LX20: =SUM(KH20:KS20) | LY20: =SUM(KT20:LE20) | LZ20: =SUM(LF20:LQ20) | MA20: =SUM(LJ20:LU20) | MB20: =SUM(LL20:LW20) | MD20: =IFERROR(KH20/KH$117,0) | ME20: =IFERROR(KI20/KI$117,0) | MF20: =IFERROR(KJ20/KJ$117,0) | MG20: =IFERROR(KK20/KK$117,0) | MH20: =IFERROR(KL20/KL$117,0) | MI20: =IFERROR(KM20/KM$117,0) | MJ20: =IFERROR(KN20/KN$117,0) | MK20: =IFERROR(KO20/KO$117,0) | ... NX20: =IFERROR(MB20/MB$117,0) | NZ20: =LY20-LX20 | OA20: =LZ20-LY20 | OB20: =MA20-LZ20 | OC20: =MB20-LZ20 | OE20: Processing services revenue | OF20: Processing services revenue | OG20: Processing services revenue
C21: E hub money transfer | D21: 411102 | E21: =CONCATENATE(D21," - ",C21) | F21: ='Income statement'!F21 | G21: ='Income statement'!G21 | H21: ='Income statement'!H21 | I21: ='Income statement'!I21 | J21: ='Income statement'!J21 | K21: ='Income statement'!K21 | L21: ='Income statement'!L21 | M21: ='Income statement'!M21 | ... AU21: ='Income statement'!AU21 | AV21: =SUM(F21:Q21) | AW21: =SUM(R21:AC21) | AX21: =SUM(AD21:AO21) | AY21: =SUM(AH21:AS21) | AZ21: =SUM(AJ21:AU21) | BB21: =SUMIFS('QofE Def adjustments'!F:F,'QofE Def adjustments'!$E:$E,'Adjusted IS'!$E21) | BC21: =SUMIFS('QofE Def adjustments'!G:G,'QofE Def adjustments'!$E:$E,'Adjusted IS'!$E21) | BD21: =SUMIFS('QofE Def adjustments'!H:H,'QofE Def adjustments'!$E:$E,'Adjusted IS'!$E21) | BE21: =SUMIFS('QofE Def adjustments'!I:I,'QofE Def adjustments'!$E:$E,'Adjusted IS'!$E21) | BF21: =SUMIFS('QofE Def adjustments'!J:J,'QofE Def adjustments'!$E:$E,'Adjusted IS'!$E21) | BG21: =SUMIFS('QofE Def adjustments'!K:K,'QofE Def adjustments'!$E:$E,'Adjusted IS'!$E21) | BH21: =SUMIFS('QofE Def adjustments'!L:L,'QofE Def adjustments'!$E:$E,'Adjusted IS'!$E21) | BI21: =SUMIFS('QofE Def adjustments'!M:M,'QofE Def adjustments'!$E:$E,'Adjusted IS'!$E21) | BJ21: =SUMIFS('QofE Def adjustments'!N:N,'QofE Def adjustments'!$E:$E,'Adjusted IS'!$E21) | BK21: =SUMIFS('QofE Def adjustments'!O:O,'QofE Def adjustments'!$E:$E,'Adjusted IS'!$E21) | BL21: =SUMIFS('QofE Def adjustments'!P:P,'QofE Def adjustments'!$E:$E,'Adjusted IS'!$E21) | BM21: =SUMIFS('QofE Def adjustments'!Q:Q,'QofE Def adjustments'!$E:$E,'Adjusted IS'!$E21) | BN21: =SUMIFS('QofE Def adjustments'!R:R,'QofE Def adjustments'!$E:$E,'Adjusted IS'!$E21) | BO21: =SUMIFS('QofE Def adjustments'!S:S,'QofE Def adjustments'!$E:$E,'Adjusted IS'!$E21) | BP21: =SUMIFS('QofE Def adjustments'!T:T,'QofE Def adjustments'!$E:$E,'Adjusted IS'!$E21) | BQ21: =SUMIFS('QofE Def adjustments'!U:U,'QofE Def adjustments'!$E:$E,'Adjusted IS'!$E21) | BR21: =SUMIFS('QofE Def adjustments'!V:V,'QofE Def adjustments'!$E:$E,'Adjusted IS'!$E21) | BS21: =SUMIFS('QofE Def adjustments'!W:W,'QofE Def adjustments'!$E:$E,'Adjusted IS'!$E21) | BT21: =SUMIFS('QofE Def adjustments'!X:X,'QofE Def adjustments'!$E:$E,'Adjusted IS'!$E21) | BU21: =SUMIFS('QofE Def adjustments'!Y:Y,'QofE Def adjustments'!$E:$E,'Adjusted IS'!$E21) | BV21: =SUMIFS('QofE Def adjustments'!Z:Z,'QofE Def adjustments'!$E:$E,'Adjusted IS'!$E21) | BW21: =SUMIFS('QofE Def adjustments'!AA:AA,'QofE Def adjustments'!$E:$E,'Adjusted IS'!$E21) | BX21: =SUMIFS('QofE Def adjustments'!AB:AB,'QofE Def adjustments'!$E:$E,'Adjusted IS'!$E21) | BY21: =SUMIFS('QofE Def adjustments'!AC:AC,'QofE Def adjustments'!$E:$E,'Adjusted IS'!$E21) | BZ21: =SUMIFS('QofE Def adjustments'!AD:AD,'QofE Def adjustments'!$E:$E,'Adjusted IS'!$E21) | CA21: =SUMIFS('QofE Def adjustments'!AE:AE,'QofE Def adjustments'!$E:$E,'Adjusted IS'!$E21) | CB21: =SUMIFS('QofE Def adjustments'!AF:AF,'QofE Def adjustments'!$E:$E,'Adjusted IS'!$E21) | CC21: =SUMIFS('QofE Def adjustments'!AG:AG,'QofE Def adjustments'!$E:$E,'Adjusted IS'!$E21) | CD21: =SUMIFS('QofE Def adjustments'!AH:AH,'QofE Def adjustments'!$E:$E,'Adjusted IS'!$E21) | CE21: =SUMIFS('QofE Def adjustments'!AI:AI,'QofE Def adjustments'!$E:$E,'Adjusted IS'!$E21) | CF21: =SUMIFS('QofE Def adjustments'!AJ:AJ,'QofE Def adjustments'!$E:$E,'Adjusted IS'!$E21) | CG21: =SUMIFS('QofE Def adjustments'!AK:AK,'QofE Def adjustments'!$E:$E,'Adjusted IS'!$E21) | CH21: =SUMIFS('QofE Def adjustments'!AL:AL,'QofE Def adjustments'!$E:$E,'Adjusted IS'!$E21) | CI21: =SUMIFS('QofE Def adjustments'!AM:AM,'QofE Def adjustments'!$E:$E,'Adjusted IS'!$E21) | CJ21: =SUMIFS('QofE Def adjustments'!AN:AN,'QofE Def adjustments'!$E:$E,'Adjusted IS'!$E21) | CK21: =SUMIFS('QofE Def adjustments'!AO:AO,'QofE Def adjustments'!$E:$E,'Adjusted IS'!$E21) | CL21: =SUMIFS('QofE Def adjustments'!AP:AP,'QofE Def adjustments'!$E:$E,'Adjusted IS'!$E21) | CM21: =SUMIFS('QofE Def adjustments'!AQ:AQ,'QofE Def adjustments'!$E:$E,'Adjusted IS'!$E21) | CN21: =SUMIFS('QofE Def adjustments'!AR:AR,'QofE Def adjustments'!$E:$E,'Adjusted IS'!$E21) | CO21: =SUMIFS('QofE Def adjustments'!AS:AS,'QofE Def adjustments'!$E:$E,'Adjusted IS'!$E21) | CP21: =SUMIFS('QofE Def adjustments'!AT:AT,'QofE Def adjustments'!$E:$E,'Adjusted IS'!$E21) | CQ21: =SUMIFS('QofE Def adjustments'!AU:AU,'QofE Def adjustments'!$E:$E,'Adjusted IS'!$E21) | CR21: =SUM(BB21:BM21) | CS21: =SUM(BN21:BY21) | CT21: =SUM(BZ21:CK21) | CU21: =SUM(CD21:CO21) | CV21: =SUM(CF21:CQ21) | CX21: =SUM(BB21,F21) | CY21: =SUM(BC21,G21) | CZ21: =SUM(BD21,H21) | DA21: =SUM(BE21,I21) | DB21: =SUM(BF21,J21) | DC21: =SUM(BG21,K21) | DD21: =SUM(BH21,L21) | DE21: =SUM(BI21,M21) | ... EM21: =SUM(CQ21,AU21) | EN21: =SUM(CX21:DI21) | EO21: =SUM(DJ21:DU21) | EP21: =SUM(DV21:EG21) | EQ21: =SUM(DZ21:EK21) | ER21: =SUM(EB21:EM21) | ET21: =SUMIFS('QofE DD adjustments'!F:F,'QofE DD adjustments'!$E:$E,'Adjusted IS'!$E21) | EU21: =SUMIFS('QofE DD adjustments'!G:G,'QofE DD adjustments'!$E:$E,'Adjusted IS'!$E21) | EV21: =SUMIFS('QofE DD adjustments'!H:H,'QofE DD adjustments'!$E:$E,'Adjusted IS'!$E21) | EW21: =SUMIFS('QofE DD adjustments'!I:I,'QofE DD adjustments'!$E:$E,'Adjusted IS'!$E21) | EX21: =SUMIFS('QofE DD adjustments'!J:J,'QofE DD adjustments'!$E:$E,'Adjusted IS'!$E21) | EY21: =SUMIFS('QofE DD adjustments'!K:K,'QofE DD adjustments'!$E:$E,'Adjusted IS'!$E21) | EZ21: =SUMIFS('QofE DD adjustments'!L:L,'QofE DD adjustments'!$E:$E,'Adjusted IS'!$E21) | FA21: =SUMIFS('QofE DD adjustments'!M:M,'QofE DD adjustments'!$E:$E,'Adjusted IS'!$E21) | FB21: =SUMIFS('QofE DD adjustments'!N:N,'QofE DD adjustments'!$E:$E,'Adjusted IS'!$E21) | FC21: =SUMIFS('QofE DD adjustments'!O:O,'QofE DD adjustments'!$E:$E,'Adjusted IS'!$E21) | FD21: =SUMIFS('QofE DD adjustments'!P:P,'QofE DD adjustments'!$E:$E,'Adjusted IS'!$E21) | FE21: =SUMIFS('QofE DD adjustments'!Q:Q,'QofE DD adjustments'!$E:$E,'Adjusted IS'!$E21) | FF21: =SUMIFS('QofE DD adjustments'!R:R,'QofE DD adjustments'!$E:$E,'Adjusted IS'!$E21) | FG21: =SUMIFS('QofE DD adjustments'!S:S,'QofE DD adjustments'!$E:$E,'Adjusted IS'!$E21) | FH21: =SUMIFS('QofE DD adjustments'!T:T,'QofE DD adjustments'!$E:$E,'Adjusted IS'!$E21) | FI21: =SUMIFS('QofE DD adjustments'!U:U,'QofE DD adjustments'!$E:$E,'Adjusted IS'!$E21) | FJ21: =SUMIFS('QofE DD adjustments'!V:V,'QofE DD adjustments'!$E:$E,'Adjusted IS'!$E21) | FK21: =SUMIFS('QofE DD adjustments'!W:W,'QofE DD adjustments'!$E:$E,'Adjusted IS'!$E21) | FL21: =SUMIFS('QofE DD adjustments'!X:X,'QofE DD adjustments'!$E:$E,'Adjusted IS'!$E21) | FM21: =SUMIFS('QofE DD adjustments'!Y:Y,'QofE DD adjustments'!$E:$E,'Adjusted IS'!$E21) | FN21: =SUMIFS('QofE DD adjustments'!Z:Z,'QofE DD adjustments'!$E:$E,'Adjusted IS'!$E21) | FO21: =SUMIFS('QofE DD adjustments'!AA:AA,'QofE DD adjustments'!$E:$E,'Adjusted IS'!$E21) | FP21: =SUMIFS('QofE DD adjustments'!AB:AB,'QofE DD adjustments'!$E:$E,'Adjusted IS'!$E21) | FQ21: =SUMIFS('QofE DD adjustments'!AC:AC,'QofE DD adjustments'!$E:$E,'Adjusted IS'!$E21) | FR21: =SUMIFS('QofE DD adjustments'!AD:AD,'QofE DD adjustments'!$E:$E,'Adjusted IS'!$E21) | FS21: =SUMIFS('QofE DD adjustments'!AE:AE,'QofE DD adjustments'!$E:$E,'Adjusted IS'!$E21) | FT21: =SUMIFS('QofE DD adjustments'!AF:AF,'QofE DD adjustments'!$E:$E,'Adjusted IS'!$E21) | FU21: =SUMIFS('QofE DD adjustments'!AG:AG,'QofE DD adjustments'!$E:$E,'Adjusted IS'!$E21) | FV21: =SUMIFS('QofE DD adjustments'!AH:AH,'QofE DD adjustments'!$E:$E,'Adjusted IS'!$E21) | FW21: =SUMIFS('QofE DD adjustments'!AI:AI,'QofE DD adjustments'!$E:$E,'Adjusted IS'!$E21) | FX21: =SUMIFS('QofE DD adjustments'!AJ:AJ,'QofE DD adjustments'!$E:$E,'Adjusted IS'!$E21) | FY21: =SUMIFS('QofE DD adjustments'!AK:AK,'QofE DD adjustments'!$E:$E,'Adjusted IS'!$E21) | FZ21: =SUMIFS('QofE DD adjustments'!AL:AL,'QofE DD adjustments'!$E:$E,'Adjusted IS'!$E21) | GA21: =SUMIFS('QofE DD adjustments'!AM:AM,'QofE DD adjustments'!$E:$E,'Adjusted IS'!$E21) | GB21: =SUMIFS('QofE DD adjustments'!AN:AN,'QofE DD adjustments'!$E:$E,'Adjusted IS'!$E21) | GC21: =SUMIFS('QofE DD adjustments'!AO:AO,'QofE DD adjustments'!$E:$E,'Adjusted IS'!$E21) | GD21: =SUMIFS('QofE DD adjustments'!AP:AP,'QofE DD adjustments'!$E:$E,'Adjusted IS'!$E21) | GE21: =SUMIFS('QofE DD adjustments'!AQ:AQ,'QofE DD adjustments'!$E:$E,'Adjusted IS'!$E21) | GF21: =SUMIFS('QofE DD adjustments'!AR:AR,'QofE DD adjustments'!$E:$E,'Adjusted IS'!$E21) | GG21: =SUMIFS('QofE DD adjustments'!AS:AS,'QofE DD adjustments'!$E:$E,'Adjusted IS'!$E21) | GH21: =SUMIFS('QofE DD adjustments'!AT:AT,'QofE DD adjustments'!$E:$E,'Adjusted IS'!$E21) | GI21: =SUMIFS('QofE DD adjustments'!AU:AU,'QofE DD adjustments'!$E:$E,'Adjusted IS'!$E21) | GJ21: =SUM(ET21:FE21) | GK21: =SUM(FF21:FQ21) | GL21: =SUM(FR21:GC21) | GM21: =SUM(FV21:GG21) | GN21: =SUM(FX21:GI21) | GP21: =SUM(ET21,CX21) | GQ21: =SUM(EU21,CY21) | GR21: =SUM(EV21,CZ21) | GS21: =SUM(EW21,DA21) | GT21: =SUM(EX21,DB21) | GU21: =SUM(EY21,DC21) | GV21: =SUM(EZ21,DD21) | GW21: =SUM(FA21,DE21) | ... IE21: =SUM(GI21,EM21) | IF21: =SUM(GP21:HA21) | IG21: =SUM(HB21:HM21) | IH21: =SUM(HN21:HY21) | II21: =SUM(HR21:IC21) | IJ21: =SUM(HT21:IE21) | IL21: =SUMIFS('QofE PF adjustments'!F:F,'QofE PF adjustments'!$E:$E,'Adjusted IS'!$E21) | IM21: =SUMIFS('QofE PF adjustments'!G:G,'QofE PF adjustments'!$E:$E,'Adjusted IS'!$E21) | IN21: =SUMIFS('QofE PF adjustments'!H:H,'QofE PF adjustments'!$E:$E,'Adjusted IS'!$E21) | IO21: =SUMIFS('QofE PF adjustments'!I:I,'QofE PF adjustments'!$E:$E,'Adjusted IS'!$E21) | IP21: =SUMIFS('QofE PF adjustments'!J:J,'QofE PF adjustments'!$E:$E,'Adjusted IS'!$E21) | IQ21: =SUMIFS('QofE PF adjustments'!K:K,'QofE PF adjustments'!$E:$E,'Adjusted IS'!$E21) | IR21: =SUMIFS('QofE PF adjustments'!L:L,'QofE PF adjustments'!$E:$E,'Adjusted IS'!$E21) | IS21: =SUMIFS('QofE PF adjustments'!M:M,'QofE PF adjustments'!$E:$E,'Adjusted IS'!$E21) | IT21: =SUMIFS('QofE PF adjustments'!N:N,'QofE PF adjustments'!$E:$E,'Adjusted IS'!$E21) | IU21: =SUMIFS('QofE PF adjustments'!O:O,'QofE PF adjustments'!$E:$E,'Adjusted IS'!$E21) | IV21: =SUMIFS('QofE PF adjustments'!P:P,'QofE PF adjustments'!$E:$E,'Adjusted IS'!$E21) | IW21: =SUMIFS('QofE PF adjustments'!Q:Q,'QofE PF adjustments'!$E:$E,'Adjusted IS'!$E21) | IX21: =SUMIFS('QofE PF adjustments'!R:R,'QofE PF adjustments'!$E:$E,'Adjusted IS'!$E21) | IY21: =SUMIFS('QofE PF adjustments'!S:S,'QofE PF adjustments'!$E:$E,'Adjusted IS'!$E21) | IZ21: =SUMIFS('QofE PF adjustments'!T:T,'QofE PF adjustments'!$E:$E,'Adjusted IS'!$E21) | JA21: =SUMIFS('QofE PF adjustments'!U:U,'QofE PF adjustments'!$E:$E,'Adjusted IS'!$E21) | JB21: =SUMIFS('QofE PF adjustments'!V:V,'QofE PF adjustments'!$E:$E,'Adjusted IS'!$E21) | JC21: =SUMIFS('QofE PF adjustments'!W:W,'QofE PF adjustments'!$E:$E,'Adjusted IS'!$E21) | JD21: =SUMIFS('QofE PF adjustments'!X:X,'QofE PF adjustments'!$E:$E,'Adjusted IS'!$E21) | JE21: =SUMIFS('QofE PF adjustments'!Y:Y,'QofE PF adjustments'!$E:$E,'Adjusted IS'!$E21) | JF21: =SUMIFS('QofE PF adjustments'!Z:Z,'QofE PF adjustments'!$E:$E,'Adjusted IS'!$E21) | JG21: =SUMIFS('QofE PF adjustments'!AA:AA,'QofE PF adjustments'!$E:$E,'Adjusted IS'!$E21) | JH21: =SUMIFS('QofE PF adjustments'!AB:AB,'QofE PF adjustments'!$E:$E,'Adjusted IS'!$E21) | JI21: =SUMIFS('QofE PF adjustments'!AC:AC,'QofE PF adjustments'!$E:$E,'Adjusted IS'!$E21) | JJ21: =SUMIFS('QofE PF adjustments'!AD:AD,'QofE PF adjustments'!$E:$E,'Adjusted IS'!$E21) | JK21: =SUMIFS('QofE PF adjustments'!AE:AE,'QofE PF adjustments'!$E:$E,'Adjusted IS'!$E21) | JL21: =SUMIFS('QofE PF adjustments'!AF:AF,'QofE PF adjustments'!$E:$E,'Adjusted IS'!$E21) | JM21: =SUMIFS('QofE PF adjustments'!AG:AG,'QofE PF adjustments'!$E:$E,'Adjusted IS'!$E21) | JN21: =SUMIFS('QofE PF adjustments'!AH:AH,'QofE PF adjustments'!$E:$E,'Adjusted IS'!$E21) | JO21: =SUMIFS('QofE PF adjustments'!AI:AI,'QofE PF adjustments'!$E:$E,'Adjusted IS'!$E21) | JP21: =SUMIFS('QofE PF adjustments'!AJ:AJ,'QofE PF adjustments'!$E:$E,'Adjusted IS'!$E21) | JQ21: =SUMIFS('QofE PF adjustments'!AK:AK,'QofE PF adjustments'!$E:$E,'Adjusted IS'!$E21) | JR21: =SUMIFS('QofE PF adjustments'!AL:AL,'QofE PF adjustments'!$E:$E,'Adjusted IS'!$E21) | JS21: =SUMIFS('QofE PF adjustments'!AM:AM,'QofE PF adjustments'!$E:$E,'Adjusted IS'!$E21) | JT21: =SUMIFS('QofE PF adjustments'!AN:AN,'QofE PF adjustments'!$E:$E,'Adjusted IS'!$E21) | JU21: =SUMIFS('QofE PF adjustments'!AO:AO,'QofE PF adjustments'!$E:$E,'Adjusted IS'!$E21) | JV21: =SUMIFS('QofE PF adjustments'!AP:AP,'QofE PF adjustments'!$E:$E,'Adjusted IS'!$E21) | JW21: =SUMIFS('QofE PF adjustments'!AQ:AQ,'QofE PF adjustments'!$E:$E,'Adjusted IS'!$E21) | JX21: =SUMIFS('QofE PF adjustments'!AR:AR,'QofE PF adjustments'!$E:$E,'Adjusted IS'!$E21) | JY21: =SUMIFS('QofE PF adjustments'!AS:AS,'QofE PF adjustments'!$E:$E,'Adjusted IS'!$E21) | JZ21: =SUMIFS('QofE PF adjustments'!AT:AT,'QofE PF adjustments'!$E:$E,'Adjusted IS'!$E21) | KA21: =SUMIFS('QofE PF adjustments'!AU:AU,'QofE PF adjustments'!$E:$E,'Adjusted IS'!$E21) | KB21: =SUM(IL21:IW21) | KC21: =SUM(IX21:JI21) | KD21: =SUM(JJ21:JU21) | KE21: =SUM(JN21:JY21) | KF21: =SUM(JP21:KA21) | KH21: =SUM(IL21,GP21) | KI21: =SUM(IM21,GQ21) | KJ21: =SUM(IN21,GR21) | KK21: =SUM(IO21,GS21) | KL21: =SUM(IP21,GT21) | KM21: =SUM(IQ21,GU21) | KN21: =SUM(IR21,GV21) | KO21: =SUM(IS21,GW21) | ... LW21: =SUM(KA21,IE21) | LX21: =SUM(KH21:KS21) | LY21: =SUM(KT21:LE21) | LZ21: =SUM(LF21:LQ21) | MA21: =SUM(LJ21:LU21) | MB21: =SUM(LL21:LW21) | MD21: =IFERROR(KH21/KH$117,0) | ME21: =IFERROR(KI21/KI$117,0) | MF21: =IFERROR(KJ21/KJ$117,0) | MG21: =IFERROR(KK21/KK$117,0) | MH21: =IFERROR(KL21/KL$117,0) | MI21: =IFERROR(KM21/KM$117,0) | MJ21: =IFERROR(KN21/KN$117,0) | MK21: =IFERROR(KO21/KO$117,0) | ... NX21: =IFERROR(MB21/MB$117,0) | NZ21: =LY21-LX21 | OA21: =LZ21-LY21 | OB21: =MA21-LZ21 | OC21: =MB21-LZ21 | OE21: Processing services revenue | OF21: Processing services revenue | OG21: Processing services revenue
C22: Switch fee - in-app transactions | D22: 411110 | E22: =CONCATENATE(D22," - ",C22) | F22: ='Income statement'!F22 | G22: ='Income statement'!G22 | H22: ='Income statement'!H22 | I22: ='Income statement'!I22 | J22: ='Income statement'!J22 | K22: ='Income statement'!K22 | L22: ='Income statement'!L22 | M22: ='Income statement'!M22 | ... AU22: ='Income statement'!AU22 | AV22: =SUM(F22:Q22) | AW22: =SUM(R22:AC22) | AX22: =SUM(AD22:AO22) | AY22: =SUM(AH22:AS22) | AZ22: =SUM(AJ22:AU22) | BB22: =SUMIFS('QofE Def adjustments'!F:F,'QofE Def adjustments'!$E:$E,'Adjusted IS'!$E22) | BC22: =SUMIFS('QofE Def adjustments'!G:G,'QofE Def adjustments'!$E:$E,'Adjusted IS'!$E22) | BD22: =SUMIFS('QofE Def adjustments'!H:H,'QofE Def adjustments'!$E:$E,'Adjusted IS'!$E22) | BE22: =SUMIFS('QofE Def adjustments'!I:I,'QofE Def adjustments'!$E:$E,'Adjusted IS'!$E22) | BF22: =SUMIFS('QofE Def adjustments'!J:J,'QofE Def adjustments'!$E:$E,'Adjusted IS'!$E22) | BG22: =SUMIFS('QofE Def adjustments'!K:K,'QofE Def adjustments'!$E:$E,'Adjusted IS'!$E22) | BH22: =SUMIFS('QofE Def adjustments'!L:L,'QofE Def adjustments'!$E:$E,'Adjusted IS'!$E22) | BI22: =SUMIFS('QofE Def adjustments'!M:M,'QofE Def adjustments'!$E:$E,'Adjusted IS'!$E22) | BJ22: =SUMIFS('QofE Def adjustments'!N:N,'QofE Def adjustments'!$E:$E,'Adjusted IS'!$E22) | BK22: =SUMIFS('QofE Def adjustments'!O:O,'QofE Def adjustments'!$E:$E,'Adjusted IS'!$E22) | BL22: =SUMIFS('QofE Def adjustments'!P:P,'QofE Def adjustments'!$E:$E,'Adjusted IS'!$E22) | BM22: =SUMIFS('QofE Def adjustments'!Q:Q,'QofE Def adjustments'!$E:$E,'Adjusted IS'!$E22) | BN22: =SUMIFS('QofE Def adjustments'!R:R,'QofE Def adjustments'!$E:$E,'Adjusted IS'!$E22) | BO22: =SUMIFS('QofE Def adjustments'!S:S,'QofE Def adjustments'!$E:$E,'Adjusted IS'!$E22) | BP22: =SUMIFS('QofE Def adjustments'!T:T,'QofE Def adjustments'!$E:$E,'Adjusted IS'!$E22) | BQ22: =SUMIFS('QofE Def adjustments'!U:U,'QofE Def adjustments'!$E:$E,'Adjusted IS'!$E22) | BR22: =SUMIFS('QofE Def adjustments'!V:V,'QofE Def adjustments'!$E:$E,'Adjusted IS'!$E22) | BS22: =SUMIFS('QofE Def adjustments'!W:W,'QofE Def adjustments'!$E:$E,'Adjusted IS'!$E22) | BT22: =SUMIFS('QofE Def adjustments'!X:X,'QofE Def adjustments'!$E:$E,'Adjusted IS'!$E22) | BU22: =SUMIFS('QofE Def adjustments'!Y:Y,'QofE Def adjustments'!$E:$E,'Adjusted IS'!$E22) | BV22: =SUMIFS('QofE Def adjustments'!Z:Z,'QofE Def adjustments'!$E:$E,'Adjusted IS'!$E22) | BW22: =SUMIFS('QofE Def adjustments'!AA:AA,'QofE Def adjustments'!$E:$E,'Adjusted IS'!$E22) | BX22: =SUMIFS('QofE Def adjustments'!AB:AB,'QofE Def adjustments'!$E:$E,'Adjusted IS'!$E22) | BY22: =SUMIFS('QofE Def adjustments'!AC:AC,'QofE Def adjustments'!$E:$E,'Adjusted IS'!$E22) | BZ22: =SUMIFS('QofE Def adjustments'!AD:AD,'QofE Def adjustments'!$E:$E,'Adjusted IS'!$E22) | CA22: =SUMIFS('QofE Def adjustments'!AE:AE,'QofE Def adjustments'!$E:$E,'Adjusted IS'!$E22) | CB22: =SUMIFS('QofE Def adjustments'!AF:AF,'QofE Def adjustments'!$E:$E,'Adjusted IS'!$E22) | CC22: =SUMIFS('QofE Def adjustments'!AG:AG,'QofE Def adjustments'!$E:$E,'Adjusted IS'!$E22) | CD22: =SUMIFS('QofE Def adjustments'!AH:AH,'QofE Def adjustments'!$E:$E,'Adjusted IS'!$E22) | CE22: =SUMIFS('QofE Def adjustments'!AI:AI,'QofE Def adjustments'!$E:$E,'Adjusted IS'!$E22) | CF22: =SUMIFS('QofE Def adjustments'!AJ:AJ,'QofE Def adjustments'!$E:$E,'Adjusted IS'!$E22) | CG22: =SUMIFS('QofE Def adjustments'!AK:AK,'QofE Def adjustments'!$E:$E,'Adjusted IS'!$E22) | CH22: =SUMIFS('QofE Def adjustments'!AL:AL,'QofE Def adjustments'!$E:$E,'Adjusted IS'!$E22) | CI22: =SUMIFS('QofE Def adjustments'!AM:AM,'QofE Def adjustments'!$E:$E,'Adjusted IS'!$E22) | CJ22: =SUMIFS('QofE Def adjustments'!AN:AN,'QofE Def adjustments'!$E:$E,'Adjusted IS'!$E22) | CK22: =SUMIFS('QofE Def adjustments'!AO:AO,'QofE Def adjustments'!$E:$E,'Adjusted IS'!$E22) | CL22: =SUMIFS('QofE Def adjustments'!AP:AP,'QofE Def adjustments'!$E:$E,'Adjusted IS'!$E22) | CM22: =SUMIFS('QofE Def adjustments'!AQ:AQ,'QofE Def adjustments'!$E:$E,'Adjusted IS'!$E22) | CN22: =SUMIFS('QofE Def adjustments'!AR:AR,'QofE Def adjustments'!$E:$E,'Adjusted IS'!$E22) | CO22: =SUMIFS('QofE Def adjustments'!AS:AS,'QofE Def adjustments'!$E:$E,'Adjusted IS'!$E22) | CP22: =SUMIFS('QofE Def adjustments'!AT:AT,'QofE Def adjustments'!$E:$E,'Adjusted IS'!$E22) | CQ22: =SUMIFS('QofE Def adjustments'!AU:AU,'QofE Def adjustments'!$E:$E,'Adjusted IS'!$E22) | CR22: =SUM(BB22:BM22) | CS22: =SUM(BN22:BY22) | CT22: =SUM(BZ22:CK22) | CU22: =SUM(CD22:CO22) | CV22: =SUM(CF22:CQ22) | CX22: =SUM(BB22,F22) | CY22: =SUM(BC22,G22) | CZ22: =SUM(BD22,H22) | DA22: =SUM(BE22,I22) | DB22: =SUM(BF22,J22) | DC22: =SUM(BG22,K22) | DD22: =SUM(BH22,L22) | DE22: =SUM(BI22,M22) | ... EM22: =SUM(CQ22,AU22) | EN22: =SUM(CX22:DI22) | EO22: =SUM(DJ22:DU22) | EP22: =SUM(DV22:EG22) | EQ22: =SUM(DZ22:EK22) | ER22: =SUM(EB22:EM22) | ET22: =SUMIFS('QofE DD adjustments'!F:F,'QofE DD adjustments'!$E:$E,'Adjusted IS'!$E22) | EU22: =SUMIFS('QofE DD adjustments'!G:G,'QofE DD adjustments'!$E:$E,'Adjusted IS'!$E22) | EV22: =SUMIFS('QofE DD adjustments'!H:H,'QofE DD adjustments'!$E:$E,'Adjusted IS'!$E22) | EW22: =SUMIFS('QofE DD adjustments'!I:I,'QofE DD adjustments'!$E:$E,'Adjusted IS'!$E22) | EX22: =SUMIFS('QofE DD adjustments'!J:J,'QofE DD adjustments'!$E:$E,'Adjusted IS'!$E22) | EY22: =SUMIFS('QofE DD adjustments'!K:K,'QofE DD adjustments'!$E:$E,'Adjusted IS'!$E22) | EZ22: =SUMIFS('QofE DD adjustments'!L:L,'QofE DD adjustments'!$E:$E,'Adjusted IS'!$E22) | FA22: =SUMIFS('QofE DD adjustments'!M:M,'QofE DD adjustments'!$E:$E,'Adjusted IS'!$E22) | FB22: =SUMIFS('QofE DD adjustments'!N:N,'QofE DD adjustments'!$E:$E,'Adjusted IS'!$E22) | FC22: =SUMIFS('QofE DD adjustments'!O:O,'QofE DD adjustments'!$E:$E,'Adjusted IS'!$E22) | FD22: =SUMIFS('QofE DD adjustments'!P:P,'QofE DD adjustments'!$E:$E,'Adjusted IS'!$E22) | FE22: =SUMIFS('QofE DD adjustments'!Q:Q,'QofE DD adjustments'!$E:$E,'Adjusted IS'!$E22) | FF22: =SUMIFS('QofE DD adjustments'!R:R,'QofE DD adjustments'!$E:$E,'Adjusted IS'!$E22) | FG22: =SUMIFS('QofE DD adjustments'!S:S,'QofE DD adjustments'!$E:$E,'Adjusted IS'!$E22) | FH22: =SUMIFS('QofE DD adjustments'!T:T,'QofE DD adjustments'!$E:$E,'Adjusted IS'!$E22) | FI22: =SUMIFS('QofE DD adjustments'!U:U,'QofE DD adjustments'!$E:$E,'Adjusted IS'!$E22) | FJ22: =SUMIFS('QofE DD adjustments'!V:V,'QofE DD adjustments'!$E:$E,'Adjusted IS'!$E22) | FK22: =SUMIFS('QofE DD adjustments'!W:W,'QofE DD adjustments'!$E:$E,'Adjusted IS'!$E22) | FL22: =SUMIFS('QofE DD adjustments'!X:X,'QofE DD adjustments'!$E:$E,'Adjusted IS'!$E22) | FM22: =SUMIFS('QofE DD adjustments'!Y:Y,'QofE DD adjustments'!$E:$E,'Adjusted IS'!$E22) | FN22: =SUMIFS('QofE DD adjustments'!Z:Z,'QofE DD adjustments'!$E:$E,'Adjusted IS'!$E22) | FO22: =SUMIFS('QofE DD adjustments'!AA:AA,'QofE DD adjustments'!$E:$E,'Adjusted IS'!$E22) | FP22: =SUMIFS('QofE DD adjustments'!AB:AB,'QofE DD adjustments'!$E:$E,'Adjusted IS'!$E22) | FQ22: =SUMIFS('QofE DD adjustments'!AC:AC,'QofE DD adjustments'!$E:$E,'Adjusted IS'!$E22) | FR22: =SUMIFS('QofE DD adjustments'!AD:AD,'QofE DD adjustments'!$E:$E,'Adjusted IS'!$E22) | FS22: =SUMIFS('QofE DD adjustments'!AE:AE,'QofE DD adjustments'!$E:$E,'Adjusted IS'!$E22) | FT22: =SUMIFS('QofE DD adjustments'!AF:AF,'QofE DD adjustments'!$E:$E,'Adjusted IS'!$E22) | FU22: =SUMIFS('QofE DD adjustments'!AG:AG,'QofE DD adjustments'!$E:$E,'Adjusted IS'!$E22) | FV22: =SUMIFS('QofE DD adjustments'!AH:AH,'QofE DD adjustments'!$E:$E,'Adjusted IS'!$E22) | FW22: =SUMIFS('QofE DD adjustments'!AI:AI,'QofE DD adjustments'!$E:$E,'Adjusted IS'!$E22) | FX22: =SUMIFS('QofE DD adjustments'!AJ:AJ,'QofE DD adjustments'!$E:$E,'Adjusted IS'!$E22) | FY22: =SUMIFS('QofE DD adjustments'!AK:AK,'QofE DD adjustments'!$E:$E,'Adjusted IS'!$E22) | FZ22: =SUMIFS('QofE DD adjustments'!AL:AL,'QofE DD adjustments'!$E:$E,'Adjusted IS'!$E22) | GA22: =SUMIFS('QofE DD adjustments'!AM:AM,'QofE DD adjustments'!$E:$E,'Adjusted IS'!$E22) | GB22: =SUMIFS('QofE DD adjustments'!AN:AN,'QofE DD adjustments'!$E:$E,'Adjusted IS'!$E22) | GC22: =SUMIFS('QofE DD adjustments'!AO:AO,'QofE DD adjustments'!$E:$E,'Adjusted IS'!$E22) | GD22: =SUMIFS('QofE DD adjustments'!AP:AP,'QofE DD adjustments'!$E:$E,'Adjusted IS'!$E22) | GE22: =SUMIFS('QofE DD adjustments'!AQ:AQ,'QofE DD adjustments'!$E:$E,'Adjusted IS'!$E22) | GF22: =SUMIFS('QofE DD adjustments'!AR:AR,'QofE DD adjustments'!$E:$E,'Adjusted IS'!$E22) | GG22: =SUMIFS('QofE DD adjustments'!AS:AS,'QofE DD adjustments'!$E:$E,'Adjusted IS'!$E22) | GH22: =SUMIFS('QofE DD adjustments'!AT:AT,'QofE DD adjustments'!$E:$E,'Adjusted IS'!$E22) | GI22: =SUMIFS('QofE DD adjustments'!AU:AU,'QofE DD adjustments'!$E:$E,'Adjusted IS'!$E22) | GJ22: =SUM(ET22:FE22) | GK22: =SUM(FF22:FQ22) | GL22: =SUM(FR22:GC22) | GM22: =SUM(FV22:GG22) | GN22: =SUM(FX22:GI22) | GP22: =SUM(ET22,CX22) | GQ22: =SUM(EU22,CY22) | GR22: =SUM(EV22,CZ22) | GS22: =SUM(EW22,DA22) | GT22: =SUM(EX22,DB22) | GU22: =SUM(EY22,DC22) | GV22: =SUM(EZ22,DD22) | GW22: =SUM(FA22,DE22) | ... IE22: =SUM(GI22,EM22) | IF22: =SUM(GP22:HA22) | IG22: =SUM(HB22:HM22) | IH22: =SUM(HN22:HY22) | II22: =SUM(HR22:IC22) | IJ22: =SUM(HT22:IE22) | IL22: =SUMIFS('QofE PF adjustments'!F:F,'QofE PF adjustments'!$E:$E,'Adjusted IS'!$E22) | IM22: =SUMIFS('QofE PF adjustments'!G:G,'QofE PF adjustments'!$E:$E,'Adjusted IS'!$E22) | IN22: =SUMIFS('QofE PF adjustments'!H:H,'QofE PF adjustments'!$E:$E,'Adjusted IS'!$E22) | IO22: =SUMIFS('QofE PF adjustments'!I:I,'QofE PF adjustments'!$E:$E,'Adjusted IS'!$E22) | IP22: =SUMIFS('QofE PF adjustments'!J:J,'QofE PF adjustments'!$E:$E,'Adjusted IS'!$E22) | IQ22: =SUMIFS('QofE PF adjustments'!K:K,'QofE PF adjustments'!$E:$E,'Adjusted IS'!$E22) | IR22: =SUMIFS('QofE PF adjustments'!L:L,'QofE PF adjustments'!$E:$E,'Adjusted IS'!$E22) | IS22: =SUMIFS('QofE PF adjustments'!M:M,'QofE PF adjustments'!$E:$E,'Adjusted IS'!$E22) | IT22: =SUMIFS('QofE PF adjustments'!N:N,'QofE PF adjustments'!$E:$E,'Adjusted IS'!$E22) | IU22: =SUMIFS('QofE PF adjustments'!O:O,'QofE PF adjustments'!$E:$E,'Adjusted IS'!$E22) | IV22: =SUMIFS('QofE PF adjustments'!P:P,'QofE PF adjustments'!$E:$E,'Adjusted IS'!$E22) | IW22: =SUMIFS('QofE PF adjustments'!Q:Q,'QofE PF adjustments'!$E:$E,'Adjusted IS'!$E22) | IX22: =SUMIFS('QofE PF adjustments'!R:R,'QofE PF adjustments'!$E:$E,'Adjusted IS'!$E22) | IY22: =SUMIFS('QofE PF adjustments'!S:S,'QofE PF adjustments'!$E:$E,'Adjusted IS'!$E22) | IZ22: =SUMIFS('QofE PF adjustments'!T:T,'QofE PF adjustments'!$E:$E,'Adjusted IS'!$E22) | JA22: =SUMIFS('QofE PF adjustments'!U:U,'QofE PF adjustments'!$E:$E,'Adjusted IS'!$E22) | JB22: =SUMIFS('QofE PF adjustments'!V:V,'QofE PF adjustments'!$E:$E,'Adjusted IS'!$E22) | JC22: =SUMIFS('QofE PF adjustments'!W:W,'QofE PF adjustments'!$E:$E,'Adjusted IS'!$E22) | JD22: =SUMIFS('QofE PF adjustments'!X:X,'QofE PF adjustments'!$E:$E,'Adjusted IS'!$E22) | JE22: =SUMIFS('QofE PF adjustments'!Y:Y,'QofE PF adjustments'!$E:$E,'Adjusted IS'!$E22) | JF22: =SUMIFS('QofE PF adjustments'!Z:Z,'QofE PF adjustments'!$E:$E,'Adjusted IS'!$E22) | JG22: =SUMIFS('QofE PF adjustments'!AA:AA,'QofE PF adjustments'!$E:$E,'Adjusted IS'!$E22) | JH22: =SUMIFS('QofE PF adjustments'!AB:AB,'QofE PF adjustments'!$E:$E,'Adjusted IS'!$E22) | JI22: =SUMIFS('QofE PF adjustments'!AC:AC,'QofE PF adjustments'!$E:$E,'Adjusted IS'!$E22) | JJ22: =SUMIFS('QofE PF adjustments'!AD:AD,'QofE PF adjustments'!$E:$E,'Adjusted IS'!$E22) | JK22: =SUMIFS('QofE PF adjustments'!AE:AE,'QofE PF adjustments'!$E:$E,'Adjusted IS'!$E22) | JL22: =SUMIFS('QofE PF adjustments'!AF:AF,'QofE PF adjustments'!$E:$E,'Adjusted IS'!$E22) | JM22: =SUMIFS('QofE PF adjustments'!AG:AG,'QofE PF adjustments'!$E:$E,'Adjusted IS'!$E22) | JN22: =SUMIFS('QofE PF adjustments'!AH:AH,'QofE PF adjustments'!$E:$E,'Adjusted IS'!$E22) | JO22: =SUMIFS('QofE PF adjustments'!AI:AI,'QofE PF adjustments'!$E:$E,'Adjusted IS'!$E22) | JP22: =SUMIFS('QofE PF adjustments'!AJ:AJ,'QofE PF adjustments'!$E:$E,'Adjusted IS'!$E22) | JQ22: =SUMIFS('QofE PF adjustments'!AK:AK,'QofE PF adjustments'!$E:$E,'Adjusted IS'!$E22) | JR22: =SUMIFS('QofE PF adjustments'!AL:AL,'QofE PF adjustments'!$E:$E,'Adjusted IS'!$E22) | JS22: =SUMIFS('QofE PF adjustments'!AM:AM,'QofE PF adjustments'!$E:$E,'Adjusted IS'!$E22) | JT22: =SUMIFS('QofE PF adjustments'!AN:AN,'QofE PF adjustments'!$E:$E,'Adjusted IS'!$E22) | JU22: =SUMIFS('QofE PF adjustments'!AO:AO,'QofE PF adjustments'!$E:$E,'Adjusted IS'!$E22) | JV22: =SUMIFS('QofE PF adjustments'!AP:AP,'QofE PF adjustments'!$E:$E,'Adjusted IS'!$E22) | JW22: =SUMIFS('QofE PF adjustments'!AQ:AQ,'QofE PF adjustments'!$E:$E,'Adjusted IS'!$E22) | JX22: =SUMIFS('QofE PF adjustments'!AR:AR,'QofE PF adjustments'!$E:$E,'Adjusted IS'!$E22) | JY22: =SUMIFS('QofE PF adjustments'!AS:AS,'QofE PF adjustments'!$E:$E,'Adjusted IS'!$E22) | JZ22: =SUMIFS('QofE PF adjustments'!AT:AT,'QofE PF adjustments'!$E:$E,'Adjusted IS'!$E22) | KA22: =SUMIFS('QofE PF adjustments'!AU:AU,'QofE PF adjustments'!$E:$E,'Adjusted IS'!$E22) | KB22: =SUM(IL22:IW22) | KC22: =SUM(IX22:JI22) | KD22: =SUM(JJ22:JU22) | KE22: =SUM(JN22:JY22) | KF22: =SUM(JP22:KA22) | KH22: =SUM(IL22,GP22) | KI22: =SUM(IM22,GQ22) | KJ22: =SUM(IN22,GR22) | KK22: =SUM(IO22,GS22) | KL22: =SUM(IP22,GT22) | KM22: =SUM(IQ22,GU22) | KN22: =SUM(IR22,GV22) | KO22: =SUM(IS22,GW22) | ... LW22: =SUM(KA22,IE22) | LX22: =SUM(KH22:KS22) | LY22: =SUM(KT22:LE22) | LZ22: =SUM(LF22:LQ22) | MA22: =SUM(LJ22:LU22) | MB22: =SUM(LL22:LW22) | MD22: =IFERROR(KH22/KH$117,0) | ME22: =IFERROR(KI22/KI$117,0) | MF22: =IFERROR(KJ22/KJ$117,0) | MG22: =IFERROR(KK22/KK$117,0) | MH22: =IFERROR(KL22/KL$117,0) | MI22: =IFERROR(KM22/KM$117,0) | MJ22: =IFERROR(KN22/KN$117,0) | MK22: =IFERROR(KO22/KO$117,0) | ... NX22: =IFERROR(MB22/MB$117,0) | NZ22: =LY22-LX22 | OA22: =LZ22-LY22 | OB22: =MA22-LZ22 | OC22: =MB22-LZ22 | OE22: Processing services revenue | OF22: Processing services revenue | OG22: Processing services revenue
C23: White-label atm transaction revenue (2018-) | D23: 411102 | E23: =CONCATENATE(D23," - ",C23) | F23: ='Income statement'!F23 | G23: ='Income statement'!G23 | H23: ='Income statement'!H23 | I23: ='Income statement'!I23 | J23: ='Income statement'!J23 | K23: ='Income statement'!K23 | L23: ='Income statement'!L23 | M23: ='Income statement'!M23 | ... AU23: ='Income statement'!AU23 | AV23: =SUM(F23:Q23) | AW23: =SUM(R23:AC23) | AX23: =SUM(AD23:AO23) | AY23: =SUM(AH23:AS23) | AZ23: =SUM(AJ23:AU23) | BB23: =SUMIFS('QofE Def adjustments'!F:F,'QofE Def adjustments'!$E:$E,'Adjusted IS'!$E23) | BC23: =SUMIFS('QofE Def adjustments'!G:G,'QofE Def adjustments'!$E:$E,'Adjusted IS'!$E23) | BD23: =SUMIFS('QofE Def adjustments'!H:H,'QofE Def adjustments'!$E:$E,'Adjusted IS'!$E23) | BE23: =SUMIFS('QofE Def adjustments'!I:I,'QofE Def adjustments'!$E:$E,'Adjusted IS'!$E23) | BF23: =SUMIFS('QofE Def adjustments'!J:J,'QofE Def adjustments'!$E:$E,'Adjusted IS'!$E23) | BG23: =SUMIFS('QofE Def adjustments'!K:K,'QofE Def adjustments'!$E:$E,'Adjusted IS'!$E23) | BH23: =SUMIFS('QofE Def adjustments'!L:L,'QofE Def adjustments'!$E:$E,'Adjusted IS'!$E23) | BI23: =SUMIFS('QofE Def adjustments'!M:M,'QofE Def adjustments'!$E:$E,'Adjusted IS'!$E23) | BJ23: =SUMIFS('QofE Def adjustments'!N:N,'QofE Def adjustments'!$E:$E,'Adjusted IS'!$E23) | BK23: =SUMIFS('QofE Def adjustments'!O:O,'QofE Def adjustments'!$E:$E,'Adjusted IS'!$E23) | BL23: =SUMIFS('QofE Def adjustments'!P:P,'QofE Def adjustments'!$E:$E,'Adjusted IS'!$E23) | BM23: =SUMIFS('QofE Def adjustments'!Q:Q,'QofE Def adjustments'!$E:$E,'Adjusted IS'!$E23) | BN23: =SUMIFS('QofE Def adjustments'!R:R,'QofE Def adjustments'!$E:$E,'Adjusted IS'!$E23) | BO23: =SUMIFS('QofE Def adjustments'!S:S,'QofE Def adjustments'!$E:$E,'Adjusted IS'!$E23) | BP23: =SUMIFS('QofE Def adjustments'!T:T,'QofE Def adjustments'!$E:$E,'Adjusted IS'!$E23) | BQ23: =SUMIFS('QofE Def adjustments'!U:U,'QofE Def adjustments'!$E:$E,'Adjusted IS'!$E23) | BR23: =SUMIFS('QofE Def adjustments'!V:V,'QofE Def adjustments'!$E:$E,'Adjusted IS'!$E23) | BS23: =SUMIFS('QofE Def adjustments'!W:W,'QofE Def adjustments'!$E:$E,'Adjusted IS'!$E23) | BT23: =SUMIFS('QofE Def adjustments'!X:X,'QofE Def adjustments'!$E:$E,'Adjusted IS'!$E23) | BU23: =SUMIFS('QofE Def adjustments'!Y:Y,'QofE Def adjustments'!$E:$E,'Adjusted IS'!$E23) | BV23: =SUMIFS('QofE Def adjustments'!Z:Z,'QofE Def adjustments'!$E:$E,'Adjusted IS'!$E23) | BW23: =SUMIFS('QofE Def adjustments'!AA:AA,'QofE Def adjustments'!$E:$E,'Adjusted IS'!$E23) | BX23: =SUMIFS('QofE Def adjustments'!AB:AB,'QofE Def adjustments'!$E:$E,'Adjusted IS'!$E23) | BY23: =SUMIFS('QofE Def adjustments'!AC:AC,'QofE Def adjustments'!$E:$E,'Adjusted IS'!$E23) | BZ23: =SUMIFS('QofE Def adjustments'!AD:AD,'QofE Def adjustments'!$E:$E,'Adjusted IS'!$E23) | CA23: =SUMIFS('QofE Def adjustments'!AE:AE,'QofE Def adjustments'!$E:$E,'Adjusted IS'!$E23) | CB23: =SUMIFS('QofE Def adjustments'!AF:AF,'QofE Def adjustments'!$E:$E,'Adjusted IS'!$E23) | CC23: =SUMIFS('QofE Def adjustments'!AG:AG,'QofE Def adjustments'!$E:$E,'Adjusted IS'!$E23) | CD23: =SUMIFS('QofE Def adjustments'!AH:AH,'QofE Def adjustments'!$E:$E,'Adjusted IS'!$E23) | CE23: =SUMIFS('QofE Def adjustments'!AI:AI,'QofE Def adjustments'!$E:$E,'Adjusted IS'!$E23) | CF23: =SUMIFS('QofE Def adjustments'!AJ:AJ,'QofE Def adjustments'!$E:$E,'Adjusted IS'!$E23) | CG23: =SUMIFS('QofE Def adjustments'!AK:AK,'QofE Def adjustments'!$E:$E,'Adjusted IS'!$E23) | CH23: =SUMIFS('QofE Def adjustments'!AL:AL,'QofE Def adjustments'!$E:$E,'Adjusted IS'!$E23) | CI23: =SUMIFS('QofE Def adjustments'!AM:AM,'QofE Def adjustments'!$E:$E,'Adjusted IS'!$E23) | CJ23: =SUMIFS('QofE Def adjustments'!AN:AN,'QofE Def adjustments'!$E:$E,'Adjusted IS'!$E23) | CK23: =SUMIFS('QofE Def adjustments'!AO:AO,'QofE Def adjustments'!$E:$E,'Adjusted IS'!$E23) | CL23: =SUMIFS('QofE Def adjustments'!AP:AP,'QofE Def adjustments'!$E:$E,'Adjusted IS'!$E23) | CM23: =SUMIFS('QofE Def adjustments'!AQ:AQ,'QofE Def adjustments'!$E:$E,'Adjusted IS'!$E23) | CN23: =SUMIFS('QofE Def adjustments'!AR:AR,'QofE Def adjustments'!$E:$E,'Adjusted IS'!$E23) | CO23: =SUMIFS('QofE Def adjustments'!AS:AS,'QofE Def adjustments'!$E:$E,'Adjusted IS'!$E23) | CP23: =SUMIFS('QofE Def adjustments'!AT:AT,'QofE Def adjustments'!$E:$E,'Adjusted IS'!$E23) | CQ23: =SUMIFS('QofE Def adjustments'!AU:AU,'QofE Def adjustments'!$E:$E,'Adjusted IS'!$E23) | CR23: =SUM(BB23:BM23) | CS23: =SUM(BN23:BY23) | CT23: =SUM(BZ23:CK23) | CU23: =SUM(CD23:CO23) | CV23: =SUM(CF23:CQ23) | CX23: =SUM(BB23,F23) | CY23: =SUM(BC23,G23) | CZ23: =SUM(BD23,H23) | DA23: =SUM(BE23,I23) | DB23: =SUM(BF23,J23) | DC23: =SUM(BG23,K23) | DD23: =SUM(BH23,L23) | DE23: =SUM(BI23,M23) | ... EM23: =SUM(CQ23,AU23) | EN23: =SUM(CX23:DI23) | EO23: =SUM(DJ23:DU23) | EP23: =SUM(DV23:EG23) | EQ23: =SUM(DZ23:EK23) | ER23: =SUM(EB23:EM23) | ET23: =SUMIFS('QofE DD adjustments'!F:F,'QofE DD adjustments'!$E:$E,'Adjusted IS'!$E23) | EU23: =SUMIFS('QofE DD adjustments'!G:G,'QofE DD adjustments'!$E:$E,'Adjusted IS'!$E23) | EV23: =SUMIFS('QofE DD adjustments'!H:H,'QofE DD adjustments'!$E:$E,'Adjusted IS'!$E23) | EW23: =SUMIFS('QofE DD adjustments'!I:I,'QofE DD adjustments'!$E:$E,'Adjusted IS'!$E23) | EX23: =SUMIFS('QofE DD adjustments'!J:J,'QofE DD adjustments'!$E:$E,'Adjusted IS'!$E23) | EY23: =SUMIFS('QofE DD adjustments'!K:K,'QofE DD adjustments'!$E:$E,'Adjusted IS'!$E23) | EZ23: =SUMIFS('QofE DD adjustments'!L:L,'QofE DD adjustments'!$E:$E,'Adjusted IS'!$E23) | FA23: =SUMIFS('QofE DD adjustments'!M:M,'QofE DD adjustments'!$E:$E,'Adjusted IS'!$E23) | FB23: =SUMIFS('QofE DD adjustments'!N:N,'QofE DD adjustments'!$E:$E,'Adjusted IS'!$E23) | FC23: =SUMIFS('QofE DD adjustments'!O:O,'QofE DD adjustments'!$E:$E,'Adjusted IS'!$E23) | FD23: =SUMIFS('QofE DD adjustments'!P:P,'QofE DD adjustments'!$E:$E,'Adjusted IS'!$E23) | FE23: =SUMIFS('QofE DD adjustments'!Q:Q,'QofE DD adjustments'!$E:$E,'Adjusted IS'!$E23) | FF23: =SUMIFS('QofE DD adjustments'!R:R,'QofE DD adjustments'!$E:$E,'Adjusted IS'!$E23) | FG23: =SUMIFS('QofE DD adjustments'!S:S,'QofE DD adjustments'!$E:$E,'Adjusted IS'!$E23) | FH23: =SUMIFS('QofE DD adjustments'!T:T,'QofE DD adjustments'!$E:$E,'Adjusted IS'!$E23) | FI23: =SUMIFS('QofE DD adjustments'!U:U,'QofE DD adjustments'!$E:$E,'Adjusted IS'!$E23) | FJ23: =SUMIFS('QofE DD adjustments'!V:V,'QofE DD adjustments'!$E:$E,'Adjusted IS'!$E23) | FK23: =SUMIFS('QofE DD adjustments'!W:W,'QofE DD adjustments'!$E:$E,'Adjusted IS'!$E23) | FL23: =SUMIFS('QofE DD adjustments'!X:X,'QofE DD adjustments'!$E:$E,'Adjusted IS'!$E23) | FM23: =SUMIFS('QofE DD adjustments'!Y:Y,'QofE DD adjustments'!$E:$E,'Adjusted IS'!$E23) | FN23: =SUMIFS('QofE DD adjustments'!Z:Z,'QofE DD adjustments'!$E:$E,'Adjusted IS'!$E23) | FO23: =SUMIFS('QofE DD adjustments'!AA:AA,'QofE DD adjustments'!$E:$E,'Adjusted IS'!$E23) | FP23: =SUMIFS('QofE DD adjustments'!AB:AB,'QofE DD adjustments'!$E:$E,'Adjusted IS'!$E23) | FQ23: =SUMIFS('QofE DD adjustments'!AC:AC,'QofE DD adjustments'!$E:$E,'Adjusted IS'!$E23) | FR23: =SUMIFS('QofE DD adjustments'!AD:AD,'QofE DD adjustments'!$E:$E,'Adjusted IS'!$E23) | FS23: =SUMIFS('QofE DD adjustments'!AE:AE,'QofE DD adjustments'!$E:$E,'Adjusted IS'!$E23) | FT23: =SUMIFS('QofE DD adjustments'!AF:AF,'QofE DD adjustments'!$E:$E,'Adjusted IS'!$E23) | FU23: =SUMIFS('QofE DD adjustments'!AG:AG,'QofE DD adjustments'!$E:$E,'Adjusted IS'!$E23) | FV23: =SUMIFS('QofE DD adjustments'!AH:AH,'QofE DD adjustments'!$E:$E,'Adjusted IS'!$E23) | FW23: =SUMIFS('QofE DD adjustments'!AI:AI,'QofE DD adjustments'!$E:$E,'Adjusted IS'!$E23) | FX23: =SUMIFS('QofE DD adjustments'!AJ:AJ,'QofE DD adjustments'!$E:$E,'Adjusted IS'!$E23) | FY23: =SUMIFS('QofE DD adjustments'!AK:AK,'QofE DD adjustments'!$E:$E,'Adjusted IS'!$E23) | FZ23: =SUMIFS('QofE DD adjustments'!AL:AL,'QofE DD adjustments'!$E:$E,'Adjusted IS'!$E23) | GA23: =SUMIFS('QofE DD adjustments'!AM:AM,'QofE DD adjustments'!$E:$E,'Adjusted IS'!$E23) | GB23: =SUMIFS('QofE DD adjustments'!AN:AN,'QofE DD adjustments'!$E:$E,'Adjusted IS'!$E23) | GC23: =SUMIFS('QofE DD adjustments'!AO:AO,'QofE DD adjustments'!$E:$E,'Adjusted IS'!$E23) | GD23: =SUMIFS('QofE DD adjustments'!AP:AP,'QofE DD adjustments'!$E:$E,'Adjusted IS'!$E23) | GE23: =SUMIFS('QofE DD adjustments'!AQ:AQ,'QofE DD adjustments'!$E:$E,'Adjusted IS'!$E23) | GF23: =SUMIFS('QofE DD adjustments'!AR:AR,'QofE DD adjustments'!$E:$E,'Adjusted IS'!$E23) | GG23: =SUMIFS('QofE DD adjustments'!AS:AS,'QofE DD adjustments'!$E:$E,'Adjusted IS'!$E23) | GH23: =SUMIFS('QofE DD adjustments'!AT:AT,'QofE DD adjustments'!$E:$E,'Adjusted IS'!$E23) | GI23: =SUMIFS('QofE DD adjustments'!AU:AU,'QofE DD adjustments'!$E:$E,'Adjusted IS'!$E23) | GJ23: =SUM(ET23:FE23) | GK23: =SUM(FF23:FQ23) | GL23: =SUM(FR23:GC23) | GM23: =SUM(FV23:GG23) | GN23: =SUM(FX23:GI23) | GP23: =SUM(ET23,CX23) | GQ23: =SUM(EU23,CY23) | GR23: =SUM(EV23,CZ23) | GS23: =SUM(EW23,DA23) | GT23: =SUM(EX23,DB23) | GU23: =SUM(EY23,DC23) | GV23: =SUM(EZ23,DD23) | GW23: =SUM(FA23,DE23) | ... IE23: =SUM(GI23,EM23) | IF23: =SUM(GP23:HA23) | IG23: =SUM(HB23:HM23) | IH23: =SUM(HN23:HY23) | II23: =SUM(HR23:IC23) | IJ23: =SUM(HT23:IE23) | IL23: =SUMIFS('QofE PF adjustments'!F:F,'QofE PF adjustments'!$E:$E,'Adjusted IS'!$E23) | IM23: =SUMIFS('QofE PF adjustments'!G:G,'QofE PF adjustments'!$E:$E,'Adjusted IS'!$E23) | IN23: =SUMIFS('QofE PF adjustments'!H:H,'QofE PF adjustments'!$E:$E,'Adjusted IS'!$E23) | IO23: =SUMIFS('QofE PF adjustments'!I:I,'QofE PF adjustments'!$E:$E,'Adjusted IS'!$E23) | IP23: =SUMIFS('QofE PF adjustments'!J:J,'QofE PF adjustments'!$E:$E,'Adjusted IS'!$E23) | IQ23: =SUMIFS('QofE PF adjustments'!K:K,'QofE PF adjustments'!$E:$E,'Adjusted IS'!$E23) | IR23: =SUMIFS('QofE PF adjustments'!L:L,'QofE PF adjustments'!$E:$E,'Adjusted IS'!$E23) | IS23: =SUMIFS('QofE PF adjustments'!M:M,'QofE PF adjustments'!$E:$E,'Adjusted IS'!$E23) | IT23: =SUMIFS('QofE PF adjustments'!N:N,'QofE PF adjustments'!$E:$E,'Adjusted IS'!$E23) | IU23: =SUMIFS('QofE PF adjustments'!O:O,'QofE PF adjustments'!$E:$E,'Adjusted IS'!$E23) | IV23: =SUMIFS('QofE PF adjustments'!P:P,'QofE PF adjustments'!$E:$E,'Adjusted IS'!$E23) | IW23: =SUMIFS('QofE PF adjustments'!Q:Q,'QofE PF adjustments'!$E:$E,'Adjusted IS'!$E23) | IX23: =SUMIFS('QofE PF adjustments'!R:R,'QofE PF adjustments'!$E:$E,'Adjusted IS'!$E23) | IY23: =SUMIFS('QofE PF adjustments'!S:S,'QofE PF adjustments'!$E:$E,'Adjusted IS'!$E23) | IZ23: =SUMIFS('QofE PF adjustments'!T:T,'QofE PF adjustments'!$E:$E,'Adjusted IS'!$E23) | JA23: =SUMIFS('QofE PF adjustments'!U:U,'QofE PF adjustments'!$E:$E,'Adjusted IS'!$E23) | JB23: =SUMIFS('QofE PF adjustments'!V:V,'QofE PF adjustments'!$E:$E,'Adjusted IS'!$E23) | JC23: =SUMIFS('QofE PF adjustments'!W:W,'QofE PF adjustments'!$E:$E,'Adjusted IS'!$E23) | JD23: =SUMIFS('QofE PF adjustments'!X:X,'QofE PF adjustments'!$E:$E,'Adjusted IS'!$E23) | JE23: =SUMIFS('QofE PF adjustments'!Y:Y,'QofE PF adjustments'!$E:$E,'Adjusted IS'!$E23) | JF23: =SUMIFS('QofE PF adjustments'!Z:Z,'QofE PF adjustments'!$E:$E,'Adjusted IS'!$E23) | JG23: =SUMIFS('QofE PF adjustments'!AA:AA,'QofE PF adjustments'!$E:$E,'Adjusted IS'!$E23) | JH23: =SUMIFS('QofE PF adjustments'!AB:AB,'QofE PF adjustments'!$E:$E,'Adjusted IS'!$E23) | JI23: =SUMIFS('QofE PF adjustments'!AC:AC,'QofE PF adjustments'!$E:$E,'Adjusted IS'!$E23) | JJ23: =SUMIFS('QofE PF adjustments'!AD:AD,'QofE PF adjustments'!$E:$E,'Adjusted IS'!$E23) | JK23: =SUMIFS('QofE PF adjustments'!AE:AE,'QofE PF adjustments'!$E:$E,'Adjusted IS'!$E23) | JL23: =SUMIFS('QofE PF adjustments'!AF:AF,'QofE PF adjustments'!$E:$E,'Adjusted IS'!$E23) | JM23: =SUMIFS('QofE PF adjustments'!AG:AG,'QofE PF adjustments'!$E:$E,'Adjusted IS'!$E23) | JN23: =SUMIFS('QofE PF adjustments'!AH:AH,'QofE PF adjustments'!$E:$E,'Adjusted IS'!$E23) | JO23: =SUMIFS('QofE PF adjustments'!AI:AI,'QofE PF adjustments'!$E:$E,'Adjusted IS'!$E23) | JP23: =SUMIFS('QofE PF adjustments'!AJ:AJ,'QofE PF adjustments'!$E:$E,'Adjusted IS'!$E23) | JQ23: =SUMIFS('QofE PF adjustments'!AK:AK,'QofE PF adjustments'!$E:$E,'Adjusted IS'!$E23) | JR23: =SUMIFS('QofE PF adjustments'!AL:AL,'QofE PF adjustments'!$E:$E,'Adjusted IS'!$E23) | JS23: =SUMIFS('QofE PF adjustments'!AM:AM,'QofE PF adjustments'!$E:$E,'Adjusted IS'!$E23) | JT23: =SUMIFS('QofE PF adjustments'!AN:AN,'QofE PF adjustments'!$E:$E,'Adjusted IS'!$E23) | JU23: =SUMIFS('QofE PF adjustments'!AO:AO,'QofE PF adjustments'!$E:$E,'Adjusted IS'!$E23) | JV23: =SUMIFS('QofE PF adjustments'!AP:AP,'QofE PF adjustments'!$E:$E,'Adjusted IS'!$E23) | JW23: =SUMIFS('QofE PF adjustments'!AQ:AQ,'QofE PF adjustments'!$E:$E,'Adjusted IS'!$E23) | JX23: =SUMIFS('QofE PF adjustments'!AR:AR,'QofE PF adjustments'!$E:$E,'Adjusted IS'!$E23) | JY23: =SUMIFS('QofE PF adjustments'!AS:AS,'QofE PF adjustments'!$E:$E,'Adjusted IS'!$E23) | JZ23: =SUMIFS('QofE PF adjustments'!AT:AT,'QofE PF adjustments'!$E:$E,'Adjusted IS'!$E23) | KA23: =SUMIFS('QofE PF adjustments'!AU:AU,'QofE PF adjustments'!$E:$E,'Adjusted IS'!$E23) | KB23: =SUM(IL23:IW23) | KC23: =SUM(IX23:JI23) | KD23: =SUM(JJ23:JU23) | KE23: =SUM(JN23:JY23) | KF23: =SUM(JP23:KA23) | KH23: =SUM(IL23,GP23) | KI23: =SUM(IM23,GQ23) | KJ23: =SUM(IN23,GR23) | KK23: =SUM(IO23,GS23) | KL23: =SUM(IP23,GT23) | KM23: =SUM(IQ23,GU23) | KN23: =SUM(IR23,GV23) | KO23: =SUM(IS23,GW23) | ... LW23: =SUM(KA23,IE23) | LX23: =SUM(KH23:KS23) | LY23: =SUM(KT23:LE23) | LZ23: =SUM(LF23:LQ23) | MA23: =SUM(LJ23:LU23) | MB23: =SUM(LL23:LW23) | MD23: =IFERROR(KH23/KH$117,0) | ME23: =IFERROR(KI23/KI$117,0) | MF23: =IFERROR(KJ23/KJ$117,0) | MG23: =IFERROR(KK23/KK$117,0) | MH23: =IFERROR(KL23/KL$117,0) | MI23: =IFERROR(KM23/KM$117,0) | MJ23: =IFERROR(KN23/KN$117,0) | MK23: =IFERROR(KO23/KO$117,0) | ... NX23: =IFERROR(MB23/MB$117,0) | NZ23: =LY23-LX23 | OA23: =LZ23-LY23 | OB23: =MA23-LZ23 | OC23: =MB23-LZ23 | OE23: Processing services revenue | OF23: Processing services revenue | OG23: Processing services revenue
