Workbook
Name Button_429: "LeaseCalc_Lease_Data_List"
Name CellAbove: INDIRECT(ADDRESS(ROW()-1,COLUMN()))
Name CIT: #N/A
Name IQ_CH: 110000
Name IQ_CQ: 5000
Name IQ_CY: 10000
Name IQ_DAILY: 500000
Name IQ_FH: 100000
Name IQ_FQ: 500
Name IQ_FY: 1000
Name IQ_LTM: 2000
Name IQ_MONTH: 15000
Name IQ_NTM: 6000
Name IQ_WEEK: 50000
Name IQ_YTD: 3000
Name TM1REBUILDOPTION: 1

Sheet Stratified BS
B1: Project North
B2: =C7
B3: Source:Everlink Balance Sheet 13 month trend (2021),Everlink Balance Sheet 13 month trend (2022),Everlink Balance Sheet 13 month trend (2023),Everlink Balance Sheet 13 month trend (to April 2024)
B4: WORKING DRAFT
C7: Stratified balance sheet
F8: As at | K8: Stratification as at 30-Apr-24 | O8: Stratification as at 30-Jun-24
C9: $'000 | D9: Code | E9: Concatenate | F9: ='Balance sheet'!AV9 | G9: ='Balance sheet'!AW9 | H9: ='Balance sheet'!AX9 | I9: ='Balance sheet'!AY9 | J9: ='Balance sheet'!AZ9 | K9: NWC | L9: PPE | M9: Net debt | N9: Others | O9: NWC | P9: PPE | Q9: Net cash | R9: Others | T9: Check | U9: Check
C10: Assets | T10: =I10-SUM(K10:N10) | U10: =J10-SUM(O10:R10)
C11: Cash-CAD - CUCA operating | D11: 100210 | E11: 100210 - Cash-CAD - CUCA Operating | F11: ='Balance sheet'!AV11 | G11: ='Balance sheet'!AW11 | H11: ='Balance sheet'!AX11 | I11: ='Balance sheet'!AY11 | J11: ='Balance sheet'!AZ11 | K11: 0 | L11: 0 | M11: =I11 | N11: 0 | O11: 0 | P11: 0 | Q11: =J11 | R11: 0 | T11: =I11-SUM(K11:N11) | U11: =J11-SUM(O11:R11)
C12: Cash -desjardins operating CAD | D12: 100215 | E12: 100215 - CASH -Desjardins Operating CAD | F12: ='Balance sheet'!AV12 | G12: ='Balance sheet'!AW12 | H12: ='Balance sheet'!AX12 | I12: ='Balance sheet'!AY12 | J12: ='Balance sheet'!AZ12 | K12: 0 | L12: 0 | M12: =I12 | N12: 0 | O12: 0 | P12: 0 | Q12: =J12 | R12: 0 | T12: =I12-SUM(K12:N12) | U12: =J12-SUM(O12:R12)
C13: Cash USD - CUCA 079 | D13: 100416 | E13: 100416 - Cash USD - CUCA 079 | F13: ='Balance sheet'!AV13 | G13: ='Balance sheet'!AW13 | H13: ='Balance sheet'!AX13 | I13: ='Balance sheet'!AY13 | J13: ='Balance sheet'!AZ13 | K13: 0 | L13: 0 | M13: =I13 | N13: 0 | O13: 0 | P13: 0 | Q13: =J13 | R13: 0 | T13: =I13-SUM(K13:N13) | U13: =J13-SUM(O13:R13)
C14: Cash USD - BMO harris 137 | D14: 100417 | E14: 100417 - Cash USD - BMO Harris 137 | F14: ='Balance sheet'!AV14 | G14: ='Balance sheet'!AW14 | H14: ='Balance sheet'!AX14 | I14: ='Balance sheet'!AY14 | J14: ='Balance sheet'!AZ14 | K14: 0 | L14: 0 | M14: =I14 | N14: 0 | O14: 0 | P14: 0 | Q14: =J14 | R14: 0 | T14: =I14-SUM(K14:N14) | U14: =J14-SUM(O14:R14)
C15: Cash CAD - CUCA 095 | D15: 100211 | E15: 100211 - Cash CAD - CUCA 095 | F15: ='Balance sheet'!AV15 | G15: ='Balance sheet'!AW15 | H15: ='Balance sheet'!AX15 | I15: ='Balance sheet'!AY15 | J15: ='Balance sheet'!AZ15 | K15: 0 | L15: 0 | M15: =I15 | N15: 0 | O15: 0 | P15: 0 | Q15: =J15 | R15: 0 | T15: =I15-SUM(K15:N15) | U15: =J15-SUM(O15:R15)
C16: Cash and cash equivalents | F16: =SUM(F11:F15) | G16: =SUM(G11:G15) | H16: =SUM(H11:H15) | I16: =SUM(I11:I15) | J16: =SUM(J11:J15) | K16: =SUM(K11:K15) | L16: =SUM(L11:L15) | M16: =SUM(M11:M15) | ... R16: =SUM(R11:R15) | T16: =I16-SUM(K16:N16) | U16: =J16-SUM(O16:R16)
C17: Cash settlement - pos desjardin 147 | D17: 100370 | E17: 100370 - Cash Settlement - POS Desjardin 147 | F17: ='Balance sheet'!AV17 | G17: ='Balance sheet'!AW17 | H17: ='Balance sheet'!AX17 | I17: ='Balance sheet'!AY17 | J17: ='Balance sheet'!AZ17 | K17: =I17 | L17: 0 | M17: 0 | N17: 0 | O17: =J17 | P17: 0 | Q17: 0 | R17: 0 | T17: =I17-SUM(K17:N17) | U17: =J17-SUM(O17:R17)
C18: Cash settlement scd desjardin 139 | D18: 100488 | E18: 100488 - Cash Settlement SCD Desjardin 139 | F18: ='Balance sheet'!AV18 | G18: ='Balance sheet'!AW18 | H18: ='Balance sheet'!AX18 | I18: ='Balance sheet'!AY18 | J18: ='Balance sheet'!AZ18 | K18: =I18 | L18: 0 | M18: 0 | N18: 0 | O18: =J18 | P18: 0 | Q18: 0 | R18: 0 | T18: =I18-SUM(K18:N18) | U18: =J18-SUM(O18:R18)
C19: Icici bank settlement CAD6932- for visa debit | D19: 100350 | E19: 100350 - ICICI Bank Settlement CAD6932- For Visa Debit | F19: ='Balance sheet'!AV19 | G19: ='Balance sheet'!AW19 | H19: ='Balance sheet'!AX19 | I19: ='Balance sheet'!AY19 | J19: ='Balance sheet'!AZ19 | K19: =I19 | L19: 0 | M19: 0 | N19: 0 | O19: =J19 | P19: 0 | Q19: 0 | R19: 0 | T19: =I19-SUM(K19:N19) | U19: =J19-SUM(O19:R19)
C20: Cash settlement e-transfer desj suspense 067 | D20: 100367 | E20: 100367 - Cash Settlement E-Transfer Desj Suspense 067 | F20: ='Balance sheet'!AV20 | G20: ='Balance sheet'!AW20 | H20: ='Balance sheet'!AX20 | I20: ='Balance sheet'!AY20 | J20: ='Balance sheet'!AZ20 | K20: =I20 | L20: 0 | M20: 0 | N20: 0 | O20: =J20 | P20: 0 | Q20: 0 | R20: 0 | T20: =I20-SUM(K20:N20) | U20: =J20-SUM(O20:R20)
C21: Cash settlement CUCA 178 | D21: 100489 | E21: 100489 - Cash Settlement CUCA 178 | F21: ='Balance sheet'!AV21 | G21: ='Balance sheet'!AW21 | H21: ='Balance sheet'!AX21 | I21: ='Balance sheet'!AY21 | J21: ='Balance sheet'!AZ21 | K21: =I21 | L21: 0 | M21: 0 | N21: 0 | O21: =J21 | P21: 0 | Q21: 0 | R21: 0 | T21: =I21-SUM(K21:N21) | U21: =J21-SUM(O21:R21)
C22: Cash settlement - pos 10403- desjardins 1154 | D22: 100373 | E22: 100373 - Cash Settlement - POS 10403- Desjardins 1154 | F22: ='Balance sheet'!AV22 | G22: ='Balance sheet'!AW22 | H22: ='Balance sheet'!AX22 | I22: ='Balance sheet'!AY22 | J22: ='Balance sheet'!AZ22 | K22: =I22 | L22: 0 | M22: 0 | N22: 0 | O22: =J22 | P22: 0 | Q22: 0 | R22: 0 | T22: =I22-SUM(K22:N22) | U22: =J22-SUM(O22:R22)
C23: Cash settlement desj etransf 1162 | D23: 100380 | E23: 100380 - Cash Settlement Desj Etransf 1162 | F23: ='Balance sheet'!AV23 | G23: ='Balance sheet'!AW23 | H23: ='Balance sheet'!AX23 | I23: ='Balance sheet'!AY23 | J23: ='Balance sheet'!AZ23 | K23: =I23 | L23: 0 | M23: 0 | N23: 0 | O23: =J23 | P23: 0 | Q23: 0 | R23: 0 | T23: =I23-SUM(K23:N23) | U23: =J23-SUM(O23:R23)
C24: Cash USD - settlement td bank, n.a 154 | D24: 100418 | E24: 100418 - Cash USD - Settlement TD Bank, N.A 154 | F24: ='Balance sheet'!AV24 | G24: ='Balance sheet'!AW24 | H24: ='Balance sheet'!AX24 | I24: ='Balance sheet'!AY24 | J24: ='Balance sheet'!AZ24 | K24: =I24 | L24: 0 | M24: 0 | N24: 0 | O24: =J24 | P24: 0 | Q24: 0 | R24: 0 | T24: =I24-SUM(K24:N24) | U24: =J24-SUM(O24:R24)
C25: Cash settlement e-transfer desjardins 059 | D25: 100359 | E25: 100359 - Cash Settlement E-Transfer Desjardins 059 | F25: ='Balance sheet'!AV25 | G25: ='Balance sheet'!AW25 | H25: ='Balance sheet'!AX25 | I25: ='Balance sheet'!AY25 | J25: ='Balance sheet'!AZ25 | K25: =I25 | L25: 0 | M25: 0 | N25: 0 | O25: =J25 | P25: 0 | Q25: 0 | R25: 0 | T25: =I25-SUM(K25:N25) | U25: =J25-SUM(O25:R25)
C26: Items in transit | F26: =SUM(F17:F25) | G26: =SUM(G17:G25) | H26: =SUM(H17:H25) | I26: =SUM(I17:I25) | J26: =SUM(J17:J25) | K26: =SUM(K17:K25) | L26: =SUM(L17:L25) | M26: =SUM(M17:M25) | ... R26: =SUM(R17:R25) | T26: =I26-SUM(K26:N26) | U26: =J26-SUM(O26:R26)
C27: A/R billings-subledger | D27: 120101 | E27: 120101 - A/R Billings-Subledger | F27: ='Balance sheet'!AV27 | G27: ='Balance sheet'!AW27 | H27: ='Balance sheet'!AX27 | I27: ='Balance sheet'!AY27 | J27: ='Balance sheet'!AZ27 | K27: =I27 | L27: 0 | M27: 0 | N27: 0 | O27: =J27 | P27: 0 | Q27: 0 | R27: 0 | T27: =I27-SUM(K27:N27) | U27: =J27-SUM(O27:R27)
C28: A/R-trade accrual | D28: 120201 | E28: 120201 - A/R-Trade Accrual | F28: ='Balance sheet'!AV28 | G28: ='Balance sheet'!AW28 | H28: ='Balance sheet'!AX28 | I28: ='Balance sheet'!AY28 | J28: ='Balance sheet'!AZ28 | K28: =I28 | L28: 0 | M28: 0 | N28: 0 | O28: =J28 | P28: 0 | Q28: 0 | R28: 0 | T28: =I28-SUM(K28:N28) | U28: =J28-SUM(O28:R28)
C29: Accrued merchant services fees | D29: 120301 | E29: 120301 - Accrued Merchant Services Fees | F29: ='Balance sheet'!AV29 | G29: ='Balance sheet'!AW29 | H29: ='Balance sheet'!AX29 | I29: ='Balance sheet'!AY29 | J29: ='Balance sheet'!AZ29 | K29: =I29 | L29: 0 | M29: 0 | N29: 0 | O29: =J29 | P29: 0 | Q29: 0 | R29: 0 | T29: =I29-SUM(K29:N29) | U29: =J29-SUM(O29:R29)
C30: Accrued other receivable | D30: 120401 | E30: 120401 - Accrued Other Receivable | F30: ='Balance sheet'!AV30 | G30: ='Balance sheet'!AW30 | H30: ='Balance sheet'!AX30 | I30: ='Balance sheet'!AY30 | J30: ='Balance sheet'!AZ30 | K30: =I30 | L30: 0 | M30: 0 | N30: 0 | O30: =J30 | P30: 0 | Q30: 0 | R30: 0 | T30: =I30-SUM(K30:N30) | U30: =J30-SUM(O30:R30)
C31: Sales tax receivables - HST/GST | D31: 130301 | E31: 130301 - Sales Tax Receivables - HST/GST | F31: ='Balance sheet'!AV31 | G31: ='Balance sheet'!AW31 | H31: ='Balance sheet'!AX31 | I31: ='Balance sheet'!AY31 | J31: ='Balance sheet'!AZ31 | K31: =I31 | L31: 0 | M31: 0 | N31: 0 | O31: =J31 | P31: 0 | Q31: 0 | R31: 0 | T31: =I31-SUM(K31:N31) | U31: =J31-SUM(O31:R31)
C32: Interest receivables | D32: 130101 | E32: 130101 - Interest Receivables | F32: ='Balance sheet'!AV32 | G32: ='Balance sheet'!AW32 | H32: ='Balance sheet'!AX32 | I32: ='Balance sheet'!AY32 | J32: ='Balance sheet'!AZ32 | K32: =I32 | L32: 0 | M32: 0 | N32: 0 | O32: =J32 | P32: 0 | Q32: 0 | R32: 0 | T32: =I32-SUM(K32:N32) | U32: =J32-SUM(O32:R32)
C33: Sales tax receivables - QST | D33: 130300 | E33: 130300 - Sales Tax Receivables - QST | F33: ='Balance sheet'!AV33 | G33: ='Balance sheet'!AW33 | H33: ='Balance sheet'!AX33 | I33: ='Balance sheet'!AY33 | J33: ='Balance sheet'!AZ33 | K33: =I33 | L33: 0 | M33: 0 | N33: 0 | O33: =J33 | P33: 0 | Q33: 0 | R33: 0 | T33: =I33-SUM(K33:N33) | U33: =J33-SUM(O33:R33)
C34: IFRS15 adjustment to accr A/R | D34: 120215 | E34: 120215 - -IFRS15 Adjustment to Accr AR- | F34: ='Balance sheet'!AV34 | G34: ='Balance sheet'!AW34 | H34: ='Balance sheet'!AX34 | I34: ='Balance sheet'!AY34 | J34: ='Balance sheet'!AZ34 | K34: =I34 | L34: 0 | M34: 0 | N34: 0 | O34: =J34 | P34: 0 | Q34: 0 | R34: 0 | T34: =I34-SUM(K34:N34) | U34: =J34-SUM(O34:R34)
C35: Corporate card payments suspense | D35: 143102 | E35: 143102 - Corporate Card Payments Suspense | F35: ='Balance sheet'!AV35 | G35: ='Balance sheet'!AW35 | H35: ='Balance sheet'!AX35 | I35: ='Balance sheet'!AY35 | J35: ='Balance sheet'!AZ35 | K35: =I35 | L35: 0 | M35: 0 | N35: 0 | O35: =J35 | P35: 0 | Q35: 0 | R35: 0 | T35: =I35-SUM(K35:N35) | U35: =J35-SUM(O35:R35)
C36: Allowances for customers A/R | D36: 125101 | E36: 125101 - Allowances for Customers A/R | F36: ='Balance sheet'!AV36 | G36: ='Balance sheet'!AW36 | H36: ='Balance sheet'!AX36 | I36: ='Balance sheet'!AY36 | J36: ='Balance sheet'!AZ36 | K36: =I36 | L36: 0 | M36: 0 | N36: 0 | O36: =J36 | P36: 0 | Q36: 0 | R36: 0 | T36: =I36-SUM(K36:N36) | U36: =J36-SUM(O36:R36)
C37: Accounts receivable and other receivables | F37: =SUM(F27:F36) | G37: =SUM(G27:G36) | H37: =SUM(H27:H36) | I37: =SUM(I27:I36) | J37: =SUM(J27:J36) | K37: =SUM(K27:K36) | L37: =SUM(L27:L36) | M37: =SUM(M27:M36) | ... R37: =SUM(R27:R36) | T37: =I37-SUM(K37:N37) | U37: =J37-SUM(O37:R37)
C38: Inventory - prepaid COGS | D38: 142113 | E38: 142113 - Inventory - Prepaid COGS | F38: ='Balance sheet'!AV38 | G38: ='Balance sheet'!AW38 | H38: ='Balance sheet'!AX38 | I38: ='Balance sheet'!AY38 | J38: ='Balance sheet'!AZ38 | K38: =I38 | L38: 0 | M38: 0 | N38: 0 | O38: =J38 | P38: 0 | Q38: 0 | R38: 0 | T38: =I38-SUM(K38:N38) | U38: =J38-SUM(O38:R38)
C39: Inventory | D39: 142101 | E39: 142101 - Inventory | F39: ='Balance sheet'!AV39 | G39: ='Balance sheet'!AW39 | H39: ='Balance sheet'!AX39 | I39: ='Balance sheet'!AY39 | J39: ='Balance sheet'!AZ39 | K39: =I39 | L39: 0 | M39: 0 | N39: 0 | O39: =J39 | P39: 0 | Q39: 0 | R39: 0 | T39: =I39-SUM(K39:N39) | U39: =J39-SUM(O39:R39)
C40: Inventory - rental units | D40: 142112 | E40: 142112 - Inventory - Rental Units | F40: ='Balance sheet'!AV40 | G40: ='Balance sheet'!AW40 | H40: ='Balance sheet'!AX40 | I40: ='Balance sheet'!AY40 | J40: ='Balance sheet'!AZ40 | K40: =I40 | L40: 0 | M40: 0 | N40: 0 | O40: =J40 | P40: 0 | Q40: 0 | R40: 0 | T40: =I40-SUM(K40:N40) | U40: =J40-SUM(O40:R40)
C41: Inventory | F41: =SUM(F38:F40) | G41: =SUM(G38:G40) | H41: =SUM(H38:H40) | I41: =SUM(I38:I40) | J41: =SUM(J38:J40) | K41: =SUM(K38:K40) | L41: =SUM(L38:L40) | M41: =SUM(M38:M40) | ... R41: =SUM(R38:R40) | T41: =I41-SUM(K41:N41) | U41: =J41-SUM(O41:R41)
C42: Prepaid SW license fees | D42: 141511 | E42: 141511 - Prepaid SW License Fees | F42: ='Balance sheet'!AV42 | G42: ='Balance sheet'!AW42 | H42: ='Balance sheet'!AX42 | I42: ='Balance sheet'!AY42 | J42: ='Balance sheet'!AZ42 | K42: =I42 | L42: 0 | M42: 0 | N42: 0 | O42: =J42 | P42: 0 | Q42: 0 | R42: 0 | T42: =I42-SUM(K42:N42) | U42: =J42-SUM(O42:R42)
C43: Prepaid SW maintenance | D43: 141204 | E43: 141204 - Prepaid SW Maintenance | F43: ='Balance sheet'!AV43 | G43: ='Balance sheet'!AW43 | H43: ='Balance sheet'!AX43 | I43: ='Balance sheet'!AY43 | J43: ='Balance sheet'!AZ43 | K43: =I43 | L43: 0 | M43: 0 | N43: 0 | O43: =J43 | P43: 0 | Q43: 0 | R43: 0 | T43: =I43-SUM(K43:N43) | U43: =J43-SUM(O43:R43)
C44: Prepaid HW maintenance | D44: 141203 | E44: 141203 - Prepaid HW Maintenance | F44: ='Balance sheet'!AV44 | G44: ='Balance sheet'!AW44 | H44: ='Balance sheet'!AX44 | I44: ='Balance sheet'!AY44 | J44: ='Balance sheet'!AZ44 | K44: =I44 | L44: 0 | M44: 0 | N44: 0 | O44: =J44 | P44: 0 | Q44: 0 | R44: 0 | T44: =I44-SUM(K44:N44) | U44: =J44-SUM(O44:R44)
C45: Prepaid insurance | D45: 143201 | E45: 143201 - Prepaid Insurance | F45: ='Balance sheet'!AV45 | G45: ='Balance sheet'!AW45 | H45: ='Balance sheet'!AX45 | I45: ='Balance sheet'!AY45 | J45: ='Balance sheet'!AZ45 | K45: =I45 | L45: 0 | M45: 0 | N45: 0 | O45: =J45 | P45: 0 | Q45: 0 | R45: 0 | T45: =I45-SUM(K45:N45) | U45: =J45-SUM(O45:R45)
C46: Prepaid rent | D46: 143201 | E46: 143201 - Prepaid Rent | F46: ='Balance sheet'!AV46 | G46: ='Balance sheet'!AW46 | H46: ='Balance sheet'!AX46 | I46: ='Balance sheet'!AY46 | J46: ='Balance sheet'!AZ46 | K46: =I46 | L46: 0 | M46: 0 | N46: 0 | O46: =J46 | P46: 0 | Q46: 0 | R46: 0 | T46: =I46-SUM(K46:N46) | U46: =J46-SUM(O46:R46)
C47: Prepaid other miscellaneous | D47: 141501 | E47: 141501 - Prepaid Other Miscellaneous | F47: ='Balance sheet'!AV47 | G47: ='Balance sheet'!AW47 | H47: ='Balance sheet'!AX47 | I47: ='Balance sheet'!AY47 | J47: ='Balance sheet'!AZ47 | K47: =I47 | L47: 0 | M47: 0 | N47: 0 | O47: =J47 | P47: 0 | Q47: 0 | R47: 0 | T47: =I47-SUM(K47:N47) | U47: =J47-SUM(O47:R47)
C48: Prepaid marketing & tradeshow | D48: 141502 | E48: 141502 - Prepaid Marketing & Tradeshow | F48: ='Balance sheet'!AV48 | G48: ='Balance sheet'!AW48 | H48: ='Balance sheet'!AX48 | I48: ='Balance sheet'!AY48 | J48: ='Balance sheet'!AZ48 | K48: =I48 | L48: 0 | M48: 0 | N48: 0 | O48: =J48 | P48: 0 | Q48: 0 | R48: 0 | T48: =I48-SUM(K48:N48) | U48: =J48-SUM(O48:R48)
C49: Prepaid expenses | F49: =SUM(F42:F48) | G49: =SUM(G42:G48) | H49: =SUM(H42:H48) | I49: =SUM(I42:I48) | J49: =SUM(J42:J48) | K49: =SUM(K42:K48) | L49: =SUM(L42:L48) | M49: =SUM(M42:M48) | ... R49: =SUM(R42:R48) | T49: =I49-SUM(K49:N49) | U49: =J49-SUM(O49:R49)
C50: Contract assets current IFRS15 | D50: 148015 | E50: 148015 - Contract Assets Current IFRS15 | F50: ='Balance sheet'!AV50 | G50: ='Balance sheet'!AW50 | H50: ='Balance sheet'!AX50 | I50: ='Balance sheet'!AY50 | J50: ='Balance sheet'!AZ50 | K50: =I50 | L50: 0 | M50: 0 | N50: 0 | O50: =J50 | P50: 0 | Q50: 0 | R50: 0 | T50: =I50-SUM(K50:N50) | U50: =J50-SUM(O50:R50)
C51: Unbilled revenue | F51: =SUM(F50:F50) | G51: =SUM(G50:G50) | H51: =SUM(H50:H50) | I51: =SUM(I50:I50) | J51: =SUM(J50:J50) | K51: =SUM(K50:K50) | L51: =SUM(L50:L50) | M51: =SUM(M50:M50) | ... R51: =SUM(R50:R50) | T51: =I51-SUM(K51:N51) | U51: =J51-SUM(O51:R51)
C52: Current assets | F52: =SUM(F51,F49,F41,F37,F26,F16) | G52: =SUM(G51,G49,G41,G37,G26,G16) | H52: =SUM(H51,H49,H41,H37,H26,H16) | I52: =SUM(I51,I49,I41,I37,I26,I16) | J52: =SUM(J51,J49,J41,J37,J26,J16) | K52: =SUM(K51,K49,K41,K37,K26,K16) | L52: =SUM(L51,L49,L41,L37,L26,L16) | M52: =SUM(M51,M49,M41,M37,M26,M16) | ... R52: =SUM(R51,R49,R41,R37,R26,R16) | T52: =I52-SUM(K52:N52) | U52: =J52-SUM(O52:R52)
C53: Data processing equipment | D53: 150801 | E53: 150801 - Data Processing Equipment | F53: ='Balance sheet'!AV53 | G53: ='Balance sheet'!AW53 | H53: ='Balance sheet'!AX53 | I53: ='Balance sheet'!AY53 | J53: ='Balance sheet'!AZ53 | K53: 0 | L53: =I53 | M53: 0 | N53: 0 | O53: 0 | P53: =J53 | Q53: 0 | R53: 0 | T53: =I53-SUM(K53:N53) | U53: =J53-SUM(O53:R53)
C54: Building - rou asset | D54: 150401 | E54: 150401 - Building - ROU Asset | F54: ='Balance sheet'!AV54 | G54: ='Balance sheet'!AW54 | H54: ='Balance sheet'!AX54 | I54: ='Balance sheet'!AY54 | J54: ='Balance sheet'!AZ54 | K54: 0 | L54: =I54 | M54: 0 | N54: 0 | O54: 0 | P54: =J54 | Q54: 0 | R54: 0 | T54: =I54-SUM(K54:N54) | U54: =J54-SUM(O54:R54)
C55: Leased asset | D55: 150920 | E55: 150920 - Leased Asset | F55: ='Balance sheet'!AV55 | G55: ='Balance sheet'!AW55 | H55: ='Balance sheet'!AX55 | I55: ='Balance sheet'!AY55 | J55: ='Balance sheet'!AZ55 | K55: 0 | L55: =I55 | M55: 0 | N55: 0 | O55: 0 | P55: =J55 | Q55: 0 | R55: 0 | T55: =I55-SUM(K55:N55) | U55: =J55-SUM(O55:R55)
C56: Leasehold improvements | D56: 150501 | E56: 150501 - Leasehold Improvements | F56: ='Balance sheet'!AV56 | G56: ='Balance sheet'!AW56 | H56: ='Balance sheet'!AX56 | I56: ='Balance sheet'!AY56 | J56: ='Balance sheet'!AZ56 | K56: 0 | L56: =I56 | M56: 0 | N56: 0 | O56: 0 | P56: =J56 | Q56: 0 | R56: 0 | T56: =I56-SUM(K56:N56) | U56: =J56-SUM(O56:R56)
C57: Capitalize HW implementation | D57: 150901 | E57: 150901 - Capitalize HW Implementation | F57: ='Balance sheet'!AV57 | G57: ='Balance sheet'!AW57 | H57: ='Balance sheet'!AX57 | I57: ='Balance sheet'!AY57 | J57: ='Balance sheet'!AZ57 | K57: 0 | L57: =I57 | M57: 0 | N57: 0 | O57: 0 | P57: =J57 | Q57: 0 | R57: 0 | T57: =I57-SUM(K57:N57) | U57: =J57-SUM(O57:R57)
C58: Network equipment | D58: 150820 | E58: 150820 - Network Equipment | F58: ='Balance sheet'!AV58 | G58: ='Balance sheet'!AW58 | H58: ='Balance sheet'!AX58 | I58: ='Balance sheet'!AY58 | J58: ='Balance sheet'!AZ58 | K58: 0 | L58: =I58 | M58: 0 | N58: 0 | O58: 0 | P58: =J58 | Q58: 0 | R58: 0 | T58: =I58-SUM(K58:N58) | U58: =J58-SUM(O58:R58)
C59: Furniture and fixtures | D59: 150601 | E59: 150601 - Furniture and Fixtures | F59: ='Balance sheet'!AV59 | G59: ='Balance sheet'!AW59 | H59: ='Balance sheet'!AX59 | I59: ='Balance sheet'!AY59 | J59: ='Balance sheet'!AZ59 | K59: 0 | L59: =I59 | M59: 0 | N59: 0 | O59: 0 | P59: =J59 | Q59: 0 | R59: 0 | T59: =I59-SUM(K59:N59) | U59: =J59-SUM(O59:R59)
C60: Purchased fixed assets - WIP | D60: 151101 | E60: 151101 - Purchased Fixed Assets - WIP | F60: ='Balance sheet'!AV60 | G60: ='Balance sheet'!AW60 | H60: ='Balance sheet'!AX60 | I60: ='Balance sheet'!AY60 | J60: ='Balance sheet'!AZ60 | K60: 0 | L60: =I60 | M60: 0 | N60: 0 | O60: 0 | P60: =J60 | Q60: 0 | R60: 0 | T60: =I60-SUM(K60:N60) | U60: =J60-SUM(O60:R60)
C61: Office equipment | D61: 150701 | E61: 150701 - Office Equipment | F61: ='Balance sheet'!AV61 | G61: ='Balance sheet'!AW61 | H61: ='Balance sheet'!AX61 | I61: ='Balance sheet'!AY61 | J61: ='Balance sheet'!AZ61 | K61: 0 | L61: =I61 | M61: 0 | N61: 0 | O61: 0 | P61: =J61 | Q61: 0 | R61: 0 | T61: =I61-SUM(K61:N61) | U61: =J61-SUM(O61:R61)
C62: Network equipment - WIP | D62: 151120 | E62: 151120 - Network Equipment - WIP | F62: ='Balance sheet'!AV62 | G62: ='Balance sheet'!AW62 | H62: ='Balance sheet'!AX62 | I62: ='Balance sheet'!AY62 | J62: ='Balance sheet'!AZ62 | K62: 0 | L62: =I62 | M62: 0 | N62: 0 | O62: 0 | P62: =J62 | Q62: 0 | R62: 0 | T62: =I62-SUM(K62:N62) | U62: =J62-SUM(O62:R62)
C63: Cap HW implementation - WIP | D63: 151105 | E63: 151105 - Cap HW implementation - WIP | F63: ='Balance sheet'!AV63 | G63: ='Balance sheet'!AW63 | H63: ='Balance sheet'!AX63 | I63: ='Balance sheet'!AY63 | J63: ='Balance sheet'!AZ63 | K63: 0 | L63: =I63 | M63: 0 | N63: 0 | O63: 0 | P63: =J63 | Q63: 0 | R63: 0 | T63: =I63-SUM(K63:N63) | U63: =J63-SUM(O63:R63)
C64: Accum dep - office equipment | D64: 155701 | E64: 155701 - Accum Dep - Office Equipment | F64: ='Balance sheet'!AV64 | G64: ='Balance sheet'!AW64 | H64: ='Balance sheet'!AX64 | I64: ='Balance sheet'!AY64 | J64: ='Balance sheet'!AZ64 | K64: 0 | L64: =I64 | M64: 0 | N64: 0 | O64: 0 | P64: =J64 | Q64: 0 | R64: 0 | T64: =I64-SUM(K64:N64) | U64: =J64-SUM(O64:R64)
... C71: Accum dep - data processing equipment | D71: 155801 | E71: 155801 - Accum Dep - Data Processing Equipment | F71: ='Balance sheet'!AV71 | G71: ='Balance sheet'!AW71 | H71: ='Balance sheet'!AX71 | I71: ='Balance sheet'!AY71 | J71: ='Balance sheet'!AZ71 | K71: 0 | L71: =I71 | M71: 0 | N71: 0 | O71: 0 | P71: =J71 | Q71: 0 | R71: 0 | T71: =I71-SUM(K71:N71) | U71: =J71-SUM(O71:R71)
C72: Property & equipment | F72: =SUM(F53:F71) | G72: =SUM(G53:G71) | H72: =SUM(H53:H71) | I72: =SUM(I53:I71) | J72: =SUM(J53:J71) | K72: =SUM(K53:K71) | L72: =SUM(L53:L71) | M72: =SUM(M53:M71) | ... R72: =SUM(R53:R71) | T72: =I72-SUM(K72:N72) | U72: =J72-SUM(O72:R72)
C73: IDSW - capitalized projects | D73: 170801 | E73: 170801 - IDSW - Capitalized Projects | F73: ='Balance sheet'!AV73 | G73: ='Balance sheet'!AW73 | H73: ='Balance sheet'!AX73 | I73: ='Balance sheet'!AY73 | J73: ='Balance sheet'!AZ73 | K73: 0 | L73: =I73 | M73: 0 | N73: 0 | O73: 0 | P73: =J73 | Q73: 0 | R73: 0 | T73: =I73-SUM(K73:N73) | U73: =J73-SUM(O73:R73)
C74: IDSW capitalized projects WIP | D74: 170805 | E74: 170805 - IDSW Capitalized Projects WIP | F74: ='Balance sheet'!AV74 | G74: ='Balance sheet'!AW74 | H74: ='Balance sheet'!AX74 | I74: ='Balance sheet'!AY74 | J74: ='Balance sheet'!AZ74 | K74: 0 | L74: =I74 | M74: 0 | N74: 0 | O74: 0 | P74: =J74 | Q74: 0 | R74: 0 | T74: =I74-SUM(K74:N74) | U74: =J74-SUM(O74:R74)
C75: Accum amort - IDSW capitalized projects | D75: 175801 | E75: 175801 - Accum Amort - IDSW Capitalized Projects | F75: ='Balance sheet'!AV75 | G75: ='Balance sheet'!AW75 | H75: ='Balance sheet'!AX75 | I75: ='Balance sheet'!AY75 | J75: ='Balance sheet'!AZ75 | K75: 0 | L75: =I75 | M75: 0 | N75: 0 | O75: 0 | P75: =J75 | Q75: 0 | R75: 0 | T75: =I75-SUM(K75:N75) | U75: =J75-SUM(O75:R75)
C76: Capitalized development | F76: =SUM(F73:F75) | G76: =SUM(G73:G75) | H76: =SUM(H73:H75) | I76: =SUM(I73:I75) | J76: =SUM(J73:J75) | K76: =SUM(K73:K75) | L76: =SUM(L73:L75) | M76: =SUM(M73:M75) | ... R76: =SUM(R73:R75) | T76: =I76-SUM(K76:N76) | U76: =J76-SUM(O76:R76)
C77: Purchased software | D77: 170101 | E77: 170101 - Purchased Software | F77: ='Balance sheet'!AV77 | G77: ='Balance sheet'!AW77 | H77: ='Balance sheet'!AX77 | I77: ='Balance sheet'!AY77 | J77: ='Balance sheet'!AZ77 | K77: 0 | L77: =I77 | M77: 0 | N77: 0 | O77: 0 | P77: =J77 | Q77: 0 | R77: 0 | T77: =I77-SUM(K77:N77) | U77: =J77-SUM(O77:R77)
C78: Purchased software - WIP | D78: 170151 | E78: 170151 - Purchased Software - WIP | F78: ='Balance sheet'!AV78 | G78: ='Balance sheet'!AW78 | H78: ='Balance sheet'!AX78 | I78: ='Balance sheet'!AY78 | J78: ='Balance sheet'!AZ78 | K78: 0 | L78: =I78 | M78: 0 | N78: 0 | O78: 0 | P78: =J78 | Q78: 0 | R78: 0 | T78: =I78-SUM(K78:N78) | U78: =J78-SUM(O78:R78)
C79: System software purchased- infrastructure | D79: 170121 | E79: 170121 - System Software Purchased- Infrastructure | F79: ='Balance sheet'!AV79 | G79: ='Balance sheet'!AW79 | H79: ='Balance sheet'!AX79 | I79: ='Balance sheet'!AY79 | J79: ='Balance sheet'!AZ79 | K79: 0 | L79: =I79 | M79: 0 | N79: 0 | O79: 0 | P79: =J79 | Q79: 0 | R79: 0 | T79: =I79-SUM(K79:N79) | U79: =J79-SUM(O79:R79)
C80: Accum amort - system software- infrastructure | D80: 175121 | E80: 175121 - Accum Amort - System Software- Infrastructure | F80: ='Balance sheet'!AV80 | G80: ='Balance sheet'!AW80 | H80: ='Balance sheet'!AX80 | I80: ='Balance sheet'!AY80 | J80: ='Balance sheet'!AZ80 | K80: 0 | L80: =I80 | M80: 0 | N80: 0 | O80: 0 | P80: =J80 | Q80: 0 | R80: 0 | T80: =I80-SUM(K80:N80) | U80: =J80-SUM(O80:R80)
C81: Accum amort - purchased software | D81: 175101 | E81: 175101 - Accum Amort - Purchased Software | F81: ='Balance sheet'!AV81 | G81: ='Balance sheet'!AW81 | H81: ='Balance sheet'!AX81 | I81: ='Balance sheet'!AY81 | J81: ='Balance sheet'!AZ81 | K81: 0 | L81: =I81 | M81: 0 | N81: 0 | O81: 0 | P81: =J81 | Q81: 0 | R81: 0 | T81: =I81-SUM(K81:N81) | U81: =J81-SUM(O81:R81)
C82: Purchased software assets | F82: =SUM(F77:F81) | G82: =SUM(G77:G81) | H82: =SUM(H77:H81) | I82: =SUM(I77:I81) | J82: =SUM(J77:J81) | K82: =SUM(K77:K81) | L82: =SUM(L77:L81) | M82: =SUM(M77:M81) | ... R82: =SUM(R77:R81) | T82: =I82-SUM(K82:N82) | U82: =J82-SUM(O82:R82)
C83: Goodwill | D83: 160101 | E83: 160101 - Goodwill | F83: ='Balance sheet'!AV83 | G83: ='Balance sheet'!AW83 | H83: ='Balance sheet'!AX83 | I83: ='Balance sheet'!AY83 | J83: ='Balance sheet'!AZ83 | K83: 0 | L83: 0 | M83: 0 | N83: =I83 | O83: 0 | P83: 0 | Q83: 0 | R83: =J83 | T83: =I83-SUM(K83:N83) | U83: =J83-SUM(O83:R83)
C84: Goodwill | F84: =SUM(F83:F83) | G84: =SUM(G83:G83) | H84: =SUM(H83:H83) | I84: =SUM(I83:I83) | J84: =SUM(J83:J83) | K84: =SUM(K83:K83) | L84: =SUM(L83:L83) | M84: =SUM(M83:M83) | ... R84: =SUM(R83:R83) | T84: =I84-SUM(K84:N84) | U84: =J84-SUM(O84:R84)
C85: Investment in shares - interac | D85: 180101 | E85: 180101 - Investment in Shares - Interac | F85: ='Balance sheet'!AV85 | G85: ='Balance sheet'!AW85 | H85: ='Balance sheet'!AX85 | I85: ='Balance sheet'!AY85 | J85: ='Balance sheet'!AZ85 | K85: 0 | L85: 0 | M85: 0 | N85: =I85 | O85: 0 | P85: 0 | Q85: 0 | R85: =J85 | T85: =I85-SUM(K85:N85) | U85: =J85-SUM(O85:R85)
C86: Investment in interac | F86: =SUM(F85:F85) | G86: =SUM(G85:G85) | H86: =SUM(H85:H85) | I86: =SUM(I85:I85) | J86: =SUM(J85:J85) | K86: =SUM(K85:K85) | L86: =SUM(L85:L85) | M86: =SUM(M85:M85) | ... R86: =SUM(R85:R85) | T86: =I86-SUM(K86:N86) | U86: =J86-SUM(O86:R86)
C87: Contract assets - lT IFRS15 | D87: 191515 | E87: 191515 - CONTRACT ASSETS - LT IFRS15 | F87: ='Balance sheet'!AV87 | G87: ='Balance sheet'!AW87 | H87: ='Balance sheet'!AX87 | I87: ='Balance sheet'!AY87 | J87: ='Balance sheet'!AZ87 | K87: =I87 | L87: 0 | M87: 0 | N87: 0 | O87: =J87 | P87: 0 | Q87: 0 | R87: 0 | T87: =I87-SUM(K87:N87) | U87: =J87-SUM(O87:R87)
C88: Deferred implementation costs - non-current | F88: =SUM(F87:F87) | G88: =SUM(G87:G87) | H88: =SUM(H87:H87) | I88: =SUM(I87:I87) | J88: =SUM(J87:J87) | K88: =SUM(K87:K87) | L88: =SUM(L87:L87) | M88: =SUM(M87:M87) | ... R88: =SUM(R87:R87) | T88: =I88-SUM(K88:N88) | U88: =J88-SUM(O88:R88)
C89: Long-term prepayments | D89: 192201 | E89: 192201 - Long-Term Prepayments | F89: ='Balance sheet'!AV89 | G89: ='Balance sheet'!AW89 | H89: ='Balance sheet'!AX89 | I89: ='Balance sheet'!AY89 | J89: ='Balance sheet'!AZ89 | K89: 0 | L89: 0 | M89: 0 | N89: =I89 | O89: 0 | P89: 0 | Q89: 0 | R89: =J89 | T89: =I89-SUM(K89:N89) | U89: =J89-SUM(O89:R89)
C90: Long-term security deposit | D90: 192202 | E90: 192202 - Long-Term Security Deposit | F90: ='Balance sheet'!AV90 | G90: ='Balance sheet'!AW90 | H90: ='Balance sheet'!AX90 | I90: ='Balance sheet'!AY90 | J90: ='Balance sheet'!AZ90 | K90: 0 | L90: 0 | M90: 0 | N90: =I90 | O90: 0 | P90: 0 | Q90: 0 | R90: =J90 | T90: =I90-SUM(K90:N90) | U90: =J90-SUM(O90:R90)
C91: Long term COGS lock n block | D91: 192203 | E91: 192203 - Long Term COGS Lock N Block | F91: ='Balance sheet'!AV91 | G91: ='Balance sheet'!AW91 | H91: ='Balance sheet'!AX91 | I91: ='Balance sheet'!AY91 | J91: ='Balance sheet'!AZ91 | K91: 0 | L91: 0 | M91: 0 | N91: =I91 | O91: 0 | P91: 0 | Q91: 0 | R91: =J91 | T91: =I91-SUM(K91:N91) | U91: =J91-SUM(O91:R91)
C92: Long-term sec deposit IFRS adj-corp | D92: 192216 | E92: 192216 - Long-Term Sec Deposit IFRS ADJ-Corp | F92: ='Balance sheet'!AV92 | G92: ='Balance sheet'!AW92 | H92: ='Balance sheet'!AX92 | I92: ='Balance sheet'!AY92 | J92: ='Balance sheet'!AZ92 | K92: 0 | L92: 0 | M92: 0 | N92: =I92 | O92: 0 | P92: 0 | Q92: 0 | R92: =J92 | T92: =I92-SUM(K92:N92) | U92: =J92-SUM(O92:R92)
C93: Prepaid contractual payments - non-current | F93: =SUM(F89:F92) | G93: =SUM(G89:G92) | H93: =SUM(H89:H92) | I93: =SUM(I89:I92) | J93: =SUM(J89:J92) | K93: =SUM(K89:K92) | L93: =SUM(L89:L92) | M93: =SUM(M89:M92) | ... R93: =SUM(R89:R92) | T93: =I93-SUM(K93:N93) | U93: =J93-SUM(O93:R93)
C94: Non current assets | F94: =SUM(F72,F76,F82,F84,F86,F88,F93) | G94: =SUM(G72,G76,G82,G84,G86,G88,G93) | H94: =SUM(H72,H76,H82,H84,H86,H88,H93) | I94: =SUM(I72,I76,I82,I84,I86,I88,I93) | J94: =SUM(J72,J76,J82,J84,J86,J88,J93) | K94: =SUM(K72,K76,K82,K84,K86,K88,K93) | L94: =SUM(L72,L76,L82,L84,L86,L88,L93) | M94: =SUM(M72,M76,M82,M84,M86,M88,M93) | ... R94: =SUM(R72,R76,R82,R84,R86,R88,R93) | T94: =I94-SUM(K94:N94) | U94: =J94-SUM(O94:R94)
C95: Assets | F95: =SUM(F94,F52) | G95: =SUM(G94,G52) | H95: =SUM(H94,H52) | I95: =SUM(I94,I52) | J95: =SUM(J94,J52) | K95: =SUM(K94,K52) | L95: =SUM(L94,L52) | M95: =SUM(M94,M52) | ... R95: =SUM(R94,R52) | T95: =I95-SUM(K95:N95) | U95: =J95-SUM(O95:R95)
C96: Liabilities
C97: Trade accounts payable - CAD | D97: 200101 | E97: 200101 - Trade Accounts Payable - CAD | F97: ='Balance sheet'!AV97 | G97: ='Balance sheet'!AW97 | H97: ='Balance sheet'!AX97 | I97: ='Balance sheet'!AY97 | J97: ='Balance sheet'!AZ97 | K97: =I97 | L97: 0 | M97: 0 | N97: 0 | O97: =J97 | P97: 0 | Q97: 0 | R97: 0 | T97: =I97-SUM(K97:N97) | U97: =J97-SUM(O97:R97)
C98: Trade accounts payable - USD | D98: 200101 | E98: 200101 - Trade Accounts Payable - USD | F98: ='Balance sheet'!AV98 | G98: ='Balance sheet'!AW98 | H98: ='Balance sheet'!AX98 | I98: ='Balance sheet'!AY98 | J98: ='Balance sheet'!AZ98 | K98: =I98 | L98: 0 | M98: 0 | N98: 0 | O98: =J98 | P98: 0 | Q98: 0 | R98: 0 | T98: =I98-SUM(K98:N98) | U98: =J98-SUM(O98:R98)
C99: Trade accounts payable | F99: =SUM(F97:F98) | G99: =SUM(G97:G98) | H99: =SUM(H97:H98) | I99: =SUM(I97:I98) | J99: =SUM(J97:J98) | K99: =SUM(K97:K98) | L99: =SUM(L97:L98) | M99: =SUM(M97:M98) | ... R99: =SUM(R97:R98) | T99: =I99-SUM(K99:N99) | U99: =J99-SUM(O99:R99)
C100: Accrued liabilities - COGS | D100: 214102 | E100: 214102 - Accrued Liabilities - COGS | F100: ='Balance sheet'!AV100 | G100: ='Balance sheet'!AW100 | H100: ='Balance sheet'!AX100 | I100: ='Balance sheet'!AY100 | J100: ='Balance sheet'!AZ100 | K100: =I100 | L100: 0 | M100: 0 | N100: 0 | O100: =J100 | P100: 0 | Q100: 0 | R100: 0 | T100: =I100-SUM(K100:N100) | U100: =J100-SUM(O100:R100)
C101: Accrued liabilites - general | D101: 214101 | E101: 214101 - Accrued Liabilites - General | F101: ='Balance sheet'!AV101 | G101: ='Balance sheet'!AW101 | H101: ='Balance sheet'!AX101 | I101: ='Balance sheet'!AY101 | J101: ='Balance sheet'!AZ101 | K101: =I101 | L101: 0 | M101: 0 | N101: 0 | O101: =J101 | P101: 0 | Q101: 0 | R101: 0 | T101: =I101-SUM(K101:N101) | U101: =J101-SUM(O101:R101)
C102: Accrued liabilities -c2c conversions team | D102: 214101 | E102: 214101 - Accrued Liabilities -C2C Conversions Team | F102: ='Balance sheet'!AV102 | G102: ='Balance sheet'!AW102 | H102: ='Balance sheet'!AX102 | I102: ='Balance sheet'!AY102 | J102: ='Balance sheet'!AZ102 | K102: =I102 | L102: 0 | M102: 0 | N102: 0 | O102: =J102 | P102: 0 | Q102: 0 | R102: 0 | T102: =I102-SUM(K102:N102) | U102: =J102-SUM(O102:R102)
C103: Accrued liabilities - celero and cu centrals | D103: 214103 | E103: 214103 - Accrued Liabilities - Celero and CU Centrals | F103: ='Balance sheet'!AV103 | G103: ='Balance sheet'!AW103 | H103: ='Balance sheet'!AX103 | I103: ='Balance sheet'!AY103 | J103: ='Balance sheet'!AZ103 | K103: =I103 | L103: 0 | M103: 0 | N103: 0 | O103: =J103 | P103: 0 | Q103: 0 | R103: 0 | T103: =I103-SUM(K103:N103) | U103: =J103-SUM(O103:R103)
C104: Accrued liabilities -intercompany - co-op vcas | D104: 249850 | E104: 249850 - Accrued Liabilities -Intercompany - Co-Op VCAS | F104: ='Balance sheet'!AV104 | G104: ='Balance sheet'!AW104 | H104: ='Balance sheet'!AX104 | I104: ='Balance sheet'!AY104 | J104: ='Balance sheet'!AZ104 | K104: =I104 | L104: 0 | M104: 0 | N104: 0 | O104: =J104 | P104: 0 | Q104: 0 | R104: 0 | T104: =I104-SUM(K104:N104) | U104: =J104-SUM(O104:R104)
C105: Accrued liabilities - fixed assets | D105: 214105 | E105: 214105 - Accrued Liabilities - Fixed Assets | F105: ='Balance sheet'!AV105 | G105: ='Balance sheet'!AW105 | H105: ='Balance sheet'!AX105 | I105: ='Balance sheet'!AY105 | J105: ='Balance sheet'!AZ105 | K105: =I105 | L105: 0 | M105: 0 | N105: 0 | O105: =J105 | P105: 0 | Q105: 0 | R105: 0 | T105: =I105-SUM(K105:N105) | U105: =J105-SUM(O105:R105)
C106: Accrued liabilities | F106: =SUM(F100:F105) | G106: =SUM(G100:G105) | H106: =SUM(H100:H105) | I106: =SUM(I100:I105) | J106: =SUM(J100:J105) | K106: =SUM(K100:K105) | L106: =SUM(L100:L105) | M106: =SUM(M100:M105) | ... R106: =SUM(R100:R105) | T106: =I106-SUM(K106:N106) | U106: =J106-SUM(O106:R106)
C107: Sales tax payable - PST BC | D107: 208323 | E107: 208323 - Sales Tax Payable - PST BC | F107: ='Balance sheet'!AV107 | G107: ='Balance sheet'!AW107 | H107: ='Balance sheet'!AX107 | I107: ='Balance sheet'!AY107 | J107: ='Balance sheet'!AZ107 | K107: =I107 | L107: 0 | M107: 0 | N107: 0 | O107: =J107 | P107: 0 | Q107: 0 | R107: 0 | T107: =I107-SUM(K107:N107) | U107: =J107-SUM(O107:R107)
C108: Sales tax payable - HST/GST | D108: 208319 | E108: 208319 - Sales Tax Payable - HST/GST | F108: ='Balance sheet'!AV108 | G108: ='Balance sheet'!AW108 | H108: ='Balance sheet'!AX108 | I108: ='Balance sheet'!AY108 | J108: ='Balance sheet'!AZ108 | K108: =I108 | L108: 0 | M108: 0 | N108: 0 | O108: =J108 | P108: 0 | Q108: 0 | R108: 0 | T108: =I108-SUM(K108:N108) | U108: =J108-SUM(O108:R108)
...
