Workbook
Name Button_429: "LeaseCalc_Lease_Data_List"
Name CellAbove: INDIRECT(ADDRESS(ROW()-1,COLUMN()))
Name CIT: #N/A
Name IQ_CH: 110000
Name IQ_CQ: 5000
Name IQ_CY: 10000
Name IQ_DAILY: 500000
Name IQ_FH: 100000
Name IQ_FQ: 500
Name IQ_FY: 1000
Name IQ_LTM: 2000
Name IQ_MONTH: 15000
Name IQ_NTM: 6000
Name IQ_WEEK: 50000
Name IQ_YTD: 3000
Name TM1REBUILDOPTION: 1

Sheet Combined | BS
A1: Combined BS
A2: Source: trial_balance.xlsx (Process-TB)
A7: Combined BS
A8: LineKey | B8: $'000 | C8: TB Account No. | D8: Sign | E8: Source | F8: Comments | G8: ='Control | Setup'!A22 | H8: ='Control | Setup'!A23 | I8: ='Control | Setup'!A24 | J8: ='Control | Setup'!A25 | K8: ='Control | Setup'!A26 | L8: ='Control | Setup'!A27 | M8: ='Control | Setup'!A28 | N8: ='Control | Setup'!A29 | O8: ='Control | Setup'!A30 | P8: ='Control | Setup'!A31 | Q8: ='Control | Setup'!A32 | R8: ='Control | Setup'!A33 | S8: ='Control | Setup'!A34 | T8: ='Control | Setup'!A35 | U8: ='Control | Setup'!A36 | V8: ='Control | Setup'!A37 | W8: ='Control | Setup'!A38 | X8: ='Control | Setup'!A39 | Y8: ='Control | Setup'!A40 | Z8: ='Control | Setup'!A41 | AA8: ='Control | Setup'!A42 | AB8: ='Control | Setup'!A43 | AC8: ='Control | Setup'!A44 | AD8: ='Control | Setup'!A45 | AE8: ='Control | Setup'!A46 | AF8: ='Control | Setup'!A47 | AG8: ='Control | Setup'!A48 | AH8: ='Control | Setup'!A49 | AI8: ='Control | Setup'!A50 | AJ8: ='Control | Setup'!A51 | AK8: ='Control | Setup'!A52 | AL8: ='Control | Setup'!A53 | AM8: ='Control | Setup'!A54 | AN8: ='Control | Setup'!A55 | AO8: ='Control | Setup'!A56 | AP8: ='Control | Setup'!A57 | AQ8: FY-2 | AR8: FY-1 | AS8: TTM
A9: BS_CASH | B9: Cash | C9: 1000 | D9: + | E9: TB/Map | G9: 41023.7 | H9: 39557.06 | I9: 41651.14 | J9: 42756.86 | K9: 40812.07 | L9: 46209.07 | M9: 44163.1 | N9: 42719.75 | O9: 45430.74 | P9: 48988.91 | Q9: 790023.03 | R9: 597759.4 | S9: 1776541 | T9: 2119578.4 | U9: 2783985.6 | V9: 2889533.3 | W9: 3539303.8 | X9: 3655467.1 | Y9: 4442624.4 | Z9: 4272562.2 | AA9: 5042780.5 | AB9: 5840215.5 | AC9: 5841481.2 | AD9: 7373215.5 | AE9: 7460901.3 | AF9: 8124172.7 | AG9: 8483836.4 | AH9: 9180881.4 | AI9: 9134460.2 | AJ9: 10236007 | AK9: 10739499 | AL9: 10865231 | AM9: 11564415 | AN9: 11204133 | AO9: 12901042 | AP9: 14066236 | AQ9: =R9 | AR9: =AD9 | AS9: =AP9
A10: BS_AR | B10: Accounts receivable | C10: 1100 | D10: + | E10: TB/Map | G10: 2859867.6 | H10: 3284302.4 | I10: 2780941.5 | J10: 2960219.1 | K10: 3381777 | L10: 3623144.2 | M10: 3167504.2 | N10: 2895578.2 | O10: 3777888.5 | P10: 3683078.5 | Q10: 3457882.9 | R10: 3950095.5 | S10: 2935322.7 | T10: 3115596 | U10: 3049858.8 | V10: 3484456.4 | W10: 3388050.7 | X10: 3591192.3 | Y10: 3566598.7 | Z10: 4162721.4 | AA10: 3804972 | AB10: 4271643 | AC10: 4900906.4 | AD10: 3750479.7 | AE10: 3814697.6 | AF10: 4032361.2 | AG10: 4215050.5 | AH10: 4121441.7 | AI10: 4531517.5 | AJ10: 4352517.3 | AK10: 4449577 | AL10: 4758999.6 | AM10: 4434027.8 | AN10: 5913684.7 | AO10: 5286741.5 | AP10: 4983244.9 | AQ10: =R10 | AR10: =AD10 | AS10: =AP10
A11: BS_INV | B11: Inventory | C11: 1200 | D11: + | E11: TB/Map | G11: 0 | H11: 0 | I11: 0 | J11: 0 | K11: 0 | L11: 0 | M11: 0 | N11: 0 | O11: 0 | P11: 0 | Q11: 0 | R11: 0 | S11: 0 | T11: 0 | U11: 0 | V11: 0 | W11: 0 | X11: 0 | Y11: 0 | Z11: 0 | AA11: 0 | AB11: 0 | AC11: 0 | AD11: 0 | AE11: 0 | AF11: 0 | AG11: 0 | AH11: 0 | AI11: 0 | AJ11: 0 | AK11: 0 | AL11: 0 | AM11: 0 | AN11: 0 | AO11: 0 | AP11: 0 | AQ11: =R11 | AR11: =AD11 | AS11: =AP11
A12: BS_OCA | B12: Other current assets | C12: 1300 | D12: + | E12: TB/Map | G12: 41023.7 | H12: 39557.06 | I12: 41651.14 | J12: 42756.86 | K12: 40812.07 | L12: 46209.07 | M12: 44163.1 | N12: 42719.75 | O12: 45430.74 | P12: 48988.91 | Q12: 48321.24 | R12: 52589.24 | S12: 42877.99 | T12: 42291.51 | U12: 44832.92 | V12: 47702.08 | W12: 46044.19 | X12: 49873.88 | Y12: 51621.34 | Z12: 51662.45 | AA12: 51545.86 | AB12: 59063.04 | AC12: 59399.61 | AD12: 55210.59 | AE12: 53992.28 | AF12: 53375.31 | AG12: 53728.94 | AH12: 55996.12 | AI12: 55606.98 | AJ12: 63317.26 | AK12: 58729.88 | AL12: 60013.37 | AM12: 59834.49 | AN12: 71183.1 | AO12: 69659.04 | AP12: 73429.05 | AQ12: =R12 | AR12: =AD12 | AS12: =AP12
A13: BS_TCA | B13: Total current assets | D13: + | E13: Formula | F13: Derived | G13: =IF(COUNT(G9:G12)=0,"",SUM(G9:G12)) | H13: =IF(COUNT(H9:H12)=0,"",SUM(H9:H12)) | I13: =IF(COUNT(I9:I12)=0,"",SUM(I9:I12)) | J13: =IF(COUNT(J9:J12)=0,"",SUM(J9:J12)) | K13: =IF(COUNT(K9:K12)=0,"",SUM(K9:K12)) | L13: =IF(COUNT(L9:L12)=0,"",SUM(L9:L12)) | M13: =IF(COUNT(M9:M12)=0,"",SUM(M9:M12)) | N13: =IF(COUNT(N9:N12)=0,"",SUM(N9:N12)) | ... AP13: =IF(COUNT(AP9:AP12)=0,"",SUM(AP9:AP12)) | AQ13: =R13 | AR13: =AD13 | AS13: =AP13
A14: BS_PPE | B14: PP&E | C14: 1500 | D14: + | E14: TB/Map | G14: 3545589 | H14: 3552680.1 | I14: 3559771.3 | J14: 3566862.5 | K14: 3573953.7 | L14: 3581044.9 | M14: 3588136 | N14: 3595227.2 | O14: 3602318.4 | P14: 3609409.6 | Q14: 3616500.8 | R14: 3623591.9 | S14: 3630683.1 | T14: 3637774.3 | U14: 3644865.5 | V14: 3651956.6 | W14: 3659047.8 | X14: 3666139 | Y14: 3673230.2 | Z14: 3680321.4 | AA14: 3687412.5 | AB14: 3694503.7 | AC14: 3701594.9 | AD14: 3708686.1 | AE14: 3715777.2 | AF14: 3722868.4 | AG14: 3729959.6 | AH14: 3737050.8 | AI14: 3744142 | AJ14: 3751233.1 | AK14: 3758324.3 | AL14: 3765415.5 | AM14: 3772506.7 | AN14: 3779597.8 | AO14: 3786689 | AP14: 3793780.2 | AQ14: =R14 | AR14: =AD14 | AS14: =AP14
A15: BS_OTA | B15: Other assets | C15: 1600 | D15: + | E15: TB/Map | G15: -29546.57 | H15: -59211.34 | I15: -88994.28 | J15: -118895.42 | K15: -148914.74 | L15: -179052.24 | M15: -209307.94 | N15: -239681.81 | O15: -270173.88 | P15: -300784.13 | Q15: -331512.57 | R15: -362359.19 | S15: -393324 | T15: -424407 | U15: -455608.18 | V15: -486927.55 | W15: -518365.11 | X15: -549920.85 | Y15: -581594.78 | Z15: -613386.89 | AA15: -645297.19 | AB15: -677325.68 | AC15: -709472.35 | AD15: -741737.21 | AE15: -774120.26 | AF15: -806621.49 | AG15: -839240.91 | AH15: -871978.51 | AI15: -904834.3 | AJ15: -937808.28 | AK15: -970900.45 | AL15: -1004110.8 | AM15: -1037439.3 | AN15: -1070886.1 | AO15: -1104451 | AP15: -1138134.1 | AQ15: =R15 | AR15: =AD15 | AS15: =AP15
A16: BS_TA | B16: Total assets | D16: + | E16: Formula | F16: Main total | G16: =IF(COUNT(G13:G15)=0,"",SUM(G13:G15)) | H16: =IF(COUNT(H13:H15)=0,"",SUM(H13:H15)) | I16: =IF(COUNT(I13:I15)=0,"",SUM(I13:I15)) | J16: =IF(COUNT(J13:J15)=0,"",SUM(J13:J15)) | K16: =IF(COUNT(K13:K15)=0,"",SUM(K13:K15)) | L16: =IF(COUNT(L13:L15)=0,"",SUM(L13:L15)) | M16: =IF(COUNT(M13:M15)=0,"",SUM(M13:M15)) | N16: =IF(COUNT(N13:N15)=0,"",SUM(N13:N15)) | ... AP16: =IF(COUNT(AP13:AP15)=0,"",SUM(AP13:AP15)) | AQ16: =R16 | AR16: =AD16 | AS16: =AP16
A17: BS_AP | B17: Accounts payable | C17: 2000 | D17: + | E17: TB/Map | G17: -1199684.4 | H17: -969874.09 | I17: -1260054.6 | J17: -1396978.1 | K17: -981917.02 | L17: -1272998.6 | M17: -1393755.7 | N17: -1161444.3 | O17: -1447000.2 | P17: -1266457 | Q17: -1558302.8 | R17: -1314206.1 | S17: -1069702.6 | T17: -1162667.8 | U17: -1296965.8 | V17: -1343950.4 | W17: -1433616.1 | X17: -1235684.5 | Y17: -1470277.1 | Z17: -1372970.8 | AA17: -1263552.7 | AB17: -1910211.5 | AC17: -1941469.1 | AD17: -1777387.9 | AE17: -1386629.2 | AF17: -1728933.4 | AG17: -1726212.9 | AH17: -1756838.7 | AI17: -1559288.6 | AJ17: -1821809.8 | AK17: -1843379.5 | AL17: -1669435.2 | AM17: -1440544.1 | AN17: -1812601 | AO17: -2188455 | AP17: -2303660.4 | AQ17: =R17 | AR17: =AD17 | AS17: =AP17
A18: BS_ACCR | B18: Accrued liabilities | C18: 2100 | D18: + | E18: TB/Map | G18: -61535.56 | H18: -59335.58 | I18: -62476.71 | J18: -64135.29 | K18: -61218.1 | L18: -69313.61 | M18: -66244.65 | N18: -64079.63 | O18: -68146.1 | P18: -73483.37 | Q18: -72481.85 | R18: -78883.87 | S18: -64316.98 | T18: -63437.26 | U18: -67249.38 | V18: -71553.12 | W18: -69066.28 | X18: -74810.82 | Y18: -77432.01 | Z18: -77493.68 | AA18: -77318.79 | AB18: -88594.57 | AC18: -89099.41 | AD18: -82815.88 | AE18: -80988.41 | AF18: -80062.97 | AG18: -80593.41 | AH18: -83994.17 | AI18: -83410.48 | AJ18: -94975.88 | AK18: -88094.81 | AL18: -90020.06 | AM18: -89751.73 | AN18: -106774.64 | AO18: -104488.56 | AP18: -110143.58 | AQ18: =R18 | AR18: =AD18 | AS18: =AP18
A19: BS_DEBT | B19: Debt | C19: 2200 | D19: + | E19: TB/Map | G19: -3516436.4 | H19: -3769315.7 | I19: -2546960.8 | J19: -2151689.8 | K19: -2575433.9 | L19: -2045961.6 | M19: -1024318 | N19: -552061.75 | O19: -681586.8 | P19: -263941.47 | Q19: 0 | R19: 0 | S19: 0 | T19: 0 | U19: 0 | V19: 0 | W19: 0 | X19: 0 | Y19: 0 | Z19: 0 | AA19: 0 | AB19: 0 | AC19: 0 | AD19: 0 | AE19: 0 | AF19: 0 | AG19: 0 | AH19: 0 | AI19: 0 | AJ19: 0 | AK19: 0 | AL19: 0 | AM19: 0 | AN19: 0 | AO19: 0 | AP19: 0 | AQ19: =R19 | AR19: =AD19 | AS19: =AP19
A20: BS_OL | B20: Other liabilities | C20: 2300 | D20: + | E20: TB/Map | G20: -102559.26 | H20: -98892.64 | I20: -104127.85 | J20: -106892.15 | K20: -102030.16 | L20: -115522.68 | M20: -110407.76 | N20: -106799.38 | O20: -113576.84 | P20: -122472.29 | Q20: -120803.09 | R20: -131473.11 | S20: -107194.96 | T20: -105728.77 | U20: -112082.29 | V20: -119255.19 | W20: -115110.47 | X20: -124684.7 | Y20: -129053.35 | Z20: -129156.13 | AA20: -128864.65 | AB20: -147657.61 | AC20: -148499.02 | AD20: -138026.46 | AE20: -134980.69 | AF20: -133438.28 | AG20: -134322.35 | AH20: -139990.29 | AI20: -139017.46 | AJ20: -158293.14 | AK20: -146824.69 | AL20: -150033.43 | AM20: -149586.21 | AN20: -177957.74 | AO20: -174147.59 | AP20: -183572.63 | AQ20: =R20 | AR20: =AD20 | AS20: =AP20
A21: BS_TL | B21: Total liabilities | D21: + | E21: Formula | F21: Derived | G21: =IF(COUNT(G17:G20)=0,"",SUM(G17:G20)) | H21: =IF(COUNT(H17:H20)=0,"",SUM(H17:H20)) | I21: =IF(COUNT(I17:I20)=0,"",SUM(I17:I20)) | J21: =IF(COUNT(J17:J20)=0,"",SUM(J17:J20)) | K21: =IF(COUNT(K17:K20)=0,"",SUM(K17:K20)) | L21: =IF(COUNT(L17:L20)=0,"",SUM(L17:L20)) | M21: =IF(COUNT(M17:M20)=0,"",SUM(M17:M20)) | N21: =IF(COUNT(N17:N20)=0,"",SUM(N17:N20)) | ... AP21: =IF(COUNT(AP17:AP20)=0,"",SUM(AP17:AP20)) | AQ21: =R21 | AR21: =AD21 | AS21: =AP21
A22: BS_EQ | B22: Equity | C22: 3000 | D22: + | E22: TB/Map | G22: -1577741.7 | H22: -1959467.3 | I22: -2361400.8 | J22: -2774004.5 | K22: -3167840.9 | L22: -3613758.5 | M22: -4039932.4 | N22: -4452178 | O22: -4890584.6 | P22: -5363327.6 | Q22: -5829627.6 | R22: -6337113.8 | S22: -6750886.3 | T22: -7158999.4 | U22: -7591637 | V22: -8051962.1 | W22: -8496288.5 | X22: -8977571.4 | Y22: -9475717.4 | Z22: -9974260 | AA22: -10471678 | AB22: -11041636 | AC22: -11614842 | AD22: -12147624 | AE22: -12668650 | AF22: -13183722 | AG22: -13702206 | AH22: -14242568 | AI22: -14779176 | AJ22: -15390187 | AK22: -15956931 | AL22: -16536060 | AM22: -17113462 | AN22: -17800379 | AO22: -18472589 | AP22: -19181179 | AQ22: =R22 | AR22: =AD22 | AS22: =AP22
A23: BS_TLE | B23: Total liabilities + equity | D23: + | E23: Formula | F23: Derived | G23: =IF(COUNT(G21:G22)=0,"",SUM(G21:G22)) | H23: =IF(COUNT(H21:H22)=0,"",SUM(H21:H22)) | I23: =IF(COUNT(I21:I22)=0,"",SUM(I21:I22)) | J23: =IF(COUNT(J21:J22)=0,"",SUM(J21:J22)) | K23: =IF(COUNT(K21:K22)=0,"",SUM(K21:K22)) | L23: =IF(COUNT(L21:L22)=0,"",SUM(L21:L22)) | M23: =IF(COUNT(M21:M22)=0,"",SUM(M21:M22)) | N23: =IF(COUNT(N21:N22)=0,"",SUM(N21:N22)) | ... AP23: =IF(COUNT(AP21:AP22)=0,"",SUM(AP21:AP22)) | AQ23: =R23 | AR23: =AD23 | AS23: =AP23
A27: BS_CHECKS
A28: Balance check (Assets - Liabilities & Equity) | G28: =IF(OR(G16="",G23=""),"",G16-G23) | H28: =IF(OR(H16="",H23=""),"",H16-H23) | I28: =IF(OR(I16="",I23=""),"",I16-I23) | J28: =IF(OR(J16="",J23=""),"",J16-J23) | K28: =IF(OR(K16="",K23=""),"",K16-K23) | L28: =IF(OR(L16="",L23=""),"",L16-L23) | M28: =IF(OR(M16="",M23=""),"",M16-M23) | N28: =IF(OR(N16="",N23=""),"",N16-N23) | ... AS28: =IF(OR(AS16="",AS23=""),"",AS16-AS23)
