Workbook
Name Button_429: "LeaseCalc_Lease_Data_List"
Name CellAbove: INDIRECT(ADDRESS(ROW()-1,COLUMN()))
Name CIT: #N/A
Name IQ_CH: 110000
Name IQ_CQ: 5000
Name IQ_CY: 10000
Name IQ_DAILY: 500000
Name IQ_FH: 100000
Name IQ_FQ: 500
Name IQ_FY: 1000
Name IQ_LTM: 2000
Name IQ_MONTH: 15000
Name IQ_NTM: 6000
Name IQ_WEEK: 50000
Name IQ_YTD: 3000
Name TM1REBUILDOPTION: 1

Sheet Combined | IS
A1: Combined IS
A2: Source: trial_balance.xlsx (Process-TB)
A7: Combined IS
A8: LineKey | B8: $'000 | C8: TB Account No. | D8: Sign | E8: Source | F8: Comments | G8: ='Control | Setup'!A22 | H8: ='Control | Setup'!A23 | I8: ='Control | Setup'!A24 | J8: ='Control | Setup'!A25 | K8: ='Control | Setup'!A26 | L8: ='Control | Setup'!A27 | M8: ='Control | Setup'!A28 | N8: ='Control | Setup'!A29 | O8: ='Control | Setup'!A30 | P8: ='Control | Setup'!A31 | Q8: ='Control | Setup'!A32 | R8: ='Control | Setup'!A33 | S8: ='Control | Setup'!A34 | T8: ='Control | Setup'!A35 | U8: ='Control | Setup'!A36 | V8: ='Control | Setup'!A37 | W8: ='Control | Setup'!A38 | X8: ='Control | Setup'!A39 | Y8: ='Control | Setup'!A40 | Z8: ='Control | Setup'!A41 | AA8: ='Control | Setup'!A42 | AB8: ='Control | Setup'!A43 | AC8: ='Control | Setup'!A44 | AD8: ='Control | Setup'!A45 | AE8: ='Control | Setup'!A46 | AF8: ='Control | Setup'!A47 | AG8: ='Control | Setup'!A48 | AH8: ='Control | Setup'!A49 | AI8: ='Control | Setup'!A50 | AJ8: ='Control | Setup'!A51 | AK8: ='Control | Setup'!A52 | AL8: ='Control | Setup'!A53 | AM8: ='Control | Setup'!A54 | AN8: ='Control | Setup'!A55 | AO8: ='Control | Setup'!A56 | AP8: ='Control | Setup'!A57 | AQ8: FY-2 | AR8: FY-1 | AS8: TTM
A9: IS_REV | B9: Revenue | C9: 4000 | D9: + | E9: TB/Map | G9: 2051185.2 | H9: 1977852.8 | I9: 2082556.9 | J9: 2137842.9 | K9: 2040603.3 | L9: 2310453.5 | M9: 2208155.1 | N9: 2135987.7 | O9: 2271536.8 | P9: 2449445.7 | Q9: 2416061.8 | R9: 2629462.2 | S9: 2143899.3 | T9: 2114575.3 | U9: 2241645.9 | V9: 2385103.9 | W9: 2302209.5 | X9: 2493693.9 | Y9: 2581066.9 | Z9: 2583122.6 | AA9: 2577293.1 | AB9: 2953152.2 | AC9: 2969980.5 | AD9: 2760529.3 | AE9: 2699613.8 | AF9: 2668765.7 | AG9: 2686447 | AH9: 2799805.8 | AI9: 2780349.2 | AJ9: 3165862.8 | AK9: 2936493.8 | AL9: 3000668.7 | AM9: 2991724.3 | AN9: 3559154.8 | AO9: 3482951.9 | AP9: 3671452.7 | AQ9: =IF(COUNT(G9:R9)=0,"",SUM(G9:R9)) | AR9: =IF(COUNT(S9:AD9)=0,"",SUM(S9:AD9)) | AS9: =IF(COUNT(AE9:AP9)=0,"",SUM(AE9:AP9))
A10: IS_COGS | B10: Cost of goods sold | C10: 5000 | D10: + | E10: TB/Map | G10: -937391.64 | H10: -903878.72 | I10: -951728.51 | J10: -976994.21 | K10: -932555.69 | L10: -1055877.2 | M10: -1009126.9 | N10: -976146.38 | O10: -1038092.3 | P10: -1119396.7 | Q10: -1104140.2 | R10: -1201664.2 | S10: -979761.97 | T10: -966360.94 | U10: -1024432.2 | V10: -1089992.5 | W10: -1052109.7 | X10: -1139618.1 | Y10: -1179547.6 | Z10: -1180487 | AA10: -1177822.9 | AB10: -1349590.6 | AC10: -1357281.1 | AD10: -1261561.9 | AE10: -1233723.5 | AF10: -1219625.9 | AG10: -1227706.3 | AH10: -1279511.2 | AI10: -1270619.6 | AJ10: -1446799.3 | AK10: -1341977.7 | AL10: -1371305.6 | AM10: -1367218 | AN10: -1626533.8 | AO10: -1591709 | AP10: -1677853.9 | AQ10: =IF(COUNT(G10:R10)=0,"",SUM(G10:R10)) | AR10: =IF(COUNT(S10:AD10)=0,"",SUM(S10:AD10)) | AS10: =IF(COUNT(AE10:AP10)=0,"",SUM(AE10:AP10))
A11: IS_GP | B11: Gross profit | D11: + | E11: Formula | F11: Derived | G11: =IF(OR(G9="",G10=""),"",G9+G10) | H11: =IF(OR(H9="",H10=""),"",H9+H10) | I11: =IF(OR(I9="",I10=""),"",I9+I10) | J11: =IF(OR(J9="",J10=""),"",J9+J10) | K11: =IF(OR(K9="",K10=""),"",K9+K10) | L11: =IF(OR(L9="",L10=""),"",L9+L10) | M11: =IF(OR(M9="",M10=""),"",M9+M10) | N11: =IF(OR(N9="",N10=""),"",N9+N10) | ... AP11: =IF(OR(AP9="",AP10=""),"",AP9+AP10) | AQ11: =IF(COUNT(G11:R11)=0,"",SUM(G11:R11)) | AR11: =IF(COUNT(S11:AD11)=0,"",SUM(S11:AD11)) | AS11: =IF(COUNT(AE11:AP11)=0,"",SUM(AE11:AP11))
A12: IS_OPEX | B12: Operating expenses | C12: 6100 | D12: + | E12: TB/Map | G12: -717914.83 | H12: -692248.46 | I12: -728894.93 | J12: -748245.02 | K12: -714211.14 | L12: -808658.74 | M12: -772854.3 | N12: -747595.7 | O12: -795037.87 | P12: -857306.01 | Q12: -845621.62 | R12: -920311.79 | S12: -750364.75 | T12: -740101.37 | U12: -784576.07 | V12: -834786.36 | W12: -805773.31 | X12: -872792.87 | Y12: -903373.42 | Z12: -904092.89 | AA12: -902052.58 | AB12: -1033603.3 | AC12: -1039493.2 | AD12: -966185.25 | AE12: -944864.82 | AF12: -934067.99 | AG12: -940256.45 | AH12: -979932.01 | AI12: -973122.23 | AJ12: -1108052 | AK12: -1027772.8 | AL12: -1050234 | AM12: -1047103.5 | AN12: -1245704.2 | AO12: -1219033.2 | AP12: -1285008.4 | AQ12: =IF(COUNT(G12:R12)=0,"",SUM(G12:R12)) | AR12: =IF(COUNT(S12:AD12)=0,"",SUM(S12:AD12)) | AS12: =IF(COUNT(AE12:AP12)=0,"",SUM(AE12:AP12))
A13: IS_OPINC | B13: Operating income | D13: + | E13: Formula | F13: Derived | G13: =IF(OR(G11="",G12=""),"",G11+G12) | H13: =IF(OR(H11="",H12=""),"",H11+H12) | I13: =IF(OR(I11="",I12=""),"",I11+I12) | J13: =IF(OR(J11="",J12=""),"",J11+J12) | K13: =IF(OR(K11="",K12=""),"",K11+K12) | L13: =IF(OR(L11="",L12=""),"",L11+L12) | M13: =IF(OR(M11="",M12=""),"",M11+M12) | N13: =IF(OR(N11="",N12=""),"",N11+N12) | ... AP13: =IF(OR(AP11="",AP12=""),"",AP11+AP12) | AQ13: =IF(COUNT(G13:R13)=0,"",SUM(G13:R13)) | AR13: =IF(COUNT(S13:AD13)=0,"",SUM(S13:AD13)) | AS13: =IF(COUNT(AE13:AP13)=0,"",SUM(AE13:AP13))
A14: IS_INT | B14: Interest expense | C14: 7100 | D14: + | E14: TB/Map | G14: 0 | H14: 0 | I14: 0 | J14: 0 | K14: 0 | L14: 0 | M14: 0 | N14: 0 | O14: 0 | P14: 0 | Q14: 0 | R14: 0 | S14: 0 | T14: 0 | U14: 0 | V14: 0 | W14: 0 | X14: 0 | Y14: 0 | Z14: 0 | AA14: 0 | AB14: 0 | AC14: 0 | AD14: 0 | AE14: 0 | AF14: 0 | AG14: 0 | AH14: 0 | AI14: 0 | AJ14: 0 | AK14: 0 | AL14: 0 | AM14: 0 | AN14: 0 | AO14: 0 | AP14: 0 | AQ14: =IF(COUNT(G14:R14)=0,"",SUM(G14:R14)) | AR14: =IF(COUNT(S14:AD14)=0,"",SUM(S14:AD14)) | AS14: =IF(COUNT(AE14:AP14)=0,"",SUM(AE14:AP14))
A15: IS_TAX | B15: Taxes | C15: 7200 | D15: + | E15: TB/Map | G15: 0 | H15: 0 | I15: 0 | J15: 0 | K15: 0 | L15: 0 | M15: 0 | N15: 0 | O15: 0 | P15: 0 | Q15: 0 | R15: 0 | S15: 0 | T15: 0 | U15: 0 | V15: 0 | W15: 0 | X15: 0 | Y15: 0 | Z15: 0 | AA15: 0 | AB15: 0 | AC15: 0 | AD15: 0 | AE15: 0 | AF15: 0 | AG15: 0 | AH15: 0 | AI15: 0 | AJ15: 0 | AK15: 0 | AL15: 0 | AM15: 0 | AN15: 0 | AO15: 0 | AP15: 0 | AQ15: =IF(COUNT(G15:R15)=0,"",SUM(G15:R15)) | AR15: =IF(COUNT(S15:AD15)=0,"",SUM(S15:AD15)) | AS15: =IF(COUNT(AE15:AP15)=0,"",SUM(AE15:AP15))
A16: IS_NI | B16: Net income | D16: + | E16: Formula | F16: Main total | G16: =IF(OR(G13="",G14="",G15=""),"",G13+G14+G15) | H16: =IF(OR(H13="",H14="",H15=""),"",H13+H14+H15) | I16: =IF(OR(I13="",I14="",I15=""),"",I13+I14+I15) | J16: =IF(OR(J13="",J14="",J15=""),"",J13+J14+J15) | K16: =IF(OR(K13="",K14="",K15=""),"",K13+K14+K15) | L16: =IF(OR(L13="",L14="",L15=""),"",L13+L14+L15) | M16: =IF(OR(M13="",M14="",M15=""),"",M13+M14+M15) | N16: =IF(OR(N13="",N14="",N15=""),"",N13+N14+N15) | ... AP16: =IF(OR(AP13="",AP14="",AP15=""),"",AP13+AP14+AP15) | AQ16: =IF(COUNT(G16:R16)=0,"",SUM(G16:R16)) | AR16: =IF(COUNT(S16:AD16)=0,"",SUM(S16:AD16)) | AS16: =IF(COUNT(AE16:AP16)=0,"",SUM(AE16:AP16))
A17: IS_ADD_DA | B17: Add back: Depreciation & amortization | C17: 7300 | D17: + | E17: TB/Map | G17: 0 | H17: 0 | I17: 0 | J17: 0 | K17: 0 | L17: 0 | M17: 0 | N17: 0 | O17: 0 | P17: 0 | Q17: 0 | R17: 0 | S17: 0 | T17: 0 | U17: 0 | V17: 0 | W17: 0 | X17: 0 | Y17: 0 | Z17: 0 | AA17: 0 | AB17: 0 | AC17: 0 | AD17: 0 | AE17: 0 | AF17: 0 | AG17: 0 | AH17: 0 | AI17: 0 | AJ17: 0 | AK17: 0 | AL17: 0 | AM17: 0 | AN17: 0 | AO17: 0 | AP17: 0 | AQ17: =IF(COUNT(G17:R17)=0,"",SUM(G17:R17)) | AR17: =IF(COUNT(S17:AD17)=0,"",SUM(S17:AD17)) | AS17: =IF(COUNT(AE17:AP17)=0,"",SUM(AE17:AP17))
A18: IS_ADD_INT | B18: Add back: Interest | C18: 7310 | D18: + | E18: TB/Map | G18: 0 | H18: 0 | I18: 0 | J18: 0 | K18: 0 | L18: 0 | M18: 0 | N18: 0 | O18: 0 | P18: 0 | Q18: 0 | R18: 0 | S18: 0 | T18: 0 | U18: 0 | V18: 0 | W18: 0 | X18: 0 | Y18: 0 | Z18: 0 | AA18: 0 | AB18: 0 | AC18: 0 | AD18: 0 | AE18: 0 | AF18: 0 | AG18: 0 | AH18: 0 | AI18: 0 | AJ18: 0 | AK18: 0 | AL18: 0 | AM18: 0 | AN18: 0 | AO18: 0 | AP18: 0 | AQ18: =IF(COUNT(G18:R18)=0,"",SUM(G18:R18)) | AR18: =IF(COUNT(S18:AD18)=0,"",SUM(S18:AD18)) | AS18: =IF(COUNT(AE18:AP18)=0,"",SUM(AE18:AP18))
A19: IS_ADD_TAX | B19: Add back: Taxes | C19: 7320 | D19: + | E19: TB/Map | G19: 0 | H19: 0 | I19: 0 | J19: 0 | K19: 0 | L19: 0 | M19: 0 | N19: 0 | O19: 0 | P19: 0 | Q19: 0 | R19: 0 | S19: 0 | T19: 0 | U19: 0 | V19: 0 | W19: 0 | X19: 0 | Y19: 0 | Z19: 0 | AA19: 0 | AB19: 0 | AC19: 0 | AD19: 0 | AE19: 0 | AF19: 0 | AG19: 0 | AH19: 0 | AI19: 0 | AJ19: 0 | AK19: 0 | AL19: 0 | AM19: 0 | AN19: 0 | AO19: 0 | AP19: 0 | AQ19: =IF(COUNT(G19:R19)=0,"",SUM(G19:R19)) | AR19: =IF(COUNT(S19:AD19)=0,"",SUM(S19:AD19)) | AS19: =IF(COUNT(AE19:AP19)=0,"",SUM(AE19:AP19))
A20: IS_EBITDA | B20: EBITDA | D20: + | E20: Formula | F20: Secondary total | G20: =IF(OR(G16="",G17="",G18="",G19=""),"",G16+G17+G18+G19) | H20: =IF(OR(H16="",H17="",H18="",H19=""),"",H16+H17+H18+H19) | I20: =IF(OR(I16="",I17="",I18="",I19=""),"",I16+I17+I18+I19) | J20: =IF(OR(J16="",J17="",J18="",J19=""),"",J16+J17+J18+J19) | K20: =IF(OR(K16="",K17="",K18="",K19=""),"",K16+K17+K18+K19) | L20: =IF(OR(L16="",L17="",L18="",L19=""),"",L16+L17+L18+L19) | M20: =IF(OR(M16="",M17="",M18="",M19=""),"",M16+M17+M18+M19) | N20: =IF(OR(N16="",N17="",N18="",N19=""),"",N16+N17+N18+N19) | ... AP20: =IF(OR(AP16="",AP17="",AP18="",AP19=""),"",AP16+AP17+AP18+AP19) | AQ20: =IF(COUNT(G20:R20)=0,"",SUM(G20:R20)) | AR20: =IF(COUNT(S20:AD20)=0,"",SUM(S20:AD20)) | AS20: =IF(COUNT(AE20:AP20)=0,"",SUM(AE20:AP20))
A27: IS_CHECKS
A28: Net income tie-out | G28: =IF(G16="","",G16-(G13+G14+G15)) | H28: =IF(H16="","",H16-(H13+H14+H15)) | I28: =IF(I16="","",I16-(I13+I14+I15)) | J28: =IF(J16="","",J16-(J13+J14+J15)) | K28: =IF(K16="","",K16-(K13+K14+K15)) | L28: =IF(L16="","",L16-(L13+L14+L15)) | M28: =IF(M16="","",M16-(M13+M14+M15)) | N28: =IF(N16="","",N16-(N13+N14+N15)) | ... AS28: =IF(AS16="","",AS16-(AS13+AS14+AS15))
A29: EBITDA tie-out | G29: =IF(G20="","",G20-(G16+G17+G18+G19)) | H29: =IF(H20="","",H20-(H16+H17+H18+H19)) | I29: =IF(I20="","",I20-(I16+I17+I18+I19)) | J29: =IF(J20="","",J20-(J16+J17+J18+J19)) | K29: =IF(K20="","",K20-(K16+K17+K18+K19)) | L29: =IF(L20="","",L20-(L16+L17+L18+L19)) | M29: =IF(M20="","",M20-(M16+M17+M18+M19)) | N29: =IF(N20="","",N20-(N16+N17+N18+N19)) | ... AS29: =IF(AS20="","",AS20-(AS16+AS17+AS18+AS19))
